Workbook

Sheet Assumptions
A2: Revenue | B2: Growth rate as per the guidance by the company for explicit forecast period | G2: ='IS-Reorg'!L75 -> 0.03
A3: Terminal year growth rate assumed to be 2.5% as the company is a mature company and is assumed to grow in-line with long-term GDP growth rate
A5: WACC | B5: =WACC!D28 -> 0.080560348 | C5: Calculated in the WACC Sheet
A6: Beta has been adjusted using smoothing techniques
A8: Litigation related assumptions
A9: 3M is going thorugh 2 major litigation settlements
A10: 1. PFAS/PWS
A11: 2. Combat Arms Earplugs
A13: 3M official settlement documents with PWS have been used for the payment liability assumptions
A14: The Company filed an 8K form in June 2023 that explains the litigations payments and their schedules

Sheet IS-Reorg
B1: Historical Period | L1: Explicit forecast period
A2: All figures in millions of U.S. Dollar | B2: 2016 | C2: 2017 | D2: =C2+1 -> 2018 | E2: =D2+1 -> 2019 | F2: =E2+1 -> 2020 | G2: =F2+1 -> 2021 | H2: =G2+1 -> 2022 | I2: =H2+1 -> 2023 | J2: =I2+1 -> 2024 | K2: =J2+1 -> 2025 | L2: 2026 | M2: =L2+1 -> 2027 | N2: =M2+1 -> 2028 | O2: =N2+1 -> 2029 | P2: =O2+1 -> 2030 | Q2: =P2+1 -> 2031 | R2: =Q2+1 -> 2032 | S2: =R2+1 -> 2033 | T2: =S2+1 -> 2034 | ... V2: =U2+1 -> 2036 | X2: Common size base 2025
A3: Operating Items
A4: ='3M-IS'!A8 -> Sales | B4: =VLOOKUP($A4,'3M-IS'!$A$8:$K$61,11,FALSE) -> 30109 | C4: =VLOOKUP($A4,'3M-IS'!$A$8:$K$61,10,FALSE) -> 31657 | D4: =VLOOKUP($A4,'3M-IS'!$A$8:$K$61,9,FALSE) -> 32765 | E4: =VLOOKUP($A4,'3M-IS'!$A$8:$K$61,8,FALSE) -> 32136 | F4: =VLOOKUP($A4,'3M-IS'!$A$8:$K$61,7,FALSE) -> 32184 | G4: =VLOOKUP($A4,'3M-IS'!$A$8:$K$61,6,FALSE) -> 35355 | H4: =VLOOKUP($A4,'3M-IS'!$A$8:$K$61,5,FALSE) -> 34229 | I4: =VLOOKUP($A4,'3M-IS'!$A$8:$K$61,4,FALSE) -> 24610 | J4: =VLOOKUP($A4,'3M-IS'!$A$8:$K$61,3,FALSE) -> 24575 | K4: =VLOOKUP($A4,'3M-IS'!$A$8:$K$61,2,FALSE) -> 24948 | L4: =L72 -> 25313.28 | M4: =M72 -> 26325.811 | N4: =N72 -> 27378.844 | O4: =O72 -> 28473.997 | P4: =P72 -> 29612.957 | Q4: =Q72 -> 30501.346 | R4: =R72 -> 31416.386 | S4: =S72 -> 32358.878 | ... V4: =V72 -> 35359.42 | X4: =K4/$K$4 -> 1 | Y4: Revenue
A5: ='3M-IS'!A9 -> Cost of Goods Sold (COGS) incl. D&A | B5: =VLOOKUP($A5,'3M-IS'!$A$8:$K$61,11,FALSE) -> 15133 | C5: =VLOOKUP($A5,'3M-IS'!$A$8:$K$61,10,FALSE) -> 15995 | D5: =VLOOKUP($A5,'3M-IS'!$A$8:$K$61,9,FALSE) -> 16575 | E5: =VLOOKUP($A5,'3M-IS'!$A$8:$K$61,8,FALSE) -> 16830 | F5: =VLOOKUP($A5,'3M-IS'!$A$8:$K$61,7,FALSE) -> 16581 | G5: =VLOOKUP($A5,'3M-IS'!$A$8:$K$61,6,FALSE) -> 18743 | H5: =VLOOKUP($A5,'3M-IS'!$A$8:$K$61,5,FALSE) -> 19263 | I5: =VLOOKUP($A5,'3M-IS'!$A$8:$K$61,4,FALSE) -> 15037 | J5: =VLOOKUP($A5,'3M-IS'!$A$8:$K$61,3,FALSE) -> 14495 | K5: =VLOOKUP($A5,'3M-IS'!$A$8:$K$61,2,FALSE) -> 15072 | L5: =L6+L7 -> 15276.658 | M5: =M6+M7 -> 15701.471 | N5: =N6+N7 -> 16140.76 | O5: =O6+O7 -> 16594.735 | P5: =P6+P7 -> 17063.615 | Q5: =Q6+Q7 -> 17391.657 | R5: =R6+R7 -> 17726.581 | S5: =S6+S7 -> 18068.36 | ... V5: =V6+V7 -> 19134.581 | X5: =K5/$K$4 -> 0.6041366 | Y5: COGS w/ D&A
A6: ='3M-IS'!A10 -> COGS excluding D&A | B6: =VLOOKUP($A6,'3M-IS'!$A$8:$K$61,11,FALSE) -> 13659 | C6: =VLOOKUP($A6,'3M-IS'!$A$8:$K$61,10,FALSE) -> 14451 | D6: =VLOOKUP($A6,'3M-IS'!$A$8:$K$61,9,FALSE) -> 15087 | E6: =VLOOKUP($A6,'3M-IS'!$A$8:$K$61,8,FALSE) -> 15237 | F6: =VLOOKUP($A6,'3M-IS'!$A$8:$K$61,7,FALSE) -> 14670 | G6: =VLOOKUP($A6,'3M-IS'!$A$8:$K$61,6,FALSE) -> 16828 | H6: =VLOOKUP($A6,'3M-IS'!$A$8:$K$61,5,FALSE) -> 17432 | I6: =VLOOKUP($A6,'3M-IS'!$A$8:$K$61,4,FALSE) -> 13604 | J6: =VLOOKUP($A6,'3M-IS'!$A$8:$K$61,3,FALSE) -> 13271 | K6: =VLOOKUP($A6,'3M-IS'!$A$8:$K$61,2,FALSE) -> 13764 | L6: =L83 -> 13965.528 | M6: =M83 -> 14392.52 | N6: =N83 -> 14831.326 | O6: =O83 -> 15282.209 | P6: =P83 -> 15745.433 | Q6: =Q83 -> 16065.289 | R6: =R83 -> 16390.166 | S6: =S83 -> 16720.077 | ... V6: =V83 -> 17740.088 | X6: =K6/$K$4 -> 0.55170755 | Y6: COGS w/o D&A
A7: ='3M-IS'!A11 -> Depreciation & Amortization Expense | B7: =VLOOKUP($A7,'3M-IS'!$A$8:$K$61,11,FALSE) -> 1474 | C7: =VLOOKUP($A7,'3M-IS'!$A$8:$K$61,10,FALSE) -> 1544 | D7: =VLOOKUP($A7,'3M-IS'!$A$8:$K$61,9,FALSE) -> 1488 | E7: =VLOOKUP($A7,'3M-IS'!$A$8:$K$61,8,FALSE) -> 1593 | F7: =VLOOKUP($A7,'3M-IS'!$A$8:$K$61,7,FALSE) -> 1911 | G7: =VLOOKUP($A7,'3M-IS'!$A$8:$K$61,6,FALSE) -> 1915 | H7: =VLOOKUP($A7,'3M-IS'!$A$8:$K$61,5,FALSE) -> 1831 | I7: =VLOOKUP($A7,'3M-IS'!$A$8:$K$61,4,FALSE) -> 1433 | J7: =VLOOKUP($A7,'3M-IS'!$A$8:$K$61,3,FALSE) -> 1224 | K7: =VLOOKUP($A7,'3M-IS'!$A$8:$K$61,2,FALSE) -> 1308 | L7: =L8+L9 -> 1311.1303 | M7: =M8+M9 -> 1308.9515 | N7: =N8+N9 -> 1309.434 | O7: =O8+O9 -> 1312.5255 | P7: =P8+P9 -> 1318.1821 | Q7: =Q8+Q9 -> 1326.3682 | R7: =R8+R9 -> 1336.4154 | S7: =S8+S9 -> 1348.2837 | ... V7: =V8+V9 -> 1394.4927 | X7: =K7/$K$4 -> 0.052429052 | Y7: D&A
A8: ='3M-IS'!A12 -> Depreciation | B8: =VLOOKUP($A8,'3M-IS'!$A$8:$K$61,11,FALSE) -> 1212 | C8: =VLOOKUP($A8,'3M-IS'!$A$8:$K$61,10,FALSE) -> 1306 | D8: =VLOOKUP($A8,'3M-IS'!$A$8:$K$61,9,FALSE) -> 1239 | E8: =VLOOKUP($A8,'3M-IS'!$A$8:$K$61,8,FALSE) -> 1252 | F8: =VLOOKUP($A8,'3M-IS'!$A$8:$K$61,7,FALSE) -> 1374 | G8: =VLOOKUP($A8,'3M-IS'!$A$8:$K$61,6,FALSE) -> 1386 | H8: =VLOOKUP($A8,'3M-IS'!$A$8:$K$61,5,FALSE) -> 1333 | I8: =VLOOKUP($A8,'3M-IS'!$A$8:$K$61,4,FALSE) -> 1306 | J8: =VLOOKUP($A8,'3M-IS'!$A$8:$K$61,3,FALSE) -> 1116 | K8: =VLOOKUP($A8,'3M-IS'!$A$8:$K$61,2,FALSE) -> 1204 | L8: =-L101 -> 1215.6149 | M8: =-M101 -> 1221.7074 | N8: =-N101 -> 1229.7449 | O8: =-O101 -> 1239.7371 | P8: =-P101 -> 1251.697 | Q8: =-Q101 -> 1265.6403 | R8: =-R101 -> 1280.9463 | S8: =-S101 -> 1297.618 | ... V8: =-V101 -> 1355.8824
A9: ='3M-IS'!A13 -> Amortization of Intangibles | B9: =VLOOKUP($A9,'3M-IS'!$A$8:$K$61,11,FALSE) -> 262 | C9: =VLOOKUP($A9,'3M-IS'!$A$8:$K$61,10,FALSE) -> 238 | D9: =VLOOKUP($A9,'3M-IS'!$A$8:$K$61,9,FALSE) -> 249 | E9: =VLOOKUP($A9,'3M-IS'!$A$8:$K$61,8,FALSE) -> 341 | F9: =VLOOKUP($A9,'3M-IS'!$A$8:$K$61,7,FALSE) -> 537 | G9: =VLOOKUP($A9,'3M-IS'!$A$8:$K$61,6,FALSE) -> 529 | H9: =VLOOKUP($A9,'3M-IS'!$A$8:$K$61,5,FALSE) -> 498 | I9: =VLOOKUP($A9,'3M-IS'!$A$8:$K$61,4,FALSE) -> 127 | J9: =VLOOKUP($A9,'3M-IS'!$A$8:$K$61,3,FALSE) -> 108 | K9: =VLOOKUP($A9,'3M-IS'!$A$8:$K$61,2,FALSE) -> 104 | L9: =-L131 -> 95.515336 | M9: =-M131 -> 87.244094 | N9: =-N131 -> 79.689109 | O9: =-O131 -> 72.788355 | P9: =-P131 -> 66.485178 | Q9: =-Q131 -> 60.72783 | R9: =-R131 -> 55.469046 | S9: =-S131 -> 50.665651 | ... V9: =-V131 -> 38.610233
A10: ='3M-IS'!A14 -> Gross Income | B10: =VLOOKUP($A10,'3M-IS'!$A$8:$K$61,11,FALSE) -> 14976 | C10: =VLOOKUP($A10,'3M-IS'!$A$8:$K$61,10,FALSE) -> 15662 | D10: =VLOOKUP($A10,'3M-IS'!$A$8:$K$61,9,FALSE) -> 16190 | E10: =VLOOKUP($A10,'3M-IS'!$A$8:$K$61,8,FALSE) -> 15306 | F10: =VLOOKUP($A10,'3M-IS'!$A$8:$K$61,7,FALSE) -> 15603 | G10: =VLOOKUP($A10,'3M-IS'!$A$8:$K$61,6,FALSE) -> 16612 | H10: =VLOOKUP($A10,'3M-IS'!$A$8:$K$61,5,FALSE) -> 14966 | I10: =VLOOKUP($A10,'3M-IS'!$A$8:$K$61,4,FALSE) -> 9573 | J10: =VLOOKUP($A10,'3M-IS'!$A$8:$K$61,3,FALSE) -> 10080 | K10: =VLOOKUP($A10,'3M-IS'!$A$8:$K$61,2,FALSE) -> 9876 | L10: =L4-L5 -> 10036.622 | M10: =M4-M5 -> 10624.34 | N10: =N4-N5 -> 11238.083 | O10: =O4-O5 -> 11879.262 | P10: =P4-P5 -> 12549.342 | Q10: =Q4-Q5 -> 13109.689 | R10: =R4-R5 -> 13689.805 | S10: =S4-S5 -> 14290.518 | ... V10: =V4-V5 -> 16224.839 | X10: =K10/$K$4 -> 0.3958634 | Y10: GIM
A11: ='3M-IS'!A15 -> SG&A Expense | B11: =VLOOKUP($A11,'3M-IS'!$A$8:$K$61,11,FALSE) -> 7957 | C11: =VLOOKUP($A11,'3M-IS'!$A$8:$K$61,10,FALSE) -> 8436 | D11: =VLOOKUP($A11,'3M-IS'!$A$8:$K$61,9,FALSE) -> 8416 | E11: =VLOOKUP($A11,'3M-IS'!$A$8:$K$61,8,FALSE) -> 8332 | F11: =VLOOKUP($A11,'3M-IS'!$A$8:$K$61,7,FALSE) -> 8646 | G11: =VLOOKUP($A11,'3M-IS'!$A$8:$K$61,6,FALSE) -> 9086 | H11: =VLOOKUP($A11,'3M-IS'!$A$8:$K$61,5,FALSE) -> 10893 | I11: =VLOOKUP($A11,'3M-IS'!$A$8:$K$61,4,FALSE) -> 5526 | J11: =VLOOKUP($A11,'3M-IS'!$A$8:$K$61,3,FALSE) -> 5149 | K11: =VLOOKUP($A11,'3M-IS'!$A$8:$K$61,2,FALSE) -> 5146 | L11: =L89 -> 5221.346 | M11: =M89 -> 5298.5707 | N11: =N89 -> 5373.6193 | O11: =O89 -> 5446.1941 | P11: =P89 -> 5515.9771 | Q11: =Q89 -> 5528.9497 | R11: =R89 -> 5537.7363 | S11: =S89 -> 5542.074 | ... V11: =V89 -> 5525.5826 | X11: =K11/$K$4 -> 0.20626904 | Y11: SG&A %
A12: ='3M-IS'!A16 -> Research & Development | B12: =VLOOKUP($A12,'3M-IS'!$A$8:$K$61,11,FALSE) -> 1735 | C12: =VLOOKUP($A12,'3M-IS'!$A$8:$K$61,10,FALSE) -> 1862 | D12: =VLOOKUP($A12,'3M-IS'!$A$8:$K$61,9,FALSE) -> 1816 | E12: =VLOOKUP($A12,'3M-IS'!$A$8:$K$61,8,FALSE) -> 1874 | F12: =VLOOKUP($A12,'3M-IS'!$A$8:$K$61,7,FALSE) -> 1862 | G12: =VLOOKUP($A12,'3M-IS'!$A$8:$K$61,6,FALSE) -> 1977 | H12: =VLOOKUP($A12,'3M-IS'!$A$8:$K$61,5,FALSE) -> 1856 | I12: =VLOOKUP($A12,'3M-IS'!$A$8:$K$61,4,FALSE) -> 1123 | J12: =VLOOKUP($A12,'3M-IS'!$A$8:$K$61,3,FALSE) -> 1070 | K12: =VLOOKUP($A12,'3M-IS'!$A$8:$K$61,2,FALSE) -> 1169 | L12: =L91 -> 1265.664 | M12: =M91 -> 1316.2906 | N12: =N91 -> 1368.9422 | O12: =O91 -> 1423.6999 | P12: =P91 -> 1480.6479 | Q12: =Q91 -> 1525.0673 | R12: =R91 -> 1570.8193 | S12: =S91 -> 1617.9439 | ... V12: =V91 -> 1767.971
A13: ='3M-IS'!A17 -> Other SG&A | B13: =VLOOKUP($A13,'3M-IS'!$A$8:$K$61,11,FALSE) -> 6222 | C13: =VLOOKUP($A13,'3M-IS'!$A$8:$K$61,10,FALSE) -> 6574 | D13: =VLOOKUP($A13,'3M-IS'!$A$8:$K$61,9,FALSE) -> 6600 | E13: =VLOOKUP($A13,'3M-IS'!$A$8:$K$61,8,FALSE) -> 6458 | F13: =VLOOKUP($A13,'3M-IS'!$A$8:$K$61,7,FALSE) -> 6784 | G13: =VLOOKUP($A13,'3M-IS'!$A$8:$K$61,6,FALSE) -> 7109 | H13: =VLOOKUP($A13,'3M-IS'!$A$8:$K$61,5,FALSE) -> 9037 | I13: =VLOOKUP($A13,'3M-IS'!$A$8:$K$61,4,FALSE) -> 4403 | J13: =VLOOKUP($A13,'3M-IS'!$A$8:$K$61,3,FALSE) -> 4079 | K13: =VLOOKUP($A13,'3M-IS'!$A$8:$K$61,2,FALSE) -> 3977 | L13: =L11-L12 -> 3955.682 | M13: =M11-M12 -> 3982.2802 | N13: =N11-N12 -> 4004.6772 | O13: =O11-O12 -> 4022.4943 | P13: =P11-P12 -> 4035.3292 | Q13: =Q11-Q12 -> 4003.8824 | R13: =R11-R12 -> 3966.9169 | S13: =S11-S12 -> 3924.1301 | ... V13: =V11-V12 -> 3757.6116
A14: ='3M-IS'!A18 -> EBIT (Operating Income) | B14: =VLOOKUP($A14,'3M-IS'!$A$8:$K$61,11,FALSE) -> 7019 | C14: =VLOOKUP($A14,'3M-IS'!$A$8:$K$61,10,FALSE) -> 7226 | D14: =VLOOKUP($A14,'3M-IS'!$A$8:$K$61,9,FALSE) -> 7774 | E14: =VLOOKUP($A14,'3M-IS'!$A$8:$K$61,8,FALSE) -> 6974 | F14: =VLOOKUP($A14,'3M-IS'!$A$8:$K$61,7,FALSE) -> 6957 | G14: =VLOOKUP($A14,'3M-IS'!$A$8:$K$61,6,FALSE) -> 7526 | H14: =VLOOKUP($A14,'3M-IS'!$A$8:$K$61,5,FALSE) -> 4073 | I14: =VLOOKUP($A14,'3M-IS'!$A$8:$K$61,4,FALSE) -> 4047 | J14: =VLOOKUP($A14,'3M-IS'!$A$8:$K$61,3,FALSE) -> 4931 | K14: =VLOOKUP($A14,'3M-IS'!$A$8:$K$61,2,FALSE) -> 4730 | L14: =L10-L11 -> 4815.276 | M14: =M10-M11 -> 5325.7691 | N14: =N10-N11 -> 5864.4639 | O14: =O10-O11 -> 6433.0683 | P14: =P10-P11 -> 7033.365 | Q14: =Q10-Q11 -> 7580.7389 | R14: =R10-R11 -> 8152.0687 | S14: =S10-S11 -> 8748.4437 | ... V14: =V10-V11 -> 10699.257 | X14: =K14/$K$4 -> 0.18959436 | Y14: EBIT Margin
A16: Tax rate | B16: =VLOOKUP($A16,'3M-IS'!$A$64:$K$64,11,FALSE) -> 0.28285836 | C16: =VLOOKUP($A16,'3M-IS'!$A$64:$K$64,10,FALSE) -> 0.35492846 | D16: =VLOOKUP($A16,'3M-IS'!$A$64:$K$64,9,FALSE) -> 0.23385714 | E16: =VLOOKUP($A16,'3M-IS'!$A$64:$K$64,8,FALSE) -> 0.19782913 | F16: =VLOOKUP($A16,'3M-IS'!$A$64:$K$64,7,FALSE) -> 0.19676233 | G16: =VLOOKUP($A16,'3M-IS'!$A$64:$K$64,6,FALSE) -> 0.17837313 | H16: =VLOOKUP($A16,'3M-IS'!$A$64:$K$64,5,FALSE) -> 0.095744681 | I16: =VLOOKUP($A16,'3M-IS'!$A$64:$K$64,4,FALSE) -> 0.25436962 | J16: =VLOOKUP($A16,'3M-IS'!$A$64:$K$64,3,FALSE) -> 0.16683959 | K16: =VLOOKUP($A16,'3M-IS'!$A$64:$K$64,2,FALSE) -> 0.23807263 | L16: 0.21 | M16: =L16 -> 0.21 | N16: =M16 -> 0.21 | O16: =N16 -> 0.21 | P16: =O16 -> 0.21 | Q16: =P16 -> 0.21 | R16: =Q16 -> 0.21 | S16: =R16 -> 0.21 | T16: =S16 -> 0.21 | ... V16: =U16 -> 0.21 | Y16: U.S. federal statutory rate; used as the normalized forward rate since 3M's effective rate (10–35%) is distorted by one-time litigation/tax items.
A17: Operating Taxes | B17: =B16*B14 -> 1985.3828 | C17: =C16*C14 -> 2564.713 | D17: =D16*D14 -> 1818.0054 | E17: =E16*E14 -> 1379.6604 | F17: =F16*F14 -> 1368.8755 | G17: =G16*G14 -> 1342.4361 | H17: =H16*H14 -> 389.96809 | I17: =I16*I14 -> 1029.4339 | ... V17: =V16*V14 -> 2246.8439
A19: NOPAT | B19: =B14-B17 -> 5033.6172 | C19: =C14-C17 -> 4661.287 | D19: =D14-D17 -> 5955.9946 | E19: =E14-E17 -> 5594.3396 | F19: =F14-F17 -> 5588.1245 | G19: =G14-G17 -> 6183.5639 | H19: =H14-H17 -> 3683.0319 | I19: =I14-I17 -> 3017.5661 | ... V19: =V14-V17 -> 8452.4127 | X19: =K19/$K$4 -> 0.14445713 | Y19: NOPAT Margin
A21: ='3M-IS'!A19 -> Nonoperating Income - Net | B21: =VLOOKUP($A21,'3M-IS'!$A$8:$K$61,11,FALSE) -> 249 | C21: =VLOOKUP($A21,'3M-IS'!$A$8:$K$61,10,FALSE) -> 771 | D21: =VLOOKUP($A21,'3M-IS'!$A$8:$K$61,9,FALSE) -> 594 | E21: =VLOOKUP($A21,'3M-IS'!$A$8:$K$61,8,FALSE) -> 368 | F21: =VLOOKUP($A21,'3M-IS'!$A$8:$K$61,7,FALSE) -> 623 | G21: =VLOOKUP($A21,'3M-IS'!$A$8:$K$61,6,FALSE) -> 276 | H21: =VLOOKUP($A21,'3M-IS'!$A$8:$K$61,5,FALSE) -> 3137 | I21: =VLOOKUP($A21,'3M-IS'!$A$8:$K$61,4,FALSE) -> 517 | J21: =VLOOKUP($A21,'3M-IS'!$A$8:$K$61,3,FALSE) -> -189 | K21: =VLOOKUP($A21,'3M-IS'!$A$8:$K$61,2,FALSE) -> -100 | L21: =L22+L23 -> 153.28782 | M21: =M22+M23 -> 122.95192 | N21: =N22+N23 -> 143.9562 | O21: =O22+O23 -> 168.7428 | P21: =P22+P23 -> 224.79501 | Q21: =Q22+Q23 -> 288.37078 | R21: =R22+R23 -> 371.39 | S21: =S22+S23 -> 460.63636 | ... V21: =V22+V23 -> 766.00806 | X21: =K21/$K$4 -> -0.0040083373
A22: ='3M-IS'!A20 -> Nonoperating Interest Income | B22: =VLOOKUP($A22,'3M-IS'!$A$8:$K$61,11,FALSE) -> 29 | C22: =VLOOKUP($A22,'3M-IS'!$A$8:$K$61,10,FALSE) -> 50 | D22: =VLOOKUP($A22,'3M-IS'!$A$8:$K$61,9,FALSE) -> 70 | E22: =VLOOKUP($A22,'3M-IS'!$A$8:$K$61,8,FALSE) -> 80 | F22: =VLOOKUP($A22,'3M-IS'!$A$8:$K$61,7,FALSE) -> 29 | G22: =VLOOKUP($A22,'3M-IS'!$A$8:$K$61,6,FALSE) -> 26 | H22: =VLOOKUP($A22,'3M-IS'!$A$8:$K$61,5,FALSE) -> 67 | I22: =VLOOKUP($A22,'3M-IS'!$A$8:$K$61,4,FALSE) -> 250 | J22: =VLOOKUP($A22,'3M-IS'!$A$8:$K$61,3,FALSE) -> 452 | K22: =VLOOKUP($A22,'3M-IS'!$A$8:$K$61,2,FALSE) -> 232 | L22: =L154 -> 153.28782 | M22: =M154 -> 122.95192 | N22: =N154 -> 143.9562 | O22: =O154 -> 168.7428 | P22: =P154 -> 224.79501 | Q22: =Q154 -> 288.37078 | R22: =R154 -> 371.39 | S22: =S154 -> 460.63636 | ... V22: =V154 -> 766.00806
A23: ='3M-IS'!A21 -> Other Income (Expense) | B23: =VLOOKUP($A23,'3M-IS'!$A$8:$K$61,11,FALSE) -> 220 | C23: =VLOOKUP($A23,'3M-IS'!$A$8:$K$61,10,FALSE) -> 721 | D23: =VLOOKUP($A23,'3M-IS'!$A$8:$K$61,9,FALSE) -> 524 | E23: =VLOOKUP($A23,'3M-IS'!$A$8:$K$61,8,FALSE) -> 288 | F23: =VLOOKUP($A23,'3M-IS'!$A$8:$K$61,7,FALSE) -> 594 | G23: =VLOOKUP($A23,'3M-IS'!$A$8:$K$61,6,FALSE) -> 250 | H23: =VLOOKUP($A23,'3M-IS'!$A$8:$K$61,5,FALSE) -> 3070 | I23: =VLOOKUP($A23,'3M-IS'!$A$8:$K$61,4,FALSE) -> 267 | J23: =VLOOKUP($A23,'3M-IS'!$A$8:$K$61,3,FALSE) -> -641 | K23: =VLOOKUP($A23,'3M-IS'!$A$8:$K$61,2,FALSE) -> -332 | L23: 0 | M23: =L23 -> 0 | N23: =M23 -> 0 | O23: =N23 -> 0 | P23: =O23 -> 0 | Q23: =P23 -> 0 | R23: =Q23 -> 0 | S23: =R23 -> 0 | T23: =S23 -> 0 | ... V23: =U23 -> 0
A24: ='3M-IS'!A22 -> Interest Expense | B24: =VLOOKUP($A24,'3M-IS'!$A$8:$K$61,11,FALSE) -> 207 | C24: =VLOOKUP($A24,'3M-IS'!$A$8:$K$61,10,FALSE) -> 84 | D24: =VLOOKUP($A24,'3M-IS'!$A$8:$K$61,9,FALSE) -> 240 | E24: =VLOOKUP($A24,'3M-IS'!$A$8:$K$61,8,FALSE) -> 431 | F24: =VLOOKUP($A24,'3M-IS'!$A$8:$K$61,7,FALSE) -> 553 | G24: =VLOOKUP($A24,'3M-IS'!$A$8:$K$61,6,FALSE) -> 457 | H24: =VLOOKUP($A24,'3M-IS'!$A$8:$K$61,5,FALSE) -> 498 | I24: =VLOOKUP($A24,'3M-IS'!$A$8:$K$61,4,FALSE) -> 932 | J24: =VLOOKUP($A24,'3M-IS'!$A$8:$K$61,3,FALSE) -> 1182 | K24: =VLOOKUP($A24,'3M-IS'!$A$8:$K$61,2,FALSE) -> 938 | L24: =C150 -> 262.7372 | M24: =D150 -> 232.169 | N24: =E150 -> 161.2202 | O24: =F150 -> 134.3414 | P24: =G150 -> 107.7512 | Q24: =H150 -> 97.4084 | R24: =I150 -> 87.9782 | S24: =J150 -> 79.0394 | ... V24: =M150 -> 56.4116
A25: ='3M-IS'!A23 -> Gross Interest Expense | B25: =VLOOKUP($A25,'3M-IS'!$A$8:$K$61,11,FALSE) -> 217 | C25: =VLOOKUP($A25,'3M-IS'!$A$8:$K$61,10,FALSE) -> 84 | D25: =VLOOKUP($A25,'3M-IS'!$A$8:$K$61,9,FALSE) -> 240 | E25: =VLOOKUP($A25,'3M-IS'!$A$8:$K$61,8,FALSE) -> 431 | F25: =VLOOKUP($A25,'3M-IS'!$A$8:$K$61,7,FALSE) -> 553 | G25: =VLOOKUP($A25,'3M-IS'!$A$8:$K$61,6,FALSE) -> 457 | H25: =VLOOKUP($A25,'3M-IS'!$A$8:$K$61,5,FALSE) -> 498 | I25: =VLOOKUP($A25,'3M-IS'!$A$8:$K$61,4,FALSE) -> 932 | J25: =VLOOKUP($A25,'3M-IS'!$A$8:$K$61,3,FALSE) -> 1182 | K25: =VLOOKUP($A25,'3M-IS'!$A$8:$K$61,2,FALSE) -> 938 | L25: =C150 -> 262.7372 | M25: =D150 -> 232.169 | N25: =E150 -> 161.2202 | O25: =F150 -> 134.3414 | P25: =G150 -> 107.7512 | Q25: =H150 -> 97.4084 | R25: =I150 -> 87.9782 | S25: =J150 -> 79.0394 | ... V25: =M150 -> 56.4116
A26: ='3M-IS'!A24 -> Interest Capitalized | B26: =VLOOKUP($A26,'3M-IS'!$A$8:$K$61,11,FALSE) -> 10 | C26: =VLOOKUP($A26,'3M-IS'!$A$8:$K$61,10,FALSE) -> 0 | D26: =VLOOKUP($A26,'3M-IS'!$A$8:$K$61,9,FALSE) -> 0 | E26: =VLOOKUP($A26,'3M-IS'!$A$8:$K$61,8,FALSE) -> 0 | F26: =VLOOKUP($A26,'3M-IS'!$A$8:$K$61,7,FALSE) -> 0 | G26: =VLOOKUP($A26,'3M-IS'!$A$8:$K$61,6,FALSE) -> 0 | H26: =VLOOKUP($A26,'3M-IS'!$A$8:$K$61,5,FALSE) -> 0 | I26: =VLOOKUP($A26,'3M-IS'!$A$8:$K$61,4,FALSE) -> 0 | J26: =VLOOKUP($A26,'3M-IS'!$A$8:$K$61,3,FALSE) -> 0 | K26: =VLOOKUP($A26,'3M-IS'!$A$8:$K$61,2,FALSE) -> 0 | L26: 0 | M26: 0 | N26: 0 | O26: 0 | P26: 0 | Q26: 0 | R26: 0 | S26: 0 | T26: 0 | U26: 0 | V26: 0
A27: ='3M-IS'!A25 -> Unusual Expense - Net | B27: =VLOOKUP($A27,'3M-IS'!$A$8:$K$61,11,FALSE) -> 8 | C27: =VLOOKUP($A27,'3M-IS'!$A$8:$K$61,10,FALSE) -> 365 | D27: =VLOOKUP($A27,'3M-IS'!$A$8:$K$61,9,FALSE) -> 1128 | E27: =VLOOKUP($A27,'3M-IS'!$A$8:$K$61,8,FALSE) -> 1199 | F27: =VLOOKUP($A27,'3M-IS'!$A$8:$K$61,7,FALSE) -> 232 | G27: =VLOOKUP($A27,'3M-IS'!$A$8:$K$61,6,FALSE) -> 141 | H27: =VLOOKUP($A27,'3M-IS'!$A$8:$K$61,5,FALSE) -> 320 | I27: =VLOOKUP($A27,'3M-IS'!$A$8:$K$61,4,FALSE) -> 14903 | J27: =VLOOKUP($A27,'3M-IS'!$A$8:$K$61,3,FALSE) -> -1259 | K27: =VLOOKUP($A27,'3M-IS'!$A$8:$K$61,2,FALSE) -> -521 | L27: =-SUM(L28:L32) -> 0 | M27: =-SUM(M28:M32) -> 0 | N27: =-SUM(N28:N32) -> 0 | O27: =-SUM(O28:O32) -> 0 | P27: =-SUM(P28:P32) -> 0 | Q27: =-SUM(Q28:Q32) -> 0 | R27: =-SUM(R28:R32) -> 0 | S27: =-SUM(S28:S32) -> 0 | ... V27: =-SUM(V28:V32) -> 0
A28: ='3M-IS'!A26 -> Impairments | B28: =VLOOKUP($A28,'3M-IS'!$A$8:$K$61,11,FALSE) -> 0 | C28: =VLOOKUP($A28,'3M-IS'!$A$8:$K$61,10,FALSE) -> 0 | D28: =VLOOKUP($A28,'3M-IS'!$A$8:$K$61,9,FALSE) -> 0 | E28: =VLOOKUP($A28,'3M-IS'!$A$8:$K$61,8,FALSE) -> 0 | F28: =VLOOKUP($A28,'3M-IS'!$A$8:$K$61,7,FALSE) -> 0 | G28: =VLOOKUP($A28,'3M-IS'!$A$8:$K$61,6,FALSE) -> 0 | H28: =VLOOKUP($A28,'3M-IS'!$A$8:$K$61,5,FALSE) -> 271 | I28: =VLOOKUP($A28,'3M-IS'!$A$8:$K$61,4,FALSE) -> 0 | J28: =VLOOKUP($A28,'3M-IS'!$A$8:$K$61,3,FALSE) -> 0 | K28: =VLOOKUP($A28,'3M-IS'!$A$8:$K$61,2,FALSE) -> 0 | L28: 0 | M28: 0 | N28: 0 | O28: 0 | P28: 0 | Q28: 0 | R28: 0 | S28: 0 | T28: 0 | U28: 0 | V28: 0
A29: ='3M-IS'!A27 -> Goodwill | B29: =VLOOKUP($A29,'3M-IS'!$A$8:$K$61,11,FALSE) -> 0 | C29: =VLOOKUP($A29,'3M-IS'!$A$8:$K$61,10,FALSE) -> 0 | D29: =VLOOKUP($A29,'3M-IS'!$A$8:$K$61,9,FALSE) -> 0 | E29: =VLOOKUP($A29,'3M-IS'!$A$8:$K$61,8,FALSE) -> 0 | F29: =VLOOKUP($A29,'3M-IS'!$A$8:$K$61,7,FALSE) -> 0 | G29: =VLOOKUP($A29,'3M-IS'!$A$8:$K$61,6,FALSE) -> 0 | H29: =VLOOKUP($A29,'3M-IS'!$A$8:$K$61,5,FALSE) -> 271 | I29: =VLOOKUP($A29,'3M-IS'!$A$8:$K$61,4,FALSE) -> 0 | J29: =VLOOKUP($A29,'3M-IS'!$A$8:$K$61,3,FALSE) -> 0 | K29: =VLOOKUP($A29,'3M-IS'!$A$8:$K$61,2,FALSE) -> 0 | L29: 0 | M29: 0 | N29: 0 | O29: 0 | P29: 0 | Q29: 0 | R29: 0 | S29: 0 | T29: 0 | U29: 0 | V29: 0
A30: ='3M-IS'!A28 -> Restructuring Expense | B30: =VLOOKUP($A30,'3M-IS'!$A$8:$K$61,11,FALSE) -> 0 | C30: =VLOOKUP($A30,'3M-IS'!$A$8:$K$61,10,FALSE) -> 146 | D30: =VLOOKUP($A30,'3M-IS'!$A$8:$K$61,9,FALSE) -> 137 | E30: =VLOOKUP($A30,'3M-IS'!$A$8:$K$61,8,FALSE) -> 444 | F30: =VLOOKUP($A30,'3M-IS'!$A$8:$K$61,7,FALSE) -> 250 | G30: =VLOOKUP($A30,'3M-IS'!$A$8:$K$61,6,FALSE) -> 124 | H30: =VLOOKUP($A30,'3M-IS'!$A$8:$K$61,5,FALSE) -> 18 | I30: =VLOOKUP($A30,'3M-IS'!$A$8:$K$61,4,FALSE) -> 415 | J30: =VLOOKUP($A30,'3M-IS'!$A$8:$K$61,3,FALSE) -> 187 | K30: =VLOOKUP($A30,'3M-IS'!$A$8:$K$61,2,FALSE) -> 21 | L30: 0 | M30: 0 | N30: 0 | O30: 0 | P30: 0 | Q30: 0 | R30: 0 | S30: 0 | T30: 0 | U30: 0 | V30: 0
A31: ='3M-IS'!A29 -> Legal Claim Expense | B31: =VLOOKUP($A31,'3M-IS'!$A$8:$K$61,11,FALSE) -> 0 | C31: =VLOOKUP($A31,'3M-IS'!$A$8:$K$61,10,FALSE) -> 0 | D31: =VLOOKUP($A31,'3M-IS'!$A$8:$K$61,9,FALSE) -> 897 | E31: =VLOOKUP($A31,'3M-IS'!$A$8:$K$61,8,FALSE) -> 762 | F31: =VLOOKUP($A31,'3M-IS'!$A$8:$K$61,7,FALSE) -> 17 | G31: =VLOOKUP($A31,'3M-IS'!$A$8:$K$61,6,FALSE) -> 0 | H31: =VLOOKUP($A31,'3M-IS'!$A$8:$K$61,5,FALSE) -> 0 | I31: =VLOOKUP($A31,'3M-IS'!$A$8:$K$61,4,FALSE) -> 14500 | J31: =VLOOKUP($A31,'3M-IS'!$A$8:$K$61,3,FALSE) -> 87 | K31: =VLOOKUP($A31,'3M-IS'!$A$8:$K$61,2,FALSE) -> 0 | L31: 0 | M31: 0 | N31: 0 | O31: 0 | P31: 0 | Q31: 0 | R31: 0 | S31: 0 | T31: 0 | U31: 0 | V31: 0
A32: ='3M-IS'!A30 -> Unrealized Valuation Gain/Loss | B32: =VLOOKUP($A32,'3M-IS'!$A$8:$K$61,11,FALSE) -> -8 | C32: =VLOOKUP($A32,'3M-IS'!$A$8:$K$61,10,FALSE) -> -123 | D32: =VLOOKUP($A32,'3M-IS'!$A$8:$K$61,9,FALSE) -> -94 | E32: =VLOOKUP($A32,'3M-IS'!$A$8:$K$61,8,FALSE) -> 7 | F32: =VLOOKUP($A32,'3M-IS'!$A$8:$K$61,7,FALSE) -> 45 | G32: =VLOOKUP($A32,'3M-IS'!$A$8:$K$61,6,FALSE) -> -6 | H32: =VLOOKUP($A32,'3M-IS'!$A$8:$K$61,5,FALSE) -> -31 | I32: =VLOOKUP($A32,'3M-IS'!$A$8:$K$61,4,FALSE) -> 12 | J32: =VLOOKUP($A32,'3M-IS'!$A$8:$K$61,3,FALSE) -> 1533 | K32: =VLOOKUP($A32,'3M-IS'!$A$8:$K$61,2,FALSE) -> 542 | L32: 0 | M32: 0 | N32: 0 | O32: 0 | P32: 0 | Q32: 0 | R32: 0 | S32: 0 | T32: 0 | U32: 0 | V32: 0
A33: ='3M-IS'!A31 -> Investments | B33: =VLOOKUP($A33,'3M-IS'!$A$8:$K$61,11,FALSE) -> 0 | C33: =VLOOKUP($A33,'3M-IS'!$A$8:$K$61,10,FALSE) -> 0 | D33: =VLOOKUP($A33,'3M-IS'!$A$8:$K$61,9,FALSE) -> 0 | E33: =VLOOKUP($A33,'3M-IS'!$A$8:$K$61,8,FALSE) -> 0 | F33: =VLOOKUP($A33,'3M-IS'!$A$8:$K$61,7,FALSE) -> 0 | G33: =VLOOKUP($A33,'3M-IS'!$A$8:$K$61,6,FALSE) -> 0 | H33: =VLOOKUP($A33,'3M-IS'!$A$8:$K$61,5,FALSE) -> 0 | I33: =VLOOKUP($A33,'3M-IS'!$A$8:$K$61,4,FALSE) -> 0 | J33: =VLOOKUP($A33,'3M-IS'!$A$8:$K$61,3,FALSE) -> 1564 | K33: =VLOOKUP($A33,'3M-IS'!$A$8:$K$61,2,FALSE) -> 402 | L33: =K33 -> 402 | M33: =L33 -> 402 | N33: =M33 -> 402 | O33: =N33 -> 402 | P33: =O33 -> 402 | Q33: =P33 -> 402 | R33: =Q33 -> 402 | S33: =R33 -> 402 | ... V33: =U33 -> 402
A34: ='3M-IS'!A32 -> Hedges/Derivatives | B34: =VLOOKUP($A34,'3M-IS'!$A$8:$K$61,11,FALSE) -> -8 | C34: =VLOOKUP($A34,'3M-IS'!$A$8:$K$61,10,FALSE) -> -123 | D34: =VLOOKUP($A34,'3M-IS'!$A$8:$K$61,9,FALSE) -> -94 | E34: =VLOOKUP($A34,'3M-IS'!$A$8:$K$61,8,FALSE) -> 7 | F34: =VLOOKUP($A34,'3M-IS'!$A$8:$K$61,7,FALSE) -> 45 | G34: =VLOOKUP($A34,'3M-IS'!$A$8:$K$61,6,FALSE) -> -6 | H34: =VLOOKUP($A34,'3M-IS'!$A$8:$K$61,5,FALSE) -> -31 | I34: =VLOOKUP($A34,'3M-IS'!$A$8:$K$61,4,FALSE) -> 12 | J34: =VLOOKUP($A34,'3M-IS'!$A$8:$K$61,3,FALSE) -> -31 | K34: =VLOOKUP($A34,'3M-IS'!$A$8:$K$61,2,FALSE) -> 140 | L34: =K34 -> 140 | M34: =L34 -> 140 | N34: =M34 -> 140 | O34: =N34 -> 140 | P34: =O34 -> 140 | Q34: =P34 -> 140 | R34: =Q34 -> 140 | S34: =R34 -> 140 | ... V34: =U34 -> 140
A35: ='3M-IS'!A33 -> Excpl Chrgs - Others | B35: =VLOOKUP($A35,'3M-IS'!$A$8:$K$61,11,FALSE) -> 0 | C35: =VLOOKUP($A35,'3M-IS'!$A$8:$K$61,10,FALSE) -> 96 | D35: =VLOOKUP($A35,'3M-IS'!$A$8:$K$61,9,FALSE) -> 0 | E35: =VLOOKUP($A35,'3M-IS'!$A$8:$K$61,8,FALSE) -> 0 | F35: =VLOOKUP($A35,'3M-IS'!$A$8:$K$61,7,FALSE) -> 10 | G35: =VLOOKUP($A35,'3M-IS'!$A$8:$K$61,6,FALSE) -> 11 | H35: =VLOOKUP($A35,'3M-IS'!$A$8:$K$61,5,FALSE) -> 0 | I35: =VLOOKUP($A35,'3M-IS'!$A$8:$K$61,4,FALSE) -> 0 | J35: =VLOOKUP($A35,'3M-IS'!$A$8:$K$61,3,FALSE) -> 0 | K35: =VLOOKUP($A35,'3M-IS'!$A$8:$K$61,2,FALSE) -> 0 | L35: =K35 -> 0 | M35: =L35 -> 0 | N35: =M35 -> 0 | O35: =N35 -> 0 | P35: =O35 -> 0 | Q35: =P35 -> 0 | R35: =Q35 -> 0 | S35: =R35 -> 0 | ... V35: =U35 -> 0
A36: ='3M-IS'!A34 -> Restructuring of Debt | B36: =VLOOKUP($A36,'3M-IS'!$A$8:$K$61,11,FALSE) -> 0 | C36: =VLOOKUP($A36,'3M-IS'!$A$8:$K$61,10,FALSE) -> 96 | D36: =VLOOKUP($A36,'3M-IS'!$A$8:$K$61,9,FALSE) -> 0 | E36: =VLOOKUP($A36,'3M-IS'!$A$8:$K$61,8,FALSE) -> 0 | F36: =VLOOKUP($A36,'3M-IS'!$A$8:$K$61,7,FALSE) -> 10 | G36: =VLOOKUP($A36,'3M-IS'!$A$8:$K$61,6,FALSE) -> 11 | H36: =VLOOKUP($A36,'3M-IS'!$A$8:$K$61,5,FALSE) -> 0 | I36: =VLOOKUP($A36,'3M-IS'!$A$8:$K$61,4,FALSE) -> 0 | J36: =VLOOKUP($A36,'3M-IS'!$A$8:$K$61,3,FALSE) -> 0 | K36: =VLOOKUP($A36,'3M-IS'!$A$8:$K$61,2,FALSE) -> 0 | L36: =K36 -> 0 | M36: =L36 -> 0 | N36: =M36 -> 0 | O36: =N36 -> 0 | P36: =O36 -> 0 | Q36: =P36 -> 0 | R36: =Q36 -> 0 | S36: =R36 -> 0 | ... V36: =U36 -> 0
A37: ='3M-IS'!A35 -> Pretax Income | B37: =VLOOKUP($A37,'3M-IS'!$A$8:$K$61,11,FALSE) -> 7053 | C37: =VLOOKUP($A37,'3M-IS'!$A$8:$K$61,10,FALSE) -> 7548 | D37: =VLOOKUP($A37,'3M-IS'!$A$8:$K$61,9,FALSE) -> 7000 | E37: =VLOOKUP($A37,'3M-IS'!$A$8:$K$61,8,FALSE) -> 5712 | F37: =VLOOKUP($A37,'3M-IS'!$A$8:$K$61,7,FALSE) -> 6795 | G37: =VLOOKUP($A37,'3M-IS'!$A$8:$K$61,6,FALSE) -> 7204 | H37: =VLOOKUP($A37,'3M-IS'!$A$8:$K$61,5,FALSE) -> 6392 | I37: =VLOOKUP($A37,'3M-IS'!$A$8:$K$61,4,FALSE) -> -11271 | J37: =VLOOKUP($A37,'3M-IS'!$A$8:$K$61,3,FALSE) -> 4819 | K37: =VLOOKUP($A37,'3M-IS'!$A$8:$K$61,2,FALSE) -> 4213 | L37: =L14+L21+L27-L24 -> 4705.8266 | M37: =M14+M21+M27-M24 -> 5216.552 | N37: =N14+N21+N27-N24 -> 5847.1999 | O37: =O14+O21+O27-O24 -> 6467.4697 | P37: =P14+P21+P27-P24 -> 7150.4088 | Q37: =Q14+Q21+Q27-Q24 -> 7771.7012 | R37: =R14+R21+R27-R24 -> 8435.4805 | S37: =S14+S21+S27-S24 -> 9130.0407 | ... V37: =V14+V21+V27-V24 -> 11408.853 | X37: =K37/$K$4 -> 0.16887125 | Y37: EBT Margin
A38: ='3M-IS'!A36 -> Income Taxes | B38: =VLOOKUP($A38,'3M-IS'!$A$8:$K$61,11,FALSE) -> 1995 | C38: =VLOOKUP($A38,'3M-IS'!$A$8:$K$61,10,FALSE) -> 2679 | D38: =VLOOKUP($A38,'3M-IS'!$A$8:$K$61,9,FALSE) -> 1637 | E38: =VLOOKUP($A38,'3M-IS'!$A$8:$K$61,8,FALSE) -> 1130 | F38: =VLOOKUP($A38,'3M-IS'!$A$8:$K$61,7,FALSE) -> 1337 | G38: =VLOOKUP($A38,'3M-IS'!$A$8:$K$61,6,FALSE) -> 1285 | H38: =VLOOKUP($A38,'3M-IS'!$A$8:$K$61,5,FALSE) -> 612 | I38: =VLOOKUP($A38,'3M-IS'!$A$8:$K$61,4,FALSE) -> -2867 | J38: =VLOOKUP($A38,'3M-IS'!$A$8:$K$61,3,FALSE) -> 804 | K38: =VLOOKUP($A38,'3M-IS'!$A$8:$K$61,2,FALSE) -> 1003 | L38: =L37*L16 -> 988.2236 | M38: =M37*M16 -> 1095.4759 | N38: =N37*N16 -> 1227.912 | O38: =O37*O16 -> 1358.1686 | P38: =P37*P16 -> 1501.5859 | Q38: =Q37*Q16 -> 1632.0573 | R38: =R37*R16 -> 1771.4509 | S38: =S37*S16 -> 1917.3085 | ... V38: =V37*V16 -> 2395.8591 | X38: =K38/$K$4 -> 0.040203624
A39: ='3M-IS'!A37 -> Income Taxes - Current Domestic | B39: =VLOOKUP($A39,'3M-IS'!$A$8:$K$61,11,FALSE) -> 1267 | C39: =VLOOKUP($A39,'3M-IS'!$A$8:$K$61,10,FALSE) -> 1704 | D39: =VLOOKUP($A39,'3M-IS'!$A$8:$K$61,9,FALSE) -> 983 | E39: =VLOOKUP($A39,'3M-IS'!$A$8:$K$61,8,FALSE) -> 593 | F39: =VLOOKUP($A39,'3M-IS'!$A$8:$K$61,7,FALSE) -> 843 | G39: =VLOOKUP($A39,'3M-IS'!$A$8:$K$61,6,FALSE) -> 860 | H39: =VLOOKUP($A39,'3M-IS'!$A$8:$K$61,5,FALSE) -> 681 | I39: =VLOOKUP($A39,'3M-IS'!$A$8:$K$61,4,FALSE) -> 340 | J39: =VLOOKUP($A39,'3M-IS'!$A$8:$K$61,3,FALSE) -> -81 | K39: =VLOOKUP($A39,'3M-IS'!$A$8:$K$61,2,FALSE) -> -12 | X39: =K39/$K$4 -> -0.00048100048
A40: ='3M-IS'!A38 -> Income Taxes - Current Foreign | B40: =VLOOKUP($A40,'3M-IS'!$A$8:$K$61,11,FALSE) -> 733 | C40: =VLOOKUP($A40,'3M-IS'!$A$8:$K$61,10,FALSE) -> 722 | D40: =VLOOKUP($A40,'3M-IS'!$A$8:$K$61,9,FALSE) -> 763 | E40: =VLOOKUP($A40,'3M-IS'!$A$8:$K$61,8,FALSE) -> 673 | F40: =VLOOKUP($A40,'3M-IS'!$A$8:$K$61,7,FALSE) -> 632 | G40: =VLOOKUP($A40,'3M-IS'!$A$8:$K$61,6,FALSE) -> 597 | H40: =VLOOKUP($A40,'3M-IS'!$A$8:$K$61,5,FALSE) -> 621 | I40: =VLOOKUP($A40,'3M-IS'!$A$8:$K$61,4,FALSE) -> 494 | J40: =VLOOKUP($A40,'3M-IS'!$A$8:$K$61,3,FALSE) -> 583 | K40: =VLOOKUP($A40,'3M-IS'!$A$8:$K$61,2,FALSE) -> 597 | X40: =K40/$K$4 -> 0.023929774
A41: ='3M-IS'!A39 -> Income Taxes - Deferred Domestic | B41: =VLOOKUP($A41,'3M-IS'!$A$8:$K$61,11,FALSE) -> 6 | C41: =VLOOKUP($A41,'3M-IS'!$A$8:$K$61,10,FALSE) -> 177 | D41: =VLOOKUP($A41,'3M-IS'!$A$8:$K$61,9,FALSE) -> -55 | E41: =VLOOKUP($A41,'3M-IS'!$A$8:$K$61,8,FALSE) -> -58 | F41: =VLOOKUP($A41,'3M-IS'!$A$8:$K$61,7,FALSE) -> -61 | G41: =VLOOKUP($A41,'3M-IS'!$A$8:$K$61,6,FALSE) -> -244 | H41: =VLOOKUP($A41,'3M-IS'!$A$8:$K$61,5,FALSE) -> -688 | I41: =VLOOKUP($A41,'3M-IS'!$A$8:$K$61,4,FALSE) -> -3579 | J41: =VLOOKUP($A41,'3M-IS'!$A$8:$K$61,3,FALSE) -> 329 | K41: =VLOOKUP($A41,'3M-IS'!$A$8:$K$61,2,FALSE) -> 328 | X41: =K41/$K$4 -> 0.013147346
A42: ='3M-IS'!A40 -> Income Taxes - Deferred Foreign | B42: =VLOOKUP($A42,'3M-IS'!$A$8:$K$61,11,FALSE) -> -11 | C42: =VLOOKUP($A42,'3M-IS'!$A$8:$K$61,10,FALSE) -> 76 | D42: =VLOOKUP($A42,'3M-IS'!$A$8:$K$61,9,FALSE) -> -54 | E42: =VLOOKUP($A42,'3M-IS'!$A$8:$K$61,8,FALSE) -> -78 | F42: =VLOOKUP($A42,'3M-IS'!$A$8:$K$61,7,FALSE) -> -77 | G42: =VLOOKUP($A42,'3M-IS'!$A$8:$K$61,6,FALSE) -> 72 | H42: =VLOOKUP($A42,'3M-IS'!$A$8:$K$61,5,FALSE) -> -2 | I42: =VLOOKUP($A42,'3M-IS'!$A$8:$K$61,4,FALSE) -> -122 | J42: =VLOOKUP($A42,'3M-IS'!$A$8:$K$61,3,FALSE) -> -27 | K42: =VLOOKUP($A42,'3M-IS'!$A$8:$K$61,2,FALSE) -> 90 | X42: =K42/$K$4 -> 0.0036075036
A43: ='3M-IS'!A41 -> Equity in Earnings of Affiliates | B43: =VLOOKUP($A43,'3M-IS'!$A$8:$K$61,11,FALSE) -> 0 | C43: =VLOOKUP($A43,'3M-IS'!$A$8:$K$61,10,FALSE) -> 0 | D43: =VLOOKUP($A43,'3M-IS'!$A$8:$K$61,9,FALSE) -> 0 | E43: =VLOOKUP($A43,'3M-IS'!$A$8:$K$61,8,FALSE) -> 0 | F43: =VLOOKUP($A43,'3M-IS'!$A$8:$K$61,7,FALSE) -> -5 | G43: =VLOOKUP($A43,'3M-IS'!$A$8:$K$61,6,FALSE) -> 10 | H43: =VLOOKUP($A43,'3M-IS'!$A$8:$K$61,5,FALSE) -> 11 | I43: =VLOOKUP($A43,'3M-IS'!$A$8:$K$61,4,FALSE) -> 18 | J43: =VLOOKUP($A43,'3M-IS'!$A$8:$K$61,3,FALSE) -> 9 | K43: =VLOOKUP($A43,'3M-IS'!$A$8:$K$61,2,FALSE) -> 52 | L43: 0 | M43: =L43 -> 0 | N43: =M43 -> 0 | O43: =N43 -> 0 | P43: =O43 -> 0 | Q43: =P43 -> 0 | R43: =Q43 -> 0 | S43: =R43 -> 0 | T43: =S43 -> 0 | ... V43: =U43 -> 0
A44: ='3M-IS'!A42 -> Consolidated Net Income | B44: =VLOOKUP($A44,'3M-IS'!$A$8:$K$61,11,FALSE) -> 5058 | C44: =VLOOKUP($A44,'3M-IS'!$A$8:$K$61,10,FALSE) -> 4869 | D44: =VLOOKUP($A44,'3M-IS'!$A$8:$K$61,9,FALSE) -> 5363 | E44: =VLOOKUP($A44,'3M-IS'!$A$8:$K$61,8,FALSE) -> 4582 | F44: =VLOOKUP($A44,'3M-IS'!$A$8:$K$61,7,FALSE) -> 5453 | G44: =VLOOKUP($A44,'3M-IS'!$A$8:$K$61,6,FALSE) -> 5929 | H44: =VLOOKUP($A44,'3M-IS'!$A$8:$K$61,5,FALSE) -> 5791 | I44: =VLOOKUP($A44,'3M-IS'!$A$8:$K$61,4,FALSE) -> -8386 | J44: =VLOOKUP($A44,'3M-IS'!$A$8:$K$61,3,FALSE) -> 4024 | K44: =VLOOKUP($A44,'3M-IS'!$A$8:$K$61,2,FALSE) -> 3262 | L44: =L37-L38+L43 -> 3717.6031 | M44: =M37-M38+M43 -> 4121.0761 | N44: =N37-N38+N43 -> 4619.2879 | O44: =O37-O38+O43 -> 5109.3011 | P44: =P37-P38+P43 -> 5648.823 | Q44: =Q37-Q38+Q43 -> 6139.644 | R44: =R37-R38+R43 -> 6664.0296 | S44: =S37-S38+S43 -> 7212.7321 | ... V44: =V37-V38+V43 -> 9012.9939 | X44: =K44/$K$4 -> 0.13075196
A45: ='3M-IS'!A43 -> Minority Interest | B45: =VLOOKUP($A45,'3M-IS'!$A$8:$K$61,11,FALSE) -> 8 | C45: =VLOOKUP($A45,'3M-IS'!$A$8:$K$61,10,FALSE) -> 11 | D45: =VLOOKUP($A45,'3M-IS'!$A$8:$K$61,9,FALSE) -> 14 | E45: =VLOOKUP($A45,'3M-IS'!$A$8:$K$61,8,FALSE) -> 12 | F45: =VLOOKUP($A45,'3M-IS'!$A$8:$K$61,7,FALSE) -> 4 | G45: =VLOOKUP($A45,'3M-IS'!$A$8:$K$61,6,FALSE) -> 8 | H45: =VLOOKUP($A45,'3M-IS'!$A$8:$K$61,5,FALSE) -> 14 | I45: =VLOOKUP($A45,'3M-IS'!$A$8:$K$61,4,FALSE) -> 16 | J45: =VLOOKUP($A45,'3M-IS'!$A$8:$K$61,3,FALSE) -> 15 | K45: =VLOOKUP($A45,'3M-IS'!$A$8:$K$61,2,FALSE) -> 12 | L45: =K45 -> 12 | M45: =L45 -> 12 | N45: =M45 -> 12 | O45: =N45 -> 12 | P45: =O45 -> 12 | Q45: =P45 -> 12 | R45: =Q45 -> 12 | S45: =R45 -> 12 | ... V45: =U45 -> 12 | X45: =K45/$K$4 -> 0.00048100048
A46: ='3M-IS'!A44 -> Net Income | B46: =VLOOKUP($A46,'3M-IS'!$A$8:$K$61,11,FALSE) -> 5050 | C46: =VLOOKUP($A46,'3M-IS'!$A$8:$K$61,10,FALSE) -> 4858 | D46: =VLOOKUP($A46,'3M-IS'!$A$8:$K$61,9,FALSE) -> 5349 | E46: =VLOOKUP($A46,'3M-IS'!$A$8:$K$61,8,FALSE) -> 4570 | F46: =VLOOKUP($A46,'3M-IS'!$A$8:$K$61,7,FALSE) -> 5449 | G46: =VLOOKUP($A46,'3M-IS'!$A$8:$K$61,6,FALSE) -> 5921 | H46: =VLOOKUP($A46,'3M-IS'!$A$8:$K$61,5,FALSE) -> 5777 | I46: =VLOOKUP($A46,'3M-IS'!$A$8:$K$61,4,FALSE) -> -8402 | J46: =VLOOKUP($A46,'3M-IS'!$A$8:$K$61,3,FALSE) -> 4009 | K46: =VLOOKUP($A46,'3M-IS'!$A$8:$K$61,2,FALSE) -> 3250 | L46: =L44-L45 -> 3705.6031 | M46: =M44-M45 -> 4109.0761 | N46: =N44-N45 -> 4607.2879 | O46: =O44-O45 -> 5097.3011 | P46: =P44-P45 -> 5636.823 | Q46: =Q44-Q45 -> 6127.644 | R46: =R44-R45 -> 6652.0296 | S46: =S44-S45 -> 7200.7321 | ... V46: =V44-V45 -> 9000.9939 | X46: =K46/$K$4 -> 0.13027096 | Y46: NIM
A47: ='3M-IS'!A45 -> Discontinued Operations | B47: =VLOOKUP($A47,'3M-IS'!$A$8:$K$61,11,FALSE) -> 0 | C47: =VLOOKUP($A47,'3M-IS'!$A$8:$K$61,10,FALSE) -> 0 | D47: =VLOOKUP($A47,'3M-IS'!$A$8:$K$61,9,FALSE) -> 0 | E47: =VLOOKUP($A47,'3M-IS'!$A$8:$K$61,8,FALSE) -> 0 | F47: =VLOOKUP($A47,'3M-IS'!$A$8:$K$61,7,FALSE) -> 0 | G47: =VLOOKUP($A47,'3M-IS'!$A$8:$K$61,6,FALSE) -> 0 | H47: =VLOOKUP($A47,'3M-IS'!$A$8:$K$61,5,FALSE) -> 0 | I47: =VLOOKUP($A47,'3M-IS'!$A$8:$K$61,4,FALSE) -> 1407 | J47: =VLOOKUP($A47,'3M-IS'!$A$8:$K$61,3,FALSE) -> 164 | K47: =VLOOKUP($A47,'3M-IS'!$A$8:$K$61,2,FALSE) -> 0 | L47: 0 | M47: 0 | N47: 0 | O47: 0 | P47: 0 | Q47: 0 | R47: 0 | S47: 0 | T47: 0 | U47: 0 | V47: 0 | X47: =K47/$K$4 -> 0
A48: ='3M-IS'!A46 -> Net Income available to Common | B48: =VLOOKUP($A48,'3M-IS'!$A$8:$K$61,11,FALSE) -> 5050 | C48: =VLOOKUP($A48,'3M-IS'!$A$8:$K$61,10,FALSE) -> 4858 | D48: =VLOOKUP($A48,'3M-IS'!$A$8:$K$61,9,FALSE) -> 5349 | E48: =VLOOKUP($A48,'3M-IS'!$A$8:$K$61,8,FALSE) -> 4570 | F48: =VLOOKUP($A48,'3M-IS'!$A$8:$K$61,7,FALSE) -> 5449 | G48: =VLOOKUP($A48,'3M-IS'!$A$8:$K$61,6,FALSE) -> 5921 | H48: =VLOOKUP($A48,'3M-IS'!$A$8:$K$61,5,FALSE) -> 5777 | I48: =VLOOKUP($A48,'3M-IS'!$A$8:$K$61,4,FALSE) -> -6995 | J48: =VLOOKUP($A48,'3M-IS'!$A$8:$K$61,3,FALSE) -> 4173 | K48: =VLOOKUP($A48,'3M-IS'!$A$8:$K$61,2,FALSE) -> 3250 | L48: =L46 -> 3705.6031 | M48: =M46 -> 4109.0761 | N48: =N46 -> 4607.2879 | O48: =O46 -> 5097.3011 | P48: =P46 -> 5636.823 | Q48: =Q46 -> 6127.644 | R48: =R46 -> 6652.0296 | S48: =S46 -> 7200.7321 | ... V48: =V46 -> 9000.9939 | X48: =K48/$K$4 -> 0.13027096
A49: ='3M-IS'!A47 -> Per Share
A50: ='3M-IS'!A49 -> EPS (basic) | B50: =VLOOKUP($A50,'3M-IS'!$A$8:$K$61,11,FALSE) -> 8.35 | C50: =VLOOKUP($A50,'3M-IS'!$A$8:$K$61,10,FALSE) -> 8.13 | D50: =VLOOKUP($A50,'3M-IS'!$A$8:$K$61,9,FALSE) -> 9.09 | E50: =VLOOKUP($A50,'3M-IS'!$A$8:$K$61,8,FALSE) -> 7.9203 | F50: =VLOOKUP($A50,'3M-IS'!$A$8:$K$61,7,FALSE) -> 9.4339 | G50: =VLOOKUP($A50,'3M-IS'!$A$8:$K$61,6,FALSE) -> 10.2262 | H50: =VLOOKUP($A50,'3M-IS'!$A$8:$K$61,5,FALSE) -> 10.2067 | I50: =VLOOKUP($A50,'3M-IS'!$A$8:$K$61,4,FALSE) -> -12.6286 | J50: =VLOOKUP($A50,'3M-IS'!$A$8:$K$61,3,FALSE) -> 7.5762 | K50: =VLOOKUP($A50,'3M-IS'!$A$8:$K$61,2,FALSE) -> 6.0476 | L50: =L48/L51 -> 6.8954281 | M50: =M48/M51 -> 7.6462153 | N50: =N48/N51 -> 8.5732935 | O50: =O48/O51 -> 9.4851155 | P50: =P48/P51 -> 10.489064 | Q50: =Q48/Q51 -> 11.402389 | R50: =R48/R51 -> 12.378172 | S50: =S48/S51 -> 13.399204 | ... V50: =V48/V51 -> 16.749151
A51: ='3M-IS'!A50 -> Basic Shares Outstanding | B51: =VLOOKUP($A51,'3M-IS'!$A$8:$K$61,11,FALSE) -> 604.7 | C51: =VLOOKUP($A51,'3M-IS'!$A$8:$K$61,10,FALSE) -> 597.5 | D51: =VLOOKUP($A51,'3M-IS'!$A$8:$K$61,9,FALSE) -> 588.5 | E51: =VLOOKUP($A51,'3M-IS'!$A$8:$K$61,8,FALSE) -> 577 | F51: =VLOOKUP($A51,'3M-IS'!$A$8:$K$61,7,FALSE) -> 577.6 | G51: =VLOOKUP($A51,'3M-IS'!$A$8:$K$61,6,FALSE) -> 579 | H51: =VLOOKUP($A51,'3M-IS'!$A$8:$K$61,5,FALSE) -> 566 | I51: =VLOOKUP($A51,'3M-IS'!$A$8:$K$61,4,FALSE) -> 553.9 | J51: =VLOOKUP($A51,'3M-IS'!$A$8:$K$61,3,FALSE) -> 550.8 | K51: =VLOOKUP($A51,'3M-IS'!$A$8:$K$61,2,FALSE) -> 537.4 | L51: =K51 -> 537.4 | M51: =L51 -> 537.4 | N51: =M51 -> 537.4 | O51: =N51 -> 537.4 | P51: =O51 -> 537.4 | Q51: =P51 -> 537.4 | R51: =Q51 -> 537.4 | S51: =R51 -> 537.4 | ... V51: =U51 -> 537.4
A52: ='3M-IS'!A51 -> Total Shares Outstanding | B52: =VLOOKUP($A52,'3M-IS'!$A$8:$K$61,11,FALSE) -> 596.72628 | C52: =VLOOKUP($A52,'3M-IS'!$A$8:$K$61,10,FALSE) -> 594.88424 | D52: =VLOOKUP($A52,'3M-IS'!$A$8:$K$61,9,FALSE) -> 576.57517 | E52: =VLOOKUP($A52,'3M-IS'!$A$8:$K$61,8,FALSE) -> 575.18484 | F52: =VLOOKUP($A52,'3M-IS'!$A$8:$K$61,7,FALSE) -> 577.74964 | G52: =VLOOKUP($A52,'3M-IS'!$A$8:$K$61,6,FALSE) -> 571.84548 | H52: =VLOOKUP($A52,'3M-IS'!$A$8:$K$61,5,FALSE) -> 549.2451 | I52: =VLOOKUP($A52,'3M-IS'!$A$8:$K$61,4,FALSE) -> 552.58114 | J52: =VLOOKUP($A52,'3M-IS'!$A$8:$K$61,3,FALSE) -> 539.4703 | K52: =VLOOKUP($A52,'3M-IS'!$A$8:$K$61,2,FALSE) -> 530.27913 | L52: =K52 -> 530.27913 | M52: =L52 -> 530.27913 | N52: =M52 -> 530.27913 | O52: =N52 -> 530.27913 | P52: =O52 -> 530.27913 | Q52: =P52 -> 530.27913 | R52: =Q52 -> 530.27913 | S52: =R52 -> 530.27913 | ... V52: =U52 -> 530.27913
A53: ='3M-IS'!A52 -> EPS (diluted) | B53: =VLOOKUP($A53,'3M-IS'!$A$8:$K$61,11,FALSE) -> 8.16 | C53: =VLOOKUP($A53,'3M-IS'!$A$8:$K$61,10,FALSE) -> 7.93 | D53: =VLOOKUP($A53,'3M-IS'!$A$8:$K$61,9,FALSE) -> 8.89 | E53: =VLOOKUP($A53,'3M-IS'!$A$8:$K$61,8,FALSE) -> 7.8106 | F53: =VLOOKUP($A53,'3M-IS'!$A$8:$K$61,7,FALSE) -> 9.3593 | G53: =VLOOKUP($A53,'3M-IS'!$A$8:$K$61,6,FALSE) -> 10.1162 | H53: =VLOOKUP($A53,'3M-IS'!$A$8:$K$61,5,FALSE) -> 10.1779 | I53: =VLOOKUP($A53,'3M-IS'!$A$8:$K$61,4,FALSE) -> -12.6286 | J53: =VLOOKUP($A53,'3M-IS'!$A$8:$K$61,3,FALSE) -> 7.5543 | K53: =VLOOKUP($A53,'3M-IS'!$A$8:$K$61,2,FALSE) -> 6.0041 | L53: =L48/L54 -> 6.8457474 | M53: =M48/M54 -> 7.5911253 | N53: =N48/N54 -> 8.511524 | O53: =O48/O54 -> 9.4167764 | P53: =P48/P54 -> 10.413492 | Q53: =Q48/Q54 -> 11.320236 | R53: =R48/R54 -> 12.288989 | S53: =S48/S54 -> 13.302664 | ... V53: =V48/V54 -> 16.628476
A54: ='3M-IS'!A53 -> Diluted Shares Outstanding | B54: =VLOOKUP($A54,'3M-IS'!$A$8:$K$61,11,FALSE) -> 618.7 | C54: =VLOOKUP($A54,'3M-IS'!$A$8:$K$61,10,FALSE) -> 612.7 | D54: =VLOOKUP($A54,'3M-IS'!$A$8:$K$61,9,FALSE) -> 602 | E54: =VLOOKUP($A54,'3M-IS'!$A$8:$K$61,8,FALSE) -> 585.1 | F54: =VLOOKUP($A54,'3M-IS'!$A$8:$K$61,7,FALSE) -> 582.2 | G54: =VLOOKUP($A54,'3M-IS'!$A$8:$K$61,6,FALSE) -> 585.3 | H54: =VLOOKUP($A54,'3M-IS'!$A$8:$K$61,5,FALSE) -> 567.6 | I54: =VLOOKUP($A54,'3M-IS'!$A$8:$K$61,4,FALSE) -> 553.9 | J54: =VLOOKUP($A54,'3M-IS'!$A$8:$K$61,3,FALSE) -> 552.4 | K54: =VLOOKUP($A54,'3M-IS'!$A$8:$K$61,2,FALSE) -> 541.3 | L54: =K54 -> 541.3 | M54: =L54 -> 541.3 | N54: =M54 -> 541.3 | O54: =N54 -> 541.3 | P54: =O54 -> 541.3 | Q54: =P54 -> 541.3 | R54: =Q54 -> 541.3 | S54: =R54 -> 541.3 | ... V54: =U54 -> 541.3
A55: ='3M-IS'!A54 -> Total Shares Outstanding | B55: =VLOOKUP($A55,'3M-IS'!$A$8:$K$61,11,FALSE) -> 596.72628 | C55: =VLOOKUP($A55,'3M-IS'!$A$8:$K$61,10,FALSE) -> 594.88424 | D55: =VLOOKUP($A55,'3M-IS'!$A$8:$K$61,9,FALSE) -> 576.57517 | E55: =VLOOKUP($A55,'3M-IS'!$A$8:$K$61,8,FALSE) -> 575.18484 | F55: =VLOOKUP($A55,'3M-IS'!$A$8:$K$61,7,FALSE) -> 577.74964 | G55: =VLOOKUP($A55,'3M-IS'!$A$8:$K$61,6,FALSE) -> 571.84548 | H55: =VLOOKUP($A55,'3M-IS'!$A$8:$K$61,5,FALSE) -> 549.2451 | I55: =VLOOKUP($A55,'3M-IS'!$A$8:$K$61,4,FALSE) -> 552.58114 | J55: =VLOOKUP($A55,'3M-IS'!$A$8:$K$61,3,FALSE) -> 539.4703 | K55: =VLOOKUP($A55,'3M-IS'!$A$8:$K$61,2,FALSE) -> 530.27913 | L55: =K55 -> 530.27913 | M55: =L55 -> 530.27913 | N55: =M55 -> 530.27913 | O55: =N55 -> 530.27913 | P55: =O55 -> 530.27913 | Q55: =P55 -> 530.27913 | R55: =Q55 -> 530.27913 | S55: =R55 -> 530.27913 | ... V55: =U55 -> 530.27913
A56: ='3M-IS'!A56 -> Dividends per Share | B56: =VLOOKUP($A56,'3M-IS'!$A$8:$K$61,11,FALSE) -> 4.44 | C56: =VLOOKUP($A56,'3M-IS'!$A$8:$K$61,10,FALSE) -> 4.7 | D56: =VLOOKUP($A56,'3M-IS'!$A$8:$K$61,9,FALSE) -> 5.44 | E56: =VLOOKUP($A56,'3M-IS'!$A$8:$K$61,8,FALSE) -> 5.76 | F56: =VLOOKUP($A56,'3M-IS'!$A$8:$K$61,7,FALSE) -> 5.88 | G56: =VLOOKUP($A56,'3M-IS'!$A$8:$K$61,6,FALSE) -> 5.92 | H56: =VLOOKUP($A56,'3M-IS'!$A$8:$K$61,5,FALSE) -> 5.96 | I56: =VLOOKUP($A56,'3M-IS'!$A$8:$K$61,4,FALSE) -> 6 | J56: =VLOOKUP($A56,'3M-IS'!$A$8:$K$61,3,FALSE) -> 3.61 | K56: =VLOOKUP($A56,'3M-IS'!$A$8:$K$61,2,FALSE) -> 2.92 | L56: =0.78*4 -> 3.12 | M56: =M57*M46/M55 -> 3.4597115 | N56: =N57*N46/N55 -> 3.87919 | O56: =O57*O46/O55 -> 4.2917655 | P56: =P57*P46/P55 -> 4.7460258 | Q56: =Q57*Q46/Q55 -> 5.1592815 | R56: =R57*R46/R55 -> 5.6007975 | S56: =S57*S46/S55 -> 6.0627876 | T56: =T57*T46/T55 -> 6.5471049 | ... V56: =V57*V46/V55 -> 7.5785508 | Y56: 2026 DPS anchored to 3M's Q1 2026 declared dividend ($0.78/qtr × 4 = $3.12); thereafter the implied ~47% payout ratio is held constant, so DPS grows with forecast net income.
A57: ='3M-IS'!A57 -> Payout Ratio | B57: =VLOOKUP($A57,'3M-IS'!$A$8:$K$61,11,FALSE) -> 54.411765 | C57: =VLOOKUP($A57,'3M-IS'!$A$8:$K$61,10,FALSE) -> 59.2686 | D57: =VLOOKUP($A57,'3M-IS'!$A$8:$K$61,9,FALSE) -> 61.192351 | E57: =VLOOKUP($A57,'3M-IS'!$A$8:$K$61,8,FALSE) -> 73.745935 | F57: =VLOOKUP($A57,'3M-IS'!$A$8:$K$61,7,FALSE) -> 62.825211 | G57: =VLOOKUP($A57,'3M-IS'!$A$8:$K$61,6,FALSE) -> 58.519998 | H57: =VLOOKUP($A57,'3M-IS'!$A$8:$K$61,5,FALSE) -> 58.558249 | I57: =VLOOKUP($A57,'3M-IS'!$A$8:$K$61,4,FALSE) -> 0 | J57: =VLOOKUP($A57,'3M-IS'!$A$8:$K$61,3,FALSE) -> 47.787353 | K57: =VLOOKUP($A57,'3M-IS'!$A$8:$K$61,2,FALSE) -> 48.633434 | L57: =L56*L55/L46 -> 0.44647818 | M57: =L57 -> 0.44647818 | N57: =M57 -> 0.44647818 | O57: =N57 -> 0.44647818 | P57: =O57 -> 0.44647818 | Q57: =P57 -> 0.44647818 | R57: =Q57 -> 0.44647818 | S57: =R57 -> 0.44647818 | T57: =S57 -> 0.44647818 | ... V57: =U57 -> 0.44647818
A58: ='3M-IS'!A58 -> EBITDA
A59: ='3M-IS'!A59 -> EBITDA | B59: =SUM(B60:B61) -> 8493 | C59: =SUM(C60:C61) -> 8770 | D59: =SUM(D60:D61) -> 9262 | E59: =SUM(E60:E61) -> 8567 | F59: =SUM(F60:F61) -> 8868 | G59: =SUM(G60:G61) -> 9441 | H59: =SUM(H60:H61) -> 5904 | I59: =SUM(I60:I61) -> 5480 | ... V59: =SUM(V60:V61) -> 12093.749 | X59: =K59/$K$4 -> 0.24202341 | Y59: EBITDA margin
A60: ='3M-IS'!A60 -> EBIT | B60: =VLOOKUP($A60,'3M-IS'!$A$8:$K$61,11,FALSE) -> 7019 | C60: =VLOOKUP($A60,'3M-IS'!$A$8:$K$61,10,FALSE) -> 7226 | D60: =VLOOKUP($A60,'3M-IS'!$A$8:$K$61,9,FALSE) -> 7774 | E60: =VLOOKUP($A60,'3M-IS'!$A$8:$K$61,8,FALSE) -> 6974 | F60: =VLOOKUP($A60,'3M-IS'!$A$8:$K$61,7,FALSE) -> 6957 | G60: =VLOOKUP($A60,'3M-IS'!$A$8:$K$61,6,FALSE) -> 7526 | H60: =VLOOKUP($A60,'3M-IS'!$A$8:$K$61,5,FALSE) -> 4073 | I60: =VLOOKUP($A60,'3M-IS'!$A$8:$K$61,4,FALSE) -> 4047 | J60: =VLOOKUP($A60,'3M-IS'!$A$8:$K$61,3,FALSE) -> 4931 | K60: =VLOOKUP($A60,'3M-IS'!$A$8:$K$61,2,FALSE) -> 4730 | L60: =L14 -> 4815.276 | M60: =M14 -> 5325.7691 | N60: =N14 -> 5864.4639 | O60: =O14 -> 6433.0683 | P60: =P14 -> 7033.365 | Q60: =Q14 -> 7580.7389 | R60: =R14 -> 8152.0687 | S60: =S14 -> 8748.4437 | ... V60: =V14 -> 10699.257
A61: ='3M-IS'!A61 -> Depreciation & Amortization Expense | B61: =VLOOKUP($A61,'3M-IS'!$A$8:$K$61,11,FALSE) -> 1474 | C61: =VLOOKUP($A61,'3M-IS'!$A$8:$K$61,10,FALSE) -> 1544 | D61: =VLOOKUP($A61,'3M-IS'!$A$8:$K$61,9,FALSE) -> 1488 | E61: =VLOOKUP($A61,'3M-IS'!$A$8:$K$61,8,FALSE) -> 1593 | F61: =VLOOKUP($A61,'3M-IS'!$A$8:$K$61,7,FALSE) -> 1911 | G61: =VLOOKUP($A61,'3M-IS'!$A$8:$K$61,6,FALSE) -> 1915 | H61: =VLOOKUP($A61,'3M-IS'!$A$8:$K$61,5,FALSE) -> 1831 | I61: =VLOOKUP($A61,'3M-IS'!$A$8:$K$61,4,FALSE) -> 1433 | J61: =VLOOKUP($A61,'3M-IS'!$A$8:$K$61,3,FALSE) -> 1224 | K61: =VLOOKUP($A61,'3M-IS'!$A$8:$K$61,2,FALSE) -> 1308 | L61: =L7 -> 1311.1303 | M61: =M7 -> 1308.9515 | N61: =N7 -> 1309.434 | O61: =O7 -> 1312.5255 | P61: =P7 -> 1318.1821 | Q61: =Q7 -> 1326.3682 | R61: =R7 -> 1336.4154 | S61: =S7 -> 1348.2837 | ... V61: =V7 -> 1394.4927
A64: Revenue/Sales
A65: Segment wise | B65: 2016 | C65: 2017 | D65: =C65+1 -> 2018 | E65: =D65+1 -> 2019 | F65: =E65+1 -> 2020 | G65: =F65+1 -> 2021 | H65: =G65+1 -> 2022 | I65: =H65+1 -> 2023 | J65: =I65+1 -> 2024 | K65: =J65+1 -> 2025 | ... V65: =U65+1 -> 2036
A66: Safety & Industrial | B66: =VLOOKUP($A66,'Segment wise'!$A$5:$K$14,2,FALSE) -> - | C66: =VLOOKUP($A66,'Segment wise'!$A$5:$K$14,3,FALSE) -> - | D66: =VLOOKUP($A66,'Segment wise'!$A$5:$K$14,4,FALSE) -> - | E66: =VLOOKUP($A66,'Segment wise'!$A$5:$K$14,5,FALSE) -> 11607 | F66: =VLOOKUP($A66,'Segment wise'!$A$5:$K$14,6,FALSE) -> 11767 | G66: =VLOOKUP($A66,'Segment wise'!$A$5:$K$14,7,FALSE) -> 12880 | H66: =VLOOKUP($A66,'Segment wise'!$A$5:$K$14,8,FALSE) -> 11604 | I66: =VLOOKUP($A66,'Segment wise'!$A$5:$K$14,9,FALSE) -> 10956 | J66: =VLOOKUP($A66,'Segment wise'!$A$5:$K$14,10,FALSE) -> 10961 | K66: =VLOOKUP($A66,'Segment wise'!$A$5:$K$14,11,FALSE) -> 11384 | L66: =K66*(1+L75) -> 11725.52 | M66: =L66*(1+M75) -> 12194.541 | N66: =M66*(1+N75) -> 12682.322 | O66: =N66*(1+O75) -> 13189.615 | P66: =O66*(1+P75) -> 13717.2 | Q66: =P66*(1+Q75) -> 14128.716 | R66: =Q66*(1+R75) -> 14552.577 | S66: =R66*(1+S75) -> 14989.155 | ... V66: =U66*(1+V75) -> 16379.054
A67: Transportation & Electronics | B67: =VLOOKUP($A67,'Segment wise'!$A$5:$K$14,2,FALSE) -> - | C67: =VLOOKUP($A67,'Segment wise'!$A$5:$K$14,3,FALSE) -> - | D67: =VLOOKUP($A67,'Segment wise'!$A$5:$K$14,4,FALSE) -> - | E67: =VLOOKUP($A67,'Segment wise'!$A$5:$K$14,5,FALSE) -> 9602 | F67: =VLOOKUP($A67,'Segment wise'!$A$5:$K$14,6,FALSE) -> 8827 | G67: =VLOOKUP($A67,'Segment wise'!$A$5:$K$14,7,FALSE) -> 9769 | H67: =VLOOKUP($A67,'Segment wise'!$A$5:$K$14,8,FALSE) -> 8902 | I67: =VLOOKUP($A67,'Segment wise'!$A$5:$K$14,9,FALSE) -> 8501 | J67: =VLOOKUP($A67,'Segment wise'!$A$5:$K$14,10,FALSE) -> 8380 | K67: =VLOOKUP($A67,'Segment wise'!$A$5:$K$14,11,FALSE) -> 8272 | L67: =K67*(1+L76) -> 8520.16 | M67: =L67*(1+M76) -> 8860.9664 | N67: =M67*(1+N76) -> 9215.4051 | O67: =N67*(1+O76) -> 9584.0213 | P67: =O67*(1+P76) -> 9967.3821 | Q67: =P67*(1+Q76) -> 10266.404 | R67: =Q67*(1+R76) -> 10574.396 | S67: =R67*(1+S76) -> 10891.628 | ... V67: =U67*(1+V76) -> 11901.575
A68: Consumer | B68: =VLOOKUP($A68,'Segment wise'!$A$5:$K$14,2,FALSE) -> 4482 | C68: =VLOOKUP($A68,'Segment wise'!$A$5:$K$14,3,FALSE) -> 4589 | D68: =VLOOKUP($A68,'Segment wise'!$A$5:$K$14,4,FALSE) -> 4796 | E68: =VLOOKUP($A68,'Segment wise'!$A$5:$K$14,5,FALSE) -> 5089 | F68: =VLOOKUP($A68,'Segment wise'!$A$5:$K$14,6,FALSE) -> 5336 | G68: =VLOOKUP($A68,'Segment wise'!$A$5:$K$14,7,FALSE) -> 5856 | H68: =VLOOKUP($A68,'Segment wise'!$A$5:$K$14,8,FALSE) -> 5298 | I68: =VLOOKUP($A68,'Segment wise'!$A$5:$K$14,9,FALSE) -> 5026 | J68: =VLOOKUP($A68,'Segment wise'!$A$5:$K$14,10,FALSE) -> 4931 | K68: =VLOOKUP($A68,'Segment wise'!$A$5:$K$14,11,FALSE) -> 4920 | L68: =K68*(1+L77) -> 5067.6 | M68: =L68*(1+M77) -> 5270.304 | N68: =M68*(1+N77) -> 5481.1162 | O68: =N68*(1+O77) -> 5700.3608 | P68: =O68*(1+P77) -> 5928.3752 | Q68: =P68*(1+Q77) -> 6106.2265 | R68: =Q68*(1+R77) -> 6289.4133 | S68: =R68*(1+S77) -> 6478.0957 | ... V68: =U68*(1+V77) -> 7078.7901
A69: Revenue from the above 3 segments | B69: =SUM(B66:B68) -> 4482 | C69: =SUM(C66:C68) -> 4589 | D69: =SUM(D66:D68) -> 4796 | E69: =SUM(E66:E68) -> 26298 | F69: =SUM(F66:F68) -> 25930 | G69: =SUM(G66:G68) -> 28505 | H69: =SUM(H66:H68) -> 25804 | I69: =SUM(I66:I68) -> 24483 | ... V69: =SUM(V66:V68) -> 35359.42
A70: Historical Segments | B70: =VLOOKUP($A70,'Segment wise'!$A$5:$K$14,2,FALSE) -> 26326 | C70: =VLOOKUP($A70,'Segment wise'!$A$5:$K$14,3,FALSE) -> 28031 | D70: =VLOOKUP($A70,'Segment wise'!$A$5:$K$14,4,FALSE) -> 30587 | E70: =VLOOKUP($A70,'Segment wise'!$A$5:$K$14,5,FALSE) -> 7431 | F70: =VLOOKUP($A70,'Segment wise'!$A$5:$K$14,6,FALSE) -> 8345 | G70: =VLOOKUP($A70,'Segment wise'!$A$5:$K$14,7,FALSE) -> 9050 | H70: =VLOOKUP($A70,'Segment wise'!$A$5:$K$14,8,FALSE) -> 8421 | I70: =VLOOKUP($A70,'Segment wise'!$A$5:$K$14,9,FALSE)*0 -> 0 | J70: =VLOOKUP($A70,'Segment wise'!$A$5:$K$14,10,FALSE) -> 32 | K70: =VLOOKUP($A70,'Segment wise'!$A$5:$K$14,11,FALSE) -> -
A71: Corporate & Other | I71: 127 | J71: =303-32 -> 271 | K71: 372 | Y71: For simplicity purposes, no corporate amd other income assumed in future years
A72: Total Company Revenue | B72: =B69+B70 -> 30808 | C72: =C69+C70 -> 32620 | D72: =D69+D70 -> 35383 | E72: =E69+E70 -> 33729 | F72: =F69+F70 -> 34275 | G72: =G69+G70 -> 37555 | H72: =H69+H70 -> 34225 | I72: =SUM(I69:I71) -> 24610 | J72: =SUM(J69:J71) -> 24575 | K72: =K69+K71 -> 24948 | L72: =L69+L70+L71 -> 25313.28 | M72: =M69+M70+M71 -> 26325.811 | N72: =N69+N70+N71 -> 27378.844 | O72: =O69+O70+O71 -> 28473.997 | P72: =P69+P70+P71 -> 29612.957 | Q72: =Q69+Q70+Q71 -> 30501.346 | R72: =R69+R70+R71 -> 31416.386 | S72: =S69+S70+S71 -> 32358.878 | ... V72: =V69+V70+V71 -> 35359.42
A73: For the purposes of uniformity, revenues from healthcare have been excluded to arrive at a growth rate.
A74: Growth rate
A75: Safety & Industrial | C75: 0 | D75: 0 | E75: 0 | F75: =F66/E66-1 -> 0.013784785 | G75: =G66/F66-1 -> 0.094586556 | H75: =H66/G66-1 -> -0.099068323 | I75: =I66/H66-1 -> -0.055842813 | J75: =J66/I66-1 -> 0.00045637094 | K75: =K66/J66-1 -> 0.038591369 | L75: =3% -> 0.03 | M75: 0.04 | N75: 0.04 | O75: 0.04 | P75: 0.04 | Q75: 0.03 | R75: 0.03 | S75: 0.03 | T75: 0.03 | U75: 0.03 | V75: 0.03 | Y75: 2026 (3%): In line with management's low-single-digit organic-growth guidance. 3M is absorbing the heaviest litigation cash outflows (PFAS/PWS and Combat Arms) and completing
A76: Transportation & Electronics | C76: 0 | D76: 0 | E76: 0 | F76: =F67/E67-1 -> -0.080712352 | G76: =G67/F67-1 -> 0.10671802 | H76: =H67/G67-1 -> -0.088750128 | I76: =I67/H67-1 -> -0.045046057 | J76: =J67/I67-1 -> -0.01423362 | K76: =K67/J67-1 -> -0.012887828 | L76: =3% -> 0.03 | M76: 0.04 | N76: 0.04 | O76: 0.04 | P76: 0.04 | Q76: 0.03 | R76: 0.03 | S76: 0.03 | T76: 0.03 | U76: 0.03 | V76: 0.03 | Y76: The Solventum separation, both of which limit growth reinvestment and management bandwidth.
A77: Consumer | C77: =C68/B68-1 -> 0.023873271 | D77: =D68/C68-1 -> 0.045107867 | E77: =E68/D68-1 -> 0.061092577 | F77: =F68/E68-1 -> 0.048536058 | G77: =G68/F68-1 -> 0.097451274 | H77: =H68/G68-1 -> -0.095286885 | I77: =I68/H68-1 -> -0.051340128 | J77: =J68/I68-1 -> -0.018901711 | K77: =K68/J68-1 -> -0.0022307848 | L77: =3% -> 0.03 | M77: 0.04 | N77: 0.04 | O77: 0.04 | P77: 0.04 | Q77: 0.03 | R77: 0.03 | S77: 0.03 | T77: 0.03 | U77: 0.03 | V77: 0.03 | Y77: 2027–2030 (4%): A modest re-acceleration as the peak settlement payments taper, the streamlined post-spinoff portfolio stabilizes, and reinvestment capacity is restored.
Y78: 2031–2036 (3% → 2.5%): Normalization toward the long-run terminal rate as the company matures into a stable, GDP-paced industrial.
A81: COGS analysis
A83: COGS w/o D&A | B83: =B6 -> 13659 | C83: =C6 -> 14451 | D83: =D6 -> 15087 | E83: =E6 -> 15237 | F83: =F6 -> 14670 | G83: =G6 -> 16828 | H83: =H6 -> 17432 | I83: =I6 -> 13604 | ... K83: =K6 -> 13764 | L83: =L84*L69 -> 13965.528 | M83: =M84*M69 -> 14392.52 | N83: =N84*N69 -> 14831.326 | O83: =O84*O69 -> 15282.209 | P83: =P84*P69 -> 15745.433 | Q83: =Q84*Q69 -> 16065.289 | R83: =R84*R69 -> 16390.166 | S83: =S84*S69 -> 16720.077 | ... V83: =V84*V69 -> 17740.088
A84: % of revenue | B84: =B83/B4 -> 0.45365173 | C84: =C83/C4 -> 0.45648672 | D84: =D83/D4 -> 0.46046086 | E84: =E83/E4 -> 0.47414115 | F84: =F83/F4 -> 0.45581655 | G84: =G83/G4 -> 0.47597228 | H84: =H83/H4 -> 0.50927576 | I84: =I83/I4 -> 0.55278342 | ... K84: =K83/K4 -> 0.55170755 | L84: =K84 -> 0.55170755 | M84: =L84-0.5% -> 0.54670755 | N84: =M84-0.5% -> 0.54170755 | O84: =N84-0.5% -> 0.53670755 | P84: =O84-0.5% -> 0.53170755 | Q84: =P84-0.5% -> 0.52670755 | R84: =Q84-0.5% -> 0.52170755 | S84: =R84-0.5% -> 0.51670755 | T84: =S84-0.5% -> 0.51170755 | ... V84: =U84-0.5% -> 0.50170755
A86: SG&A | B86: =B11/B4 -> 0.26427314 | C86: =C11/C4 -> 0.26648135 | D86: =D11/D4 -> 0.25685945 | E86: =E11/E4 -> 0.25927309 | F86: =F11/F4 -> 0.2686428 | G86: =G11/G4 -> 0.25699335 | H86: =H11/H4 -> 0.31823892 | I86: =I11/I4 -> 0.22454287 | ... K86: =K11/K4 -> 0.20626904
A87: SG&A for 2026 | B87: =K86 -> 0.20626904
A88: SG&A for 2027 and beyond | M88: =B87-0.5% -> 0.20126904 | N88: =M88-0.5% -> 0.19626904 | O88: =N88-0.5% -> 0.19126904 | P88: =O88-0.5% -> 0.18626904 | Q88: =P88-0.5% -> 0.18126904 | R88: =Q88-0.5% -> 0.17626904 | S88: =R88-0.5% -> 0.17126904 | T88: =S88-0.5% -> 0.16626904 | U88: =T88-0.5% -> 0.16126904 | V88: =U88-0.5% -> 0.15626904 | Y88: Based on amnagement guidance on Cost Rationalization.
A89: SG&A forecated | B89: =B11 -> 7957 | C89: =C11 -> 8436 | D89: =D11 -> 8416 | E89: =E11 -> 8332 | F89: =F11 -> 8646 | G89: =G11 -> 9086 | H89: =H11 -> 10893 | I89: =I11 -> 5526 | ... K89: =K11 -> 5146 | L89: =$B$87*L72 -> 5221.346 | M89: =M88*M72 -> 5298.5707 | N89: =N88*N72 -> 5373.6193 | O89: =O88*O72 -> 5446.1941 | P89: =P88*P72 -> 5515.9771 | Q89: =Q88*Q72 -> 5528.9497 | R89: =R88*R72 -> 5537.7363 | S89: =S88*S72 -> 5542.074 | T89: =T88*T72 -> 5541.688 | ... V89: =V88*V72 -> 5525.5826
A91: R&D costs | B91: =B12 -> 1735 | C91: =C12 -> 1862 | D91: =D12 -> 1816 | E91: =E12 -> 1874 | F91: =F12 -> 1862 | G91: =G12 -> 1977 | H91: =H12 -> 1856 | I91: =I12 -> 1123 | ... K91: =K12 -> 1169 | L91: =$B$94*L4 -> 1265.664 | M91: =$B$94*M4 -> 1316.2906 | N91: =$B$94*N4 -> 1368.9422 | O91: =$B$94*O4 -> 1423.6999 | P91: =$B$94*P4 -> 1480.6479 | Q91: =$B$94*Q4 -> 1525.0673 | R91: =$B$94*R4 -> 1570.8193 | S91: =$B$94*S4 -> 1617.9439 | ... V91: =$B$94*V4 -> 1767.971
A92: % of sales | B92: =B91/B4 -> 0.057623966 | C92: =C91/C4 -> 0.058817955 | D92: =D91/D4 -> 0.055424996 | E92: =E91/E4 -> 0.058314663 | F92: =F91/F4 -> 0.057854835 | G92: =G91/G4 -> 0.055918541 | H92: =H91/H4 -> 0.054223027 | I92: =I91/I4 -> 0.045631857 | ... K92: =K91/K4 -> 0.046857464
A93: Average | B93: =AVERAGE(B92:K92) -> 0.053420749
A94: Hardcoded | B94: 0.05
A95: Operating income margin | B95: =B14/B4 -> 0.23311967 | C95: =C14/C4 -> 0.22825915 | D95: =D14/D4 -> 0.23726537 | E95: =E14/E4 -> 0.21701519 | F95: =F14/F4 -> 0.21616331 | G95: =G14/G4 -> 0.21286947 | H95: =H14/H4 -> 0.11899267 | I95: =I14/I4 -> 0.16444535 | ... K95: =K14/K4 -> 0.18959436
A96: Operating margin target | B96: 0.25 | C96: As per the guidance given by the company for 2026, this is adjusted number and not GAAP. For our calculations, we are calculating GAAP numbers.
A98: Property Plant and Equipment Schedule | B98: Company guidance: Planning to become asset light and keep the capex investments amount constant.
A99: Opening PPE | B99: 8515 | C99: =B103 -> 8516 | D99: =C103 -> 8866 | E99: =D103 -> 8738 | F99: =E103 -> 10191 | G99: =F103 -> 10285 | H99: =G103 -> 10287 | I99: =H103 -> 10007 | J99: =I103 -> 8347 | ... V99: =U103 -> 5600.1432
A100: Add: Capex | B100: =-'3M-CFS'!K28 -> 1420 | C100: =-VLOOKUP('3M-CFS'!$A$27,'3M-CFS'!$A$10:$K$58,10, FALSE) -> 1373 | D100: =-VLOOKUP('3M-CFS'!$A$27,'3M-CFS'!$A$10:$K$58,9, FALSE) -> 1577 | E100: =-VLOOKUP('3M-CFS'!$A$27,'3M-CFS'!$A$10:$K$58,8, FALSE) -> 1699 | F100: =-VLOOKUP('3M-CFS'!$A$27,'3M-CFS'!$A$10:$K$58,7, FALSE) -> 1501 | G100: =-VLOOKUP('3M-CFS'!$A$27,'3M-CFS'!$A$10:$K$58,6, FALSE) -> 1603 | H100: =-VLOOKUP('3M-CFS'!$A$27,'3M-CFS'!$A$10:$K$58,5, FALSE) -> 1749 | I100: =-VLOOKUP('3M-CFS'!$A$27,'3M-CFS'!$A$10:$K$58,4, FALSE) -> 1615 | J100: =-VLOOKUP('3M-CFS'!$A$27,'3M-CFS'!$A$10:$K$58,3, FALSE) -> 1181 | K100: =-VLOOKUP('3M-CFS'!$A$27,'3M-CFS'!$A$10:$K$58,2, FALSE) -> 910 | L100: 1100 | M100: =M105*M72 -> 1144 | N100: =N105*N72 -> 1189.76 | O100: =O105*O72 -> 1237.3504 | P100: =P105*P72 -> 1286.8444 | Q100: =Q105*Q72 -> 1325.4497 | R100: =R105*R72 -> 1365.2132 | S100: =S105*S72 -> 1406.1696 | T100: =T105*T72 -> 1448.3547 | ... V100: =V105*V72 -> 1536.5595
A101: Less: Depreciation | B101: =-B8 -> -1212 | C101: =-C8 -> -1306 | D101: =-D8 -> -1239 | E101: =-E8 -> -1252 | F101: =-F8 -> -1374 | G101: =-G8 -> -1386 | H101: =-H8 -> -1333 | I101: =-I8 -> -1306 | ... K101: =-K8 -> -1204 | L101: =-L117 -> -1215.6149 | M101: =-M117 -> -1221.7074 | N101: =-N117 -> -1229.7449 | O101: =-O117 -> -1239.7371 | P101: =-P117 -> -1251.697 | Q101: =-Q117 -> -1265.6403 | R101: =-R117 -> -1280.9463 | S101: =-S117 -> -1297.618 | ... V101: =-V117 -> -1355.8824
A102: FX Disposals | B102: =B103-(SUM(B99:B101)) -> -207 | C102: =C103-(SUM(C99:C101)) -> 283 | D102: =D103-(SUM(D99:D101)) -> -466 | E102: =E103-(SUM(E99:E101)) -> 1006 | F102: =F103-(SUM(F99:F101)) -> -33 | G102: =G103-(SUM(G99:G101)) -> -215 | H102: =H103-(SUM(H99:H101)) -> -696 | I102: =I103-(SUM(I99:I101)) -> -1969 | ... K102: =K103-(SUM(K99:K101)) -> -42 | L102: =L103-(L99+L100+L101) -> -226.56727 | M102: =M103-(M99+M100+M101) -> -227.70279 | N102: =N103-(N99+N100+N101) -> -229.20082 | O102: =O103-(O99+O100+O101) -> -231.06318 | P102: =P103-(P99+P100+P101) -> -233.29226 | Q102: =Q103-(Q99+Q100+Q101) -> -235.89104 | R102: =R103-(R99+R100+R101) -> -238.74378 | S102: =S103-(S99+S100+S101) -> -241.85107 | ... V102: =V103-(V99+V100+V101) -> -252.71043
A103: Ending Net PP&E | B103: ='BS-Reorg'!B19 -> 8516 | C103: ='BS-Reorg'!C19 -> 8866 | D103: ='BS-Reorg'!D19 -> 8738 | E103: ='BS-Reorg'!E19 -> 10191 | F103: ='BS-Reorg'!F19 -> 10285 | G103: ='BS-Reorg'!G19 -> 10287 | H103: ='BS-Reorg'!H19 -> 10007 | I103: ='BS-Reorg'!I19 -> 8347 | ... K103: ='BS-Reorg'!K19 -> 7617 | L103: =L120 -> 7274.8178 | M103: =M120 -> 6969.4075 | N103: =N120 -> 6700.2218 | O103: =O120 -> 6466.7719 | P103: =P120 -> 6268.6271 | Q103: =Q120 -> 6092.5454 | R103: =R120 -> 5938.0686 | S103: =S120 -> 5804.7691 | ... V103: =V120 -> 5528.1099
A105: Capex/Sales ratio | B105: =B100/B4 -> 0.047161978 | C105: =C100/C4 -> 0.043371134 | D105: =D100/D4 -> 0.048130627 | E105: =E100/E4 -> 0.052869057 | F105: =F100/F4 -> 0.046638081 | G105: =G100/G4 -> 0.045340122 | H105: =H100/H4 -> 0.051097023 | I105: =I100/I4 -> 0.06562373 | ... K105: =K100/K4 -> 0.03647587 | L105: =L100/L69 -> 0.043455451 | M105: =L105 -> 0.043455451 | N105: =M105 -> 0.043455451 | O105: =N105 -> 0.043455451 | P105: =O105 -> 0.043455451 | Q105: =P105 -> 0.043455451 | R105: =Q105 -> 0.043455451 | S105: =R105 -> 0.043455451 | T105: =S105 -> 0.043455451 | ... V105: =U105 -> 0.043455451
B106: Capex projected to be $1.1 billion for 2026
A108: Depreciation calculation | J108: 2024 | K108: 2025 | L108: 2026 | M108: 2027 | N108: 2028 | O108: =N108+1 -> 2029 | P108: =O108+1 -> 2030 | Q108: =P108+1 -> 2031 | R108: =Q108+1 -> 2032 | S108: =R108+1 -> 2033 | T108: =S108+1 -> 2034 | U108: =T108+1 -> 2035 | V108: =U108+1 -> 2036
A109: Opening PPE, Gross | B109: 23098 | C109: =B112 -> 23499 | D109: =C112 -> 24914 | E109: =D112 -> 24873 | F109: =E112 -> 26982 | G109: =F112 -> 27514 | H109: =G112 -> 28071 | I109: =H112 -> 26827 | J109: =I112 -> 24151 | ... V109: =U112 -> 27257.854
A110: Capex | B110: =B100 -> 1420 | C110: =C100 -> 1373 | D110: =D100 -> 1577 | E110: =E100 -> 1699 | F110: =F100 -> 1501 | G110: =G100 -> 1603 | H110: =H100 -> 1749 | I110: =I100 -> 1615 | ... V110: =V100 -> 1536.5595
A111: Less: Asset retirement | B111: =B109+B110-B112 -> 1019 | C111: =(C109+C110-C112)*0 -> 0 | D111: =D109+D110-D112 -> 1618 | E111: =(E109+E110-E112)*0 -> 0 | F111: =F109+F110-F112 -> 969 | G111: =G109+G110-G112 -> 1046 | H111: =H109+H110-H112 -> 2993 | I111: =I109+I110-I112 -> 4291 | J111: =J109+J110-J112 -> 1361 | K111: =K109+K110-K112 -> 443 | L111: =$B$115*L109 -> 977.52 | M111: =$B$115*M109 -> 982.4192 | N111: =$B$115*N109 -> 988.88243 | O111: =$B$115*O109 -> 996.91753 | P111: =$B$115*P109 -> 1006.5348 | Q111: =$B$115*Q109 -> 1017.7472 | R111: =$B$115*R109 -> 1030.0553 | S111: =$B$115*S109 -> 1043.4616 | ... V111: =$B$115*V109 -> 1090.3142
A112: Ending Gross PPE | B112: 23499 | C112: ='BS-Reorg'!C20 -> 24914 | D112: ='BS-Reorg'!D20 -> 24873 | E112: ='BS-Reorg'!E20 -> 26982 | F112: ='BS-Reorg'!F20 -> 27514 | G112: ='BS-Reorg'!G20 -> 28071 | H112: ='BS-Reorg'!H20 -> 26827 | I112: ='BS-Reorg'!I20 -> 24151 | J112: ='BS-Reorg'!J20 -> 23971 | K112: ='BS-Reorg'!K20 -> 24438 | L112: =L109+L110-L111 -> 24560.48 | M112: =M109+M110-M111 -> 24722.061 | N112: =N109+N110-N111 -> 24922.938 | O112: =O109+O110-O111 -> 25163.371 | P112: =P109+P110-P111 -> 25443.681 | Q112: =Q109+Q110-Q111 -> 25751.383 | R112: =R109+R110-R111 -> 26086.541 | S112: =S109+S110-S111 -> 26449.249 | ... V112: =V109+V110-V111 -> 27704.099
A113: Depreciation rate | B113: =-B101/(AVERAGE(B109,B112)) -> 0.052020516 | C113: =-C101/(AVERAGE(C109,C112)) -> 0.053952451 | D113: =-D101/(AVERAGE(D109,D112)) -> 0.049772029 | E113: =-E101/(AVERAGE(E109,E112)) -> 0.048288497 | F113: =-F101/(AVERAGE(F109,F112)) -> 0.050425719 | G113: =-G101/(AVERAGE(G109,G112)) -> 0.049869569 | H113: =-H101/(AVERAGE(H109,H112)) -> 0.048562789 | I113: =-I101/(AVERAGE(I109,I112)) -> 0.051237789 | ... K113: =-K101/(AVERAGE(K109,K112)) -> 0.049742816
...

Sheet Litigation related payments
A1: Two settlements currently in progress
A3: 1. PWS settlement with annual payments expected to be completed by 2036 | D3: The source of this information is the 8K filed by 3M on its offical website which has schedules of payment.
A4: Risk free rate in 2023 | B4: 0.0234
A5: Amount | B5: 12.5 | C5: billion | D5: Announced maximum payment | E5: 3M 8-K 22-Jun-2023
A6: PV of amount | B6: 10.3 | C6: billion
A8: Imputed interest payments
A9: PV Accrual: $10,300M ,Total scheduled payments: $11,380M , Effective imputation rate: 2.34% , Payments: 2024 - 2036
A10: Year | B10: Opening Liability | C10: Imputed Interest (Rate × Opening) | D10: Cash Paid (Operating CF) | E10: Closing Liability
A11: 2024 | B11: 10300 | C11: =B11*$B$4 -> 241.02 | D11: 2900 | E11: =ROUND(B11+C11-D11,0) -> 7641
A12: 2025 | B12: 7641 | C12: =B12*$B$4 -> 178.7994 | D12: 1100 | E12: =ROUND(B12+C12-D12,0) -> 6720
A13: 2026 | B13: 6720 | C13: =B13*$B$4 -> 157.248 | D13: 900 | E13: =ROUND(B13+C13-D13,0) -> 5977
A14: 2027 | B14: 5977 | C14: =B14*$B$4 -> 139.8618 | D14: 2600 | E14: =ROUND(B14+C14-D14,0) -> 3517
A15: 2028 | B15: 3517 | C15: =B15*$B$4 -> 82.2978 | D15: 650 | E15: =ROUND(B15+C15-D15,0) -> 2949
A16: 2029 | B16: 2949 | C16: =B16*$B$4 -> 69.0066 | D16: 550 | E16: =ROUND(B16+C16-D16,0) -> 2468
A17: 2030 | B17: 2468 | C17: =B17*$B$4 -> 57.7512 | D17: 500 | E17: =ROUND(B17+C17-D17,0) -> 2026
A18: 2031 | B18: 2026 | C18: =B18*$B$4 -> 47.4084 | D18: 450 | E18: =ROUND(B18+C18-D18,0) -> 1623
A19: 2032 | B19: 1623 | C19: =B19*$B$4 -> 37.9782 | D19: 420 | E19: =ROUND(B19+C19-D19,0) -> 1241
A20: 2033 | B20: 1241 | C20: =B20*$B$4 -> 29.0394 | D20: 380 | E20: =ROUND(B20+C20-D20,0) -> 890
A21: 2034 | B21: 890 | C21: =B21*$B$4 -> 20.826 | D21: 350 | E21: =ROUND(B21+C21-D21,0) -> 561
A22: 2035 | B22: 561 | C22: =B22*$B$4 -> 13.1274 | D22: 300 | E22: =ROUND(B22+C22-D22,0) -> 274
A23: 2036 | B23: 274 | C23: =B23*$B$4 -> 6.4116 | D23: 280 | E23: =ROUND(B23+C23-D23,0) -> 0
A24: TOTALS | C24: =SUM(C11:C23) -> 1080.7758 | D24: =SUM(D11:D23) -> 11380
A25: Rate that amortizes the disclosed $10.3B present-value liability to zero over 3M's scheduled 2024–2036 payments (per 8-K dated
A26: 22-Jun-2023 and Q2-2023 10-Q). Held at the 2023 recognition-date rate per ASC 835-30 (long-term obligations are not remeasured for later rate changes).
A28: 2. Combat Arms Earplugs settlement | C28: 0.0156
A30: Opening PV: ~$5,700M , Nominal: $6,000M , Effective imputation rate: 1.56% , Payments: 2024 - 2029
A31: Year | B31: Opening Liability | C31: Imputed Interest (Rate × Opening) | D31: Cash Paid (Operating CF) | E31: Closing Liability
A32: 2024 | B32: 5700 | C32: =$C$28*B32 -> 88.92 | D32: 1400 | E32: =MAX(0,ROUND(B32+C32-D32,0)) -> 4389
A33: 2025 | B33: 4389 | C33: =$C$28*B33 -> 68.4684 | D33: 900 | E33: =MAX(0,ROUND(B33+C33-D33,0)) -> 3557
A34: 2026 | B34: 3557 | C34: =$C$28*B34 -> 55.4892 | D34: 900 | E34: =MAX(0,ROUND(B34+C34-D34,0)) -> 2712
A35: 2027 | B35: 2712 | C35: =$C$28*B35 -> 42.3072 | D35: 900 | E35: =MAX(0,ROUND(B35+C35-D35,0)) -> 1854
A36: 2028 | B36: 1854 | C36: =$C$28*B36 -> 28.9224 | D36: 900 | E36: =MAX(0,ROUND(B36+C36-D36,0)) -> 983
A37: 2029 | B37: 983 | C37: =$C$28*B37 -> 15.3348 | D37: 1000 | E37: =MAX(0,ROUND(B37+C37-D37,0)) -> 0
A38: TOTALS | C38: =SUM(C32:C37) -> 299.442 | D38: =SUM(D32:D37) -> 6000
B40: 2026 | C40: 2027 | D40: 2028 | E40: 2029 | F40: =E40+1 -> 2030 | G40: =F40+1 -> 2031 | H40: =G40+1 -> 2032 | I40: =H40+1 -> 2033 | J40: =I40+1 -> 2034 | K40: =J40+1 -> 2035 | L40: =K40+1 -> 2036
A41: Total imputed interest expense | B41: =C34+C13 -> 212.7372 | C41: =C35+C14 -> 182.169 | D41: =C36+C15 -> 111.2202 | E41: =C16+C37 -> 84.3414 | F41: =C17 -> 57.7512 | G41: =C18 -> 47.4084 | H41: =C19 -> 37.9782 | I41: =C20 -> 29.0394 | J41: =C21 -> 20.826 | K41: =C22 -> 13.1274 | L41: =C23 -> 6.4116
A43: Amortizes the disclosed ~$5.7B PV liability to zero over the 2024–2029 schedule (FY2023 10-K). Lower than the PWS rate because of the
A44: smaller PV-to-nominal gap over a shorter term.

Sheet BS-Reorg
L1: Explicit forecast period
A2: All figures in millions of U.S. Dollar | B2: 2016 | C2: 2017 | D2: =C2+1 -> 2018 | E2: =D2+1 -> 2019 | F2: =E2+1 -> 2020 | G2: =F2+1 -> 2021 | H2: =G2+1 -> 2022 | I2: =H2+1 -> 2023 | J2: =I2+1 -> 2024 | K2: =J2+1 -> 2025 | L2: 2026 | M2: =L2+1 -> 2027 | N2: =M2+1 -> 2028 | O2: =N2+1 -> 2029 | P2: =O2+1 -> 2030 | Q2: =P2+1 -> 2031 | R2: =Q2+1 -> 2032 | S2: =R2+1 -> 2033 | T2: =S2+1 -> 2034 | ... V2: =U2+1 -> 2036
A4: Cash & Short-Term Investments | B4: =B5+B6 -> 2678 | C4: =C5+C6 -> 4129 | D4: =D5+D6 -> 3233 | E4: =E5+E6 -> 2921 | F4: =F5+F6 -> 5038 | G4: =G5+G6 -> 4765 | H4: =H5+H6 -> 3893 | I4: =I5+I6 -> 5785 | ... K4: =K5+K6 -> 5933 | L4: =L71-(L7+L11+L15+L19+L28+L31+L34+L35) -> 6354.9985 | M4: =M71-(M7+M11+M15+M19+M28+M31+M34+M35) -> 5097.3341 | N4: =N71-(N7+N11+N15+N19+N28+N31+N34+N35) -> 5968.1288 | O4: =O71-(O7+O11+O15+O19+O28+O31+O34+O35) -> 6995.7301 | P4: =P71-(P7+P11+P15+P19+P28+P31+P34+P35) -> 9319.5397 | Q4: =Q71-(Q7+Q11+Q15+Q19+Q28+Q31+Q34+Q35) -> 11955.261 | R4: =R71-(R7+R11+R15+R19+R28+R31+R34+R35) -> 15397.067 | S4: =S71-(S7+S11+S15+S19+S28+S31+S34+S35) -> 19097.038 | ... V4: =V71-(V7+V11+V15+V19+V28+V31+V34+V35) -> 31757.122 | X4: Cash is a plug, excluded from invested capital; valuation uses 2025 cash only (Valuation!K25).
A5: Cash Only | B5: =VLOOKUP($A5,'3M-BS'!$A$12:$K$79,11, FALSE) -> 2398 | C5: =VLOOKUP($A5,'3M-BS'!$A$12:$K$79,10, FALSE) -> 3053 | D5: =VLOOKUP($A5,'3M-BS'!$A$12:$K$79,9, FALSE) -> 2853 | E5: =VLOOKUP($A5,'3M-BS'!$A$12:$K$79,8, FALSE) -> 2353 | F5: =VLOOKUP($A5,'3M-BS'!$A$12:$K$79,7, FALSE) -> 4634 | G5: =VLOOKUP($A5,'3M-BS'!$A$12:$K$79,6, FALSE) -> 4564 | H5: =VLOOKUP($A5,'3M-BS'!$A$12:$K$79,5, FALSE) -> 3655 | I5: =VLOOKUP($A5,'3M-BS'!$A$12:$K$79,4, FALSE) -> 5735 | J5: =VLOOKUP($A5,'3M-BS'!$A$12:$K$79,3, FALSE) -> 5600 | K5: =VLOOKUP($A5,'3M-BS'!$A$12:$K$79,2, FALSE) -> 5235 | L5: =$K$5/$K$4*L4 -> 5607.3516 | M5: =$K$5/$K$4*M4 -> 4497.6477 | N5: =$K$5/$K$4*N4 -> 5265.996 | O5: =$K$5/$K$4*O4 -> 6172.7031 | P5: =$K$5/$K$4*P4 -> 8223.1233 | Q5: =$K$5/$K$4*Q4 -> 10548.76 | R5: =$K$5/$K$4*R4 -> 13585.648 | S5: =$K$5/$K$4*S4 -> 16850.328 | ... V5: =$K$5/$K$4*V4 -> 28020.99 | X5: Unmodeled capital return inflates the projected balance but does not affect intrinsic value.
A6: Total Short Term Investments | B6: =VLOOKUP($A6,'3M-BS'!$A$12:$K$79,11, FALSE) -> 280 | C6: =VLOOKUP($A6,'3M-BS'!$A$12:$K$79,10, FALSE) -> 1076 | D6: =VLOOKUP($A6,'3M-BS'!$A$12:$K$79,9, FALSE) -> 380 | E6: =VLOOKUP($A6,'3M-BS'!$A$12:$K$79,8, FALSE) -> 568 | F6: =VLOOKUP($A6,'3M-BS'!$A$12:$K$79,7, FALSE) -> 404 | G6: =VLOOKUP($A6,'3M-BS'!$A$12:$K$79,6, FALSE) -> 201 | H6: =VLOOKUP($A6,'3M-BS'!$A$12:$K$79,5, FALSE) -> 238 | I6: =VLOOKUP($A6,'3M-BS'!$A$12:$K$79,4, FALSE) -> 50 | J6: =VLOOKUP($A6,'3M-BS'!$A$12:$K$79,3, FALSE) -> 2128 | K6: =VLOOKUP($A6,'3M-BS'!$A$12:$K$79,2, FALSE) -> 698 | L6: =$K$6/$K$5*L4 -> 847.33313 | M6: =$K$6/$K$5*M4 -> 679.64455 | N6: =$K$6/$K$5*N4 -> 795.75051 | O6: =$K$6/$K$5*O4 -> 932.76402 | P6: =$K$6/$K$5*P4 -> 1242.6053 | Q6: =$K$6/$K$5*Q4 -> 1594.0348 | R6: =$K$6/$K$5*R4 -> 2052.9423 | S6: =$K$6/$K$5*S4 -> 2546.2718 | ... V6: =$K$6/$K$5*V4 -> 4234.283
A7: ='3M-BS'!A14 -> Short-Term Receivables | B7: =VLOOKUP($A7,'3M-BS'!$A$12:$K$79,11, FALSE) -> 4392 | C7: =VLOOKUP($A7,'3M-BS'!$A$12:$K$79,10, FALSE) -> 4911 | D7: =VLOOKUP($A7,'3M-BS'!$A$12:$K$79,9, FALSE) -> 5020 | E7: =VLOOKUP($A7,'3M-BS'!$A$12:$K$79,8, FALSE) -> 4791 | F7: =VLOOKUP($A7,'3M-BS'!$A$12:$K$79,7, FALSE) -> 4705 | G7: =VLOOKUP($A7,'3M-BS'!$A$12:$K$79,6, FALSE) -> 4660 | H7: =VLOOKUP($A7,'3M-BS'!$A$12:$K$79,5, FALSE) -> 4532 | I7: =VLOOKUP($A7,'3M-BS'!$A$12:$K$79,4, FALSE) -> 3601 | J7: =VLOOKUP($A7,'3M-BS'!$A$12:$K$79,3, FALSE) -> 3194 | K7: =VLOOKUP($A7,'3M-BS'!$A$12:$K$79,2, FALSE) -> 3533 | L7: =L8 -> 3584.729 | M7: =M8 -> 3728.1181 | N7: =N8 -> 3866.6493 | O7: =O8 -> 4032.3326 | P7: =P8 -> 4193.6259 | Q7: =Q8 -> 4319.4346 | R7: =R8 -> 4436.8619 | S7: =S8 -> 4582.4882 | ... V7: =V8 -> 4993.7272
A8: ='3M-BS'!A15 -> Accounts Receivables, Net | B8: =VLOOKUP($A8,'3M-BS'!$A$12:$K$79,11, FALSE) -> 4392 | C8: =VLOOKUP($A8,'3M-BS'!$A$12:$K$79,10, FALSE) -> 4911 | D8: =VLOOKUP($A8,'3M-BS'!$A$12:$K$79,9, FALSE) -> 5020 | E8: =VLOOKUP($A8,'3M-BS'!$A$12:$K$79,8, FALSE) -> 4791 | F8: =VLOOKUP($A8,'3M-BS'!$A$12:$K$79,7, FALSE) -> 4705 | G8: =VLOOKUP($A8,'3M-BS'!$A$12:$K$79,6, FALSE) -> 4660 | H8: =VLOOKUP($A8,'3M-BS'!$A$12:$K$79,5, FALSE) -> 4532 | I8: =VLOOKUP($A8,'3M-BS'!$A$12:$K$79,4, FALSE) -> 3601 | J8: =VLOOKUP($A8,'3M-BS'!$A$12:$K$79,3, FALSE) -> 3194 | K8: =VLOOKUP($A8,'3M-BS'!$A$12:$K$79,2, FALSE) -> 3533 | L8: =L95 -> 3584.729 | M8: =M95 -> 3728.1181 | N8: =N95 -> 3866.6493 | O8: =O95 -> 4032.3326 | P8: =P95 -> 4193.6259 | Q8: =Q95 -> 4319.4346 | R8: =R95 -> 4436.8619 | S8: =S95 -> 4582.4882 | ... V8: =V95 -> 4993.7272
A9: ='3M-BS'!A16 -> Accounts Receivables, Gross | B9: =VLOOKUP($A9,'3M-BS'!$A$12:$K$79,11, FALSE) -> 4480 | C9: =VLOOKUP($A9,'3M-BS'!$A$12:$K$79,10, FALSE) -> 5014 | D9: =VLOOKUP($A9,'3M-BS'!$A$12:$K$79,9, FALSE) -> 5115 | E9: =VLOOKUP($A9,'3M-BS'!$A$12:$K$79,8, FALSE) -> 4952 | F9: =VLOOKUP($A9,'3M-BS'!$A$12:$K$79,7, FALSE) -> 4938 | G9: =VLOOKUP($A9,'3M-BS'!$A$12:$K$79,6, FALSE) -> 4849 | H9: =VLOOKUP($A9,'3M-BS'!$A$12:$K$79,5, FALSE) -> 4706 | I9: =VLOOKUP($A9,'3M-BS'!$A$12:$K$79,4, FALSE) -> 3663 | J9: =VLOOKUP($A9,'3M-BS'!$A$12:$K$79,3, FALSE) -> 3254 | K9: =VLOOKUP($A9,'3M-BS'!$A$12:$K$79,2, FALSE) -> 3594 | L9: =L8-L10 -> 3645.729 | M9: =M8-M10 -> 3789.1181 | N9: =N8-N10 -> 3927.6493 | O9: =O8-O10 -> 4093.3326 | P9: =P8-P10 -> 4254.6259 | Q9: =Q8-Q10 -> 4380.4346 | R9: =R8-R10 -> 4497.8619 | S9: =S8-S10 -> 4643.4882 | ... V9: =V8-V10 -> 5054.7272
A10: ='3M-BS'!A17 -> Bad Debt/Doubtful Accounts | B10: =VLOOKUP($A10,'3M-BS'!$A$12:$K$79,11, FALSE) -> -88 | C10: =VLOOKUP($A10,'3M-BS'!$A$12:$K$79,10, FALSE) -> -103 | D10: =VLOOKUP($A10,'3M-BS'!$A$12:$K$79,9, FALSE) -> -95 | E10: =VLOOKUP($A10,'3M-BS'!$A$12:$K$79,8, FALSE) -> -161 | F10: =VLOOKUP($A10,'3M-BS'!$A$12:$K$79,7, FALSE) -> -233 | G10: =VLOOKUP($A10,'3M-BS'!$A$12:$K$79,6, FALSE) -> -189 | H10: =VLOOKUP($A10,'3M-BS'!$A$12:$K$79,5, FALSE) -> -174 | I10: =VLOOKUP($A10,'3M-BS'!$A$12:$K$79,4, FALSE) -> -62 | J10: =VLOOKUP($A10,'3M-BS'!$A$12:$K$79,3, FALSE) -> -60 | K10: =VLOOKUP($A10,'3M-BS'!$A$12:$K$79,2, FALSE) -> -61 | L10: =K10 -> -61 | M10: =L10 -> -61 | N10: =M10 -> -61 | O10: =N10 -> -61 | P10: =O10 -> -61 | Q10: =P10 -> -61 | R10: =Q10 -> -61 | S10: =R10 -> -61 | ... V10: =U10 -> -61
A11: ='3M-BS'!A18 -> Inventories | B11: =VLOOKUP($A11,'3M-BS'!$A$12:$K$79,11, FALSE) -> 3385 | C11: =VLOOKUP($A11,'3M-BS'!$A$12:$K$79,10, FALSE) -> 4034 | D11: =VLOOKUP($A11,'3M-BS'!$A$12:$K$79,9, FALSE) -> 4366 | E11: =VLOOKUP($A11,'3M-BS'!$A$12:$K$79,8, FALSE) -> 4134 | F11: =VLOOKUP($A11,'3M-BS'!$A$12:$K$79,7, FALSE) -> 4239 | G11: =VLOOKUP($A11,'3M-BS'!$A$12:$K$79,6, FALSE) -> 4985 | H11: =VLOOKUP($A11,'3M-BS'!$A$12:$K$79,5, FALSE) -> 5372 | I11: =VLOOKUP($A11,'3M-BS'!$A$12:$K$79,4, FALSE) -> 3944 | J11: =VLOOKUP($A11,'3M-BS'!$A$12:$K$79,3, FALSE) -> 3698 | K11: =VLOOKUP($A11,'3M-BS'!$A$12:$K$79,2, FALSE) -> 3661 | L11: =L96 -> 3714.6031 | M11: =M96 -> 3828.176 | N11: =N96 -> 3934.1131 | O11: =O96 -> 4064.819 | P11: =P96 -> 4188.0289 | Q11: =Q96 -> 4273.1055 | R11: =R96 -> 4347.6062 | S11: =S96 -> 4447.2683 | ... V11: =V96 -> 4705.6824
A12: ='3M-BS'!A19 -> Finished Goods | B12: =VLOOKUP($A12,'3M-BS'!$A$12:$K$79,11, FALSE) -> 1629 | C12: =VLOOKUP($A12,'3M-BS'!$A$12:$K$79,10, FALSE) -> 1915 | D12: =VLOOKUP($A12,'3M-BS'!$A$12:$K$79,9, FALSE) -> 2120 | E12: =VLOOKUP($A12,'3M-BS'!$A$12:$K$79,8, FALSE) -> 2003 | F12: =VLOOKUP($A12,'3M-BS'!$A$12:$K$79,7, FALSE) -> 2081 | G12: =VLOOKUP($A12,'3M-BS'!$A$12:$K$79,6, FALSE) -> 2196 | H12: =VLOOKUP($A12,'3M-BS'!$A$12:$K$79,5, FALSE) -> 2497 | I12: =VLOOKUP($A12,'3M-BS'!$A$12:$K$79,4, FALSE) -> 1842 | J12: =VLOOKUP($A12,'3M-BS'!$A$12:$K$79,3, FALSE) -> 1849 | K12: =VLOOKUP($A12,'3M-BS'!$A$12:$K$79,2, FALSE) -> 1744 | L12: =$K$12/$K$11*L$11 -> 1769.535 | M12: =$K$12/$K$11*M$11 -> 1823.6381 | N12: =$K$12/$K$11*N$11 -> 1874.1036 | O12: =$K$12/$K$11*O$11 -> 1936.3683 | P12: =$K$12/$K$11*P$11 -> 1995.0621 | Q12: =$K$12/$K$11*Q$11 -> 2035.5903 | R12: =$K$12/$K$11*R$11 -> 2071.0804 | S12: =$K$12/$K$11*S$11 -> 2118.5566 | ... V12: =$K$12/$K$11*V$11 -> 2241.658
A13: ='3M-BS'!A20 -> Work in Progress | B13: =VLOOKUP($A13,'3M-BS'!$A$12:$K$79,11, FALSE) -> 1039 | C13: =VLOOKUP($A13,'3M-BS'!$A$12:$K$79,10, FALSE) -> 1218 | D13: =VLOOKUP($A13,'3M-BS'!$A$12:$K$79,9, FALSE) -> 1292 | E13: =VLOOKUP($A13,'3M-BS'!$A$12:$K$79,8, FALSE) -> 1194 | F13: =VLOOKUP($A13,'3M-BS'!$A$12:$K$79,7, FALSE) -> 1226 | G13: =VLOOKUP($A13,'3M-BS'!$A$12:$K$79,6, FALSE) -> 1577 | H13: =VLOOKUP($A13,'3M-BS'!$A$12:$K$79,5, FALSE) -> 1606 | I13: =VLOOKUP($A13,'3M-BS'!$A$12:$K$79,4, FALSE) -> 1242 | J13: =VLOOKUP($A13,'3M-BS'!$A$12:$K$79,3, FALSE) -> 1051 | K13: =VLOOKUP($A13,'3M-BS'!$A$12:$K$79,2, FALSE) -> 1126 | L13: =$K13/$K$11*L$11 -> 1142.4865 | M13: =$K13/$K$11*M$11 -> 1177.4177 | N13: =$K13/$K$11*N$11 -> 1210.0004 | O13: =$K13/$K$11*O$11 -> 1250.2011 | P13: =$K13/$K$11*P$11 -> 1288.0963 | Q13: =$K13/$K$11*Q$11 -> 1314.263 | R13: =$K13/$K$11*R$11 -> 1337.1769 | S13: =$K13/$K$11*S$11 -> 1367.8296 | ... V13: =$K13/$K$11*V$11 -> 1447.309
A14: ='3M-BS'!A21 -> Raw Materials | B14: =VLOOKUP($A14,'3M-BS'!$A$12:$K$79,11, FALSE) -> 717 | C14: =VLOOKUP($A14,'3M-BS'!$A$12:$K$79,10, FALSE) -> 901 | D14: =VLOOKUP($A14,'3M-BS'!$A$12:$K$79,9, FALSE) -> 954 | E14: =VLOOKUP($A14,'3M-BS'!$A$12:$K$79,8, FALSE) -> 937 | F14: =VLOOKUP($A14,'3M-BS'!$A$12:$K$79,7, FALSE) -> 932 | G14: =VLOOKUP($A14,'3M-BS'!$A$12:$K$79,6, FALSE) -> 1212 | H14: =VLOOKUP($A14,'3M-BS'!$A$12:$K$79,5, FALSE) -> 1269 | I14: =VLOOKUP($A14,'3M-BS'!$A$12:$K$79,4, FALSE) -> 860 | J14: =VLOOKUP($A14,'3M-BS'!$A$12:$K$79,3, FALSE) -> 798 | K14: =VLOOKUP($A14,'3M-BS'!$A$12:$K$79,2, FALSE) -> 791 | L14: =$K14/$K$11*L$11 -> 802.58155 | M14: =$K14/$K$11*M$11 -> 827.12025 | N14: =$K14/$K$11*N$11 -> 850.00913 | O14: =$K14/$K$11*O$11 -> 878.24961 | P14: =$K14/$K$11*P$11 -> 904.8705 | Q14: =$K14/$K$11*Q$11 -> 923.25224 | R14: =$K14/$K$11*R$11 -> 939.34894 | S14: =$K14/$K$11*S$11 -> 960.88205 | ... V14: =$K14/$K$11*V$11 -> 1016.7153
A15: ='3M-BS'!A22 -> Other Current Assets | B15: =VLOOKUP($A15,'3M-BS'!$A$12:$K$79,11, FALSE) -> 1271 | C15: =VLOOKUP($A15,'3M-BS'!$A$12:$K$79,10, FALSE) -> 1203 | D15: =VLOOKUP($A15,'3M-BS'!$A$12:$K$79,9, FALSE) -> 1090 | E15: =VLOOKUP($A15,'3M-BS'!$A$12:$K$79,8, FALSE) -> 1125 | F15: =VLOOKUP($A15,'3M-BS'!$A$12:$K$79,7, FALSE) -> 1000 | G15: =VLOOKUP($A15,'3M-BS'!$A$12:$K$79,6, FALSE) -> 993 | H15: =VLOOKUP($A15,'3M-BS'!$A$12:$K$79,5, FALSE) -> 891 | I15: =VLOOKUP($A15,'3M-BS'!$A$12:$K$79,4, FALSE) -> 3049 | J15: =VLOOKUP($A15,'3M-BS'!$A$12:$K$79,3, FALSE) -> 1264 | K15: =VLOOKUP($A15,'3M-BS'!$A$12:$K$79,2, FALSE) -> 3260 | L15: =L16+L17 -> 3307.7318 | M15: =M16+M17 -> 3440.0411 | N15: =N16+N17 -> 3577.6427 | O15: =O16+O17 -> 3720.7484 | P15: =P16+P17 -> 3869.5784 | Q15: =Q16+Q17 -> 3985.6657 | R15: =R16+R17 -> 4105.2357 | S15: =S16+S17 -> 4228.3927 | ... V15: =V16+V17 -> 4620.4789
A16: ='3M-BS'!A23 -> Prepaid Expenses | B16: =VLOOKUP($A16,'3M-BS'!$A$12:$K$79,11, FALSE) -> 0 | C16: =VLOOKUP($A16,'3M-BS'!$A$12:$K$79,10, FALSE) -> 937 | D16: =VLOOKUP($A16,'3M-BS'!$A$12:$K$79,9, FALSE) -> 741 | E16: =VLOOKUP($A16,'3M-BS'!$A$12:$K$79,8, FALSE) -> 704 | F16: =VLOOKUP($A16,'3M-BS'!$A$12:$K$79,7, FALSE) -> 675 | G16: =VLOOKUP($A16,'3M-BS'!$A$12:$K$79,6, FALSE) -> 654 | H16: =VLOOKUP($A16,'3M-BS'!$A$12:$K$79,5, FALSE) -> 435 | I16: =VLOOKUP($A16,'3M-BS'!$A$12:$K$79,4, FALSE) -> 344 | J16: =VLOOKUP($A16,'3M-BS'!$A$12:$K$79,3, FALSE) -> 436 | K16: =VLOOKUP($A16,'3M-BS'!$A$12:$K$79,2, FALSE) -> 391 | L16: =$K$16/$K$85*L85 -> 396.72489 | M16: =$K$16/$K$85*M85 -> 412.59388 | N16: =$K$16/$K$85*N85 -> 429.09764 | O16: =$K$16/$K$85*O85 -> 446.26154 | P16: =$K$16/$K$85*P85 -> 464.112 | Q16: =$K$16/$K$85*Q85 -> 478.03537 | R16: =$K$16/$K$85*R85 -> 492.37643 | S16: =$K$16/$K$85*S85 -> 507.14772 | ... V16: =$K$16/$K$85*V85 -> 554.17401
A17: ='3M-BS'!A24 -> Miscellaneous Current Assets | B17: =VLOOKUP($A17,'3M-BS'!$A$12:$K$79,11, FALSE) -> 1271 | C17: =VLOOKUP($A17,'3M-BS'!$A$12:$K$79,10, FALSE) -> 266 | D17: =VLOOKUP($A17,'3M-BS'!$A$12:$K$79,9, FALSE) -> 349 | E17: =VLOOKUP($A17,'3M-BS'!$A$12:$K$79,8, FALSE) -> 421 | F17: =VLOOKUP($A17,'3M-BS'!$A$12:$K$79,7, FALSE) -> 325 | G17: =VLOOKUP($A17,'3M-BS'!$A$12:$K$79,6, FALSE) -> 339 | H17: =VLOOKUP($A17,'3M-BS'!$A$12:$K$79,5, FALSE) -> 456 | I17: =VLOOKUP($A17,'3M-BS'!$A$12:$K$79,4, FALSE) -> 2705 | J17: =VLOOKUP($A17,'3M-BS'!$A$12:$K$79,3, FALSE) -> 828 | K17: =VLOOKUP($A17,'3M-BS'!$A$12:$K$79,2, FALSE) -> 2869 | L17: =$K$17/$K$85*L85 -> 2911.0069 | M17: =$K$17/$K$85*M85 -> 3027.4472 | N17: =$K$17/$K$85*N85 -> 3148.5451 | O17: =$K$17/$K$85*O85 -> 3274.4869 | P17: =$K$17/$K$85*P85 -> 3405.4663 | Q17: =$K$17/$K$85*Q85 -> 3507.6303 | R17: =$K$17/$K$85*R85 -> 3612.8592 | S17: =$K$17/$K$85*S85 -> 3721.245 | ... V17: =$K$17/$K$85*V85 -> 4066.3049
A19: ='3M-BS'!A26 -> Net Property, Plant & Equipment | B19: =VLOOKUP($A19,'3M-BS'!$A$12:$K$79,11, FALSE) -> 8516 | C19: =VLOOKUP($A19,'3M-BS'!$A$12:$K$79,10, FALSE) -> 8866 | D19: =VLOOKUP($A19,'3M-BS'!$A$12:$K$79,9, FALSE) -> 8738 | E19: =VLOOKUP($A19,'3M-BS'!$A$12:$K$79,8, FALSE) -> 10191 | F19: =VLOOKUP($A19,'3M-BS'!$A$12:$K$79,7, FALSE) -> 10285 | G19: =VLOOKUP($A19,'3M-BS'!$A$12:$K$79,6, FALSE) -> 10287 | H19: =VLOOKUP($A19,'3M-BS'!$A$12:$K$79,5, FALSE) -> 10007 | I19: =VLOOKUP($A19,'3M-BS'!$A$12:$K$79,4, FALSE) -> 8347 | J19: =VLOOKUP($A19,'3M-BS'!$A$12:$K$79,3, FALSE) -> 7953 | K19: =VLOOKUP($A19,'3M-BS'!$A$12:$K$79,2, FALSE) -> 7617 | L19: ='IS-Reorg'!L103 -> 7274.8178 | M19: ='IS-Reorg'!M103 -> 6969.4075 | N19: ='IS-Reorg'!N103 -> 6700.2218 | O19: ='IS-Reorg'!O103 -> 6466.7719 | P19: ='IS-Reorg'!P103 -> 6268.6271 | Q19: ='IS-Reorg'!Q103 -> 6092.5454 | R19: ='IS-Reorg'!R103 -> 5938.0686 | S19: ='IS-Reorg'!S103 -> 5804.7691 | ... V19: ='IS-Reorg'!V103 -> 5528.1099
A20: ='3M-BS'!A27 -> Property, Plant & Equipment - Gross | B20: =VLOOKUP($A20,'3M-BS'!$A$12:$K$79,11, FALSE) -> 23499 | C20: =VLOOKUP($A20,'3M-BS'!$A$12:$K$79,10, FALSE) -> 24914 | D20: =VLOOKUP($A20,'3M-BS'!$A$12:$K$79,9, FALSE) -> 24873 | E20: =VLOOKUP($A20,'3M-BS'!$A$12:$K$79,8, FALSE) -> 26982 | F20: =VLOOKUP($A20,'3M-BS'!$A$12:$K$79,7, FALSE) -> 27514 | G20: =VLOOKUP($A20,'3M-BS'!$A$12:$K$79,6, FALSE) -> 28071 | H20: =VLOOKUP($A20,'3M-BS'!$A$12:$K$79,5, FALSE) -> 26827 | I20: =VLOOKUP($A20,'3M-BS'!$A$12:$K$79,4, FALSE) -> 24151 | J20: =VLOOKUP($A20,'3M-BS'!$A$12:$K$79,3, FALSE) -> 23971 | K20: =VLOOKUP($A20,'3M-BS'!$A$12:$K$79,2, FALSE) -> 24438 | L20: ='IS-Reorg'!L112 -> 24560.48 | M20: ='IS-Reorg'!M112 -> 24722.061 | N20: ='IS-Reorg'!N112 -> 24922.938 | O20: ='IS-Reorg'!O112 -> 25163.371 | P20: ='IS-Reorg'!P112 -> 25443.681 | Q20: ='IS-Reorg'!Q112 -> 25751.383 | R20: ='IS-Reorg'!R112 -> 26086.541 | S20: ='IS-Reorg'!S112 -> 26449.249 | ... V20: ='IS-Reorg'!V112 -> 27704.099
A21: ='3M-BS'!A28 -> Buildings | B21: =VLOOKUP($A21,'3M-BS'!$A$12:$K$79,11, FALSE) -> 7252 | C21: =VLOOKUP($A21,'3M-BS'!$A$12:$K$79,10, FALSE) -> 7681 | D21: =VLOOKUP($A21,'3M-BS'!$A$12:$K$79,9, FALSE) -> 7517 | E21: =VLOOKUP($A21,'3M-BS'!$A$12:$K$79,8, FALSE) -> 7877 | F21: =VLOOKUP($A21,'3M-BS'!$A$12:$K$79,7, FALSE) -> 8021 | G21: =VLOOKUP($A21,'3M-BS'!$A$12:$K$79,6, FALSE) -> 8086 | H21: =VLOOKUP($A21,'3M-BS'!$A$12:$K$79,5, FALSE) -> 7560 | I21: =VLOOKUP($A21,'3M-BS'!$A$12:$K$79,4, FALSE) -> 7031 | J21: =VLOOKUP($A21,'3M-BS'!$A$12:$K$79,3, FALSE) -> 7432 | K21: =VLOOKUP($A21,'3M-BS'!$A$12:$K$79,2, FALSE) -> 7729 | L21: =$K21/$K$20*L20 -> 7767.7367 | M21: =$K21/$K$20*M20 -> 7818.8398 | N21: =$K21/$K$20*N20 -> 7882.3713 | O21: =$K21/$K$20*O20 -> 7958.413 | P21: =$K21/$K$20*P20 -> 8047.0664 | Q21: =$K21/$K$20*Q20 -> 8144.3834 | R21: =$K21/$K$20*R20 -> 8250.3837 | S21: =$K21/$K$20*S20 -> 8365.0973 | ... V21: =$K21/$K$20*V20 -> 8761.9684
A22: ='3M-BS'!A29 -> Land & Improvements | B22: =VLOOKUP($A22,'3M-BS'!$A$12:$K$79,11, FALSE) -> 341 | C22: =VLOOKUP($A22,'3M-BS'!$A$12:$K$79,10, FALSE) -> 348 | D22: =VLOOKUP($A22,'3M-BS'!$A$12:$K$79,9, FALSE) -> 340 | E22: =VLOOKUP($A22,'3M-BS'!$A$12:$K$79,8, FALSE) -> 351 | F22: =VLOOKUP($A22,'3M-BS'!$A$12:$K$79,7, FALSE) -> 338 | G22: =VLOOKUP($A22,'3M-BS'!$A$12:$K$79,6, FALSE) -> 312 | H22: =VLOOKUP($A22,'3M-BS'!$A$12:$K$79,5, FALSE) -> 255 | I22: =VLOOKUP($A22,'3M-BS'!$A$12:$K$79,4, FALSE) -> 215 | J22: =VLOOKUP($A22,'3M-BS'!$A$12:$K$79,3, FALSE) -> 200 | K22: =VLOOKUP($A22,'3M-BS'!$A$12:$K$79,2, FALSE) -> 202 | L22: =$K22/$K$20*L$20 -> 203.0124 | M22: =$K22/$K$20*M$20 -> 204.34799 | N22: =$K22/$K$20*N$20 -> 206.00841 | O22: =$K22/$K$20*O$20 -> 207.99578 | P22: =$K22/$K$20*P$20 -> 210.31277 | Q22: =$K22/$K$20*Q$20 -> 212.85618 | R22: =$K22/$K$20*R$20 -> 215.62654 | S22: =$K22/$K$20*S$20 -> 218.62461 | ... V22: =$K22/$K$20*V$20 -> 228.99697
A23: ='3M-BS'!A30 -> Machinery & Equipment | B23: =VLOOKUP($A23,'3M-BS'!$A$12:$K$79,11, FALSE) -> 14935 | C23: =VLOOKUP($A23,'3M-BS'!$A$12:$K$79,10, FALSE) -> 15907 | D23: =VLOOKUP($A23,'3M-BS'!$A$12:$K$79,9, FALSE) -> 15680 | E23: =VLOOKUP($A23,'3M-BS'!$A$12:$K$79,8, FALSE) -> 16586 | F23: =VLOOKUP($A23,'3M-BS'!$A$12:$K$79,7, FALSE) -> 16866 | G23: =VLOOKUP($A23,'3M-BS'!$A$12:$K$79,6, FALSE) -> 17305 | H23: =VLOOKUP($A23,'3M-BS'!$A$12:$K$79,5, FALSE) -> 16455 | I23: =VLOOKUP($A23,'3M-BS'!$A$12:$K$79,4, FALSE) -> 14716 | J23: =VLOOKUP($A23,'3M-BS'!$A$12:$K$79,3, FALSE) -> 14780 | K23: =VLOOKUP($A23,'3M-BS'!$A$12:$K$79,2, FALSE) -> 15328 | L23: =$K23/$K$20*L$20 -> 15404.822 | M23: =$K23/$K$20*M$20 -> 15506.169 | N23: =$K23/$K$20*N$20 -> 15632.163 | O23: =$K23/$K$20*O$20 -> 15782.967 | P23: =$K23/$K$20*P$20 -> 15958.783 | Q23: =$K23/$K$20*Q$20 -> 16151.78 | R23: =$K23/$K$20*R$20 -> 16361.998 | S23: =$K23/$K$20*S$20 -> 16589.496 | ... V23: =$K23/$K$20*V$20 -> 17376.563
A24: ='3M-BS'!A31 -> Construction in Progress | B24: =VLOOKUP($A24,'3M-BS'!$A$12:$K$79,11, FALSE) -> 809 | C24: =VLOOKUP($A24,'3M-BS'!$A$12:$K$79,10, FALSE) -> 843 | D24: =VLOOKUP($A24,'3M-BS'!$A$12:$K$79,9, FALSE) -> 1193 | E24: =VLOOKUP($A24,'3M-BS'!$A$12:$K$79,8, FALSE) -> 1310 | F24: =VLOOKUP($A24,'3M-BS'!$A$12:$K$79,7, FALSE) -> 1425 | G24: =VLOOKUP($A24,'3M-BS'!$A$12:$K$79,6, FALSE) -> 1510 | H24: =VLOOKUP($A24,'3M-BS'!$A$12:$K$79,5, FALSE) -> 1728 | I24: =VLOOKUP($A24,'3M-BS'!$A$12:$K$79,4, FALSE) -> 1532 | J24: =VLOOKUP($A24,'3M-BS'!$A$12:$K$79,3, FALSE) -> 994 | K24: =VLOOKUP($A24,'3M-BS'!$A$12:$K$79,2, FALSE) -> 663 | L24: =$K24/$K$20*L$20 -> 666.32287 | M24: =$K24/$K$20*M$20 -> 670.70654 | N24: =$K24/$K$20*N$20 -> 676.15632 | O24: =$K24/$K$20*O$20 -> 682.67923 | P24: =$K24/$K$20*P$20 -> 690.284 | Q24: =$K24/$K$20*Q$20 -> 698.63193 | R24: =$K24/$K$20*R$20 -> 707.72473 | S24: =$K24/$K$20*S$20 -> 717.56495 | ... V24: =$K24/$K$20*V$20 -> 751.60888
A25: ='3M-BS'!A32 -> Leases | B25: =VLOOKUP($A25,'3M-BS'!$A$12:$K$79,11, FALSE) -> 162 | C25: =VLOOKUP($A25,'3M-BS'!$A$12:$K$79,10, FALSE) -> 135 | D25: =VLOOKUP($A25,'3M-BS'!$A$12:$K$79,9, FALSE) -> 143 | E25: =VLOOKUP($A25,'3M-BS'!$A$12:$K$79,8, FALSE) -> 0 | F25: =VLOOKUP($A25,'3M-BS'!$A$12:$K$79,7, FALSE) -> 0 | G25: =VLOOKUP($A25,'3M-BS'!$A$12:$K$79,6, FALSE) -> 0 | H25: =VLOOKUP($A25,'3M-BS'!$A$12:$K$79,5, FALSE) -> 0 | I25: =VLOOKUP($A25,'3M-BS'!$A$12:$K$79,4, FALSE) -> 0 | J25: =VLOOKUP($A25,'3M-BS'!$A$12:$K$79,3, FALSE) -> 0 | K25: =VLOOKUP($A25,'3M-BS'!$A$12:$K$79,2, FALSE) -> 0 | L25: =K25 -> 0 | M25: =L25 -> 0 | N25: =M25 -> 0 | O25: =N25 -> 0 | P25: =O25 -> 0 | Q25: =P25 -> 0 | R25: =Q25 -> 0 | S25: =R25 -> 0 | ... V25: =U25 -> 0
A26: ='3M-BS'!A33 -> Operating Lease Right-of-Use Assets | B26: =VLOOKUP($A26,'3M-BS'!$A$12:$K$79,11, FALSE) -> 0 | C26: =VLOOKUP($A26,'3M-BS'!$A$12:$K$79,10, FALSE) -> 0 | D26: =VLOOKUP($A26,'3M-BS'!$A$12:$K$79,9, FALSE) -> 0 | E26: =VLOOKUP($A26,'3M-BS'!$A$12:$K$79,8, FALSE) -> 858 | F26: =VLOOKUP($A26,'3M-BS'!$A$12:$K$79,7, FALSE) -> 864 | G26: =VLOOKUP($A26,'3M-BS'!$A$12:$K$79,6, FALSE) -> 858 | H26: =VLOOKUP($A26,'3M-BS'!$A$12:$K$79,5, FALSE) -> 829 | I26: =VLOOKUP($A26,'3M-BS'!$A$12:$K$79,4, FALSE) -> 657 | J26: =VLOOKUP($A26,'3M-BS'!$A$12:$K$79,3, FALSE) -> 565 | K26: =VLOOKUP($A26,'3M-BS'!$A$12:$K$79,2, FALSE) -> 516 | L26: =$K26/$K$20*L$20 -> 518.58612 | M26: =$K26/$K$20*M$20 -> 521.99785 | N26: =$K26/$K$20*N$20 -> 526.23931 | O26: =$K26/$K$20*O$20 -> 531.31597 | P26: =$K26/$K$20*P$20 -> 537.23461 | Q26: =$K26/$K$20*Q$20 -> 543.73164 | R26: =$K26/$K$20*R$20 -> 550.80838 | S26: =$K26/$K$20*S$20 -> 558.46684 | ... V26: =$K26/$K$20*V$20 -> 584.96257
A27: ='3M-BS'!A34 -> Accumulated Depreciation | B27: =VLOOKUP($A27,'3M-BS'!$A$12:$K$79,11, FALSE) -> 14983 | C27: =VLOOKUP($A27,'3M-BS'!$A$12:$K$79,10, FALSE) -> 16048 | D27: =VLOOKUP($A27,'3M-BS'!$A$12:$K$79,9, FALSE) -> 16135 | E27: =VLOOKUP($A27,'3M-BS'!$A$12:$K$79,8, FALSE) -> 16791 | F27: =VLOOKUP($A27,'3M-BS'!$A$12:$K$79,7, FALSE) -> 17229 | G27: =VLOOKUP($A27,'3M-BS'!$A$12:$K$79,6, FALSE) -> 17784 | H27: =VLOOKUP($A27,'3M-BS'!$A$12:$K$79,5, FALSE) -> 16820 | I27: =VLOOKUP($A27,'3M-BS'!$A$12:$K$79,4, FALSE) -> 15804 | J27: =VLOOKUP($A27,'3M-BS'!$A$12:$K$79,3, FALSE) -> 16018 | K27: =VLOOKUP($A27,'3M-BS'!$A$12:$K$79,2, FALSE) -> 16821 | L27: ='IS-Reorg'!L119 -> 17285.662 | M27: ='IS-Reorg'!M119 -> 17752.653 | N27: ='IS-Reorg'!N119 -> 18222.717 | O27: ='IS-Reorg'!O119 -> 18696.599 | P27: ='IS-Reorg'!P119 -> 19175.054 | Q27: ='IS-Reorg'!Q119 -> 19658.838 | R27: ='IS-Reorg'!R119 -> 20148.473 | S27: ='IS-Reorg'!S119 -> 20644.48 | ... V27: ='IS-Reorg'!V119 -> 22175.989
A28: Total Long-Term Investments | B28: =VLOOKUP($A28,'3M-BS'!$A$12:$K$79,11, FALSE) -> 256 | C28: =VLOOKUP($A28,'3M-BS'!$A$12:$K$79,10, FALSE) -> 191 | D28: =VLOOKUP($A28,'3M-BS'!$A$12:$K$79,9, FALSE) -> 246 | E28: =VLOOKUP($A28,'3M-BS'!$A$12:$K$79,8, FALSE) -> 263 | F28: =VLOOKUP($A28,'3M-BS'!$A$12:$K$79,7, FALSE) -> 224 | G28: =VLOOKUP($A28,'3M-BS'!$A$12:$K$79,6, FALSE) -> 303 | H28: =VLOOKUP($A28,'3M-BS'!$A$12:$K$79,5, FALSE) -> 976 | I28: =VLOOKUP($A28,'3M-BS'!$A$12:$K$79,4, FALSE) -> 221 | J28: =VLOOKUP($A28,'3M-BS'!$A$12:$K$79,3, FALSE) -> 2583 | K28: =VLOOKUP($A28,'3M-BS'!$A$12:$K$79,2, FALSE) -> 161 | L28: =L29+L30 -> 163.35731 | M28: =M29+M30 -> 169.8916 | N28: =N29+N30 -> 176.68726 | O28: =O29+O30 -> 183.75475 | P28: =P29+P30 -> 191.10494 | Q28: =Q29+Q30 -> 196.83809 | R28: =R29+R30 -> 202.74323 | S28: =S29+S30 -> 208.82553 | ... V28: =V29+V30 -> 228.1893
A29: LT Investment - Affiliate Companies | B29: =VLOOKUP($A29,'3M-BS'!$A$12:$K$79,11, FALSE) -> 60 | C29: =VLOOKUP($A29,'3M-BS'!$A$12:$K$79,10, FALSE) -> 70 | D29: =VLOOKUP($A29,'3M-BS'!$A$12:$K$79,9, FALSE) -> 70 | E29: =VLOOKUP($A29,'3M-BS'!$A$12:$K$79,8, FALSE) -> 70 | F29: =VLOOKUP($A29,'3M-BS'!$A$12:$K$79,7, FALSE) -> 134 | G29: =VLOOKUP($A29,'3M-BS'!$A$12:$K$79,6, FALSE) -> 129 | H29: =VLOOKUP($A29,'3M-BS'!$A$12:$K$79,5, FALSE) -> 81 | I29: =VLOOKUP($A29,'3M-BS'!$A$12:$K$79,4, FALSE) -> 73 | J29: =VLOOKUP($A29,'3M-BS'!$A$12:$K$79,3, FALSE) -> 75 | K29: =VLOOKUP($A29,'3M-BS'!$A$12:$K$79,2, FALSE) -> 0 | L29: =K29 -> 0 | M29: =L29 -> 0 | N29: =M29 -> 0 | O29: =N29 -> 0 | P29: =O29 -> 0 | Q29: =P29 -> 0 | R29: =Q29 -> 0 | S29: =R29 -> 0 | ... V29: =U29 -> 0
A30: Other Long-Term Investments | B30: =VLOOKUP($A30,'3M-BS'!$A$12:$K$79,11, FALSE) -> 196 | C30: =VLOOKUP($A30,'3M-BS'!$A$12:$K$79,10, FALSE) -> 121 | D30: =VLOOKUP($A30,'3M-BS'!$A$12:$K$79,9, FALSE) -> 176 | E30: =VLOOKUP($A30,'3M-BS'!$A$12:$K$79,8, FALSE) -> 193 | F30: =VLOOKUP($A30,'3M-BS'!$A$12:$K$79,7, FALSE) -> 90 | G30: =VLOOKUP($A30,'3M-BS'!$A$12:$K$79,6, FALSE) -> 174 | H30: =VLOOKUP($A30,'3M-BS'!$A$12:$K$79,5, FALSE) -> 895 | I30: =VLOOKUP($A30,'3M-BS'!$A$12:$K$79,4, FALSE) -> 148 | J30: =VLOOKUP($A30,'3M-BS'!$A$12:$K$79,3, FALSE) -> 2508 | K30: =VLOOKUP($A30,'3M-BS'!$A$12:$K$79,2, FALSE) -> 161 | L30: =$K$30/$K$85*L85 -> 163.35731 | M30: =$K$30/$K$85*M85 -> 169.8916 | N30: =$K$30/$K$85*N85 -> 176.68726 | O30: =$K$30/$K$85*O85 -> 183.75475 | P30: =$K$30/$K$85*P85 -> 191.10494 | Q30: =$K$30/$K$85*Q85 -> 196.83809 | R30: =$K$30/$K$85*R85 -> 202.74323 | S30: =$K$30/$K$85*S85 -> 208.82553 | ... V30: =$K$30/$K$85*V85 -> 228.1893
A31: ='3M-BS'!A38 -> Intangible Assets | B31: =VLOOKUP($A31,'3M-BS'!$A$12:$K$79,11, FALSE) -> 11486 | C31: =VLOOKUP($A31,'3M-BS'!$A$12:$K$79,10, FALSE) -> 13449 | D31: =VLOOKUP($A31,'3M-BS'!$A$12:$K$79,9, FALSE) -> 12708 | E31: =VLOOKUP($A31,'3M-BS'!$A$12:$K$79,8, FALSE) -> 19823 | F31: =VLOOKUP($A31,'3M-BS'!$A$12:$K$79,7, FALSE) -> 19637 | G31: =VLOOKUP($A31,'3M-BS'!$A$12:$K$79,6, FALSE) -> 18774 | H31: =VLOOKUP($A31,'3M-BS'!$A$12:$K$79,5, FALSE) -> 17489 | I31: =VLOOKUP($A31,'3M-BS'!$A$12:$K$79,4, FALSE) -> 7705 | J31: =VLOOKUP($A31,'3M-BS'!$A$12:$K$79,3, FALSE) -> 7491 | K31: =VLOOKUP($A31,'3M-BS'!$A$12:$K$79,2, FALSE) -> 7522 | L31: =L32+L33 -> 7426.4847 | M31: =M32+M33 -> 7339.2406 | N31: =N32+N33 -> 7259.5515 | O31: =O32+O33 -> 7186.7631 | P31: =P32+P33 -> 7120.2779 | Q31: =Q32+Q33 -> 7059.5501 | R31: =R32+R33 -> 7004.0811 | S31: =S32+S33 -> 6953.4154 | ... V31: =V32+V33 -> 6826.2563
A32: ='3M-BS'!A39 -> Goodwill | B32: =VLOOKUP($A32,'3M-BS'!$A$12:$K$79,11, FALSE) -> 9166 | C32: =VLOOKUP($A32,'3M-BS'!$A$12:$K$79,10, FALSE) -> 10513 | D32: =VLOOKUP($A32,'3M-BS'!$A$12:$K$79,9, FALSE) -> 10051 | E32: =VLOOKUP($A32,'3M-BS'!$A$12:$K$79,8, FALSE) -> 13444 | F32: =VLOOKUP($A32,'3M-BS'!$A$12:$K$79,7, FALSE) -> 13802 | G32: =VLOOKUP($A32,'3M-BS'!$A$12:$K$79,6, FALSE) -> 13486 | H32: =VLOOKUP($A32,'3M-BS'!$A$12:$K$79,5, FALSE) -> 12790 | I32: =VLOOKUP($A32,'3M-BS'!$A$12:$K$79,4, FALSE) -> 6382 | J32: =VLOOKUP($A32,'3M-BS'!$A$12:$K$79,3, FALSE) -> 6281 | K32: =VLOOKUP($A32,'3M-BS'!$A$12:$K$79,2, FALSE) -> 6419 | L32: =K32 -> 6419 | M32: =L32 -> 6419 | N32: =M32 -> 6419 | O32: =N32 -> 6419 | P32: =O32 -> 6419 | Q32: =P32 -> 6419 | R32: =Q32 -> 6419 | S32: =R32 -> 6419 | ... V32: =U32 -> 6419
A33: ='3M-BS'!A40 -> Other Intangible Assets | B33: =VLOOKUP($A33,'3M-BS'!$A$12:$K$79,11, FALSE) -> 2320 | C33: =VLOOKUP($A33,'3M-BS'!$A$12:$K$79,10, FALSE) -> 2936 | D33: =VLOOKUP($A33,'3M-BS'!$A$12:$K$79,9, FALSE) -> 2657 | E33: =VLOOKUP($A33,'3M-BS'!$A$12:$K$79,8, FALSE) -> 6379 | F33: =VLOOKUP($A33,'3M-BS'!$A$12:$K$79,7, FALSE) -> 5835 | G33: =VLOOKUP($A33,'3M-BS'!$A$12:$K$79,6, FALSE) -> 5288 | H33: =VLOOKUP($A33,'3M-BS'!$A$12:$K$79,5, FALSE) -> 4699 | I33: =VLOOKUP($A33,'3M-BS'!$A$12:$K$79,4, FALSE) -> 1323 | J33: =VLOOKUP($A33,'3M-BS'!$A$12:$K$79,3, FALSE) -> 1210 | K33: =VLOOKUP($A33,'3M-BS'!$A$12:$K$79,2, FALSE) -> 1103 | L33: ='IS-Reorg'!L133 -> 1007.4847 | M33: ='IS-Reorg'!M133 -> 920.24057 | N33: ='IS-Reorg'!N133 -> 840.55146 | O33: ='IS-Reorg'!O133 -> 767.76311 | P33: ='IS-Reorg'!P133 -> 701.27793 | Q33: ='IS-Reorg'!Q133 -> 640.5501 | R33: ='IS-Reorg'!R133 -> 585.08105 | S33: ='IS-Reorg'!S133 -> 534.4154 | ... V33: ='IS-Reorg'!V133 -> 407.25625
A34: ='3M-BS'!A41 -> Deferred Tax Assets | B34: =VLOOKUP($A34,'3M-BS'!$A$12:$K$79,11, FALSE) -> 422 | C34: =VLOOKUP($A34,'3M-BS'!$A$12:$K$79,10, FALSE) -> 511 | D34: =VLOOKUP($A34,'3M-BS'!$A$12:$K$79,9, FALSE) -> 365 | E34: =VLOOKUP($A34,'3M-BS'!$A$12:$K$79,8, FALSE) -> 521 | F34: =VLOOKUP($A34,'3M-BS'!$A$12:$K$79,7, FALSE) -> 871 | G34: =VLOOKUP($A34,'3M-BS'!$A$12:$K$79,6, FALSE) -> 581 | H34: =VLOOKUP($A34,'3M-BS'!$A$12:$K$79,5, FALSE) -> 959 | I34: =VLOOKUP($A34,'3M-BS'!$A$12:$K$79,4, FALSE) -> 4779 | J34: =VLOOKUP($A34,'3M-BS'!$A$12:$K$79,3, FALSE) -> 4146 | K34: =VLOOKUP($A34,'3M-BS'!$A$12:$K$79,2, FALSE) -> 3826 | L34: =K34 -> 3826 | M34: =L34 -> 3826 | N34: =M34 -> 3826 | O34: =N34 -> 3826 | P34: =O34 -> 3826 | Q34: =P34 -> 3826 | R34: =Q34 -> 3826 | S34: =R34 -> 3826 | ... V34: =U34 -> 3826
A35: ='3M-BS'!A42 -> Other Assets | B35: =VLOOKUP($A35,'3M-BS'!$A$12:$K$79,11, FALSE) -> 500 | C35: =VLOOKUP($A35,'3M-BS'!$A$12:$K$79,10, FALSE) -> 693 | D35: =VLOOKUP($A35,'3M-BS'!$A$12:$K$79,9, FALSE) -> 734 | E35: =VLOOKUP($A35,'3M-BS'!$A$12:$K$79,8, FALSE) -> 890 | F35: =VLOOKUP($A35,'3M-BS'!$A$12:$K$79,7, FALSE) -> 1345 | G35: =VLOOKUP($A35,'3M-BS'!$A$12:$K$79,6, FALSE) -> 1724 | H35: =VLOOKUP($A35,'3M-BS'!$A$12:$K$79,5, FALSE) -> 2336 | I35: =VLOOKUP($A35,'3M-BS'!$A$12:$K$79,4, FALSE) -> 13149 | J35: =VLOOKUP($A35,'3M-BS'!$A$12:$K$79,3, FALSE) -> 1811 | K35: =VLOOKUP($A35,'3M-BS'!$A$12:$K$79,2, FALSE) -> 2220 | L35: =L36+L37 -> 2220 | M35: =M36+M37 -> 2220 | N35: =N36+N37 -> 2220 | O35: =O36+O37 -> 2220 | P35: =P36+P37 -> 2220 | Q35: =Q36+Q37 -> 2220 | R35: =R36+R37 -> 2220 | S35: =S36+S37 -> 2220 | ... V35: =V36+V37 -> 2220
A36: ='3M-BS'!A43 -> Deferred Charges | B36: =VLOOKUP($A36,'3M-BS'!$A$12:$K$79,11, FALSE) -> 52 | C36: =VLOOKUP($A36,'3M-BS'!$A$12:$K$79,10, FALSE) -> 237 | D36: =VLOOKUP($A36,'3M-BS'!$A$12:$K$79,9, FALSE) -> 208 | E36: =VLOOKUP($A36,'3M-BS'!$A$12:$K$79,8, FALSE) -> 230 | F36: =VLOOKUP($A36,'3M-BS'!$A$12:$K$79,7, FALSE) -> 630 | G36: =VLOOKUP($A36,'3M-BS'!$A$12:$K$79,6, FALSE) -> 943 | H36: =VLOOKUP($A36,'3M-BS'!$A$12:$K$79,5, FALSE) -> 1225 | I36: =VLOOKUP($A36,'3M-BS'!$A$12:$K$79,4, FALSE) -> 1239 | J36: =VLOOKUP($A36,'3M-BS'!$A$12:$K$79,3, FALSE) -> 1243 | K36: =VLOOKUP($A36,'3M-BS'!$A$12:$K$79,2, FALSE) -> 0 | L36: =K36 -> 0 | M36: =L36 -> 0 | N36: =M36 -> 0 | O36: =N36 -> 0 | P36: =O36 -> 0 | Q36: =P36 -> 0 | R36: =Q36 -> 0 | S36: =R36 -> 0 | ... V36: =U36 -> 0
A37: ='3M-BS'!A44 -> Tangible Other Assets | B37: =VLOOKUP($A37,'3M-BS'!$A$12:$K$79,11, FALSE) -> 448 | C37: =VLOOKUP($A37,'3M-BS'!$A$12:$K$79,10, FALSE) -> 456 | D37: =VLOOKUP($A37,'3M-BS'!$A$12:$K$79,9, FALSE) -> 526 | E37: =VLOOKUP($A37,'3M-BS'!$A$12:$K$79,8, FALSE) -> 660 | F37: =VLOOKUP($A37,'3M-BS'!$A$12:$K$79,7, FALSE) -> 715 | G37: =VLOOKUP($A37,'3M-BS'!$A$12:$K$79,6, FALSE) -> 781 | H37: =VLOOKUP($A37,'3M-BS'!$A$12:$K$79,5, FALSE) -> 1111 | I37: =VLOOKUP($A37,'3M-BS'!$A$12:$K$79,4, FALSE) -> 11910 | J37: =VLOOKUP($A37,'3M-BS'!$A$12:$K$79,3, FALSE) -> 568 | K37: =VLOOKUP($A37,'3M-BS'!$A$12:$K$79,2, FALSE) -> 2220 | L37: =K37 -> 2220 | M37: =L37 -> 2220 | N37: =M37 -> 2220 | O37: =N37 -> 2220 | P37: =O37 -> 2220 | Q37: =P37 -> 2220 | R37: =Q37 -> 2220 | S37: =R37 -> 2220 | ... V37: =U37 -> 2220
A38: Total Assets | B38: =B35+B34+B31+B19+B15+B11+B7+B4+B28 -> 32906 | C38: =C35+C34+C31+C19+C15+C11+C7+C4+C28 -> 37987 | D38: =D35+D34+D31+D19+D15+D11+D7+D4+D28 -> 36500 | E38: =E35+E34+E31+E19+E15+E11+E7+E4+E28 -> 44659 | F38: =F35+F34+F31+F19+F15+F11+F7+F4+F28 -> 47344 | G38: =G35+G34+G31+G19+G15+G11+G7+G4+G28 -> 47072 | H38: =H35+H34+H31+H19+H15+H11+H7+H4+H28 -> 46455 | I38: =I35+I34+I31+I19+I15+I11+I7+I4+I28 -> 50580 | ... V38: =V35+V34+V31+V19+V15+V11+V7+V4+V28 -> 64705.566
A39: Total Operating Assets | B39: =B35+B34+B31+B19+B15+B11+B7 -> 29972 | C39: =C35+C34+C31+C19+C15+C11+C7 -> 33667 | D39: =D35+D34+D31+D19+D15+D11+D7 -> 33021 | E39: =E35+E34+E31+E19+E15+E11+E7 -> 41475 | F39: =F35+F34+F31+F19+F15+F11+F7 -> 42082 | G39: =G35+G34+G31+G19+G15+G11+G7 -> 42004 | H39: =H35+H34+H31+H19+H15+H11+H7 -> 41586 | I39: =I35+I34+I31+I19+I15+I11+I7 -> 44574 | ... V39: =V35+V34+V31+V19+V15+V11+V7 -> 32720.255
A42: ST Debt & Curr. Portion LT Debt | B42: =VLOOKUP($A42,'3M-BS'!$A$48:$K$64,11, FALSE) -> 972 | C42: =VLOOKUP($A42,'3M-BS'!$A$48:$K$64,10, FALSE) -> 1853 | D42: =VLOOKUP($A42,'3M-BS'!$A$48:$K$64,9, FALSE) -> 1211 | E42: =VLOOKUP($A42,'3M-BS'!$A$48:$K$64,8, FALSE) -> 3063 | F42: =VLOOKUP($A42,'3M-BS'!$A$48:$K$64,7, FALSE) -> 1084 | G42: =VLOOKUP($A42,'3M-BS'!$A$48:$K$64,6, FALSE) -> 1577 | H42: =VLOOKUP($A42,'3M-BS'!$A$48:$K$64,5, FALSE) -> 2210 | I42: =VLOOKUP($A42,'3M-BS'!$A$48:$K$64,4, FALSE) -> 3139 | J42: =VLOOKUP($A42,'3M-BS'!$A$48:$K$64,3, FALSE) -> 2082 | K42: =VLOOKUP($A42,'3M-BS'!$A$48:$K$64,2, FALSE) -> 1837 | L42: ='IS-Reorg'!C144 -> 863 | M42: ='IS-Reorg'!D144 -> 863 | N42: ='IS-Reorg'!E144 -> 1793 | O42: ='IS-Reorg'!F144 -> 1728 | P42: ='IS-Reorg'!G144 -> 587 | Q42: ='IS-Reorg'!H144 -> 0 | R42: ='IS-Reorg'!I144 -> 0 | S42: ='IS-Reorg'!J144 -> 0 | ... V42: ='IS-Reorg'!M144 -> 0
A43: ='3M-BS'!A49 -> Accounts Payable | B43: =VLOOKUP($A43,'3M-BS'!$A$48:$K$64,11, FALSE) -> 1798 | C43: =VLOOKUP($A43,'3M-BS'!$A$48:$K$64,10, FALSE) -> 1945 | D43: =VLOOKUP($A43,'3M-BS'!$A$48:$K$64,9, FALSE) -> 2266 | E43: =VLOOKUP($A43,'3M-BS'!$A$48:$K$64,8, FALSE) -> 2228 | F43: =VLOOKUP($A43,'3M-BS'!$A$48:$K$64,7, FALSE) -> 2561 | G43: =VLOOKUP($A43,'3M-BS'!$A$48:$K$64,6, FALSE) -> 2994 | H43: =VLOOKUP($A43,'3M-BS'!$A$48:$K$64,5, FALSE) -> 3183 | I43: =VLOOKUP($A43,'3M-BS'!$A$48:$K$64,4, FALSE) -> 2776 | J43: =VLOOKUP($A43,'3M-BS'!$A$48:$K$64,3, FALSE) -> 2660 | K43: =VLOOKUP($A43,'3M-BS'!$A$48:$K$64,2, FALSE) -> 2702 | L43: =L97 -> 2741.5618 | M43: =M97 -> 2825.3842 | N43: =N97 -> 2911.526 | O43: =O97 -> 3000.0385 | P43: =P97 -> 3090.9736 | Q43: =Q97 -> 3153.7643 | R43: =R97 -> 3217.5406 | S43: =S97 -> 3282.3051 | ... V43: =V97 -> 3482.5427
A44: ='3M-BS'!A50 -> Income Tax Payable | B44: =VLOOKUP($A44,'3M-BS'!$A$48:$K$64,11, FALSE) -> 299 | C44: =VLOOKUP($A44,'3M-BS'!$A$48:$K$64,10, FALSE) -> 310 | D44: =VLOOKUP($A44,'3M-BS'!$A$48:$K$64,9, FALSE) -> 243 | E44: =VLOOKUP($A44,'3M-BS'!$A$48:$K$64,8, FALSE) -> 194 | F44: =VLOOKUP($A44,'3M-BS'!$A$48:$K$64,7, FALSE) -> 300 | G44: =VLOOKUP($A44,'3M-BS'!$A$48:$K$64,6, FALSE) -> 260 | H44: =VLOOKUP($A44,'3M-BS'!$A$48:$K$64,5, FALSE) -> 259 | I44: =VLOOKUP($A44,'3M-BS'!$A$48:$K$64,4, FALSE) -> 304 | J44: =VLOOKUP($A44,'3M-BS'!$A$48:$K$64,3, FALSE) -> 331 | K44: =VLOOKUP($A44,'3M-BS'!$A$48:$K$64,2, FALSE) -> 0 | L44: =K44 -> 0 | M44: =L44 -> 0 | N44: =M44 -> 0 | O44: =N44 -> 0 | P44: =O44 -> 0 | Q44: =P44 -> 0 | R44: =Q44 -> 0 | S44: =R44 -> 0 | ... V44: =U44 -> 0
A45: ='3M-BS'!A51 -> Other Current Liabilities | B45: =VLOOKUP($A45,'3M-BS'!$A$48:$K$64,11, FALSE) -> 3150 | C45: =VLOOKUP($A45,'3M-BS'!$A$48:$K$64,10, FALSE) -> 3579 | D45: =VLOOKUP($A45,'3M-BS'!$A$48:$K$64,9, FALSE) -> 3524 | E45: =VLOOKUP($A45,'3M-BS'!$A$48:$K$64,8, FALSE) -> 3737 | F45: =VLOOKUP($A45,'3M-BS'!$A$48:$K$64,7, FALSE) -> 4003 | G45: =VLOOKUP($A45,'3M-BS'!$A$48:$K$64,6, FALSE) -> 4204 | H45: =VLOOKUP($A45,'3M-BS'!$A$48:$K$64,5, FALSE) -> 3871 | I45: =VLOOKUP($A45,'3M-BS'!$A$48:$K$64,4, FALSE) -> 9078 | J45: =VLOOKUP($A45,'3M-BS'!$A$48:$K$64,3, FALSE) -> 6183 | K45: =VLOOKUP($A45,'3M-BS'!$A$48:$K$64,2, FALSE) -> 5056 | L45: =$K$45/$K$85*L85 -> 5130.0282 | M45: =$K$45/$K$85*M85 -> 5335.2293 | N45: =$K$45/$K$85*N85 -> 5548.6385 | O45: =$K$45/$K$85*O85 -> 5770.584 | P45: =$K$45/$K$85*P85 -> 6001.4074 | Q45: =$K$45/$K$85*Q85 -> 6181.4496 | R45: =$K$45/$K$85*R85 -> 6366.8931 | S45: =$K$45/$K$85*S85 -> 6557.8999 | ... V45: =$K$45/$K$85*V85 -> 7165.9943
A46: ='3M-BS'!A52 -> Accrued Payroll | B46: =VLOOKUP($A46,'3M-BS'!$A$48:$K$64,11, FALSE) -> 899 | C46: =VLOOKUP($A46,'3M-BS'!$A$48:$K$64,10, FALSE) -> 1147 | D46: =VLOOKUP($A46,'3M-BS'!$A$48:$K$64,9, FALSE) -> 1053 | E46: =VLOOKUP($A46,'3M-BS'!$A$48:$K$64,8, FALSE) -> 998 | F46: =VLOOKUP($A46,'3M-BS'!$A$48:$K$64,7, FALSE) -> 1010 | G46: =VLOOKUP($A46,'3M-BS'!$A$48:$K$64,6, FALSE) -> 1317 | H46: =VLOOKUP($A46,'3M-BS'!$A$48:$K$64,5, FALSE) -> 1016 | I46: =VLOOKUP($A46,'3M-BS'!$A$48:$K$64,4, FALSE) -> 998 | J46: =VLOOKUP($A46,'3M-BS'!$A$48:$K$64,3, FALSE) -> 968 | K46: =VLOOKUP($A46,'3M-BS'!$A$48:$K$64,2, FALSE) -> 718 | L46: =$K$46/$K$85*L85 -> 728.51271 | M46: =$K$46/$K$85*M85 -> 757.65322 | N46: =$K$46/$K$85*N85 -> 787.95935 | O46: =$K$46/$K$85*O85 -> 819.47772 | P46: =$K$46/$K$85*P85 -> 852.25683 | Q46: =$K$46/$K$85*Q85 -> 877.82453 | R46: =$K$46/$K$85*R85 -> 904.15927 | S46: =$K$46/$K$85*S85 -> 931.28405 | ... V46: =$K$46/$K$85*V85 -> 1017.6392
A47: ='3M-BS'!A53 -> Miscellaneous Current Liabilities | B47: =VLOOKUP($A47,'3M-BS'!$A$48:$K$64,11, FALSE) -> 2251 | C47: =VLOOKUP($A47,'3M-BS'!$A$48:$K$64,10, FALSE) -> 2432 | D47: =VLOOKUP($A47,'3M-BS'!$A$48:$K$64,9, FALSE) -> 2471 | E47: =VLOOKUP($A47,'3M-BS'!$A$48:$K$64,8, FALSE) -> 2739 | F47: =VLOOKUP($A47,'3M-BS'!$A$48:$K$64,7, FALSE) -> 2993 | G47: =VLOOKUP($A47,'3M-BS'!$A$48:$K$64,6, FALSE) -> 2887 | H47: =VLOOKUP($A47,'3M-BS'!$A$48:$K$64,5, FALSE) -> 2855 | I47: =VLOOKUP($A47,'3M-BS'!$A$48:$K$64,4, FALSE) -> 8080 | J47: =VLOOKUP($A47,'3M-BS'!$A$48:$K$64,3, FALSE) -> 5215 | K47: =VLOOKUP($A47,'3M-BS'!$A$48:$K$64,2, FALSE) -> 4338 | L47: =$K$47/$K$85*L85 -> 4401.5155 | M47: =$K$47/$K$85*M85 -> 4577.5761 | N47: =$K$47/$K$85*N85 -> 4760.6792 | O47: =$K$47/$K$85*O85 -> 4951.1063 | P47: =$K$47/$K$85*P85 -> 5149.1506 | Q47: =$K$47/$K$85*Q85 -> 5303.6251 | R47: =$K$47/$K$85*R85 -> 5462.7339 | S47: =$K$47/$K$85*S85 -> 5626.6159 | ... V47: =$K$47/$K$85*V85 -> 6148.3551
A48: Long-Term Debt | B48: =VLOOKUP($A48,'3M-BS'!$A$48:$K$64,11, FALSE) -> 10723 | C48: =VLOOKUP($A48,'3M-BS'!$A$48:$K$64,10, FALSE) -> 12156 | D48: =VLOOKUP($A48,'3M-BS'!$A$48:$K$64,9, FALSE) -> 13486 | E48: =VLOOKUP($A48,'3M-BS'!$A$48:$K$64,8, FALSE) -> 18236 | F48: =VLOOKUP($A48,'3M-BS'!$A$48:$K$64,7, FALSE) -> 18691 | G48: =VLOOKUP($A48,'3M-BS'!$A$48:$K$64,6, FALSE) -> 16740 | H48: =VLOOKUP($A48,'3M-BS'!$A$48:$K$64,5, FALSE) -> 14656 | I48: =VLOOKUP($A48,'3M-BS'!$A$48:$K$64,4, FALSE) -> 13612 | J48: =VLOOKUP($A48,'3M-BS'!$A$48:$K$64,3, FALSE) -> 11577 | K48: =VLOOKUP($A48,'3M-BS'!$A$48:$K$64,2, FALSE) -> 11295 | L48: =L49+L50 -> 11602 | M48: =M49+M50 -> 11102 | N48: =N49+N50 -> 9672 | O48: =O49+O50 -> 9237 | P48: =P49+P50 -> 9878 | Q48: =Q49+Q50 -> 9965 | R48: =R49+R50 -> 9965 | S48: =S49+S50 -> 9965 | ... V48: =V49+V50 -> 9465
A49: Long-Term Debt excl Lease Obligations | B49: =VLOOKUP($A49,'3M-BS'!$A$48:$K$64,11, FALSE) -> 10678 | C49: =VLOOKUP($A49,'3M-BS'!$A$48:$K$64,10, FALSE) -> 12096 | D49: =VLOOKUP($A49,'3M-BS'!$A$48:$K$64,9, FALSE) -> 13411 | E49: =VLOOKUP($A49,'3M-BS'!$A$48:$K$64,8, FALSE) -> 17518 | F49: =VLOOKUP($A49,'3M-BS'!$A$48:$K$64,7, FALSE) -> 17989 | G49: =VLOOKUP($A49,'3M-BS'!$A$48:$K$64,6, FALSE) -> 16056 | H49: =VLOOKUP($A49,'3M-BS'!$A$48:$K$64,5, FALSE) -> 14001 | I49: =VLOOKUP($A49,'3M-BS'!$A$48:$K$64,4, FALSE) -> 13088 | J49: =VLOOKUP($A49,'3M-BS'!$A$48:$K$64,3, FALSE) -> 11125 | K49: =VLOOKUP($A49,'3M-BS'!$A$48:$K$64,2, FALSE) -> 10932 | L49: ='IS-Reorg'!C143-'IS-Reorg'!C144 -> 11239 | M49: ='IS-Reorg'!D143-'IS-Reorg'!D144 -> 10739 | N49: ='IS-Reorg'!E143-'IS-Reorg'!E144 -> 9309 | O49: ='IS-Reorg'!F143-'IS-Reorg'!F144 -> 8874 | P49: ='IS-Reorg'!G143-'IS-Reorg'!G144 -> 9515 | Q49: ='IS-Reorg'!H143-'IS-Reorg'!H144 -> 9602 | R49: ='IS-Reorg'!I143-'IS-Reorg'!I144 -> 9602 | S49: ='IS-Reorg'!J143-'IS-Reorg'!J144 -> 9602 | ... V49: ='IS-Reorg'!M143-'IS-Reorg'!M144 -> 9102
A50: Capital and Operating Lease Obligations | B50: =VLOOKUP($A50,'3M-BS'!$A$48:$K$64,11, FALSE) -> 45 | C50: =VLOOKUP($A50,'3M-BS'!$A$48:$K$64,10, FALSE) -> 60 | D50: =VLOOKUP($A50,'3M-BS'!$A$48:$K$64,9, FALSE) -> 75 | E50: =VLOOKUP($A50,'3M-BS'!$A$48:$K$64,8, FALSE) -> 718 | F50: =VLOOKUP($A50,'3M-BS'!$A$48:$K$64,7, FALSE) -> 702 | G50: =VLOOKUP($A50,'3M-BS'!$A$48:$K$64,6, FALSE) -> 684 | H50: =VLOOKUP($A50,'3M-BS'!$A$48:$K$64,5, FALSE) -> 655 | I50: =VLOOKUP($A50,'3M-BS'!$A$48:$K$64,4, FALSE) -> 524 | J50: =VLOOKUP($A50,'3M-BS'!$A$48:$K$64,3, FALSE) -> 452 | K50: =VLOOKUP($A50,'3M-BS'!$A$48:$K$64,2, FALSE) -> 363 | L50: =K50 -> 363 | M50: =L50 -> 363 | N50: =M50 -> 363 | O50: =N50 -> 363 | P50: =O50 -> 363 | Q50: =P50 -> 363 | R50: =Q50 -> 363 | S50: =R50 -> 363 | ... V50: =U50 -> 363
A51: ='3M-BS'!A59 -> Provision for Risks & Charges | B51: =VLOOKUP($A51,'3M-BS'!$A$48:$K$64,11, FALSE) -> 4274 | C51: =VLOOKUP($A51,'3M-BS'!$A$48:$K$64,10, FALSE) -> 3939 | D51: =VLOOKUP($A51,'3M-BS'!$A$48:$K$64,9, FALSE) -> 3286 | E51: =VLOOKUP($A51,'3M-BS'!$A$48:$K$64,8, FALSE) -> 4223 | F51: =VLOOKUP($A51,'3M-BS'!$A$48:$K$64,7, FALSE) -> 4815 | G51: =VLOOKUP($A51,'3M-BS'!$A$48:$K$64,6, FALSE) -> 3270 | H51: =VLOOKUP($A51,'3M-BS'!$A$48:$K$64,5, FALSE) -> 2352 | I51: =VLOOKUP($A51,'3M-BS'!$A$48:$K$64,4, FALSE) -> 2156 | J51: =VLOOKUP($A51,'3M-BS'!$A$48:$K$64,3, FALSE) -> 1813 | K51: =VLOOKUP($A51,'3M-BS'!$A$48:$K$64,2, FALSE) -> 1631 | L51: =K51 -> 1631 | M51: =L51 -> 1631 | N51: =M51 -> 1631 | O51: =N51 -> 1631 | P51: =O51 -> 1631 | Q51: =P51 -> 1631 | R51: =Q51 -> 1631 | S51: =R51 -> 1631 | ... V51: =U51 -> 1631
A52: ='3M-BS'!A60 -> Deferred Tax Liabilities | B52: =VLOOKUP($A52,'3M-BS'!$A$48:$K$64,11, FALSE) -> 145 | C52: =VLOOKUP($A52,'3M-BS'!$A$48:$K$64,10, FALSE) -> 235 | D52: =VLOOKUP($A52,'3M-BS'!$A$48:$K$64,9, FALSE) -> 279 | E52: =VLOOKUP($A52,'3M-BS'!$A$48:$K$64,8, FALSE) -> 301 | F52: =VLOOKUP($A52,'3M-BS'!$A$48:$K$64,7, FALSE) -> 333 | G52: =VLOOKUP($A52,'3M-BS'!$A$48:$K$64,6, FALSE) -> 458 | H52: =VLOOKUP($A52,'3M-BS'!$A$48:$K$64,5, FALSE) -> 559 | I52: =VLOOKUP($A52,'3M-BS'!$A$48:$K$64,4, FALSE) -> 315 | J52: =VLOOKUP($A52,'3M-BS'!$A$48:$K$64,3, FALSE) -> 354 | K52: =VLOOKUP($A52,'3M-BS'!$A$48:$K$64,2, FALSE) -> 418 | L52: =K52 -> 418 | M52: =L52 -> 418 | N52: =M52 -> 418 | O52: =N52 -> 418 | P52: =O52 -> 418 | Q52: =P52 -> 418 | R52: =Q52 -> 418 | S52: =R52 -> 418 | ... V52: =U52 -> 418
A53: ='3M-BS'!A61 -> Other Liabilities | B53: =VLOOKUP($A53,'3M-BS'!$A$48:$K$64,11, FALSE) -> 1202 | C53: =VLOOKUP($A53,'3M-BS'!$A$48:$K$64,10, FALSE) -> 2348 | D53: =VLOOKUP($A53,'3M-BS'!$A$48:$K$64,9, FALSE) -> 2357 | E53: =VLOOKUP($A53,'3M-BS'!$A$48:$K$64,8, FALSE) -> 2551 | F53: =VLOOKUP($A53,'3M-BS'!$A$48:$K$64,7, FALSE) -> 2626 | G53: =VLOOKUP($A53,'3M-BS'!$A$48:$K$64,6, FALSE) -> 2452 | H53: =VLOOKUP($A53,'3M-BS'!$A$48:$K$64,5, FALSE) -> 4595 | I53: =VLOOKUP($A53,'3M-BS'!$A$48:$K$64,4, FALSE) -> 14332 | J53: =VLOOKUP($A53,'3M-BS'!$A$48:$K$64,3, FALSE) -> 10974 | K53: =VLOOKUP($A53,'3M-BS'!$A$48:$K$64,2, FALSE) -> 10047 | L53: =L54+L55 -> 8689 | M53: =M54+M55 -> 5371 | N53: =N54+N55 -> 3932 | O53: =O54+O55 -> 2468 | P53: =P54+P55 -> 2026 | Q53: =Q54+Q55 -> 1623 | R53: =R54+R55 -> 1241 | S53: =S54+S55 -> 890 | ... V53: =V54+V55 -> 0
A54: ='3M-BS'!A62 -> Other Liabilities (excl. Deferred Income) | B54: =VLOOKUP($A54,'3M-BS'!$A$48:$K$64,11, FALSE) -> 1187 | C54: =VLOOKUP($A54,'3M-BS'!$A$48:$K$64,10, FALSE) -> 2348 | D54: =VLOOKUP($A54,'3M-BS'!$A$48:$K$64,9, FALSE) -> 2357 | E54: =VLOOKUP($A54,'3M-BS'!$A$48:$K$64,8, FALSE) -> 2551 | F54: =VLOOKUP($A54,'3M-BS'!$A$48:$K$64,7, FALSE) -> 2626 | G54: =VLOOKUP($A54,'3M-BS'!$A$48:$K$64,6, FALSE) -> 2452 | H54: =VLOOKUP($A54,'3M-BS'!$A$48:$K$64,5, FALSE) -> 4595 | I54: =VLOOKUP($A54,'3M-BS'!$A$48:$K$64,4, FALSE) -> 14332 | J54: =VLOOKUP($A54,'3M-BS'!$A$48:$K$64,3, FALSE) -> 10974 | K54: =VLOOKUP($A54,'3M-BS'!$A$48:$K$64,2, FALSE) -> 10047 | L54: 8689 | M54: 5371 | N54: 3932 | O54: 2468 | P54: 2026 | Q54: 1623 | R54: 1241 | S54: 890 | T54: 561 | U54: 274 | V54: 0
A55: ='3M-BS'!A63 -> Deferred Income | B55: =VLOOKUP($A55,'3M-BS'!$A$48:$K$64,11, FALSE) -> 15 | C55: =VLOOKUP($A55,'3M-BS'!$A$48:$K$64,10, FALSE) -> 0 | D55: =VLOOKUP($A55,'3M-BS'!$A$48:$K$64,9, FALSE) -> 0 | E55: =VLOOKUP($A55,'3M-BS'!$A$48:$K$64,8, FALSE) -> 0 | F55: =VLOOKUP($A55,'3M-BS'!$A$48:$K$64,7, FALSE) -> 0 | G55: =VLOOKUP($A55,'3M-BS'!$A$48:$K$64,6, FALSE) -> 0 | H55: =VLOOKUP($A55,'3M-BS'!$A$48:$K$64,5, FALSE) -> 0 | I55: =VLOOKUP($A55,'3M-BS'!$A$48:$K$64,4, FALSE) -> 0 | J55: =VLOOKUP($A55,'3M-BS'!$A$48:$K$64,3, FALSE) -> 0 | K55: =VLOOKUP($A55,'3M-BS'!$A$48:$K$64,2, FALSE) -> 0 | L55: =K55 -> 0 | M55: =L55 -> 0 | N55: =M55 -> 0 | O55: =N55 -> 0 | P55: =O55 -> 0 | Q55: =P55 -> 0 | R55: =Q55 -> 0 | S55: =R55 -> 0 | ... V55: =U55 -> 0
A56: Total Liabilities | B56: =SUM(B53+B52+B51+B48+B45+B44+B43+B42) -> 22563 | C56: =SUM(C53+C52+C51+C48+C45+C44+C43+C42) -> 26365 | D56: =SUM(D53+D52+D51+D48+D45+D44+D43+D42) -> 26652 | E56: =SUM(E53+E52+E51+E48+E45+E44+E43+E42) -> 34533 | F56: =SUM(F53+F52+F51+F48+F45+F44+F43+F42) -> 34413 | G56: =SUM(G53+G52+G51+G48+G45+G44+G43+G42) -> 31955 | H56: =SUM(H53+H52+H51+H48+H45+H44+H43+H42) -> 31685 | I56: =SUM(I53+I52+I51+I48+I45+I44+I43+I42) -> 45712 | ... V56: =SUM(V53+V52+V51+V48+V45+V44+V43+V42) -> 22162.537
A57: Total Operating Liabilities | B57: =B53+B52+B51+B45+B44+B43 -> 10868 | C57: =C53+C52+C51+C45+C44+C43 -> 12356 | D57: =D53+D52+D51+D45+D44+D43 -> 11955 | E57: =E53+E52+E51+E45+E44+E43 -> 13234 | F57: =F53+F52+F51+F45+F44+F43 -> 14638 | G57: =G53+G52+G51+G45+G44+G43 -> 13638 | H57: =H53+H52+H51+H45+H44+H43 -> 14819 | I57: =I53*0+I52+I51+I45+I44+I43 -> 14629 | J57: =J53+J52+J51+J45+J44+J43 -> 22315 | K57: =K53+K52+K51+K45+K44+K43 -> 19854 | L57: =L53+L52+L51+L45+L44+L43 -> 18609.59 | M57: =M53+M52+M51+M45+M44+M43 -> 15580.614 | N57: =N53+N52+N51+N45+N44+N43 -> 14441.165 | O57: =O53+O52+O51+O45+O44+O43 -> 13287.623 | P57: =P53+P52+P51+P45+P44+P43 -> 13167.381 | Q57: =Q53+Q52+Q51+Q45+Q44+Q43 -> 13007.214 | ... V57: =V53+V52+V51+V45+V44+V43 -> 12697.537
A60: Equity
A61: Common Equity | B61: =VLOOKUP($A61,'3M-BS'!$A$9:$K$79,11, FALSE) -> 10298 | C61: =VLOOKUP($A61,'3M-BS'!$A$9:$K$79,10, FALSE) -> 11563 | D61: =VLOOKUP($A61,'3M-BS'!$A$9:$K$79,9, FALSE) -> 9796 | E61: =VLOOKUP($A61,'3M-BS'!$A$9:$K$79,8, FALSE) -> 10063 | F61: =VLOOKUP($A61,'3M-BS'!$A$9:$K$79,7, FALSE) -> 12867 | G61: =VLOOKUP($A61,'3M-BS'!$A$9:$K$79,6, FALSE) -> 15046 | H61: =VLOOKUP($A61,'3M-BS'!$A$9:$K$79,5, FALSE) -> 14722 | I61: =VLOOKUP($A61,'3M-BS'!$A$9:$K$79,4, FALSE) -> 4807 | J61: =VLOOKUP($A61,'3M-BS'!$A$9:$K$79,3, FALSE) -> 3842 | K61: =VLOOKUP($A61,'3M-BS'!$A$9:$K$79,2, FALSE) -> 4702 | L61: =SUM(L62:L67) -> 6753.1322 | M61: =SUM(M62:M67) -> 9027.5955 | N61: =SUM(N62:N67) -> 11577.83 | O61: =SUM(O62:O67) -> 14399.297 | P61: =SUM(P62:P67) -> 17519.402 | Q61: =SUM(Q62:Q67) -> 20911.187 | R61: =SUM(R62:R67) -> 24593.23 | S61: =SUM(S62:S67) -> 28578.992 | ... V61: =SUM(V62:V67) -> 42498.029
A62: Common Stock Par/Carry Value | B62: =VLOOKUP($A62,'3M-BS'!$A$9:$K$79,11, FALSE) -> 9 | C62: =VLOOKUP($A62,'3M-BS'!$A$9:$K$79,10, FALSE) -> 9 | D62: =VLOOKUP($A62,'3M-BS'!$A$9:$K$79,9, FALSE) -> 9 | E62: =VLOOKUP($A62,'3M-BS'!$A$9:$K$79,8, FALSE) -> 9 | F62: =VLOOKUP($A62,'3M-BS'!$A$9:$K$79,7, FALSE) -> 9 | G62: =VLOOKUP($A62,'3M-BS'!$A$9:$K$79,6, FALSE) -> 9 | H62: =VLOOKUP($A62,'3M-BS'!$A$9:$K$79,5, FALSE) -> 9 | I62: =VLOOKUP($A62,'3M-BS'!$A$9:$K$79,4, FALSE) -> 9 | J62: =VLOOKUP($A62,'3M-BS'!$A$9:$K$79,3, FALSE) -> 9 | K62: =VLOOKUP($A62,'3M-BS'!$A$9:$K$79,2, FALSE) -> 9 | L62: =K62 -> 9 | M62: =L62 -> 9 | N62: =M62 -> 9 | O62: =N62 -> 9 | P62: =O62 -> 9 | Q62: =P62 -> 9 | R62: =Q62 -> 9 | S62: =R62 -> 9 | ... V62: =U62 -> 9
A63: Additional Paid-In Capital/Capital Surplus | B63: =VLOOKUP($A63,'3M-BS'!$A$9:$K$79,11, FALSE) -> 5061 | C63: =VLOOKUP($A63,'3M-BS'!$A$9:$K$79,10, FALSE) -> 5352 | D63: =VLOOKUP($A63,'3M-BS'!$A$9:$K$79,9, FALSE) -> 5643 | E63: =VLOOKUP($A63,'3M-BS'!$A$9:$K$79,8, FALSE) -> 5907 | F63: =VLOOKUP($A63,'3M-BS'!$A$9:$K$79,7, FALSE) -> 6162 | G63: =VLOOKUP($A63,'3M-BS'!$A$9:$K$79,6, FALSE) -> 6429 | H63: =VLOOKUP($A63,'3M-BS'!$A$9:$K$79,5, FALSE) -> 6691 | I63: =VLOOKUP($A63,'3M-BS'!$A$9:$K$79,4, FALSE) -> 6956 | J63: =VLOOKUP($A63,'3M-BS'!$A$9:$K$79,3, FALSE) -> 7229 | K63: =VLOOKUP($A63,'3M-BS'!$A$9:$K$79,2, FALSE) -> 7440 | L63: =K63 -> 7440 | M63: =L63 -> 7440 | N63: =M63 -> 7440 | O63: =N63 -> 7440 | P63: =O63 -> 7440 | Q63: =P63 -> 7440 | R63: =Q63 -> 7440 | S63: =R63 -> 7440 | ... V63: =U63 -> 7440
A64: Retained Earnings | B64: =VLOOKUP($A64,'3M-BS'!$A$9:$K$79,11, FALSE) -> 37907 | C64: =VLOOKUP($A64,'3M-BS'!$A$9:$K$79,10, FALSE) -> 39115 | D64: =VLOOKUP($A64,'3M-BS'!$A$9:$K$79,9, FALSE) -> 40636 | E64: =VLOOKUP($A64,'3M-BS'!$A$9:$K$79,8, FALSE) -> 42135 | F64: =VLOOKUP($A64,'3M-BS'!$A$9:$K$79,7, FALSE) -> 43821 | G64: =VLOOKUP($A64,'3M-BS'!$A$9:$K$79,6, FALSE) -> 45821 | H64: =VLOOKUP($A64,'3M-BS'!$A$9:$K$79,5, FALSE) -> 47950 | I64: =VLOOKUP($A64,'3M-BS'!$A$9:$K$79,4, FALSE) -> 37479 | J64: =VLOOKUP($A64,'3M-BS'!$A$9:$K$79,3, FALSE) -> 36797 | K64: =VLOOKUP($A64,'3M-BS'!$A$9:$K$79,2, FALSE) -> 38258 | L64: =K64+'IS-Reorg'!L46-'IS-Reorg'!L56*'IS-Reorg'!L55 -> 40309.132 | M64: =L64+'IS-Reorg'!M46-'IS-Reorg'!M56*'IS-Reorg'!M55 -> 42583.595 | N64: =M64+'IS-Reorg'!N46-'IS-Reorg'!N56*'IS-Reorg'!N55 -> 45133.83 | O64: =N64+'IS-Reorg'!O46-'IS-Reorg'!O56*'IS-Reorg'!O55 -> 47955.297 | P64: =O64+'IS-Reorg'!P46-'IS-Reorg'!P56*'IS-Reorg'!P55 -> 51075.402 | Q64: =P64+'IS-Reorg'!Q46-'IS-Reorg'!Q56*'IS-Reorg'!Q55 -> 54467.187 | R64: =Q64+'IS-Reorg'!R46-'IS-Reorg'!R56*'IS-Reorg'!R55 -> 58149.23 | S64: =R64+'IS-Reorg'!S46-'IS-Reorg'!S56*'IS-Reorg'!S55 -> 62134.992 | ... V64: =U64+'IS-Reorg'!V46-'IS-Reorg'!V56*'IS-Reorg'!V55 -> 76054.029
A65: Cumulative Translation Adjustment/Unrealized For. Exch. Gain | B65: =VLOOKUP($A65,'3M-BS'!$A$9:$K$79,11, FALSE) -> -2008 | C65: =VLOOKUP($A65,'3M-BS'!$A$9:$K$79,10, FALSE) -> -1638 | D65: =VLOOKUP($A65,'3M-BS'!$A$9:$K$79,9, FALSE) -> -2098 | E65: =VLOOKUP($A65,'3M-BS'!$A$9:$K$79,8, FALSE) -> -1899 | F65: =VLOOKUP($A65,'3M-BS'!$A$9:$K$79,7, FALSE) -> -1450 | G65: =VLOOKUP($A65,'3M-BS'!$A$9:$K$79,6, FALSE) -> -1943 | H65: =VLOOKUP($A65,'3M-BS'!$A$9:$K$79,5, FALSE) -> -2828 | I65: =VLOOKUP($A65,'3M-BS'!$A$9:$K$79,4, FALSE) -> -2506 | J65: =VLOOKUP($A65,'3M-BS'!$A$9:$K$79,3, FALSE) -> -2953 | K65: =VLOOKUP($A65,'3M-BS'!$A$9:$K$79,2, FALSE) -> -2520 | L65: =K65 -> -2520 | M65: =L65 -> -2520 | N65: =M65 -> -2520 | O65: =N65 -> -2520 | P65: =O65 -> -2520 | Q65: =P65 -> -2520 | R65: =Q65 -> -2520 | S65: =R65 -> -2520 | ... V65: =U65 -> -2520
A66: Other Appropriated Reserves | B66: =VLOOKUP($A66,'3M-BS'!$A$9:$K$79,11, FALSE) -> -5237 | C66: =VLOOKUP($A66,'3M-BS'!$A$9:$K$79,10, FALSE) -> -5388 | D66: =VLOOKUP($A66,'3M-BS'!$A$9:$K$79,9, FALSE) -> -4768 | E66: =VLOOKUP($A66,'3M-BS'!$A$9:$K$79,8, FALSE) -> -6240 | F66: =VLOOKUP($A66,'3M-BS'!$A$9:$K$79,7, FALSE) -> -6271 | G66: =VLOOKUP($A66,'3M-BS'!$A$9:$K$79,6, FALSE) -> -4807 | H66: =VLOOKUP($A66,'3M-BS'!$A$9:$K$79,5, FALSE) -> -3845 | I66: =VLOOKUP($A66,'3M-BS'!$A$9:$K$79,4, FALSE) -> -4272 | J66: =VLOOKUP($A66,'3M-BS'!$A$9:$K$79,3, FALSE) -> -2778 | K66: =VLOOKUP($A66,'3M-BS'!$A$9:$K$79,2, FALSE) -> -2549 | L66: =K66 -> -2549 | M66: =L66 -> -2549 | N66: =M66 -> -2549 | O66: =N66 -> -2549 | P66: =O66 -> -2549 | Q66: =P66 -> -2549 | R66: =Q66 -> -2549 | S66: =R66 -> -2549 | ... V66: =U66 -> -2549
A67: Treasury Stock | B67: =VLOOKUP($A67,'3M-BS'!$A$9:$K$79,11, FALSE) -> -25434 | C67: =VLOOKUP($A67,'3M-BS'!$A$9:$K$79,10, FALSE) -> -25887 | D67: =VLOOKUP($A67,'3M-BS'!$A$9:$K$79,9, FALSE) -> -29626 | E67: =VLOOKUP($A67,'3M-BS'!$A$9:$K$79,8, FALSE) -> -29849 | F67: =VLOOKUP($A67,'3M-BS'!$A$9:$K$79,7, FALSE) -> -29404 | G67: =VLOOKUP($A67,'3M-BS'!$A$9:$K$79,6, FALSE) -> -30463 | H67: =VLOOKUP($A67,'3M-BS'!$A$9:$K$79,5, FALSE) -> -33255 | I67: =VLOOKUP($A67,'3M-BS'!$A$9:$K$79,4, FALSE) -> -32859 | J67: =VLOOKUP($A67,'3M-BS'!$A$9:$K$79,3, FALSE) -> -34462 | K67: =VLOOKUP($A67,'3M-BS'!$A$9:$K$79,2, FALSE) -> -35936 | L67: =K67 -> -35936 | M67: =L67 -> -35936 | N67: =M67 -> -35936 | O67: =N67 -> -35936 | P67: =O67 -> -35936 | Q67: =P67 -> -35936 | R67: =Q67 -> -35936 | S67: =R67 -> -35936 | ... V67: =U67 -> -35936
A68: Total Shareholders' Equity | B68: =VLOOKUP($A68,'3M-BS'!$A$9:$K$79,11, FALSE) -> 10298 | C68: =VLOOKUP($A68,'3M-BS'!$A$9:$K$79,10, FALSE) -> 11563 | D68: =VLOOKUP($A68,'3M-BS'!$A$9:$K$79,9, FALSE) -> 9796 | E68: =VLOOKUP($A68,'3M-BS'!$A$9:$K$79,8, FALSE) -> 10063 | F68: =VLOOKUP($A68,'3M-BS'!$A$9:$K$79,7, FALSE) -> 12867 | G68: =VLOOKUP($A68,'3M-BS'!$A$9:$K$79,6, FALSE) -> 15046 | H68: =VLOOKUP($A68,'3M-BS'!$A$9:$K$79,5, FALSE) -> 14722 | I68: =VLOOKUP($A68,'3M-BS'!$A$9:$K$79,4, FALSE) -> 4807 | J68: =VLOOKUP($A68,'3M-BS'!$A$9:$K$79,3, FALSE) -> 3842 | K68: =VLOOKUP($A68,'3M-BS'!$A$9:$K$79,2, FALSE) -> 4702 | L68: =SUM(L62:L67) -> 6753.1322 | M68: =SUM(M62:M67) -> 9027.5955 | N68: =SUM(N62:N67) -> 11577.83 | O68: =SUM(O62:O67) -> 14399.297 | P68: =SUM(P62:P67) -> 17519.402 | Q68: =SUM(Q62:Q67) -> 20911.187 | R68: =SUM(R62:R67) -> 24593.23 | S68: =SUM(S62:S67) -> 28578.992 | ... V68: =SUM(V62:V67) -> 42498.029
A69: Accumulated Minority Interest | B69: =VLOOKUP($A69,'3M-BS'!$A$9:$K$79,11, FALSE) -> 45 | C69: =VLOOKUP($A69,'3M-BS'!$A$9:$K$79,10, FALSE) -> 59 | D69: =VLOOKUP($A69,'3M-BS'!$A$9:$K$79,9, FALSE) -> 52 | E69: =VLOOKUP($A69,'3M-BS'!$A$9:$K$79,8, FALSE) -> 63 | F69: =VLOOKUP($A69,'3M-BS'!$A$9:$K$79,7, FALSE) -> 64 | G69: =VLOOKUP($A69,'3M-BS'!$A$9:$K$79,6, FALSE) -> 71 | H69: =VLOOKUP($A69,'3M-BS'!$A$9:$K$79,5, FALSE) -> 48 | I69: =VLOOKUP($A69,'3M-BS'!$A$9:$K$79,4, FALSE) -> 61 | J69: =VLOOKUP($A69,'3M-BS'!$A$9:$K$79,3, FALSE) -> 52 | K69: =VLOOKUP($A69,'3M-BS'!$A$9:$K$79,2, FALSE) -> 45 | L69: =K69 -> 45 | M69: =L69 -> 45 | N69: =M69 -> 45 | O69: =N69 -> 45 | P69: =O69 -> 45 | Q69: =P69 -> 45 | R69: =Q69 -> 45 | S69: =R69 -> 45 | ... V69: =U69 -> 45
A70: Total Equity | B70: =VLOOKUP($A70,'3M-BS'!$A$9:$K$79,11, FALSE) -> 10343 | C70: =VLOOKUP($A70,'3M-BS'!$A$9:$K$79,10, FALSE) -> 11622 | D70: =VLOOKUP($A70,'3M-BS'!$A$9:$K$79,9, FALSE) -> 9848 | E70: =VLOOKUP($A70,'3M-BS'!$A$9:$K$79,8, FALSE) -> 10126 | F70: =VLOOKUP($A70,'3M-BS'!$A$9:$K$79,7, FALSE) -> 12931 | G70: =VLOOKUP($A70,'3M-BS'!$A$9:$K$79,6, FALSE) -> 15117 | H70: =VLOOKUP($A70,'3M-BS'!$A$9:$K$79,5, FALSE) -> 14770 | I70: =VLOOKUP($A70,'3M-BS'!$A$9:$K$79,4, FALSE) -> 4868 | J70: =VLOOKUP($A70,'3M-BS'!$A$9:$K$79,3, FALSE) -> 3894 | K70: =VLOOKUP($A70,'3M-BS'!$A$9:$K$79,2, FALSE) -> 4747 | L70: =L68+L69 -> 6798.1322 | M70: =M68+M69 -> 9072.5955 | N70: =N68+N69 -> 11622.83 | O70: =O68+O69 -> 14444.297 | P70: =P68+P69 -> 17564.402 | Q70: =Q68+Q69 -> 20956.187 | R70: =R68+R69 -> 24638.23 | S70: =S68+S69 -> 28623.992 | ... V70: =V68+V69 -> 42543.029
A71: Total Liabilities & Shareholders' Equity | B71: =B70+B56 -> 32906 | C71: =C70+C56 -> 37987 | D71: =D70+D56 -> 36500 | E71: =E70+E56 -> 44659 | F71: =F70+F56 -> 47344 | G71: =G70+G56 -> 47072 | H71: =H70+H56 -> 46455 | I71: =I70+I56 -> 50580 | ... V71: =V70+V56 -> 64705.566
A72: Per Share
A73: Book Value per Share | B73: =VLOOKUP($A73,'3M-BS'!$A$9:$K$79,11, FALSE) -> 17.25749 | C73: =VLOOKUP($A73,'3M-BS'!$A$9:$K$79,10, FALSE) -> 19.4374 | D73: =VLOOKUP($A73,'3M-BS'!$A$9:$K$79,9, FALSE) -> 16.98998 | E73: =VLOOKUP($A73,'3M-BS'!$A$9:$K$79,8, FALSE) -> 17.49525 | F73: =VLOOKUP($A73,'3M-BS'!$A$9:$K$79,7, FALSE) -> 22.27089 | G73: =VLOOKUP($A73,'3M-BS'!$A$9:$K$79,6, FALSE) -> 26.3113 | H73: =VLOOKUP($A73,'3M-BS'!$A$9:$K$79,5, FALSE) -> 26.80406 | I73: =VLOOKUP($A73,'3M-BS'!$A$9:$K$79,4, FALSE) -> 8.69917 | J73: =VLOOKUP($A73,'3M-BS'!$A$9:$K$79,3, FALSE) -> 7.1218 | K73: =VLOOKUP($A73,'3M-BS'!$A$9:$K$79,2, FALSE) -> 8.86703
A74: Tangible Book Value per Share | B74: =VLOOKUP($A74,'3M-BS'!$A$9:$K$79,11, FALSE) -> -1.990863 | C74: =VLOOKUP($A74,'3M-BS'!$A$9:$K$79,10, FALSE) -> -3.170365 | D74: =VLOOKUP($A74,'3M-BS'!$A$9:$K$79,9, FALSE) -> -5.050512 | E74: =VLOOKUP($A74,'3M-BS'!$A$9:$K$79,8, FALSE) -> -16.968458 | F74: =VLOOKUP($A74,'3M-BS'!$A$9:$K$79,7, FALSE) -> -11.717878 | G74: =VLOOKUP($A74,'3M-BS'!$A$9:$K$79,6, FALSE) -> -6.519244 | H74: =VLOOKUP($A74,'3M-BS'!$A$9:$K$79,5, FALSE) -> -5.037824 | I74: =VLOOKUP($A74,'3M-BS'!$A$9:$K$79,4, FALSE) -> -5.244479 | J74: =VLOOKUP($A74,'3M-BS'!$A$9:$K$79,3, FALSE) -> -6.764042 | K74: =VLOOKUP($A74,'3M-BS'!$A$9:$K$79,2, FALSE) -> -5.317954
A76: Check | B76: =B38-B71 -> 0 | C76: =C38-C71 -> 0 | D76: =D38-D71 -> 0 | E76: =E38-E71 -> 0 | F76: =F38-F71 -> 0 | G76: =G38-G71 -> 0 | H76: =H38-H71 -> 0 | I76: =I38-I71 -> 0 | ... V76: =V38-V71 -> 0
A78: Invested Capital with Goodwill | B78: =B39-B57 -> 19104 | C78: =C39-C57 -> 21311 | D78: =D39-D57 -> 21066 | E78: =E39-E57 -> 28241 | F78: =F39-F57 -> 27444 | G78: =G39-G57 -> 28366 | H78: =H39-H57 -> 26767 | I78: =I39-I57 -> 29945 | ... V78: =V39-V57 -> 20022.718
A79: Invested Capital without Goodwill | B79: =B78-B32 -> 9938 | C79: =C78-C32 -> 10798 | D79: =D78-D32 -> 11015 | E79: =E78-E32 -> 14797 | F79: =F78-F32 -> 13642 | G79: =G78-G32 -> 14880 | H79: =H78-H32 -> 13977 | I79: =I78-I32 -> 23563 | ... V79: =V78-V32 -> 13603.718
B83: 2016 | C83: 2017 | D83: =C83+1 -> 2018 | E83: =D83+1 -> 2019 | F83: =E83+1 -> 2020 | G83: =F83+1 -> 2021 | H83: =G83+1 -> 2022 | I83: =H83+1 -> 2023 | J83: =I83+1 -> 2024 | K83: =J83+1 -> 2025 | L83: 2026 | M83: =L83+1 -> 2027 | N83: =M83+1 -> 2028 | O83: =N83+1 -> 2029 | P83: =O83+1 -> 2030 | Q83: =P83+1 -> 2031 | R83: =Q83+1 -> 2032 | S83: =R83+1 -> 2033 | T83: =S83+1 -> 2034 | ... V83: =U83+1 -> 2036
A84: Number of Days Per Period | B84: 366 | C84: 365 | D84: 365 | E84: 365 | F84: 366 | G84: 365 | H84: 365 | I84: 365 | J84: 366 | K84: 365 | L84: 365 | M84: 365 | N84: 366 | O84: 365 | P84: 365 | Q84: 365 | R84: 366 | S84: 365 | T84: 365 | U84: 365 | V84: 366
A85: Revenues | B85: ='IS-Reorg'!B4 -> 30109 | C85: ='IS-Reorg'!C4 -> 31657 | D85: ='IS-Reorg'!D4 -> 32765 | E85: ='IS-Reorg'!E4 -> 32136 | F85: ='IS-Reorg'!F4 -> 32184 | G85: ='IS-Reorg'!G4 -> 35355 | H85: ='IS-Reorg'!H4 -> 34229 | I85: ='IS-Reorg'!I4 -> 24610 | ... V85: ='IS-Reorg'!V4 -> 35359.42
A86: Cost of Goods Sold | B86: ='IS-Reorg'!B6 -> 13659 | C86: ='IS-Reorg'!C6 -> 14451 | D86: ='IS-Reorg'!D6 -> 15087 | E86: ='IS-Reorg'!E6 -> 15237 | F86: ='IS-Reorg'!F6 -> 14670 | G86: ='IS-Reorg'!G6 -> 16828 | H86: ='IS-Reorg'!H6 -> 17432 | I86: ='IS-Reorg'!I6 -> 13604 | ... V86: ='IS-Reorg'!V6 -> 17740.088
A88: Number of Days for WC
A89: Accounts Receivable | B89: =B95/B85*B84 -> 53.388422 | C89: =C95/C85*C84 -> 56.623022 | D89: =D95/D85*D84 -> 55.922478 | E89: =E95/E85*E84 -> 54.416075 | F89: =F95/F85*F84 -> 53.505779 | G89: =G95/G85*G84 -> 48.109178 | H89: =H95/H85*H84 -> 48.326857 | I89: =I95/I85*I84 -> 53.407761 | ... K89: =K95/K85*K84 -> 51.689314 | L89: =K89 -> 51.689314 | M89: =L89 -> 51.689314 | N89: =M89 -> 51.689314 | O89: =N89 -> 51.689314 | P89: =O89 -> 51.689314 | Q89: =P89 -> 51.689314 | R89: =Q89 -> 51.689314 | S89: =R89 -> 51.689314 | ... V89: =U89 -> 51.689314
A90: Inventory | B90: =B96/B86*365 -> 90.455011 | C90: =C96/C86*365 -> 101.88983 | D90: =D96/D86*365 -> 105.6267 | E90: =E96/E86*365 -> 99.029336 | F90: =F96/F86*365 -> 105.46933 | G90: =G96/G86*365 -> 108.12485 | H90: =H96/H86*365 -> 112.48164 | I90: =I96/I86*365 -> 105.81888 | ... K90: =K96/K86*365 -> 97.08406 | L90: =K90 -> 97.08406 | M90: =L90 -> 97.08406 | N90: =M90 -> 97.08406 | O90: =N90 -> 97.08406 | P90: =O90 -> 97.08406 | Q90: =P90 -> 97.08406 | R90: =Q90 -> 97.08406 | S90: =R90 -> 97.08406 | ... V90: =U90 -> 97.08406
A91: Accounts Payable | B91: =B97/B86*B84 -> 48.178344 | C91: =C97/C86*C84 -> 49.126358 | D91: =D97/D86*D84 -> 54.821369 | E91: =E97/E86*E84 -> 53.371399 | F91: =F97/F86*F84 -> 63.89407 | G91: =G97/G86*G84 -> 64.939981 | H91: =H97/H86*H84 -> 66.647258 | I91: =I97/I86*I84 -> 74.481035 | ... K91: =K97/K86*K84 -> 71.652863 | L91: =K91 -> 71.652863 | M91: =L91 -> 71.652863 | N91: =M91 -> 71.652863 | O91: =N91 -> 71.652863 | P91: =O91 -> 71.652863 | Q91: =P91 -> 71.652863 | R91: =Q91 -> 71.652863 | S91: =R91 -> 71.652863 | ... V91: =U91 -> 71.652863
A94: Total Amounts for WC Items
A95: Accounts Receivable | B95: =B7 -> 4392 | C95: =C7 -> 4911 | D95: =D7 -> 5020 | E95: =E7 -> 4791 | F95: =F7 -> 4705 | G95: =G7 -> 4660 | H95: =H7 -> 4532 | I95: =I7 -> 3601 | ... K95: =K7 -> 3533 | L95: =L89*L85/L84 -> 3584.729 | M95: =M89*M85/M84 -> 3728.1181 | N95: =N89*N85/N84 -> 3866.6493 | O95: =O89*O85/O84 -> 4032.3326 | P95: =P89*P85/P84 -> 4193.6259 | Q95: =Q89*Q85/Q84 -> 4319.4346 | R95: =R89*R85/R84 -> 4436.8619 | S95: =S89*S85/S84 -> 4582.4882 | ... V95: =V89*V85/V84 -> 4993.7272
A96: Inventory | B96: =B11 -> 3385 | C96: =C11 -> 4034 | D96: =D11 -> 4366 | E96: =E11 -> 4134 | F96: =F11 -> 4239 | G96: =G11 -> 4985 | H96: =H11 -> 5372 | I96: =I11 -> 3944 | ... K96: =K11 -> 3661 | L96: =L90*L86/L84 -> 3714.6031 | M96: =M90*M86/M84 -> 3828.176 | N96: =N90*N86/N84 -> 3934.1131 | O96: =O90*O86/O84 -> 4064.819 | P96: =P90*P86/P84 -> 4188.0289 | Q96: =Q90*Q86/Q84 -> 4273.1055 | R96: =R90*R86/R84 -> 4347.6062 | S96: =S90*S86/S84 -> 4447.2683 | ... V96: =V90*V86/V84 -> 4705.6824
A97: Accounts Payable | B97: =B43 -> 1798 | C97: =C43 -> 1945 | D97: =D43 -> 2266 | E97: =E43 -> 2228 | F97: =F43 -> 2561 | G97: =G43 -> 2994 | H97: =H43 -> 3183 | I97: =I43 -> 2776 | ... K97: =K43 -> 2702 | L97: =L91*L86/365 -> 2741.5618 | M97: =M91*M86/365 -> 2825.3842 | N97: =N91*N86/365 -> 2911.526 | O97: =O91*O86/365 -> 3000.0385 | P97: =P91*P86/365 -> 3090.9736 | Q97: =Q91*Q86/365 -> 3153.7643 | R97: =R91*R86/365 -> 3217.5406 | S97: =S91*S86/365 -> 3282.3051 | ... V97: =V91*V86/365 -> 3482.5427
A100: Net Working Capital
A101: Current Assets | B101: =B95+B96 -> 7777 | C101: =C95+C96 -> 8945 | D101: =D95+D96 -> 9386 | E101: =E95+E96 -> 8925 | F101: =F95+F96 -> 8944 | G101: =G95+G96 -> 9645 | H101: =H95+H96 -> 9904 | I101: =I95+I96 -> 7545 | ... V101: =V95+V96 -> 9699.4095
A102: Current Liabilities | B102: =B97 -> 1798 | C102: =C97 -> 1945 | D102: =D97 -> 2266 | E102: =E97 -> 2228 | F102: =F97 -> 2561 | G102: =G97 -> 2994 | H102: =H97 -> 3183 | I102: =I97 -> 2776 | ... V102: =V97 -> 3482.5427
A103: Net Working Capital | B103: =B101-B102 -> 5979 | C103: =C101-C102 -> 7000 | D103: =D101-D102 -> 7120 | E103: =E101-E102 -> 6697 | F103: =F101-F102 -> 6383 | G103: =G101-G102 -> 6651 | H103: =H101-H102 -> 6721 | I103: =I101-I102 -> 4769 | ... V103: =V101-V102 -> 6216.8669

Sheet Beta
A1: Date | B1: Rf | C1: Monthly Rf | D1: Re | E1: Re monthly return % | F1: Rm | G1: Rm monthly return % | H1: Rm-Rf | I1: Re-Rf
A2: 44287 | B2: =1.64 -> 1.64 | C2: =B2/100/12 -> 0.0013666667 | D2: 164.82387 | E2: =D2/161.09-1 -> 0.023178782 | F2: 4181.1749 | G2: =F2/3972.89-1 -> 0.052426545 | H2: =G2-C2 -> 0.051059878 | I2: =E2-C2 -> 0.021812115 | L2: SUMMARY OUTPUT
A3: 44317 | B3: 1.62 | C3: =B3/100/12 -> 0.00135 | D3: 169.75671 | E3: =D3/D2-1 -> 0.029927947 | F3: 4204.1105 | G3: =F3/F2-1 -> 0.0054854558 | H3: =G3-C3 -> 0.0041354558 | I3: =E3-C3 -> 0.028577947
A4: 44348 | B4: 1.52 | C4: =B4/100/12 -> 0.0012666667 | D4: 166.06963 | E4: =D4/D3-1 -> -0.021719789 | F4: 4297.4966 | G4: =F4/F3-1 -> 0.022213043 | H4: =G4-C4 -> 0.020946376 | I4: =E4-C4 -> -0.022986456 | L4: Regression Statistics
A5: 44378 | B5: 1.32 | C5: =B5/100/12 -> 0.0011 | D5: 165.49274 | E5: =D5/D4-1 -> -0.0034737839 | F5: 4395.264 | G5: =F5/F4-1 -> 0.022749835 | H5: =G5-C5 -> 0.021649835 | I5: =E5-C5 -> -0.0045737839 | L5: Multiple R | M5: 0.57878335
A6: 44409 | B6: 1.28 | C6: =B6/100/12 -> 0.0010666667 | D6: 162.81729 | E6: =D6/D5-1 -> -0.01616657 | F6: 4522.6801 | G6: =F6/F5-1 -> 0.028989419 | H6: =G6-C6 -> 0.027922752 | I6: =E6-C6 -> -0.017233237 | L6: R Square | M6: 0.33499017
A7: 44440 | B7: 1.37 | C7: =B7/100/12 -> 0.0011416667 | D7: 146.66432 | E7: =D7/D6-1 -> -0.099209181 | F7: 4307.5388 | G7: =F7/F6-1 -> -0.047569442 | H7: =G7-C7 -> -0.048711108 | I7: =E7-C7 -> -0.10035085 | L7: Adjusted R Square | M7: 0.32352449
A8: 44470 | B8: 1.58 | C8: =B8/100/12 -> 0.0013166667 | D8: 149.38992 | E8: =D8/D7-1 -> 0.018583934 | F8: 4605.3766 | G8: =F8/F7-1 -> 0.069143405 | H8: =G8-C8 -> 0.067826739 | I8: =E8-C8 -> 0.017267267 | L8: Standard Error | M8: 0.066990033
A9: 44501 | B9: 1.56 | C9: =B9/100/12 -> 0.0013 | D9: 142.16623 | E9: =D9/D8-1 -> -0.048354601 | F9: 4567.0015 | G9: =F9/F8-1 -> -0.0083326853 | H9: =G9-C9 -> -0.0096326853 | I9: =E9-C9 -> -0.049654601 | L9: Observations | M9: 60
A10: 44531 | B10: 1.47 | C10: =B10/100/12 -> 0.001225 | D10: 148.51205 | E10: =D10/D9-1 -> 0.04463662 | F10: 4766.183 | G10: =F10/F9-1 -> 0.043613184 | H10: =G10-C10 -> 0.042388184 | I10: =E10-C10 -> 0.04341162
A11: 44562 | B11: 1.76 | C11: =B11/100/12 -> 0.0014666667 | D11: 138.80522 | E11: =D11/D10-1 -> -0.065360555 | F11: 4515.5476 | G11: =F11/F10-1 -> -0.052586188 | H11: =G11-C11 -> -0.054052855 | I11: =E11-C11 -> -0.066827222 | L11: ANOVA
A12: 44593 | B12: 1.93 | C12: =B12/100/12 -> 0.0016083333 | D12: 124.28258 | E12: =D12/D11-1 -> -0.10462604 | F12: 4373.9391 | G12: =F12/F11-1 -> -0.03136019 | H12: =G12-C12 -> -0.032968523 | I12: =E12-C12 -> -0.10623437 | M12: df | N12: SS | O12: MS | P12: F | Q12: Significance F
A13: 44621 | B13: 2.13 | C13: =B13/100/12 -> 0.001775 | D13: 124.47488 | E13: =D13/D12-1 -> 0.0015473126 | F13: 4530.4135 | G13: =F13/F12-1 -> 0.035774229 | H13: =G13-C13 -> 0.033999229 | I13: =E13-C13 -> -0.00022768742 | L13: Regression | M13: 1 | N13: 0.131115 | O13: 0.131115 | P13: 29.216756 | Q13: 1.2719831e-06
A14: 44652 | B14: 2.75 | C14: =B14/100/12 -> 0.0022916667 | D14: 120.57877 | E14: =D14/D13-1 -> -0.031300403 | F14: 4131.9264 | G14: =F14/F13-1 -> -0.087958206 | H14: =G14-C14 -> -0.090249873 | I14: =E14-C14 -> -0.033592069 | L14: Residual | M14: 58 | N14: 0.26028454 | O14: 0.0044876645
A15: 44682 | B15: 2.9 | C15: =B15/100/12 -> 0.0024166667 | D15: 124.81767 | E15: =D15/D14-1 -> 0.035154572 | F15: 4132.1478 | G15: =F15/F14-1 -> 5.3575878e-05 | H15: =G15-C15 -> -0.0023630908 | I15: =E15-C15 -> 0.032737905 | L15: Total | M15: 59 | N15: 0.39139954
A16: 44713 | B16: 3.14 | C16: =B16/100/12 -> 0.0026166667 | D16: 108.1965 | E16: =D16/D15-1 -> -0.13316356 | F16: 3785.3848 | G16: =F16/F15-1 -> -0.083918329 | H16: =G16-C16 -> -0.086534995 | I16: =E16-C16 -> -0.13578023
A17: 44743 | B17: 2.9 | C17: =B17/100/12 -> 0.0024166667 | D17: 119.75942 | E17: =D17/D16-1 -> 0.10686963 | F17: 4130.2858 | G17: =F17/F16-1 -> 0.091113834 | H17: =G17-C17 -> 0.088697168 | I17: =E17-C17 -> 0.10445296 | M17: Coefficients | N17: Standard Error | O17: t Stat | P17: P-value | Q17: Lower 95% | R17: Upper 95% | S17: Lower 95.0% | T17: Upper 95.0%
A18: 44774 | B18: 2.9 | C18: =B18/100/12 -> 0.0024166667 | D18: 103.96596 | E18: =D18/D17-1 -> -0.13187656 | F18: 3954.999 | G18: =F18/F17-1 -> -0.042439381 | H18: =G18-C18 -> -0.044856048 | I18: =E18-C18 -> -0.13429322 | L18: Intercept | M18: -0.0082342357 | N18: 0.0087393213 | O18: -0.9422054 | P18: 0.34999558 | Q18: -0.025727888 | R18: 0.0092594165 | S18: -0.025727888 | T18: 0.0092594165
A19: 44805 | B19: 3.52 | C19: =B19/100/12 -> 0.0029333333 | D19: 92.386314 | E19: =D19/D18-1 -> -0.11137921 | F19: 3585.6241 | G19: =F19/F18-1 -> -0.093394435 | H19: =G19-C19 -> -0.096327768 | I19: =E19-C19 -> -0.11431254 | L19: X Variable 1 | M19: 1.0721027 | N19: 0.19834461 | O19: 5.4052526 | P19: 1.2719831e-06 | Q19: 0.67507286 | R19: 1.4691326 | S19: 0.67507286 | T19: 1.4691326
A20: 44835 | B20: 3.98 | C20: =B20/100/12 -> 0.0033166667 | D20: 105.16991 | E20: =D20/D19-1 -> 0.1383711 | F20: 3871.9772 | G20: =F20/F19-1 -> 0.079861444 | H20: =G20-C20 -> 0.076544777 | I20: =E20-C20 -> 0.13505443
A21: 44866 | B21: 3.89 | C21: =B21/100/12 -> 0.0032416667 | D21: 105.3204 | E21: =D21/D20-1 -> 0.0014309226 | F21: 4080.1066 | G21: =F21/F20-1 -> 0.053752726 | H21: =G21-C21 -> 0.050511059 | I21: =E21-C21 -> -0.0018107441 | L21: Beta | M21: =M19 -> 1.0721027
A22: 44896 | B22: 3.62 | C22: =B22/100/12 -> 0.0030166667 | D22: 100.26214 | E22: =D22/D21-1 -> -0.048027353 | F22: 3839.4966 | G22: =F22/F21-1 -> -0.058971491 | H22: =G22-C22 -> -0.061988157 | I22: =E22-C22 -> -0.051044019
A23: 44927 | B23: 3.53 | C23: =B23/100/12 -> 0.0029416667 | D23: 96.21554 | E23: =D23/D22-1 -> -0.0403602 | F23: 4076.6038 | G23: =F23/F22-1 -> 0.061754771 | H23: =G23-C23 -> 0.058813104 | I23: =E23-C23 -> -0.043301866 | L23: Adjusted beta after beta smoothing
A24: 44958 | B24: 3.75 | C24: =B24/100/12 -> 0.003125 | D24: 90.07874 | E24: =D24/D23-1 -> -0.063781797 | F24: 3970.1534 | G24: =F24/F23-1 -> -0.026112515 | H24: =G24-C24 -> -0.029237515 | I24: =E24-C24 -> -0.066906797
A25: 44986 | B25: 3.66 | C25: =B25/100/12 -> 0.00305 | D25: 87.87987 | E25: =D25/D24-1 -> -0.024410532 | F25: 4109.3124 | G25: =F25/F24-1 -> 0.035051291 | H25: =G25-C25 -> 0.032001291 | I25: =E25-C25 -> -0.027460532 | L25: Adj Beta | M25: =0.67*M21+0.33 -> 1.0483088
A26: 45017 | B26: 3.46 | C26: =B26/100/12 -> 0.0028833333 | D26: 88.807915 | E26: =D26/D25-1 -> 0.010560382 | F26: 4169.4814 | G26: =F26/F25-1 -> 0.014642098 | H26: =G26-C26 -> 0.011758765 | I26: =E26-C26 -> 0.0076770487
A27: 45047 | B27: 3.57 | C27: =B27/100/12 -> 0.002975 | D27: 78.014175 | E27: =D27/D26-1 -> -0.12154029 | F27: 4179.8255 | G27: =F27/F26-1 -> 0.0024808987 | H27: =G27-C27 -> -0.00049410129 | I27: =E27-C27 -> -0.12451529 | L27: Yahoo Finance reports a beta of 1.09 for MMM (5-yr monthly vs S&P 500, as of May 2026), closely corroborating this model's raw regression beta (1.07)
A28: 45078 | B28: 3.75 | C28: =B28/100/12 -> 0.003125 | D28: 83.68277 | E28: =D28/D27-1 -> 0.07266109 | F28: 4450.3813 | G28: =F28/F27-1 -> 0.064728983 | H28: =G28-C28 -> 0.061603983 | I28: =E28-C28 -> 0.06953609 | L28: and adjusted beta (1.05).
A29: 45108 | B29: 3.9 | C29: =B29/100/12 -> 0.00325 | D29: 93.22239 | E29: =D29/D28-1 -> 0.11399742 | F29: 4588.9611 | G29: =F29/F28-1 -> 0.031138866 | H29: =G29-C29 -> 0.027888866 | I29: =E29-C29 -> 0.11074742
A30: 45139 | B30: 4.17 | C30: =B30/100/12 -> 0.003475 | D30: 89.18414 | E30: =D30/D29-1 -> -0.043318456 | F30: 4507.6618 | G30: =F30/F29-1 -> -0.017716286 | H30: =G30-C30 -> -0.021191286 | I30: =E30-C30 -> -0.046793456
A31: 45170 | B31: 4.38 | C31: =B31/100/12 -> 0.00365 | D31: 78.27337 | E31: =D31/D30-1 -> -0.1223398 | F31: 4288.0541 | G31: =F31/F30-1 -> -0.048718755 | H31: =G31-C31 -> -0.052368755 | I31: =E31-C31 -> -0.1259898
A32: 45200 | B32: 4.8 | C32: =B32/100/12 -> 0.004 | D32: 76.04104 | E32: =D32/D31-1 -> -0.028519661 | F32: 4193.801 | G32: =F32/F31-1 -> -0.021980405 | H32: =G32-C32 -> -0.025980405 | I32: =E32-C32 -> -0.032519661
A33: 45231 | B33: 4.5 | C33: =B33/100/12 -> 0.00375 | D33: 82.82997 | E33: =D33/D32-1 -> 0.089279815 | F33: 4567.7986 | G33: =F33/F32-1 -> 0.089178693 | H33: =G33-C33 -> 0.085428693 | I33: =E33-C33 -> 0.085529815
A34: 45261 | B34: 4.02 | C34: =B34/100/12 -> 0.00335 | D34: 91.39974 | E34: =D34/D33-1 -> 0.10346219 | F34: 4769.8294 | G34: =F34/F33-1 -> 0.044229351 | H34: =G34-C34 -> 0.040879351 | I34: =E34-C34 -> 0.10011219
A35: 45292 | B35: 4.06 | C35: =B35/100/12 -> 0.0033833333 | D35: 78.8837 | E35: =D35/D34-1 -> -0.13693737 | F35: 4845.6472 | G35: =F35/F34-1 -> 0.015895278 | H35: =G35-C35 -> 0.012511945 | I35: =E35-C35 -> -0.1403207
A36: 45323 | B36: 4.21 | C36: =B36/100/12 -> 0.0035083333 | D36: 77.01926 | E36: =D36/D35-1 -> -0.023635301 | F36: 5096.2695 | G36: =F36/F35-1 -> 0.051721125 | H36: =G36-C36 -> 0.048212792 | I36: =E36-C36 -> -0.027143634
A37: 45352 | B37: 4.21 | C37: =B37/100/12 -> 0.0035083333 | D37: 88.6825 | E37: =D37/D36-1 -> 0.15143277 | F37: 5254.3544 | G37: =F37/F36-1 -> 0.03101973 | H37: =G37-C37 -> 0.027511396 | I37: =E37-C37 -> 0.14792444
A38: 45383 | B38: 4.54 | C38: =B38/100/12 -> 0.0037833333 | D38: 96.51 | E38: =D38/D37-1 -> 0.088264314 | F38: 5035.6917 | G38: =F38/F37-1 -> -0.041615526 | H38: =G38-C38 -> -0.045398859 | I38: =E38-C38 -> 0.08448098
A39: 45413 | B39: 4.48 | C39: =B39/100/12 -> 0.0037333333 | D39: 100.14 | E39: =D39/D38-1 -> 0.037612683 | F39: 5277.5073 | G39: =F39/F38-1 -> 0.048020348 | H39: =G39-C39 -> 0.044287015 | I39: =E39-C39 -> 0.033879349
A40: 45444 | B40: 4.31 | C40: =B40/100/12 -> 0.0035916667 | D40: 102.19 | E40: =D40/D39-1 -> 0.02047134 | F40: 5460.4826 | G40: =F40/F39-1 -> 0.034670776 | H40: =G40-C40 -> 0.031079109 | I40: =E40-C40 -> 0.016879673
... A61: 46082 | B61: 4.25 | C61: =B61/100/12 -> 0.0035416667 | D61: 145.23 | E61: =D61/D60-1 -> -0.1215219 | F61: 6528.5174 | G61: =F61/F60-1 -> -0.050932883 | H61: =G61-C61 -> -0.05447455 | I61: =E61-C61 -> -0.12506356

Sheet WACC
A1: Book value of debt | B1: in $ millions
B2: Debt | C2: Interest rate
A3: USD Fixed | B3: 10355 | C3: 0.0376
A4: USD Floating | B4: 199 | C4: 0.0377
A5: Euro Fixed | B5: 2048 | C5: 0.0173
A6: Total | B6: =SUM(B3:B5) -> 12602 | D6: This contains ST debt as well
A8: Market value of debt | C8: After tax Weighted average cost of debt
A9: USD | B9: ='TRACE Bond details'!G20 -> 8406.7558 | C9: ='TRACE Bond details'!B27 -> 0.039243081 | D9: From TRACE bond details sheet
A10: Euro | B10: ='TRACE Bond details'!B37 -> 1993.4485 | C10: ='TRACE Bond details'!B40 -> 0.022847484
B11: =SUM(B9:B10) -> 10400.204 | C11: =B9/B11*C9+(B10/B11)*C10 -> 0.036100472
A12: Total debt | B12: =B11 -> 10400.204
A15: Cost of Equity
A16: Implied equity risk premium | B16: 0.0423 | C16: Source: Damodaran
A17: Adjusted beta | B17: =Beta!M25 -> 1.0483088
A18: Tax rate | B18: 0.21 | C18: Statutory tax rate
A19: Rf | B19: 0.042
A20: Cost of equity | B20: =B19+B17*B16 -> 0.086343463
A21: 3M stock price | B21: 150.78
A22: Shares outstanding | B22: 530279131
A24: WACC
A25: 2025 | B25: Amount (In million$) | C25: Weights | D25: Rate
A26: Equity | B26: =B21*B22/10^6 -> 79955.487 | C26: =B26/B28 -> 0.88489708 | D26: =B20 -> 0.086343463
A27: Debt | B27: =B11 -> 10400.204 | C27: =B27/B28 -> 0.11510292 | D27: =C11 -> 0.036100472
A28: Total | B28: =B26+B27 -> 90355.692 | C28: =SUM(C26:C27) -> 1 | D28: =(B26/B28)*D26+(B27/B28)*D27 -> 0.080560348 | E28: Mature industrial company with moderate debt.

Sheet TRACE Bond details
A2: Tax rate | B2: 0.21
A4: Bond Description | B4: Maturity Date | C4: Coupon (%) | D4: TRACE Price (% of par) | E4: YTM / YTW (%) | F4: Face Value ($M) | G4: Market Value ($M) | H4: Weight (%) | I4: Wtd YTM (bps contrib)
A5: 2.250% Notes due Sep 2026 | B5: Sep-26 | C5: 0.0225 | D5: 0.9909 | E5: 0.0402 | F5: 650 | G5: =D5*F5 -> 644.085 | H5: =G5/SUM(G5:G19) -> 0.076615167 | I5: =H5*E5 -> 0.0030799297
A6: 6.375% Notes due Feb 2028 | B6: Feb-28 | C6: 0.06375 | D6: 1.0397 | E6: 0.042 | F6: 219.78 | G6: =D6*F6 -> 228.50527 | H6: =G6/SUM(G5:G19) -> 0.027181147 | I6: =H6*E6 -> 0.0011416082
A7: 3.625% Notes due Sep 2028 | B7: Sep-28 | C7: 0.03625 | D7: 0.9852 | E7: 0.0425 | F7: 600 | G7: =D7*F7 -> 591.12 | H7: =G7/SUM(G5:G19) -> 0.070314877 | I7: =H7*E7 -> 0.0029883823
A8: 3.375% Notes due Mar 2029 | B8: Mar-29 | C8: 0.03375 | D8: 0.9745 | E8: 0.043 | F8: 800 | G8: =D8*F8 -> 779.6 | H8: =G8/SUM(G5:G19) -> 0.092734941 | I8: =H8*E8 -> 0.0039876025
A9: 2.375% Notes due Aug 2029 | B9: Aug-29 | C9: 0.02375 | D9: 0.9366 | E9: 0.0438 | F9: 1000 | G9: =D9*F9 -> 936.6 | H9: =G9/SUM(G5:G19) -> 0.1114104 | I9: =H9*E9 -> 0.0048797754
A10: 3.050% Notes due Apr 2030 | B10: Apr-30 | C10: 0.0305 | D10: 0.9519 | E10: 0.0437 | F10: 600 | G10: =D10*F10 -> 571.14 | H10: =G10/SUM(G5:G19) -> 0.067938217 | I10: =H10*E10 -> 0.0029689001
A11: 4.800% Notes due Mar 2030 | B11: Mar-30 | C11: 0.048 | D11: 1.0151 | E11: 0.0438 | F11: 550 | G11: =D11*F11 -> 558.305 | H11: =G11/SUM(G5:G19) -> 0.066411469 | I11: =H11*E11 -> 0.0029088223
A12: 5.150% Notes due Mar 2035 | B12: Mar-35 | C12: 0.0515 | D12: 1.0103 | E12: 0.0504 | F12: 550 | G12: =D12*F12 -> 555.665 | H12: =G12/SUM(G5:G19) -> 0.066097436 | I12: =H12*E12 -> 0.0033313108
A13: 5.700% Notes due Mar 2037 | B13: Mar-37 | C13: 0.057 | D13: 1.0375 | E13: 0.0531 | F13: 555.28 | G13: =D13*F13 -> 576.103 | H13: =G13/SUM(G5:G19) -> 0.068528576 | I13: =H13*E13 -> 0.0036388674
A14: 3.875% Notes due Jun 2044 | B14: Jun-44 | C14: 0.03875 | D14: 0.7957 | E14: 0.0565 | F14: 325 | G14: =D14*F14 -> 258.6025 | H14: =G14/SUM(G5:G19) -> 0.030761272 | I14: =H14*E14 -> 0.0017380119
A15: 3.125% Notes due Sep 2046 | B15: Sep-46 | C15: 0.03125 | D15: 0.6772 | E15: 0.0584 | F15: 500 | G15: =D15*F15 -> 338.6 | H15: =G15/SUM(G5:G19) -> 0.040277131 | I15: =H15*E15 -> 0.0023521844
A16: 3.625% Notes due Oct 2047 | B16: Oct-47 | C16: 0.03625 | D16: 0.7277 | E16: 0.0586 | F16: 500 | G16: =D16*F16 -> 363.85 | H16: =G16/SUM(G5:G19) -> 0.043280667 | I16: =H16*E16 -> 0.0025362471
A17: 4.000% Notes due Sep 2048 | B17: Sep-48 | C17: 0.04 | D17: 0.757 | E17: 0.0597 | F17: 1150 | G17: =D17*F17 -> 870.55 | H17: =G17/SUM(G5:G19) -> 0.10355362 | I17: =H17*E17 -> 0.0061821512
A18: 3.250% Notes due Aug 2049 | B18: Aug-49 | C18: 0.0325 | D18: 0.6633 | E18: 0.0592 | F18: 1000 | G18: =D18*F18 -> 663.3 | H18: =G18/SUM(G5:G19) -> 0.078900829 | I18: =H18*E18 -> 0.0046709291
A19: 3.700% Notes due Apr 2050 | B19: Apr-50 | C19: 0.037 | D19: 0.7242 | E19: 0.0584 | F19: 650 | G19: =D19*F19 -> 470.73 | H19: =G19/SUM(G5:G19) -> 0.055994252 | I19: =H19*E19 -> 0.0032700643
A20: TOTAL / WACD (Pre-Tax) | F20: =SUM(F5:F19) -> 9650.06 | G20: =SUM(G5:G19) -> 8406.7558 | H20: 100.0% | I20: =SUM(I5:I19) -> 0.049674787
A22: Summary
A23: Total Face Value ($M) | B23: =F20 -> 9650.06
A24: Total Market Value ($M) | B24: =G20 -> 8406.7558
A25: Avg Price (% of Par) | B25: =G20/F20 -> 0.87116098
A26: Pre-Tax WACD | B26: =I20 -> 0.049674787
A27: After-Tax WACD | B27: =I20*(1-B2) -> 0.039243081
A28: Book vs Market Gap ($M) | B28: =G20-F20 -> -1243.3042
A30: Euro bonds | B30: Maturity Date | C30: Coupon (%) | D30: EUR YTM (%) | E30: Face Value (EUR M) | F30: Price (% of par) | G30: Mkt Value (EUR M) | H30: EUR/USD Spot | I30: Mkt Value (USD M)
A31: 1.500% Notes due Nov 2026 | B31: Nov-26 | C31: 0.015 | D31: 0.0236 | E31: 750 | F31: 0.9985 | G31: 748.875 | H31: 1.1779 | I31: 882.09986
A32: 1.750% Notes due Mar 2030 | B32: Mar-30 | C32: 0.0175 | D32: 0.0325 | E32: 500 | F32: 0.952 | G32: 476 | H32: 1.1779 | I32: 560.6804
A33: 1.500% Notes due Mar 2031 | B33: Mar-31 | C33: 0.015 | D33: 0.0338 | E33: 500 | F33: 0.935 | G33: 467.5 | H33: 1.1779 | I33: 550.66825
E34: =SUM(E31:E33) -> 1750 | G34: =SUM(G31:G33) -> 1692.375 | I34: 1993.4485
A35: Total Face Value (EUR M) | B35: =E34 -> 1750
A36: Total Market Value (EUR M) | B36: =G34 -> 1692.375
A37: Total Market Value (USD M) | B37: =I34 -> 1993.4485
A38: EUR/USD Spot | B38: 1.1779
A39: Pre-Tax WACD (EUR bonds, USD-weighted) | B39: =I31/I34*D31+(I32/I34)*D32+(I33/I34)*D33 -> 0.028920866
A40: After-Tax WACD (EUR bonds) | B40: =B39*(1-B2) -> 0.022847484

Sheet Valuation
A1: Terminal growth rate | K1: 0.025
A2: WACC | K2: =WACC!D28 -> 0.080560348
A4: Current share price | K4: =WACC!B21 -> 150.78
A5: Number of stock options/RSUs | K5: ='IS-Reorg'!L54-'IS-Reorg'!L55 -> 11.020869
K8: 0 | L8: 1 | M8: 2 | N8: 3 | O8: 4 | P8: 5 | Q8: 6 | R8: 7 | S8: 8 | T8: 9 | U8: 10 | V8: 11
A9: All figures in millions of U.S. Dollar | B9: 2016 | C9: 2017 | D9: =C9+1 -> 2018 | E9: =D9+1 -> 2019 | F9: =E9+1 -> 2020 | G9: =F9+1 -> 2021 | H9: =G9+1 -> 2022 | I9: =H9+1 -> 2023 | J9: =I9+1 -> 2024 | K9: =J9+1 -> 2025 | ... V9: =U9+1 -> 2036 | W9: Terminal Year
A10: NOPAT | B10: ='IS-Reorg'!B19 -> 5033.6172 | C10: ='IS-Reorg'!C19 -> 4661.287 | D10: ='IS-Reorg'!D19 -> 5955.9946 | E10: ='IS-Reorg'!E19 -> 5594.3396 | F10: ='IS-Reorg'!F19 -> 5588.1245 | G10: ='IS-Reorg'!G19 -> 6183.5639 | H10: ='IS-Reorg'!H19 -> 3683.0319 | I10: ='IS-Reorg'!I19 -> 3017.5661 | ... V10: ='IS-Reorg'!V19 -> 8452.4127 | W10: =V10*(1+K1) -> 8663.723
A11: Less: Investments in Invested Capital | C11: ='BS-Reorg'!C78-'BS-Reorg'!B78 -> 2207 | D11: ='BS-Reorg'!D78-'BS-Reorg'!C78 -> -245 | E11: ='BS-Reorg'!E78-'BS-Reorg'!D78 -> 7175 | F11: ='BS-Reorg'!F78-'BS-Reorg'!E78 -> -797 | G11: ='BS-Reorg'!G78-'BS-Reorg'!F78 -> 922 | H11: ='BS-Reorg'!H78-'BS-Reorg'!G78 -> -1599 | I11: ='BS-Reorg'!I78-'BS-Reorg'!H78 -> 3178 | J11: ='BS-Reorg'!J78-'BS-Reorg'!I78 -> -22703 | ... V11: ='BS-Reorg'!V78-'BS-Reorg'!U78 -> 232.52981 | W11: =W10*K3 -> 0
A12: Add: Non-cash operating Expenses | C12: ='IS-Reorg'!C7 -> 1544 | D12: ='IS-Reorg'!D7 -> 1488 | E12: ='IS-Reorg'!E7 -> 1593 | F12: ='IS-Reorg'!F7 -> 1911 | G12: ='IS-Reorg'!G7 -> 1915 | H12: ='IS-Reorg'!H7 -> 1831 | I12: ='IS-Reorg'!I7 -> 1433 | J12: ='IS-Reorg'!J7 -> 1224 | ... V12: ='IS-Reorg'!V7 -> 1394.4927 | W12: 0
A13: Free Cash Flow | C13: =C10-C11+C12 -> 3998.287 | D13: =D10-D11+D12 -> 7688.9946 | E13: =E10-E11+E12 -> 12.339636 | F13: =F10-F11+F12 -> 8296.1245 | G13: =G10-G11+G12 -> 7176.5639 | H13: =H10-H11+H12 -> 7113.0319 | I13: =I10-I11+I12 -> 1272.5661 | J13: =J10-J11+J12 -> 28035.314 | ... W13: =W10-W11+W12 -> 8663.723
A14: Invested Capital | B14: ='BS-Reorg'!B78 -> 19104 | C14: ='BS-Reorg'!C78 -> 21311 | D14: ='BS-Reorg'!D78 -> 21066 | E14: ='BS-Reorg'!E78 -> 28241 | F14: ='BS-Reorg'!F78 -> 27444 | G14: ='BS-Reorg'!G78 -> 28366 | H14: ='BS-Reorg'!H78 -> 26767 | I14: ='BS-Reorg'!I78 -> 29945 | ... V14: ='BS-Reorg'!V78 -> 20022.718
A15: ROIC | C15: =C10/AVERAGE(B14:C14) -> 0.23067114 | D15: =D10/AVERAGE(C14:D14) -> 0.28109562 | E15: =E10/AVERAGE(D14:E14) -> 0.22691868 | F15: =F10/AVERAGE(E14:F14) -> 0.20070484 | G15: =G10/AVERAGE(F14:G14) -> 0.2215934 | H15: =H10/AVERAGE(G14:H14) -> 0.13360535 | I15: =I10/AVERAGE(H14:I14) -> 0.1064172 | J15: =J10/AVERAGE(I14:J14) -> 0.22095431 | ... V15: =V10/AVERAGE(U14:V14) -> 0.42460668
A17: Discount factor | K17: =1/(1+$K$2)^K8 -> 1 | L17: =1/(1+$K$2)^L8 -> 0.92544577 | M17: =1/(1+$K$2)^M8 -> 0.85644987 | N17: =1/(1+$K$2)^N8 -> 0.7925979 | O17: =1/(1+$K$2)^O8 -> 0.73350637 | P17: =1/(1+$K$2)^P8 -> 0.67882037 | Q17: =1/(1+$K$2)^Q8 -> 0.62821144 | R17: =1/(1+$K$2)^R8 -> 0.58137562 | ... V17: =1/(1+$K$2)^V8 -> 0.42644272
A18: Present value of FCF | L18: =L13*L17 -> 3845.6177 | M18: =M13*M17 -> 2133.1732 | N18: =N13*N17 -> 3780.4673 | O18: =O13*O17 -> 3746.6412 | P18: =P13*P17 -> 4470.4365 | Q18: =Q13*Q17 -> 4438.2017 | R18: =R13*R17 -> 4384.8613 | S18: =S13*S17 -> 4293.4089 | ... V18: =V13*V17 -> 4099.9805
A19: Terminal value | K19: =W10*(1-(K1/K2))/(K2-K1) -> 107543.27
A20: Present value of TV | K20: =K19*V17 -> 45861.043
A22: Enterprise value | K22: =K20+SUM(L18:V18) -> 89457.325 | O22: Sensitity Analysis
O23: =K36 -> 135.67126 | P23: 0.01 | Q23: 0.015 | R23: 0.02 | S23: 0.025 | T23: 0.03
A24: Less: Debt | K24: ='BS-Reorg'!K42+'BS-Reorg'!K49+'BS-Reorg'!K50 -> 13132 | O24: =O25-0.5% -> 0.07056 | P24: 161.93243 | Q24: 162.46597 | R24: 162.99951 | S24: 163.53305 | T24: 164.06659
A25: Add: Excess Cash | K25: ='BS-Reorg'!K4-(2%*'IS-Reorg'!K4) -> 5434.04 | L25: operating cash assumed to be 2% of revenue each year, as of end date 2025 | O25: =O26-0.5% -> 0.07556 | P25: 147.23594 | Q25: 147.70928 | R25: 148.18262 | S25: 148.65596 | T25: 149.1293
A26: Less: Net Debt | K26: =K24-K25 -> 7697.96 | O26: 0.08056 | P26: 134.40647 | Q26: 134.82835 | R26: 135.25023 | S26: 135.67211 | T26: 136.09399
A27: Less: Minority Interest | K27: ='BS-Reorg'!K69 -> 45 | O27: =O26+0.5% -> 0.08556 | P27: 123.11558 | Q27: 123.49314 | R27: 123.87069 | S27: 124.24825 | T27: 124.62581
A28: Less: Litigation liabilities + Other Liabilities | K28: ='BS-Reorg'!K53 -> 10047 | O28: =O27+0.5% -> 0.09056 | P28: 113.10739 | Q28: 113.44652 | R28: 113.78565 | S28: 114.12478 | T28: 114.46391
A29: Less: Provisions | K29: ='BS-Reorg'!K51 -> 1631 | O29: =O28+0.5% -> 0.09556 | P29: 104.1796 | Q29: 104.48522 | R29: 104.79083 | S29: 105.09644 | T29: 105.40206
A30: Less: Employee stock options/RSUs | K30: =K4*K5 -> 1661.7266
A31: Add: Deferred Tax Asset (net) | K31: ='BS-Reorg'!K34-'BS-Reorg'!K52 -> 3408
A32: Add: LT Investments | K32: ='BS-Reorg'!K28 -> 161
A33: Equity Value | K33: =K22-K26-K27-K28-K29-K30+K31+K32 -> 71943.639
A34: Undiluted Shares Outstanding | K34: ='IS-Reorg'!K55 -> 530.27913
A36: Intrinsic Value per share | K36: =K33/K34 -> 135.67126
A37: 12-month target price | K37: =K36*(1+WACC!B20)-'IS-Reorg'!L56 -> 144.26559
A39: Note: Pension liabilities appear to have been fully funded and therefore this has not been included in the final calulation for equity value.

Sheet Segment wise
A1: MMM-US
A2: Sales
B3: DEC '16 | C3: DEC '17 | D3: DEC '18 | E3: DEC '19 | F3: DEC '20 | G3: DEC '21 | H3: DEC '22 | I3: DEC '23 | J3: DEC '24 | K3: DEC '25
B4: 366 Days | C4: 365 Days | D4: 365 Days | E4: 365 Days | F4: 366 Days | G4: 365 Days | H4: 365 Days | I4: 365 Days | J4: 366 Days | K4: 365 Days
A5: Total | B5: 30808 | C5: 32620 | D5: 35383 | E5: 33729 | F5: 34275 | G5: 37555 | H5: 34225 | I5: 32678 | J5: 24304 | K5: 24576
A6: Safety & Industrial | B6: - | C6: - | D6: - | E6: 11607 | F6: 11767 | G6: 12880 | H6: 11604 | I6: 10956 | J6: 10961 | K6: 11384
A7: Transportation & Electronics | B7: - | C7: - | D7: - | E7: 9602 | F7: 8827 | G7: 9769 | H7: 8902 | I7: 8501 | J7: 8380 | K7: 8272
A8: Consumer | B8: 4482 | C8: 4589 | D8: 4796 | E8: 5089 | F8: 5336 | G8: 5856 | H8: 5298 | I8: 5026 | J8: 4931 | K8: 4920
A9: Historical Segments | B9: 26326 | C9: 28031 | D9: 30587 | E9: 7431 | F9: 8345 | G9: 9050 | H9: 8421 | I9: 8195 | J9: 32 | K9: -
A10: Other | B10: - | C10: - | D10: - | E10: - | F10: - | G10: - | H10: - | I10: - | J10: 32 | K10: -
A11: Health Care | B11: 5527 | C11: 5813 | D11: 6021 | E11: 7431 | F11: 8345 | G11: 9050 | H11: 8421 | I11: 8195 | J11: - | K11: -
A12: Industrial | B12: 10313 | C12: 10911 | D12: 12267 | E12: - | F12: - | G12: - | H12: - | I12: - | J12: - | K12: -
A13: Safety & Graphics | B13: 5660 | C13: 6148 | D13: 6827 | E13: - | F13: - | G13: - | H13: - | I13: - | J13: - | K13: -
A14: Electronics & Energy | B14: 4826 | C14: 5159 | D14: 5472 | E14: - | F14: - | G14: - | H14: - | I14: - | J14: - | K14: -
A15: All figures in millions of U.S. Dollar
A17: Percent of Total (%)
B18: DEC '16 | C18: DEC '17 | D18: DEC '18 | E18: DEC '19 | F18: DEC '20 | G18: DEC '21 | H18: DEC '22 | I18: DEC '23 | J18: DEC '24 | K18: DEC '25
A19: Total | B19: 99.999998 | C19: 99.999997 | D19: 99.999996 | E19: 100 | F19: 100 | G19: 100 | H19: 100 | I19: 100 | J19: 100 | K19: 100
A20: Safety & Industrial | B20: - | C20: - | D20: - | E20: 34.412525 | F20: 34.331146 | G20: 34.296368 | H20: 33.905041 | I20: 33.527145 | J20: 45.099571 | K20: 46.321617
A21: Transportation & Electronics | B21: - | C21: - | D21: - | E21: 28.468084 | F21: 25.753466 | G21: 26.012516 | H21: 26.010227 | I21: 26.014444 | J21: 34.479923 | K21: 33.658852
A22: Consumer | B22: 14.548169 | C22: 14.068057 | D22: 13.554531 | E22: 15.087907 | F22: 15.568198 | G22: 15.593129 | H22: 15.479912 | I22: 15.380378 | J22: 20.288841 | K22: 20.019531
A23: Historical Segments | B23: 85.451829 | C23: 85.93194 | D23: 86.445465 | E23: 22.031487 | F23: 24.347193 | G23: 24.09799 | H23: 24.60482 | I23: 25.078033 | J23: 0.131666 | K23: -
A24: Other | B24: - | C24: - | D24: - | E24: - | F24: - | G24: - | H24: - | I24: - | J24: 0.131666 | K24: -
A25: Health Care | B25: 17.940145 | C25: 17.820354 | D25: 17.016645 | E25: 22.031487 | F25: 24.347193 | G25: 24.09799 | H25: 24.60482 | I25: 25.078033 | J25: - | K25: -
A26: Industrial | B26: 33.475071 | C26: 33.448803 | D26: 34.669189 | E26: - | F26: - | G26: - | H26: - | I26: - | J26: - | K26: -
A27: Safety & Graphics | B27: 18.371851 | C27: 18.847332 | D27: 19.294577 | E27: - | F27: - | G27: - | H27: - | I27: - | J27: - | K27: -
A28: Electronics & Energy | B28: 15.664762 | C28: 15.815451 | D28: 15.465054 | E28: - | F28: - | G28: - | H28: - | I28: - | J28: - | K28: -
A30: Growth (%)
B31: DEC '16 | C31: DEC '17 | D31: DEC '18 | E31: DEC '19 | F31: DEC '20 | G31: DEC '21 | H31: DEC '22 | I31: DEC '23 | J31: DEC '24 | K31: DEC '25
A32: Total | B32: -0.313865 | C32: 5.88159 | D32: 8.47026 | E32: -4.67456 | F32: 1.61879 | G32: 9.56966 | H32: -8.86699 | I32: -4.52009 | J32: -25.6258 | K32: 1.11916
A33: Safety & Industrial | B33: - | C33: - | D33: - | E33: - | F33: 1.378479 | G33: 9.458655 | H33: -9.906833 | I33: -5.584281 | J33: 0.045637 | K33: 3.859137
A34: Transportation & Electronics | B34: - | C34: - | D34: - | E34: - | F34: -8.071235 | G34: 10.671803 | H34: -8.875012 | I34: -4.504606 | J34: -1.423362 | K34: -1.288783
A35: Consumer | B35: 1.356852 | C35: 2.387327 | D35: 4.510787 | E35: 6.109258 | F35: 4.853606 | G35: 9.745128 | H35: -9.528688 | I35: -5.134013 | J35: -1.890171 | K35: -0.223078
A36: Historical Segments | B36: -0.592833 | C36: 6.47649 | D36: 9.11848 | E36: -75.7054 | F36: 12.2998 | G36: 8.44817 | H36: -6.95028 | I36: -2.68377 | J36: -99.6095 | K36: -
A37: Other | B37: - | C37: - | D37: - | E37: - | F37: - | G37: - | H37: - | I37: - | J37: - | K37: -
A38: Health Care | B38: 1.97417 | C38: 5.174597 | D38: 3.578187 | E38: 23.418037 | F38: 12.299825 | G38: 8.448173 | H38: -6.950276 | I38: -2.683767 | J38: - | K38: -
A39: Industrial | B39: -0.145236 | C39: 5.798507 | D39: 12.427825 | E39: - | F39: - | G39: - | H39: - | I39: - | J39: - | K39: -
A40: Safety & Graphics | B40: 2.629193 | C40: 8.621908 | D40: 11.044242 | E40: - | F40: - | G40: - | H40: - | I40: - | J40: - | K40: -
A41: Electronics & Energy | B41: -7.547893 | C41: 6.900125 | D41: 6.067067 | E41: - | F41: - | G41: - | H41: - | I41: - | J41: - | K41: -
A43: Segments Table
A46: Segments Table

Sheet Historical analysis and Ratios
A1: Profitabilty ratios | B1: Formula | C1: 2016 | D1: 2017 | E1: 2018 | F1: 2019 | G1: 2020 | H1: 2021 | I1: 2022 | J1: 2023 | K1: 2024 | L1: 2025 | M1: Analysis
A2: Gross Margin | B2: gross income / revenue | C2: ='IS-Reorg'!B10/'IS-Reorg'!B4 -> 0.49739281 | D2: ='IS-Reorg'!C10/'IS-Reorg'!C4 -> 0.4947405 | E2: ='IS-Reorg'!D10/'IS-Reorg'!D4 -> 0.49412483 | F2: ='IS-Reorg'!E10/'IS-Reorg'!E4 -> 0.47628827 | G2: ='IS-Reorg'!F10/'IS-Reorg'!F4 -> 0.48480611 | H2: ='IS-Reorg'!G10/'IS-Reorg'!G4 -> 0.46986282 | I2: ='IS-Reorg'!H10/'IS-Reorg'!H4 -> 0.43723159 | J2: ='IS-Reorg'!I10/'IS-Reorg'!I4 -> 0.38898822 | ... L2: ='IS-Reorg'!K10/'IS-Reorg'!K4 -> 0.3958634 | M2: Declined from ~50% in 2016-2018 to ~40% by 2025, driven by the Solventum spinoff removing the higher-margin Health Care segment.
A3: EBIT Margin | B3: ebit / revenue | C3: ='IS-Reorg'!B14/'IS-Reorg'!B4 -> 0.23311967 | D3: ='IS-Reorg'!C14/'IS-Reorg'!C4 -> 0.22825915 | E3: ='IS-Reorg'!D14/'IS-Reorg'!D4 -> 0.23726537 | F3: ='IS-Reorg'!E14/'IS-Reorg'!E4 -> 0.21701519 | G3: ='IS-Reorg'!F14/'IS-Reorg'!F4 -> 0.21616331 | H3: ='IS-Reorg'!G14/'IS-Reorg'!G4 -> 0.21286947 | I3: ='IS-Reorg'!H14/'IS-Reorg'!H4 -> 0.11899267 | J3: ='IS-Reorg'!I14/'IS-Reorg'!I4 -> 0.16444535 | ... L3: ='IS-Reorg'!K14/'IS-Reorg'!K4 -> 0.18959436 | M3: Compressed to 11.9% in 2022 from ~22-24% pre-2022 as litigation charges surged; partial recovery to 19.0% in 2025 as one-time charges recede.
A4: EBITDA Margin | B4: ebitda / revenue | C4: ='IS-Reorg'!B59/'IS-Reorg'!B4 -> 0.28207513 | D4: ='IS-Reorg'!C59/'IS-Reorg'!C4 -> 0.27703194 | E4: ='IS-Reorg'!D59/'IS-Reorg'!D4 -> 0.28267969 | F4: ='IS-Reorg'!E59/'IS-Reorg'!E4 -> 0.26658576 | G4: ='IS-Reorg'!F59/'IS-Reorg'!F4 -> 0.27554064 | H4: ='IS-Reorg'!G59/'IS-Reorg'!G4 -> 0.26703437 | I4: ='IS-Reorg'!H59/'IS-Reorg'!H4 -> 0.17248532 | J4: ='IS-Reorg'!I59/'IS-Reorg'!I4 -> 0.22267371 | ... L4: ='IS-Reorg'!K59/'IS-Reorg'!K4 -> 0.24202341 | M4: Tracked EBIT margin with a 4-5% D&A premium; the 2022-2023 trough at 17-22% followed by recovery to 24.2% in 2025 confirms intact underlying profitability.
A5: Net Profit Margin | B5: net income / revenue | C5: ='IS-Reorg'!B46/'IS-Reorg'!B4 -> 0.16772394 | D5: ='IS-Reorg'!C46/'IS-Reorg'!C4 -> 0.15345737 | E5: ='IS-Reorg'!D46/'IS-Reorg'!D4 -> 0.16325347 | F5: ='IS-Reorg'!E46/'IS-Reorg'!E4 -> 0.14220812 | G5: ='IS-Reorg'!F46/'IS-Reorg'!F4 -> 0.16930773 | H5: ='IS-Reorg'!G46/'IS-Reorg'!G4 -> 0.16747278 | I5: ='IS-Reorg'!H46/'IS-Reorg'!H4 -> 0.16877502 | J5: ='IS-Reorg'!I46/'IS-Reorg'!I4 -> -0.34140593 | ... L5: ='IS-Reorg'!K46/'IS-Reorg'!K4 -> 0.13027096 | M5: N/M in 2023 due to $14.5B PFAS/CAE litigation charge; the 13.0% in 2025 understates recurring earnings as settlement payments are now cash outflows, not IS charges.
A6: NOPAT Margin | B6: nopat / revenue | C6: ='IS-Reorg'!B19/'IS-Reorg'!B4 -> 0.16717982 | D6: ='IS-Reorg'!C19/'IS-Reorg'!C4 -> 0.14724348 | E6: ='IS-Reorg'!D19/'IS-Reorg'!D4 -> 0.18177917 | F6: ='IS-Reorg'!E19/'IS-Reorg'!E4 -> 0.17408326 | G6: ='IS-Reorg'!F19/'IS-Reorg'!F4 -> 0.17363052 | H6: ='IS-Reorg'!G19/'IS-Reorg'!G4 -> 0.17489927 | I6: ='IS-Reorg'!H19/'IS-Reorg'!H4 -> 0.10759975 | J6: ='IS-Reorg'!I19/'IS-Reorg'!I4 -> 0.12261545 | ... L6: ='IS-Reorg'!K19/'IS-Reorg'!K4 -> 0.14445713 | M6: The cleanest profitability measure; declined from 18.2% in 2018 to 10.8% in 2022, recovering to 14.4% in 2025, reflecting structural improvement in core operating efficiency.
A7: Return on Assets (ROA) | B7: net income / total assets | C7: ='IS-Reorg'!B46/'BS-Reorg'!B38 -> 0.15346745 | D7: ='IS-Reorg'!C46/'BS-Reorg'!C38 -> 0.12788586 | E7: ='IS-Reorg'!D46/'BS-Reorg'!D38 -> 0.14654795 | F7: ='IS-Reorg'!E46/'BS-Reorg'!E38 -> 0.102331 | G7: ='IS-Reorg'!F46/'BS-Reorg'!F38 -> 0.11509378 | H7: ='IS-Reorg'!G46/'BS-Reorg'!G38 -> 0.12578603 | I7: ='IS-Reorg'!H46/'BS-Reorg'!H38 -> 0.1243569 | J7: ='IS-Reorg'!I46/'BS-Reorg'!I38 -> -0.16611309 | ... L7: ='IS-Reorg'!K46/'BS-Reorg'!K38 -> 0.086131503 | M7: Declined from 15.3% in 2016 to 8.6% in 2025, partly from goodwill/intangible inflation; N/M in 2023 is entirely from the litigation-driven net loss.
A8: Return on Equity (ROE) | B8: net income / common equity | C8: =IFERROR('IS-Reorg'!B46/'BS-Reorg'!B61,"-") -> 0.49038648 | D8: =IFERROR('IS-Reorg'!C46/'BS-Reorg'!C61,"-") -> 0.42013318 | E8: =IFERROR('IS-Reorg'!D46/'BS-Reorg'!D61,"-") -> 0.5460392 | F8: =IFERROR('IS-Reorg'!E46/'BS-Reorg'!E61,"-") -> 0.45413892 | G8: =IFERROR('IS-Reorg'!F46/'BS-Reorg'!F61,"-") -> 0.42348644 | H8: =IFERROR('IS-Reorg'!G46/'BS-Reorg'!G61,"-") -> 0.39352652 | I8: =IFERROR('IS-Reorg'!H46/'BS-Reorg'!H61,"-") -> 0.39240592 | J8: =IFERROR('IS-Reorg'!I46/'BS-Reorg'!I61,"-") -> -1.7478677 | ... L8: =IFERROR('IS-Reorg'!K46/'BS-Reorg'!K61,"-") -> 0.69119524 | M8: Economically distorted due to treasury buybacks depleting book equity toward zero; N/M from 2023-2025 reflects the near-zero denominator problem making ROE unreliable.
A9: Return on Invested Capital (ROIC) | B9: nopat / avg ic with goodwill | C9: ='IS-Reorg'!B19/AVERAGE('BS-Reorg'!B78) -> 0.26348499 | D9: ='IS-Reorg'!C19/AVERAGE('BS-Reorg'!B78,'BS-Reorg'!C78) -> 0.23067114 | E9: ='IS-Reorg'!D19/AVERAGE('BS-Reorg'!C78,'BS-Reorg'!D78) -> 0.28109562 | F9: ='IS-Reorg'!E19/AVERAGE('BS-Reorg'!D78,'BS-Reorg'!E78) -> 0.22691868 | G9: ='IS-Reorg'!F19/AVERAGE('BS-Reorg'!E78,'BS-Reorg'!F78) -> 0.20070484 | H9: ='IS-Reorg'!G19/AVERAGE('BS-Reorg'!F78,'BS-Reorg'!G78) -> 0.2215934 | I9: ='IS-Reorg'!H19/AVERAGE('BS-Reorg'!G78,'BS-Reorg'!H78) -> 0.13360535 | J9: ='IS-Reorg'!I19/AVERAGE('BS-Reorg'!H78,'BS-Reorg'!I78) -> 0.1064172 | K9: ='IS-Reorg'!J19/AVERAGE('BS-Reorg'!I78,'BS-Reorg'!J78) -> 0.22095431 | L9: ='IS-Reorg'!K19/AVERAGE('BS-Reorg'!J78,'BS-Reorg'!K78) -> 0.3788213 | M9: Averaged ~23% pre-litigation, fell to 10.1% in 2023 as IC was inflated by settlement liabilities, normalized to 30.6% in 2025 confirming strong capital returns on a clean base.
A11: Leverage and Solvency ratios
A12: Debt / Equity | B12: (st debt + lt debt) / total equity | C12: =('BS-Reorg'!B42+'BS-Reorg'!B48)/'BS-Reorg'!B70 -> 1.1307164 | D12: =('BS-Reorg'!C42+'BS-Reorg'!C48)/'BS-Reorg'!C70 -> 1.2053863 | E12: =('BS-Reorg'!D42+'BS-Reorg'!D48)/'BS-Reorg'!D70 -> 1.4923842 | F12: =('BS-Reorg'!E42+'BS-Reorg'!E48)/'BS-Reorg'!E70 -> 2.1033972 | G12: =('BS-Reorg'!F42+'BS-Reorg'!F48)/'BS-Reorg'!F70 -> 1.5292707 | H12: =('BS-Reorg'!G42+'BS-Reorg'!G48)/'BS-Reorg'!G70 -> 1.2116822 | I12: =('BS-Reorg'!H42+'BS-Reorg'!H48)/'BS-Reorg'!H70 -> 1.1419093 | J12: =('BS-Reorg'!I42+'BS-Reorg'!I48)/'BS-Reorg'!I70 -> 3.4410435 | ... L12: =('BS-Reorg'!K42+'BS-Reorg'!K48)/'BS-Reorg'!K70 -> 2.7663788 | M12: Unreliable due to near-zero equity from buybacks; peaked at 3.4x in 2023 as litigation losses wiped equity; Debt/Assets is more informative given denominator distortion.
A13: Debt / Total Assets | B13: (st debt + lt debt) / total assets | C13: =('BS-Reorg'!B42+'BS-Reorg'!B48)/'BS-Reorg'!B38 -> 0.35540631 | D13: =('BS-Reorg'!C42+'BS-Reorg'!C48)/'BS-Reorg'!C38 -> 0.36878406 | E13: =('BS-Reorg'!D42+'BS-Reorg'!D48)/'BS-Reorg'!D38 -> 0.40265753 | F13: =('BS-Reorg'!E42+'BS-Reorg'!E48)/'BS-Reorg'!E38 -> 0.47692514 | G13: =('BS-Reorg'!F42+'BS-Reorg'!F48)/'BS-Reorg'!F38 -> 0.41768756 | H13: =('BS-Reorg'!G42+'BS-Reorg'!G48)/'BS-Reorg'!G38 -> 0.38912729 | I13: =('BS-Reorg'!H42+'BS-Reorg'!H48)/'BS-Reorg'!H38 -> 0.36306103 | J13: =('BS-Reorg'!I42+'BS-Reorg'!I48)/'BS-Reorg'!I38 -> 0.33117833 | ... L13: =('BS-Reorg'!K42+'BS-Reorg'!K48)/'BS-Reorg'!K38 -> 0.34802428 | M13: Rose from 35.5% in 2016 to 47.7% in 2019 from acquisitions, then declined to 34.8% by 2025 reflecting deleveraging and transfer of $8.4B Solventum debt.
A14: Net Debt / EBITDA | B14: (total debt - Cash) / EBITDA) | C14: =('BS-Reorg'!B42+'BS-Reorg'!B48-'BS-Reorg'!B4)/'IS-Reorg'!B59 -> 1.0616979 | D14: =('BS-Reorg'!C42+'BS-Reorg'!C48-'BS-Reorg'!C4)/'IS-Reorg'!C59 -> 1.1265678 | E14: =('BS-Reorg'!D42+'BS-Reorg'!D48-'BS-Reorg'!D4)/'IS-Reorg'!D59 -> 1.2377456 | F14: =('BS-Reorg'!E42+'BS-Reorg'!E48-'BS-Reorg'!E4)/'IS-Reorg'!E59 -> 2.1452084 | G14: =('BS-Reorg'!F42+'BS-Reorg'!F48-'BS-Reorg'!F4)/'IS-Reorg'!F59 -> 1.6618178 | H14: =('BS-Reorg'!G42+'BS-Reorg'!G48-'BS-Reorg'!G4)/'IS-Reorg'!G59 -> 1.4354412 | I14: =('BS-Reorg'!H42+'BS-Reorg'!H48-'BS-Reorg'!H4)/'IS-Reorg'!H59 -> 2.1973238 | J14: =('BS-Reorg'!I42+'BS-Reorg'!I48-'BS-Reorg'!I4)/'IS-Reorg'!I59 -> 2.0010949 | ... L14: =('BS-Reorg'!K42+'BS-Reorg'!K48-'BS-Reorg'!K4)/'IS-Reorg'!K59 -> 1.1922822 | M14: Rose to 2.2x in 2022 but improved to 1.2x in 2025 as EBITDA recovered and gross debt declined; within the 2.0-2.5x investment-grade industrial range.
A15: Interest Coverage (EBIT / Interest) | B15: ebit / interest expense | C15: ='IS-Reorg'!B14/'IS-Reorg'!B24 -> 33.908213 | D15: ='IS-Reorg'!C14/'IS-Reorg'!C24 -> 86.02381 | E15: ='IS-Reorg'!D14/'IS-Reorg'!D24 -> 32.391667 | F15: ='IS-Reorg'!E14/'IS-Reorg'!E24 -> 16.180974 | G15: ='IS-Reorg'!F14/'IS-Reorg'!F24 -> 12.58047 | H15: ='IS-Reorg'!G14/'IS-Reorg'!G24 -> 16.468271 | I15: ='IS-Reorg'!H14/'IS-Reorg'!H24 -> 8.1787149 | J15: ='IS-Reorg'!I14/'IS-Reorg'!I24 -> 4.3422747 | ... L15: ='IS-Reorg'!K14/'IS-Reorg'!K24 -> 5.0426439 | M15: Declined from 86x in 2017 to 5.0x in 2025 as debt and interest rates rose; remains above the 3.0x EBITDA/interest covenant floor in 3M's $4.25B revolving credit facility.
A16: Interest Coverage (EBITDA / Interest) | B16: ebitda / interest expense | C16: ='IS-Reorg'!B59/'IS-Reorg'!B24 -> 41.028986 | D16: ='IS-Reorg'!C59/'IS-Reorg'!C24 -> 104.40476 | E16: ='IS-Reorg'!D59/'IS-Reorg'!D24 -> 38.591667 | F16: ='IS-Reorg'!E59/'IS-Reorg'!E24 -> 19.87703 | G16: ='IS-Reorg'!F59/'IS-Reorg'!F24 -> 16.036166 | H16: ='IS-Reorg'!G59/'IS-Reorg'!G24 -> 20.658643 | I16: ='IS-Reorg'!H59/'IS-Reorg'!H24 -> 11.855422 | J16: ='IS-Reorg'!I59/'IS-Reorg'!I24 -> 5.8798283 | ... L16: ='IS-Reorg'!K59/'IS-Reorg'!K24 -> 6.4371002 | M16: EBITDA coverage declined from 104x in 2017 to 6.4x in 2025; still healthy confirming 3M's ability to service its $12.6B debt load comfortably.
A18: Liquidity Ratios
A19: Current Ratio | B19: (cash+ar+inventory) / (st debt+ap+other curr liab) | C19: =('BS-Reorg'!B4+'BS-Reorg'!B7+'BS-Reorg'!B11)/('BS-Reorg'!B42+'BS-Reorg'!B43+'BS-Reorg'!B45) -> 1.7660473 | D19: =('BS-Reorg'!C4+'BS-Reorg'!C7+'BS-Reorg'!C11)/('BS-Reorg'!C42+'BS-Reorg'!C43+'BS-Reorg'!C45) -> 1.7722651 | E19: =('BS-Reorg'!D4+'BS-Reorg'!D7+'BS-Reorg'!D11)/('BS-Reorg'!D42+'BS-Reorg'!D43+'BS-Reorg'!D45) -> 1.8024568 | F19: =('BS-Reorg'!E4+'BS-Reorg'!E7+'BS-Reorg'!E11)/('BS-Reorg'!E42+'BS-Reorg'!E43+'BS-Reorg'!E45) -> 1.31214 | G19: =('BS-Reorg'!F4+'BS-Reorg'!F7+'BS-Reorg'!F11)/('BS-Reorg'!F42+'BS-Reorg'!F43+'BS-Reorg'!F45) -> 1.8281904 | H19: =('BS-Reorg'!G4+'BS-Reorg'!G7+'BS-Reorg'!G11)/('BS-Reorg'!G42+'BS-Reorg'!G43+'BS-Reorg'!G45) -> 1.6421652 | I19: =('BS-Reorg'!H4+'BS-Reorg'!H7+'BS-Reorg'!H11)/('BS-Reorg'!H42+'BS-Reorg'!H43+'BS-Reorg'!H45) -> 1.4893135 | J19: =('BS-Reorg'!I4+'BS-Reorg'!I7+'BS-Reorg'!I11)/('BS-Reorg'!I42+'BS-Reorg'!I43+'BS-Reorg'!I45) -> 0.88908157 | ... L19: =('BS-Reorg'!K4+'BS-Reorg'!K7+'BS-Reorg'!K11)/('BS-Reorg'!K42+'BS-Reorg'!K43+'BS-Reorg'!K45) -> 1.3681084 | M19: Generally healthy at 1.5-1.8x from 2016-2022; fell to 0.89x in 2023 as accrued litigation liabilities were classified as current — a technical reclassification, not a genuine cash issue.
A20: Quick Ratio | B20: (cash + ar) / (st debt+ap+other curr liab) | C20: =('BS-Reorg'!B4+'BS-Reorg'!B7)/('BS-Reorg'!B42+'BS-Reorg'!B43+'BS-Reorg'!B45) -> 1.1942568 | D20: =('BS-Reorg'!C4+'BS-Reorg'!C7)/('BS-Reorg'!C42+'BS-Reorg'!C43+'BS-Reorg'!C45) -> 1.2254304 | E20: =('BS-Reorg'!D4+'BS-Reorg'!D7)/('BS-Reorg'!D42+'BS-Reorg'!D43+'BS-Reorg'!D45) -> 1.1788316 | F20: =('BS-Reorg'!E4+'BS-Reorg'!E7)/('BS-Reorg'!E42+'BS-Reorg'!E43+'BS-Reorg'!E45) -> 0.85423128 | G20: =('BS-Reorg'!F4+'BS-Reorg'!F7)/('BS-Reorg'!F42+'BS-Reorg'!F43+'BS-Reorg'!F45) -> 1.2739278 | H20: =('BS-Reorg'!G4+'BS-Reorg'!G7)/('BS-Reorg'!G42+'BS-Reorg'!G43+'BS-Reorg'!G45) -> 1.0740741 | I20: =('BS-Reorg'!H4+'BS-Reorg'!H7)/('BS-Reorg'!H42+'BS-Reorg'!H43+'BS-Reorg'!H45) -> 0.90943437 | J20: =('BS-Reorg'!I4+'BS-Reorg'!I7)/('BS-Reorg'!I42+'BS-Reorg'!I43+'BS-Reorg'!I45) -> 0.62602548 | ... L20: =('BS-Reorg'!K4+'BS-Reorg'!K7)/('BS-Reorg'!K42+'BS-Reorg'!K43+'BS-Reorg'!K45) -> 0.9865555 | M20: Mirrors current ratio; the 2023 dip to 0.63x was driven entirely by litigation liability reclassification rather than actual short-term cash stress.
A21: Cash Ratio | B21: cash & st investments / (st debt+ap+other curr liab) | C21: ='BS-Reorg'!B4/('BS-Reorg'!B42+'BS-Reorg'!B43+'BS-Reorg'!B45) -> 0.45236486 | D21: ='BS-Reorg'!C4/('BS-Reorg'!C42+'BS-Reorg'!C43+'BS-Reorg'!C45) -> 0.55971262 | E21: ='BS-Reorg'!D4/('BS-Reorg'!D42+'BS-Reorg'!D43+'BS-Reorg'!D45) -> 0.46179117 | F21: ='BS-Reorg'!E4/('BS-Reorg'!E42+'BS-Reorg'!E43+'BS-Reorg'!E45) -> 0.32354896 | G21: ='BS-Reorg'!F4/('BS-Reorg'!F42+'BS-Reorg'!F43+'BS-Reorg'!F45) -> 0.65873431 | H21: ='BS-Reorg'!G4/('BS-Reorg'!G42+'BS-Reorg'!G43+'BS-Reorg'!G45) -> 0.54301994 | I21: ='BS-Reorg'!H4/('BS-Reorg'!H42+'BS-Reorg'!H43+'BS-Reorg'!H45) -> 0.42022884 | J21: ='BS-Reorg'!I4/('BS-Reorg'!I42+'BS-Reorg'!I43+'BS-Reorg'!I45) -> 0.38584673 | ... L21: ='BS-Reorg'!K4/('BS-Reorg'!K42+'BS-Reorg'!K43+'BS-Reorg'!K45) -> 0.61834289 | M21: Ranged 0.32-0.71x, reflecting healthy treasury cash balances; the 0.62x in 2025 confirms substantial liquidity buffer well above operational requirements.
A23: Effiecinecy and Activity Ratios
A24: Asset Turnover | B24: revenue / total assets | C24: ='IS-Reorg'!B4/'BS-Reorg'!B38 -> 0.9150003 | D24: ='IS-Reorg'!C4/'BS-Reorg'!C38 -> 0.83336405 | E24: ='IS-Reorg'!D4/'BS-Reorg'!D38 -> 0.89767123 | F24: ='IS-Reorg'!E4/'BS-Reorg'!E38 -> 0.7195862 | G24: ='IS-Reorg'!F4/'BS-Reorg'!F38 -> 0.67979047 | H24: ='IS-Reorg'!G4/'BS-Reorg'!G38 -> 0.75108345 | I24: ='IS-Reorg'!H4/'BS-Reorg'!H38 -> 0.73682058 | J24: ='IS-Reorg'!I4/'BS-Reorg'!I38 -> 0.48655595 | ... L24: ='IS-Reorg'!K4/'BS-Reorg'!K38 -> 0.66117192 | M24: Declined from 0.92x in 2016 to 0.49x in 2023 as assets were inflated by goodwill, DTA, and intangibles; modest recovery to 0.66x in 2025 post-Solventum reflects a leaner asset base.
A25: Days Sales Outstanding (DSO) | B25: accounts receivable / revenue × 365 | C25: ='BS-Reorg'!B7/'IS-Reorg'!B4*365 -> 53.242552 | D25: ='BS-Reorg'!C7/'IS-Reorg'!C4*365 -> 56.623022 | E25: ='BS-Reorg'!D7/'IS-Reorg'!D4*365 -> 55.922478 | F25: ='BS-Reorg'!E7/'IS-Reorg'!E4*365 -> 54.416075 | G25: ='BS-Reorg'!F7/'IS-Reorg'!F4*365 -> 53.359589 | H25: ='BS-Reorg'!G7/'IS-Reorg'!G4*365 -> 48.109178 | I25: ='BS-Reorg'!H7/'IS-Reorg'!H4*365 -> 48.326857 | J25: ='BS-Reorg'!I7/'IS-Reorg'!I4*365 -> 53.407761 | ... L25: ='BS-Reorg'!K7/'IS-Reorg'!K4*365 -> 51.689314 | M25: Remarkably stable at 47-57 days throughout the decade confirming consistent receivables management and stable customer credit terms across 3M's diversified customer base.
A26: Days Inventory Outstanding (DIO) | B26: inventory / cogs excl d&a × 365 | C26: ='BS-Reorg'!B11/'IS-Reorg'!B6*365 -> 90.455011 | D26: ='BS-Reorg'!C11/'IS-Reorg'!C6*365 -> 101.88983 | E26: ='BS-Reorg'!D11/'IS-Reorg'!D6*365 -> 105.6267 | F26: ='BS-Reorg'!E11/'IS-Reorg'!E6*365 -> 99.029336 | G26: ='BS-Reorg'!F11/'IS-Reorg'!F6*365 -> 105.46933 | H26: ='BS-Reorg'!G11/'IS-Reorg'!G6*365 -> 108.12485 | I26: ='BS-Reorg'!H11/'IS-Reorg'!H6*365 -> 112.48164 | J26: ='BS-Reorg'!I11/'IS-Reorg'!I6*365 -> 105.81888 | ... L26: ='BS-Reorg'!K11/'IS-Reorg'!K6*365 -> 97.08406 | M26: Rose from 90 days in 2016 to 112 days in 2022 during supply chain disruptions, normalizing to 97 days by 2025; reflects deliberate inventory buffering during material shortage periods.
A27: Days Payable Outstanding (DPO) | B27: accounts payable / cogs excl d&a × 365 | C27: ='BS-Reorg'!B43/'IS-Reorg'!B6*365 -> 48.046709 | D27: ='BS-Reorg'!C43/'IS-Reorg'!C6*365 -> 49.126358 | E27: ='BS-Reorg'!D43/'IS-Reorg'!D6*365 -> 54.821369 | F27: ='BS-Reorg'!E43/'IS-Reorg'!E6*365 -> 53.371399 | G27: ='BS-Reorg'!F43/'IS-Reorg'!F6*365 -> 63.719496 | H27: ='BS-Reorg'!G43/'IS-Reorg'!G6*365 -> 64.939981 | I27: ='BS-Reorg'!H43/'IS-Reorg'!H6*365 -> 66.647258 | J27: ='BS-Reorg'!I43/'IS-Reorg'!I6*365 -> 74.481035 | ... L27: ='BS-Reorg'!K43/'IS-Reorg'!K6*365 -> 71.652863 | M27: Steadily extended from 48 days in 2016 to 72 days in 2025, indicating improving supplier payment terms leveraged from 3M's scale and changed business mix post-Solventum.
A28: Cash Conversion Cycle (CCC) | B28: dso + dio − DPO | C28: ='BS-Reorg'!B7/'IS-Reorg'!B4*365+'BS-Reorg'!B11/'IS-Reorg'!B6*365-'BS-Reorg'!B43/'IS-Reorg'!B6*365 -> 95.650854 | D28: ='BS-Reorg'!C7/'IS-Reorg'!C4*365+'BS-Reorg'!C11/'IS-Reorg'!C6*365-'BS-Reorg'!C43/'IS-Reorg'!C6*365 -> 109.3865 | E28: ='BS-Reorg'!D7/'IS-Reorg'!D4*365+'BS-Reorg'!D11/'IS-Reorg'!D6*365-'BS-Reorg'!D43/'IS-Reorg'!D6*365 -> 106.72781 | F28: ='BS-Reorg'!E7/'IS-Reorg'!E4*365+'BS-Reorg'!E11/'IS-Reorg'!E6*365-'BS-Reorg'!E43/'IS-Reorg'!E6*365 -> 100.07401 | G28: ='BS-Reorg'!F7/'IS-Reorg'!F4*365+'BS-Reorg'!F11/'IS-Reorg'!F6*365-'BS-Reorg'!F43/'IS-Reorg'!F6*365 -> 95.109418 | H28: ='BS-Reorg'!G7/'IS-Reorg'!G4*365+'BS-Reorg'!G11/'IS-Reorg'!G6*365-'BS-Reorg'!G43/'IS-Reorg'!G6*365 -> 91.294049 | I28: ='BS-Reorg'!H7/'IS-Reorg'!H4*365+'BS-Reorg'!H11/'IS-Reorg'!H6*365-'BS-Reorg'!H43/'IS-Reorg'!H6*365 -> 94.161242 | J28: ='BS-Reorg'!I7/'IS-Reorg'!I4*365+'BS-Reorg'!I11/'IS-Reorg'!I6*365-'BS-Reorg'!I43/'IS-Reorg'!I6*365 -> 84.745603 | ... L28: ='BS-Reorg'!K7/'IS-Reorg'!K4*365+'BS-Reorg'!K11/'IS-Reorg'!K6*365-'BS-Reorg'!K43/'IS-Reorg'!K6*365 -> 77.120511 | M28: Improved from 109 days in 2017 to 77 days in 2025, driven by DPO extension and Solventum removing longer-cycle healthcare inventory; genuine working capital efficiency gains.
A30: Cashflow ratios
A31: Operating Cash Flow Margin | B31: operating cf / revenue | C31: ='3M-CFS'!K25/'IS-Reorg'!B4 -> 0.22126275 | D31: ='3M-CFS'!J25/'IS-Reorg'!C4 -> 0.1971128 | E31: ='3M-CFS'!I25/'IS-Reorg'!D4 -> 0.19652068 | F31: ='3M-CFS'!H25/'IS-Reorg'!E4 -> 0.22000249 | G31: ='3M-CFS'!G25/'IS-Reorg'!F4 -> 0.25208178 | H31: ='3M-CFS'!F25/'IS-Reorg'!G4 -> 0.21083298 | I31: ='3M-CFS'!E25/'IS-Reorg'!H4 -> 0.16334103 | J31: ='3M-CFS'!D25/'IS-Reorg'!I4 -> 0.27143438 | K31: ='3M-CFS'!C25/'IS-Reorg'!J4 -> 0.074018311 | L31: ='3M-CFS'!B25/'IS-Reorg'!K4 -> 0.092432259 | M31: Solid at 19-25% from 2016-2021; declining to 7-9% in 2024-2025 directly from PFAS and CAE litigation cash payments classified as operating outflows under GAAP.
A32: Free Cash Flow Margin | B32: fcf / revenue | C32: ='3M-CFS'!K56/'IS-Reorg'!B4 -> 0.17410077 | D32: ='3M-CFS'!J56/'IS-Reorg'!C4 -> 0.15374167 | E32: ='3M-CFS'!I56/'IS-Reorg'!D4 -> 0.14839005 | F32: ='3M-CFS'!H56/'IS-Reorg'!E4 -> 0.16713343 | G32: ='3M-CFS'!G56/'IS-Reorg'!F4 -> 0.2054437 | H32: ='3M-CFS'!F56/'IS-Reorg'!G4 -> 0.16549286 | I32: ='3M-CFS'!E56/'IS-Reorg'!H4 -> 0.112244 | J32: ='3M-CFS'!D56/'IS-Reorg'!I4 -> 0.20581065 | K32: ='3M-CFS'!C56/'IS-Reorg'!J4 -> 0.025961343 | L32: ='3M-CFS'!B56/'IS-Reorg'!K4 -> 0.055956389 | M32: Healthy at 14-21% for most years; compressed to 2.6% in 2024 by litigation payments; natural FCF recovery as settlements wind down through 2029 is embedded in the forecast.
A33: CapEx as % of Revenue | B33: capex / revenue | C33: =ABS('3M-CFS'!K27)/'IS-Reorg'!B4 -> 0.047161978 | D33: =ABS('3M-CFS'!J27)/'IS-Reorg'!C4 -> 0.043371134 | E33: =ABS('3M-CFS'!I27)/'IS-Reorg'!D4 -> 0.048130627 | F33: =ABS('3M-CFS'!H27)/'IS-Reorg'!E4 -> 0.052869057 | G33: =ABS('3M-CFS'!G27)/'IS-Reorg'!F4 -> 0.046638081 | H33: =ABS('3M-CFS'!F27)/'IS-Reorg'!G4 -> 0.045340122 | I33: =ABS('3M-CFS'!E27)/'IS-Reorg'!H4 -> 0.051097023 | J33: =ABS('3M-CFS'!D27)/'IS-Reorg'!I4 -> 0.06562373 | K33: =ABS('3M-CFS'!C27)/'IS-Reorg'!J4 -> 0.048056968 | L33: =ABS('3M-CFS'!B27)/'IS-Reorg'!K4 -> 0.03647587 | M33: Consistently 4.3-5.3% throughout, declining to 3.6% in 2025; reflects 3M's relatively asset-light model where IP and innovation drive competitive advantage over physical capital.

Sheet 3M-BS
A1: 3M Company (MMM)
B4: =B45-B35-B11 -> 31639 | C4: =C45-C35-C11 -> 29557 | D4: =D45-D35-D11 -> 44574 | E4: =E45-E35-E11 -> 41586 | F4: =F45-F35-F11 -> 42004 | G4: =G45-G35-G11 -> 42082 | H4: =H45-H35-H11 -> 41475 | I4: =I45-I35-I11 -> 33021 | ... K4: =K45-K35-K11 -> 29972
A5: 3M Company
A6: MMM 88579Y101 2595708 NYSE Common stock
A7: Source: FactSet Fundamentals
B8: DEC '25 | C8: DEC '24 | D8: DEC '23 | E8: DEC '22 | F8: DEC '21 | G8: DEC '20 | H8: DEC '19 | I8: DEC '18 | J8: DEC '17 | K8: DEC '16
D9: Restate | G9: Restate | J9: Restate
A10: Assets
A11: Cash & Short-Term Investments | B11: 5933 | C11: 7728 | D11: 5785 | E11: 3893 | F11: 4765 | G11: 5038 | H11: 2921 | I11: 3233 | J11: 4129 | K11: 2678
A12: Cash Only | B12: 5235 | C12: 5600 | D12: 5735 | E12: 3655 | F12: 4564 | G12: 4634 | H12: 2353 | I12: 2853 | J12: 3053 | K12: 2398
A13: Total Short Term Investments | B13: 698 | C13: 2128 | D13: 50 | E13: 238 | F13: 201 | G13: 404 | H13: 568 | I13: 380 | J13: 1076 | K13: 280
A14: Short-Term Receivables | B14: 3533 | C14: 3194 | D14: 3601 | E14: 4532 | F14: 4660 | G14: 4705 | H14: 4791 | I14: 5020 | J14: 4911 | K14: 4392
A15: Accounts Receivables, Net | B15: 3533 | C15: 3194 | D15: 3601 | E15: 4532 | F15: 4660 | G15: 4705 | H15: 4791 | I15: 5020 | J15: 4911 | K15: 4392
A16: Accounts Receivables, Gross | B16: 3594 | C16: 3254 | D16: 3663 | E16: 4706 | F16: 4849 | G16: 4938 | H16: 4952 | I16: 5115 | J16: 5014 | K16: 4480
A17: Bad Debt/Doubtful Accounts | B17: -61 | C17: -60 | D17: -62 | E17: -174 | F17: -189 | G17: -233 | H17: -161 | I17: -95 | J17: -103 | K17: -88
A18: Inventories | B18: 3661 | C18: 3698 | D18: 3944 | E18: 5372 | F18: 4985 | G18: 4239 | H18: 4134 | I18: 4366 | J18: 4034 | K18: 3385
A19: Finished Goods | B19: 1744 | C19: 1849 | D19: 1842 | E19: 2497 | F19: 2196 | G19: 2081 | H19: 2003 | I19: 2120 | J19: 1915 | K19: 1629
A20: Work in Progress | B20: 1126 | C20: 1051 | D20: 1242 | E20: 1606 | F20: 1577 | G20: 1226 | H20: 1194 | I20: 1292 | J20: 1218 | K20: 1039
A21: Raw Materials | B21: 791 | C21: 798 | D21: 860 | E21: 1269 | F21: 1212 | G21: 932 | H21: 937 | I21: 954 | J21: 901 | K21: 717
A22: Other Current Assets | B22: 3260 | C22: 1264 | D22: 3049 | E22: 891 | F22: 993 | G22: 1000 | H22: 1125 | I22: 1090 | J22: 1203 | K22: 1271
A23: Prepaid Expenses | B23: 391 | C23: 436 | D23: 344 | E23: 435 | F23: 654 | G23: 675 | H23: 704 | I23: 741 | J23: 937
A24: Miscellaneous Current Assets | B24: 2869 | C24: 828 | D24: 2705 | E24: 456 | F24: 339 | G24: 325 | H24: 421 | I24: 349 | J24: 266 | K24: 1271
A25: Total Current Assets | B25: 16387 | C25: 15884 | D25: 16379 | E25: 14688 | F25: 15403 | G25: 14982 | H25: 12971 | I25: 13709 | J25: 14277 | K25: 11726
A26: Net Property, Plant & Equipment | B26: 7617 | C26: 7953 | D26: 8347 | E26: 10007 | F26: 10287 | G26: 10285 | H26: 10191 | I26: 8738 | J26: 8866 | K26: 8516
A27: Property, Plant & Equipment - Gross | B27: 24438 | C27: 23971 | D27: 24151 | E27: 26827 | F27: 28071 | G27: 27514 | H27: 26982 | I27: 24873 | J27: 24914 | K27: 23499
A28: Buildings | B28: 7729 | C28: 7432 | D28: 7031 | E28: 7560 | F28: 8086 | G28: 8021 | H28: 7877 | I28: 7517 | J28: 7681 | K28: 7252
A29: Land & Improvements | B29: 202 | C29: 200 | D29: 215 | E29: 255 | F29: 312 | G29: 338 | H29: 351 | I29: 340 | J29: 348 | K29: 341
A30: Machinery & Equipment | B30: 15328 | C30: 14780 | D30: 14716 | E30: 16455 | F30: 17305 | G30: 16866 | H30: 16586 | I30: 15680 | J30: 15907 | K30: 14935
A31: Construction in Progress | B31: 663 | C31: 994 | D31: 1532 | E31: 1728 | F31: 1510 | G31: 1425 | H31: 1310 | I31: 1193 | J31: 843 | K31: 809
A32: Leases | I32: 143 | J32: 135 | K32: 162
A33: Operating Lease Right-of-Use Assets | B33: 516 | C33: 565 | D33: 657 | E33: 829 | F33: 858 | G33: 864 | H33: 858
A34: Accumulated Depreciation | B34: 16821 | C34: 16018 | D34: 15804 | E34: 16820 | F34: 17784 | G34: 17229 | H34: 16791 | I34: 16135 | J34: 16048 | K34: 14983
A35: Total Long-Term Investments | B35: 161 | C35: 2583 | D35: 221 | E35: 976 | F35: 303 | G35: 224 | H35: 263 | I35: 246 | J35: 191 | K35: 256
A36: LT Investment - Affiliate Companies | C36: 75 | D36: 73 | E36: 81 | F36: 129 | G36: 134 | H36: 70 | I36: 70 | J36: 70 | K36: 60
A37: Other Long-Term Investments | B37: 161 | C37: 2508 | D37: 148 | E37: 895 | F37: 174 | G37: 90 | H37: 193 | I37: 176 | J37: 121 | K37: 196
A38: Intangible Assets | B38: 7522 | C38: 7491 | D38: 7705 | E38: 17489 | F38: 18774 | G38: 19637 | H38: 19823 | I38: 12708 | J38: 13449 | K38: 11486
A39: Goodwill | B39: 6419 | C39: 6281 | D39: 6382 | E39: 12790 | F39: 13486 | G39: 13802 | H39: 13444 | I39: 10051 | J39: 10513 | K39: 9166
A40: Other Intangible Assets | B40: 1103 | C40: 1210 | D40: 1323 | E40: 4699 | F40: 5288 | G40: 5835 | H40: 6379 | I40: 2657 | J40: 2936 | K40: 2320
A41: Deferred Tax Assets | B41: 3826 | C41: 4146 | D41: 4779 | E41: 959 | F41: 581 | G41: 871 | H41: 521 | I41: 365 | J41: 511 | K41: 422
A42: Other Assets | B42: 2220 | C42: 1811 | D42: 13149 | E42: 2336 | F42: 1724 | G42: 1345 | H42: 890 | I42: 734 | J42: 693 | K42: 500
A43: Deferred Charges | C43: 1243 | D43: 1239 | E43: 1225 | F43: 943 | G43: 630 | H43: 230 | I43: 208 | J43: 237 | K43: 52
A44: Tangible Other Assets | B44: 2220 | C44: 568 | D44: 11910 | E44: 1111 | F44: 781 | G44: 715 | H44: 660 | I44: 526 | J44: 456 | K44: 448
A45: Total Assets | B45: 37733 | C45: 39868 | D45: 50580 | E45: 46455 | F45: 47072 | G45: 47344 | H45: 44659 | I45: 36500 | J45: 37987 | K45: 32906
A46: Liabilities & Shareholders' Equity
A47: Current | B47: =B64-B56-B48 -> 19854 | C47: =C64-C56-C48 -> 22315 | D47: =D64-D56-D48 -> 28961 | E47: =E64-E56-E48 -> 14819 | F47: =F64-F56-F48 -> 13638 | G47: =G64-G56-G48 -> 14638 | H47: =H64-H56-H48 -> 13234 | I47: =I64-I56-I48 -> 11955 | ... K47: =K64-K56-K48 -> 10868
A48: ST Debt & Curr. Portion LT Debt | B48: 1837 | C48: 2082 | D48: 3139 | E48: 2210 | F48: 1577 | G48: 1084 | H48: 3063 | I48: 1211 | J48: 1853 | K48: 972
A49: Accounts Payable | B49: 2702 | C49: 2660 | D49: 2776 | E49: 3183 | F49: 2994 | G49: 2561 | H49: 2228 | I49: 2266 | J49: 1945 | K49: 1798
A50: Income Tax Payable | C50: 331 | D50: 304 | E50: 259 | F50: 260 | G50: 300 | H50: 194 | I50: 243 | J50: 310 | K50: 299
A51: Other Current Liabilities | B51: 5056 | C51: 6183 | D51: 9078 | E51: 3871 | F51: 4204 | G51: 4003 | H51: 3737 | I51: 3524 | J51: 3579 | K51: 3150
A52: Accrued Payroll | B52: 718 | C52: 968 | D52: 998 | E52: 1016 | F52: 1317 | G52: 1010 | H52: 998 | I52: 1053 | J52: 1147 | K52: 899
A53: Miscellaneous Current Liabilities | B53: 4338 | C53: 5215 | D53: 8080 | E53: 2855 | F53: 2887 | G53: 2993 | H53: 2739 | I53: 2471 | J53: 2432 | K53: 2251
A54: Total Current Liabilities | B54: 9595 | C54: 11256 | D54: 15297 | E54: 9523 | F54: 9035 | G54: 7948 | H54: 9222 | I54: 7244 | J54: 7687 | K54: 6219
A55: Long-Term
A56: Long-Term Debt | B56: 11295 | C56: 11577 | D56: 13612 | E56: 14656 | F56: 16740 | G56: 18691 | H56: 18236 | I56: 13486 | J56: 12156 | K56: 10723
A57: Long-Term Debt excl Lease Obligations | B57: 10932 | C57: 11125 | D57: 13088 | E57: 14001 | F57: 16056 | G57: 17989 | H57: 17518 | I57: 13411 | J57: 12096 | K57: 10678
A58: Capital and Operating Lease Obligations | B58: 363 | C58: 452 | D58: 524 | E58: 655 | F58: 684 | G58: 702 | H58: 718 | I58: 75 | J58: 60 | K58: 45
A59: Provision for Risks & Charges | B59: 1631 | C59: 1813 | D59: 2156 | E59: 2352 | F59: 3270 | G59: 4815 | H59: 4223 | I59: 3286 | J59: 3939 | K59: 4274
A60: Deferred Tax Liabilities | B60: 418 | C60: 354 | D60: 315 | E60: 559 | F60: 458 | G60: 333 | H60: 301 | I60: 279 | J60: 235 | K60: 145
A61: Other Liabilities | B61: 10047 | C61: 10974 | D61: 14332 | E61: 4595 | F61: 2452 | G61: 2626 | H61: 2551 | I61: 2357 | J61: 2348 | K61: 1202
A62: Other Liabilities (excl. Deferred Income) | B62: 10047 | C62: 10974 | D62: 14332 | E62: 4595 | F62: 2452 | G62: 2626 | H62: 2551 | I62: 2357 | J62: 2348 | K62: 1187
A63: Deferred Income | K63: 15
A64: Total Liabilities | B64: 32986 | C64: 35974 | D64: 45712 | E64: 31685 | F64: 31955 | G64: 34413 | H64: 34533 | I64: 26652 | J64: 26365 | K64: 22563
A65: Equity
A66: Common Equity | B66: 4702 | C66: 3842 | D66: 4807 | E66: 14722 | F66: 15046 | G66: 12867 | H66: 10063 | I66: 9796 | J66: 11563 | K66: 10298
A67: Common Stock Par/Carry Value | B67: 9 | C67: 9 | D67: 9 | E67: 9 | F67: 9 | G67: 9 | H67: 9 | I67: 9 | J67: 9 | K67: 9
A68: Additional Paid-In Capital/Capital Surplus | B68: 7440 | C68: 7229 | D68: 6956 | E68: 6691 | F68: 6429 | G68: 6162 | H68: 5907 | I68: 5643 | J68: 5352 | K68: 5061
A69: Retained Earnings | B69: 38258 | C69: 36797 | D69: 37479 | E69: 47950 | F69: 45821 | G69: 43821 | H69: 42135 | I69: 40636 | J69: 39115 | K69: 37907
A70: Cumulative Translation Adjustment/Unrealized For. Exch. Gain | B70: -2520 | C70: -2953 | D70: -2506 | E70: -2828 | F70: -1943 | G70: -1450 | H70: -1899 | I70: -2098 | J70: -1638 | K70: -2008
A71: Other Appropriated Reserves | B71: -2549 | C71: -2778 | D71: -4272 | E71: -3845 | F71: -4807 | G71: -6271 | H71: -6240 | I71: -4768 | J71: -5388 | K71: -5237
A72: Treasury Stock | B72: -35936 | C72: -34462 | D72: -32859 | E72: -33255 | F72: -30463 | G72: -29404 | H72: -29849 | I72: -29626 | J72: -25887 | K72: -25434
A73: Total Shareholders' Equity | B73: 4702 | C73: 3842 | D73: 4807 | E73: 14722 | F73: 15046 | G73: 12867 | H73: 10063 | I73: 9796 | J73: 11563 | K73: 10298
A74: Accumulated Minority Interest | B74: 45 | C74: 52 | D74: 61 | E74: 48 | F74: 71 | G74: 64 | H74: 63 | I74: 52 | J74: 59 | K74: 45
A75: Total Equity | B75: 4747 | C75: 3894 | D75: 4868 | E75: 14770 | F75: 15117 | G75: 12931 | H75: 10126 | I75: 9848 | J75: 11622 | K75: 10343
A76: Total Liabilities & Shareholders' Equity | B76: 37733 | C76: 39868 | D76: 50580 | E76: 46455 | F76: 47072 | G76: 47344 | H76: 44659 | I76: 36500 | J76: 37987 | K76: 32906
A77: Per Share
A78: Book Value per Share | B78: 8.86703 | C78: 7.1218 | D78: 8.69917 | E78: 26.80406 | F78: 26.3113 | G78: 22.27089 | H78: 17.49525 | I78: 16.98998 | J78: 19.4374 | K78: 17.25749
A79: Tangible Book Value per Share | B79: -5.317954 | C79: -6.764042 | D79: -5.244479 | E79: -5.037824 | F79: -6.519244 | G79: -11.717878 | H79: -16.968458 | I79: -5.050512 | J79: -3.170365 | K79: -1.990863
A80: All figures in millions of U.S. Dollar except per share items.
A82: Invested Capital (D+E-Cash) | B82: =B75+B56+B48-B11-B35 -> 11785 | C82: =C75+C56+C48-C11-C35 -> 7242 | D82: =D75+D56+D48-D11-D35 -> 15613 | E82: =E75+E56+E48-E11-E35 -> 26767 | F82: =F75+F56+F48-F11-F35 -> 28366 | G82: =G75+G56+G48-G11-G35 -> 27444 | H82: =H75+H56+H48-H11-H35 -> 28241 | I82: =I75+I56+I48-I11-I35 -> 21066 | ... K82: =K75+K56+K48-K11-K35 -> 19104
A84: Invested Capital (OA-OL) | B84: =(B45-B11-B35)-(B64-B56-B48) -> 11785 | C84: =(C45-C11-C35)-(C64-C56-C48) -> 7242 | D84: =(D45-D11-D35)-(D64-D56-D48) -> 15613 | E84: =(E45-E11-E35)-(E64-E56-E48) -> 26767 | F84: =(F45-F11-F35)-(F64-F56-F48) -> 28366 | G84: =(G45-G11-G35)-(G64-G56-G48) -> 27444 | H84: =(H45-H11-H35)-(H64-H56-H48) -> 28241 | I84: =(I45-I11-I35)-(I64-I56-I48) -> 21066 | ... K84: =(K45-K11-K35)-(K64-K56-K48) -> 19104
A86: Difference | B86: =B82-B84 -> 0 | C86: =C82-C84 -> 0 | D86: =D82-D84 -> 0 | E86: =E82-E84 -> 0 | F86: =F82-F84 -> 0 | G86: =G82-G84 -> 0 | H86: =H82-H84 -> 0 | I86: =I82-I84 -> 0 | ... K86: =K82-K84 -> 0

Sheet 3M-CFS
A1: 3M Company (MMM)
A5: 3M Company
A6: MMM 88579Y101 2595708 NYSE Common stock
A7: Source: FactSet Fundamentals
B8: DEC '25 | C8: DEC '24 | D8: DEC '23 | E8: DEC '22 | F8: DEC '21 | G8: DEC '20 | H8: DEC '19 | I8: DEC '18 | J8: DEC '17 | K8: DEC '16
D9: Restate | G9: Restate | J9: Restate
A10: Operating Activities
A11: Net Income / Starting Line | B11: 3262 | C11: 4188 | D11: -6979 | E11: 5791 | F11: 5929 | G11: 5453 | H11: 4582 | I11: 5363 | J11: 4869 | K11: 5058
A12: Depreciation, Depletion & Amortization | B12: 1308 | C12: 1224 | D12: 1433 | E12: 1831 | F12: 1915 | G12: 1911 | H12: 1593 | I12: 1488 | J12: 1544 | K12: 1474
A13: Depreciation and Depletion | B13: 1204 | C13: 1116 | D13: 1306 | E13: 1333 | F13: 1386 | G13: 1374 | H13: 1252 | I13: 1239 | J13: 1306 | K13: 1212
A14: Amortization of Intangible Assets | B14: 104 | C14: 108 | D14: 127 | E14: 498 | F14: 529 | G14: 537 | H14: 341 | I14: 249 | J14: 238 | K14: 262
A15: Deferred Taxes & Investment Tax Credit | B15: 418 | C15: 321 | D15: -3855 | E15: -663 | F15: -166 | G15: -165 | H15: -273 | I15: -57 | J15: 107 | K15: 7
A16: Deferred Taxes | B16: 418 | C16: 321 | D16: -3855 | E16: -663 | F16: -166 | G16: -165 | H16: -273 | I16: -57 | J16: 107 | K16: 7
A17: Other Funds | B17: 514 | C17: 1309 | D17: 785 | E17: -1552 | F17: 300 | G17: 39 | H17: 476 | I17: -203 | J17: -895 | K17: 166
A18: Funds from Operations | B18: 5502 | C18: 7042 | D18: -8616 | E18: 5407 | F18: 7978 | G18: 7238 | H18: 6378 | I18: 6591 | J18: 5625 | K18: 6705
A19: Changes in Working Capital | B19: -3196 | C19: -5223 | D19: 15296 | E19: 184 | F19: -524 | G19: 875 | H19: 692 | I19: -152 | J19: 615 | K19: -43
A20: Receivables | B20: -211 | C20: 114 | D20: -170 | E20: -105 | F20: -122 | G20: 165 | H20: 345 | I20: -305 | J20: -245 | K20: -313
A21: Inventories | B21: 139 | C21: 41 | D21: 567 | E21: -629 | F21: -903 | G21: -91 | H21: 370 | I21: -509 | J21: -387 | K21: 57
A22: Accounts Payable | B22: 21 | C22: 46 | D22: 138 | E22: 111 | F22: 518 | G22: 252 | H22: -117 | I22: 408 | J22: 24 | K22: 148
A23: Income Taxes Payable | C23: -272 | D23: -218 | E23: -47 | F23: -244 | G23: 132 | H23: 205 | I23: 134 | J23: 967 | K23: 101
A24: Other Assets/Liabilities | B24: -3145 | C24: -5152 | D24: 14979 | E24: 854 | F24: 227 | G24: 417 | H24: -111 | I24: 120 | J24: 256 | K24: -36
A25: Net Operating Cash Flow | B25: 2306 | C25: 1819 | D25: 6680 | E25: 5591 | F25: 7454 | G25: 8113 | H25: 7070 | I25: 6439 | J25: 6240 | K25: 6662
A26: Investing Activities
A27: Capital Expenditures | B27: -910 | C27: -1181 | D27: -1615 | E27: -1749 | F27: -1603 | G27: -1501 | H27: -1699 | I27: -1577 | J27: -1373 | K27: -1420
A28: Capital Expenditures (Fixed Assets) | B28: -910 | C28: -1181 | D28: -1615 | E28: -1749 | F28: -1603 | G28: -1501 | H28: -1699 | I28: -1577 | J28: -1373 | K28: -1420
A29: Net Assets from Acquisitions | B29: 0 | C29: 0 | D29: 0 | E29: 0 | F29: 0 | G29: -25 | H29: -4984 | I29: 0 | J29: -2023 | K29: -16
A30: Sale of Fixed Assets & Businesses | B30: 100 | C30: 61 | D30: 179 | E30: 691 | F30: 51 | G30: 704 | H30: 359 | I30: 1121 | J30: 1114 | K30: 200
A31: Purchase/Sale of Investments | B31: 2163 | C31: -2079 | D31: 194 | E31: 11 | F31: 204 | G31: 232 | H31: -192 | I31: 669 | J31: -798 | K31: -163
A32: Purchase of Investments | B32: 1305 | C32: 4153 | D32: 1466 | E32: 1250 | F32: 2202 | G32: 1579 | H32: 1635 | I32: 1828 | J32: 2152 | K32: 1410
A33: Sale/Maturity of Investments | B33: 3468 | C33: 2074 | D33: 1660 | E33: 1261 | F33: 2406 | G33: 1811 | H33: 1443 | I33: 2497 | J33: 1354 | K33: 1247
A34: Other Funds | B34: -3 | C34: -7 | D34: 35 | E34: 1 | F34: 31 | G34: 10 | H34: 72 | I34: 9 | J34: -6 | K34: -4
A35: Other Uses | B35: -3 | C35: -7 | D35: 0 | E35: 0 | F35: 0 | G35: 0 | H35: 0 | I35: 0 | J35: -6 | K35: -4
A36: Other Sources | B36: 0 | C36: 0 | D36: 35 | E36: 1 | F36: 31 | G36: 10 | H36: 72 | I36: 9 | J36: 0 | K36: 0
A37: Net Investing Cash Flow | B37: 1350 | C37: -3206 | D37: -1207 | E37: -1046 | F37: -1317 | G37: -580 | H37: -6444 | I37: 222 | J37: -3086 | K37: -1403
A38: Financing Activities
A39: Cash Dividends Paid | B39: -1562 | C39: -1982 | D39: -3311 | E39: -3369 | F39: -3420 | G39: -3388 | H39: -3316 | I39: -3193 | J39: -2803 | K39: -2678
A40: Common Dividends | B40: -1562 | C40: -1982 | D40: -3311 | E40: -3369 | F40: -3420 | G40: -3388 | H40: -3316 | I40: -3193 | J40: -2803 | K40: -2678
A41: Change in Capital Stock | B41: -1689 | C41: -1709 | D41: 231 | E41: -1083 | F41: -1560 | G41: 61 | H41: -860 | I41: -4385 | J41: -1334 | K41: -2949
A42: Repurchase of Common & Preferred Stk. | B42: -3251 | C42: -1801 | D42: -33 | E42: -1464 | F42: -2199 | G42: -368 | H42: -1407 | I42: -4870 | J42: -2068 | K42: -3753
A43: Sale of Common & Preferred Stock | B43: 1562 | C43: 92 | D43: 264 | E43: 381 | F43: 639 | G43: 429 | H43: 547 | I43: 485 | J43: 734 | K43: 804
A44: Proceeds from Stock Options | B44: 1562 | C44: 92 | D44: 264 | E44: 381 | F44: 639 | G44: 429 | H44: 547 | I44: 485 | J44: 734 | K44: 804
A45: Issuance/Reduction of Debt, Net | B45: -716 | C45: 5506 | D45: -46 | E45: -838 | F45: -1145 | G45: -1875 | H45: 3249 | I45: 933 | J45: 1603 | K45: 1043
A46: Change in Current Debt | B46: 0 | C46: -205 | D46: 205 | E46: 340 | F46: -2 | G46: -143 | H46: -316 | I46: -284 | J46: 578 | K46: -797
A47: Change in Long-Term Debt | B47: -716 | C47: 5711 | D47: -251 | E47: -1178 | F47: -1143 | G47: -1732 | H47: 3565 | I47: 1217 | J47: 1025 | K47: 1840
A48: Issuance of Long-Term Debt | B48: 1099 | C48: 8367 | D48: 2835 | E48: 1 | F48: 1 | G48: 1750 | H48: 6281 | I48: 2251 | J48: 1987 | K48: 2832
A49: Reduction in Long-Term Debt | B49: -1815 | C49: -2656 | D49: -3086 | E49: -1179 | F49: -1144 | G49: -3482 | H49: -2716 | I49: -1034 | J49: -962 | K49: -992
A50: Other Funds | B50: -49 | C50: -717 | D50: -21 | E50: -60 | F50: -20 | G50: -98 | H50: -197 | I50: -56 | J50: -121 | K50: -42
... A52: Net Financing Cash Flow | B52: -4016 | C52: 1098 | D52: -3147 | E52: -5350 | F52: -6145 | G52: -5300 | H52: -1124 | I52: -6701 | J52: -2655 | K52: -4626
A53: All Activities
A54: Exchange Rate Effect | B54: 41 | C54: -44 | D54: -48 | E54: -104 | F54: -62 | G54: 48 | H54: -2 | I54: -160 | J54: 156 | K54: -33
A55: Net Change in Cash | B55: -319 | C55: -333 | D55: 2278 | E55: -909 | F55: -70 | G55: 2281 | H55: -500 | I55: -200 | J55: 655 | K55: 600
A56: Free Cash Flow | B56: 1396 | C56: 638 | D56: 5065 | E56: 3842 | F56: 5851 | G56: 6612 | H56: 5371 | I56: 4862 | J56: 4867 | K56: 5242
A57: Free Cash Flow per Share | B57: 2.578977 | C57: 1.15496 | D57: 9.14425 | E57: 6.768851 | F57: 9.996583 | G57: 11.356922 | H57: 9.179627 | I57: 8.076412 | J57: 7.943529 | K57: 8.472604
A58: Free Cash Flow Yield (%) | B58: 1.610853 | C58: 0.894694 | D58: 8.364663 | E58: 5.644472 | F58: 5.627756 | G58: 6.497467 | H58: 5.20328 | I58: 4.238696 | J58: 3.374911 | K58: 4.744696
A59: All figures in millions of U.S. Dollar except per share items.

Sheet 3M-IS
A1: 3M Company (MMM)
A3: 3M Company
A4: MMM 88579Y101 2595708 NYSE Common stock
A5: Source: FactSet Fundamentals
B6: DEC '25 | C6: DEC '24 | D6: DEC '23 | E6: DEC '22 | F6: DEC '21 | G6: DEC '20 | H6: DEC '19 | I6: DEC '18 | J6: DEC '17 | K6: DEC '16
D7: Restate | G7: Restate | J7: Restate
A8: Sales | B8: 24948 | C8: 24575 | D8: 24610 | E8: 34229 | F8: 35355 | G8: 32184 | H8: 32136 | I8: 32765 | J8: 31657 | K8: 30109
A9: Cost of Goods Sold (COGS) incl. D&A | B9: 15072 | C9: 14495 | D9: 15037 | E9: 19263 | F9: 18743 | G9: 16581 | H9: 16830 | I9: 16575 | J9: 15995 | K9: 15133
A10: COGS excluding D&A | B10: 13764 | C10: 13271 | D10: 13604 | E10: 17432 | F10: 16828 | G10: 14670 | H10: 15237 | I10: 15087 | J10: 14451 | K10: 13659
A11: Depreciation & Amortization Expense | B11: 1308 | C11: 1224 | D11: 1433 | E11: 1831 | F11: 1915 | G11: 1911 | H11: 1593 | I11: 1488 | J11: 1544 | K11: 1474
A12: Depreciation | B12: 1204 | C12: 1116 | D12: 1306 | E12: 1333 | F12: 1386 | G12: 1374 | H12: 1252 | I12: 1239 | J12: 1306 | K12: 1212
A13: Amortization of Intangibles | B13: 104 | C13: 108 | D13: 127 | E13: 498 | F13: 529 | G13: 537 | H13: 341 | I13: 249 | J13: 238 | K13: 262
A14: Gross Income | B14: 9876 | C14: 10080 | D14: 9573 | E14: 14966 | F14: 16612 | G14: 15603 | H14: 15306 | I14: 16190 | J14: 15662 | K14: 14976
A15: SG&A Expense | B15: 5146 | C15: 5149 | D15: 5526 | E15: 10893 | F15: 9086 | G15: 8646 | H15: 8332 | I15: 8416 | J15: 8436 | K15: 7957
A16: Research & Development | B16: 1169 | C16: 1070 | D16: 1123 | E16: 1856 | F16: 1977 | G16: 1862 | H16: 1874 | I16: 1816 | J16: 1862 | K16: 1735
A17: Other SG&A | B17: 3977 | C17: 4079 | D17: 4403 | E17: 9037 | F17: 7109 | G17: 6784 | H17: 6458 | I17: 6600 | J17: 6574 | K17: 6222
A18: EBIT (Operating Income) | B18: 4730 | C18: 4931 | D18: 4047 | E18: 4073 | F18: 7526 | G18: 6957 | H18: 6974 | I18: 7774 | J18: 7226 | K18: 7019
A19: Nonoperating Income - Net | B19: -100 | C19: -189 | D19: 517 | E19: 3137 | F19: 276 | G19: 623 | H19: 368 | I19: 594 | J19: 771 | K19: 249
... A25: Unusual Expense - Net | B25: -521 | C25: -1259 | D25: 14903 | E25: 320 | F25: 141 | G25: 232 | H25: 1199 | I25: 1128 | J25: 365 | K25: 8
A26: Impairments | C26: 0 | D26: 0 | E26: 271
A27: Goodwill | B27: 0 | C27: 0 | D27: 0 | E27: 271 | F27: 0 | G27: 0 | H27: 0 | I27: 0 | J27: 0 | K27: 0
A28: Restructuring Expense | B28: 21 | C28: 187 | D28: 415 | E28: 18 | F28: 124 | G28: 250 | H28: 444 | I28: 137 | J28: 146 | K28: 0
A29: Legal Claim Expense | C29: 87 | D29: 14500 | G29: 17 | H29: 762 | I29: 897
A30: Unrealized Valuation Gain/Loss | B30: 542 | C30: 1533 | D30: 12 | E30: -31 | F30: -6 | G30: 45 | H30: 7 | I30: -94 | J30: -123 | K30: -8
A31: Investments | B31: 402 | C31: 1564 | D31: 0
A32: Hedges/Derivatives | B32: 140 | C32: -31 | D32: 12 | E32: -31 | F32: -6 | G32: 45 | H32: 7 | I32: -94 | J32: -123 | K32: -8
A33: Excpl Chrgs - Others | F33: 11 | G33: 10 | H33: 0 | I33: 0 | J33: 96
A34: Restructuring of Debt | F34: 11 | G34: 10 | H34: 0 | I34: 0 | J34: 96
A35: Pretax Income | B35: 4213 | C35: 4819 | D35: -11271 | E35: 6392 | F35: 7204 | G35: 6795 | H35: 5712 | I35: 7000 | J35: 7548 | K35: 7053
A36: Income Taxes | B36: 1003 | C36: 804 | D36: -2867 | E36: 612 | F36: 1285 | G36: 1337 | H36: 1130 | I36: 1637 | J36: 2679 | K36: 1995
A37: Income Taxes - Current Domestic | B37: -12 | C37: -81 | D37: 340 | E37: 681 | F37: 860 | G37: 843 | H37: 593 | I37: 983 | J37: 1704 | K37: 1267
A38: Income Taxes - Current Foreign | B38: 597 | C38: 583 | D38: 494 | E38: 621 | F38: 597 | G38: 632 | H38: 673 | I38: 763 | J38: 722 | K38: 733
A39: Income Taxes - Deferred Domestic | B39: 328 | C39: 329 | D39: -3579 | E39: -688 | F39: -244 | G39: -61 | H39: -58 | I39: -55 | J39: 177 | K39: 6
A40: Income Taxes - Deferred Foreign | B40: 90 | C40: -27 | D40: -122 | E40: -2 | F40: 72 | G40: -77 | H40: -78 | I40: -54 | J40: 76 | K40: -11
A41: Equity in Earnings of Affiliates | B41: 52 | C41: 9 | D41: 18 | E41: 11 | F41: 10 | G41: -5 | H41: 0 | I41: 0 | J41: 0 | K41: 0
A42: Consolidated Net Income | B42: 3262 | C42: 4024 | D42: -8386 | E42: 5791 | F42: 5929 | G42: 5453 | H42: 4582 | I42: 5363 | J42: 4869 | K42: 5058
A43: Minority Interest | B43: 12 | C43: 15 | D43: 16 | E43: 14 | F43: 8 | G43: 4 | H43: 12 | I43: 14 | J43: 11 | K43: 8
A44: Net Income | B44: 3250 | C44: 4009 | D44: -8402 | E44: 5777 | F44: 5921 | G44: 5449 | H44: 4570 | I44: 5349 | J44: 4858 | K44: 5050
A45: Discontinued Operations | B45: 0 | C45: 164 | D45: 1407 | E45: 0 | F45: 0 | G45: 0 | H45: 0 | I45: 0 | J45: 0 | K45: 0
A46: Net Income available to Common | B46: 3250 | C46: 4173 | D46: -6995 | E46: 5777 | F46: 5921 | G46: 5449 | H46: 4570 | I46: 5349 | J46: 4858 | K46: 5050
A47: Per Share
A48: EPS (recurring) | B48: 5.330316 | C48: 5.958907 | D48: 6.205272 | E48: 10.572586 | F48: 10.284811 | G48: 9.638269 | H48: 9.245086 | I48: 10.19701 | J48: 8.345846 | K48: 8.171327
A49: EPS (basic) | B49: 6.0476 | C49: 7.5762 | D49: -12.6286 | E49: 10.2067 | F49: 10.2262 | G49: 9.4339 | H49: 7.9203 | I49: 9.09 | J49: 8.13 | K49: 8.35
A50: Basic Shares Outstanding | B50: 537.4 | C50: 550.8 | D50: 553.9 | E50: 566 | F50: 579 | G50: 577.6 | H50: 577 | I50: 588.5 | J50: 597.5 | K50: 604.7
A51: Total Shares Outstanding | B51: 530.27913 | C51: 539.4703 | D51: 552.58114 | E51: 549.2451 | F51: 571.84548 | G51: 577.74964 | H51: 575.18484 | I51: 576.57517 | J51: 594.88424 | K51: 596.72628
A52: EPS (diluted) | B52: 6.0041 | C52: 7.5543 | D52: -12.6286 | E52: 10.1779 | F52: 10.1162 | G52: 9.3593 | H52: 7.8106 | I52: 8.89 | J52: 7.93 | K52: 8.16
A53: Diluted Shares Outstanding | B53: 541.3 | C53: 552.4 | D53: 553.9 | E53: 567.6 | F53: 585.3 | G53: 582.2 | H53: 585.1 | I53: 602 | J53: 612.7 | K53: 618.7
A54: Total Shares Outstanding | B54: 530.27913 | C54: 539.4703 | D54: 552.58114 | E54: 549.2451 | F54: 571.84548 | G54: 577.74964 | H54: 575.18484 | I54: 576.57517 | J54: 594.88424 | K54: 596.72628
A55: Earnings Persistence | B55: 82.988 | C55: 66.733 | D55: 61.624 | E55: 90.228 | F55: 92.654 | G55: 88.61 | H55: 76.399 | I55: 90.641 | J55: 84.679 | K55: 91.161
A56: Dividends per Share | B56: 2.92 | C56: 3.61 | D56: 6 | E56: 5.96 | F56: 5.92 | G56: 5.88 | H56: 5.76 | I56: 5.44 | J56: 4.7 | K56: 4.44
A57: Payout Ratio | B57: 48.633434 | C57: 47.787353 | E57: 58.558249 | F57: 58.519998 | G57: 62.825211 | H57: 73.745935 | I57: 61.192351 | J57: 59.2686 | K57: 54.411765
A58: EBITDA
A59: EBITDA | B59: 6038 | C59: 6155 | D59: 5480 | E59: 5904 | F59: 9441 | G59: 8868 | H59: 8567 | I59: 9262 | J59: 8770 | K59: 8493
A60: EBIT | B60: 4730 | C60: 4931 | D60: 4047 | E60: 4073 | F60: 7526 | G60: 6957 | H60: 6974 | I60: 7774 | J60: 7226 | K60: 7019
A61: Depreciation & Amortization Expense | B61: 1308 | C61: 1224 | D61: 1433 | E61: 1831 | F61: 1915 | G61: 1911 | H61: 1593 | I61: 1488 | J61: 1544 | K61: 1474
A62: All figures in millions of U.S. Dollar except per share items.
A64: Tax rate | B64: =B36/B35 -> 0.23807263 | C64: =C36/C35 -> 0.16683959 | D64: =D36/D35 -> 0.25436962 | E64: =E36/E35 -> 0.095744681 | F64: =F36/F35 -> 0.17837313 | G64: =G36/G35 -> 0.19676233 | H64: =H36/H35 -> 0.19782913 | I64: =I36/I35 -> 0.23385714 | ... K64: =K36/K35 -> 0.28285836

Sheet MMM-US
A1: 3M Company
A2: MMM 88579Y101 2595708 NYSE Common stock
A5: Instrument ID | B5: Description | C5: Balance Sheet Amt Out (USD) | D5: Current Amt Out (USD) | E5: Coupon Rate | F5: Coupon Type | G5: Issue Date | H5: Maturity Date | I5: Issue Curr | J5: Seniority | K5: Price | L5: YTW | M5: OAS (LIBOR)
A6: ST Debt | C6: 1670 | D6: 1670
A7: - | B7: Commercial Paper | C7: 0 | D7: 0 | E7: - | F7: Variable | G7: - | H7: - | I7: USD | J7: SNR Unsec | K7: - | L7: - | M7: -
A8: - | B8: Current Portion Of LTD | C8: 1670 | D8: 1670 | E8: - | F8: - | G8: - | H8: - | I8: USD | J8: Other | K8: - | L8: - | M8: -
A9: 88580DN8 | B9: 3M Company 0.000% 08-JAN-2027 | C9: - | D9: - | E9: 0 | F9: Zero | G9: 04/26 | H9: 01/27 | I9: USD | J9: Other | K9: - | L9: - | M9: -
A10: 88580DN7 | B10: 3M Company 0.000% 07-JAN-2027 | C10: - | D10: - | E10: 0 | F10: Zero | G10: 04/26 | H10: 01/27 | I10: USD | J10: Other | K10: - | L10: - | M10: -
A11: 60406BN8 | B11: 3M Company 0.000% 08-JAN-2027 | C11: - | D11: - | E11: 0 | F11: Zero | G11: 04/26 | H11: 01/27 | I11: USD | J11: Other | K11: - | L11: - | M11: -
A12: 60406BN7 | B12: 3M Company 0.000% 07-JAN-2027 | C12: - | D12: - | E12: 0 | F12: Zero | G12: 04/26 | H12: 01/27 | I12: USD | J12: Other | K12: - | L12: - | M12: -
A13: 88580DMX | B13: 3M Company 0.000% 31-DEC-2026 | C13: - | D13: - | E13: 0 | F13: Zero | G13: 04/26 | H13: 12/26 | I13: USD | J13: Other | K13: - | L13: - | M13: -
A14: 88580DMW | B14: 3M Company 0.000% 30-DEC-2026 | C14: - | D14: - | E14: 0 | F14: Zero | G14: 04/26 | H14: 12/26 | I14: USD | J14: Other | K14: - | L14: - | M14: -
A15: 60406BMX | B15: 3M Company 0.000% 31-DEC-2026 | C15: - | D15: - | E15: 0 | F15: Zero | G15: 04/26 | H15: 12/26 | I15: USD | J15: Other | K15: - | L15: - | M15: -
A16: 60406BMW | B16: 3M Company 0.000% 30-DEC-2026 | C16: - | D16: - | E16: 0 | F16: Zero | G16: 04/26 | H16: 12/26 | I16: USD | J16: Other | K16: - | L16: - | M16: -
A17: 88580DMV | B17: 3M Company 0.000% 29-DEC-2026 | C17: - | D17: - | E17: 0 | F17: Zero | G17: 04/26 | H17: 12/26 | I17: USD | J17: Other | K17: - | L17: - | M17: -
A18: 60406BMV | B18: 3M Company 0.000% 29-DEC-2026 | C18: - | D18: - | E18: 0 | F18: Zero | G18: 04/26 | H18: 12/26 | I18: USD | J18: Other | K18: - | L18: - | M18: -
