Workbook

Sheet Dashboard
K3: Q4 FY'25 | L3: FY'26 Q1 | M3: Rest of FY'26 (Estimated) | N3: FY'26 End (Estimated)
J4: United States of America | K4: 629 | L4: 4 | M4: 16 | N4: 649
J5: Canada | K5: 110 | L5: 2 | M5: 3 | N5: 115
J6: Other International | K6: 175 | L6: 1 | M6: 2 | N6: 178
J7: Stores | K7: 914 | L7: 7 | M7: 21 | N7: 942
K10: Terminal Growth rate
J11: WACC | K11: WACC/Terminal growth rate | L11: 0.025 | M11: =L11+0.01 -> 0.035 | N11: =M11+0.01 -> 0.045 | O11: =N11+0.01 -> 0.055 | P11: =O11+0.01 -> 0.065
K12: =6.33% -> 0.0633 | L12: 470.73824 | M12: 617.60094 | N12: 924.96932 | O12: 1972.9844 | P12: -9308.5898
K13: =K12+0.01 -> 0.0733 | L13: 374.83029 | M13: 458.49742 | N13: 601.29326 | O13: 900.15013 | P13: 1919.144
K14: =K13+0.01 -> 0.0833 | L14: 311.87194 | M14: 365.32865 | N14: 446.7001 | O14: 585.57786 | P14: 876.23461
K15: =K14+0.01 -> 0.0933 | L15: 267.3887 | M15: 304.16406 | N15: 356.1673 | O15: 435.32629 | P15: 570.42801
K16: =K15+0.01 -> 0.1033 | L16: 234.30054 | M16: 260.94463 | N16: 296.72905 | O16: 347.33104 | P16: 424.35705
J18: Revenue Base case time series versus Historical Average
K19: 2026E | L19: 2027E | M19: 2028E | N19: 2029E
J20: Base Case | K20: 290232 | L20: 313495 | M20: 336757 | N20: 365768
J21: Historical growth | K21: 299318 | L21: 325508 | M21: 353990 | N21: 384965

Sheet Revenue Forecast ETS
B1: Reported revenue | E1: Lower bound | H1: Upper bound
A2: Date | B2: Net Sales | C2: Membership fee | D2: Revenue | E2: Net Sales | F2: Membership fee | G2: Revenue | H2: Net Sales | I2: Membership fee | J2: Revenue | L2: Growth rate | M2: Scenario | N2: 2
A3: 44885 | B3: 53437 | C3: 1000 | D3: =B3+C3 -> 54437
A4: =A3+84 -> 44969 | B4: 54239 | C4: 1027 | D4: =B4+C4 -> 55266 | M4: Year | N4: 2026 | O4: 2027 | P4: 2028 | Q4: 2029
A5: =A4+84 -> 45053 | B5: 52604 | C5: 1044 | D5: =B5+C5 -> 53648 | M5: Total Revenue | N5: =CHOOSE($N$2,N7,N8,N9) -> 290231.72 | O5: =CHOOSE($N$2,O7,O8,O9) -> 313494.72 | P5: =CHOOSE($N$2,P7,P8,P9) -> 336757.12 | Q5: =CHOOSE($N$2,Q7,Q8,Q9) -> 365767.83
A6: 45172 | B6: 77430 | C6: 1509 | D6: =B6+C6 -> 78939 | K6: =SUM(D3:D6) -> 242290 | M6: Growth | N6: =N5/K14-1 -> 0.054486974 | O6: =O5/N5-1 -> 0.080153179 | P6: =P5/O5-1 -> 0.074203504 | Q6: =Q5/P5-1 -> 0.086147269
A7: =A6+84 -> 45256 | B7: 56717 | C7: 1082 | D7: =B7+C7 -> 57799 | M7: Bull Case | N7: =SUM(J16:J18,D15) -> 342409.2 | O7: =SUM(J19:J22) -> 425778.7 | P7: =SUM(J23:J26) -> 484245.6 | Q7: =SUM(J27:J30) -> 542187.92
A8: =A7+84 -> 45340 | B8: 57331 | C8: 1111 | D8: =B8+C8 -> 58442 | M8: Base Case | N8: =SUM(D15:D18) -> 290231.72 | O8: =SUM(D19:D22) -> 313494.72 | P8: =SUM(D23:D26) -> 336757.12 | Q8: =SUM(D27:D30) -> 365767.83
A9: =A8+84 -> 45424 | B9: 57392 | C9: 1123 | D9: =B9+C9 -> 58515 | M9: Bear Case | N9: =SUM(D15,G16:G18) -> 238054.24 | O9: =SUM(G19:G22) -> 201210.73 | P9: =SUM(G23:G26) -> 189268.65 | Q9: =SUM(G27:G30) -> 189347.74
A10: 45536 | B10: 78185 | C10: 1512 | D10: =B10+C10 -> 79697 | K10: =SUM(D7:D10) -> 254453 | L10: =K10/K6-1 -> 0.050200173 | M10: CAGR | N10: 0.0793
A11: =A10+84 -> 45620 | B11: 60985 | C11: 1166 | D11: =B11+C11 -> 62151
A12: =A11+84 -> 45704 | B12: 62530 | C12: 1193 | D12: =B12+C12 -> 63723 | M12: Scenario | N12: 1
A13: =A12+84 -> 45788 | B13: 61965 | C13: 1240 | D13: =B13+C13 -> 63205
A14: 45900 | B14: 84432 | C14: 1724 | D14: =B14+C14 -> 86156 | K14: =SUM(D11:D14) -> 275235 | L14: =K14/K10-1 -> 0.081673236 | M14: Year | N14: 2026 | O14: 2027 | P14: 2028 | Q14: 2029
A15: =A14+84 -> 45984 | B15: 65978 | C15: 1329 | D15: =B15+C15 -> 67307 | M15: Membership fee | N15: =CHOOSE($N$12,N17,N18,N19) -> 7025.2045 | O15: =CHOOSE($N$12,O17,O18,O19) -> 8987.5015 | P15: =CHOOSE($N$12,P17,P18,P19) -> 10346.426 | Q15: =CHOOSE($N$12,Q17,Q18,Q19) -> 11670.4
A16: =A15+84 -> 46068 | B16: =_xlfn.FORECAST.ETS(A16,$B$3:$B$15,$A$3:$A$15,4) -> 65061.901 | C16: =_xlfn.FORECAST.ETS(A16,$C$3:$C$15,$A$3:$A$15,4) -> 1322.0642 | D16: =B16+C16 -> 66383.966 | E16: =B16-_xlfn.FORECAST.ETS.CONFINT(A16,$B$3:$B$15,$A$3:$A$15,0.95,4) -> 51541.772 | F16: =C16-_xlfn.FORECAST.ETS.CONFINT(A16,$C$3:$C$15,$A$3:$A$15,0.95,4) -> 1034.9094 | G16: =E16+F16 -> 52576.681 | H16: =B16+_xlfn.FORECAST.ETS.CONFINT(A16,$B$3:$B$15,$A$3:$A$15,0.95,4) -> 78582.031 | I16: =C16+_xlfn.FORECAST.ETS.CONFINT(A16,$C$3:$C$15,$A$3:$A$15,0.95,4) -> 1609.2191 | J16: =H16+I16 -> 80191.25 | M16: Growth | O16: =O15/N15-1 -> 0.27932241 | P16: =P15/O15-1 -> 0.15120157 | Q16: =Q15/P15-1 -> 0.12796441
A17: =A16+84 -> 46152 | B17: =_xlfn.FORECAST.ETS(A17,$B$3:$B$15,$A$3:$A$15,4) -> 70086.579 | C17: =_xlfn.FORECAST.ETS(A17,$C$3:$C$15,$A$3:$A$15,4) -> 1512.0549 | D17: =B17+C17 -> 71598.634 | E17: =B17-_xlfn.FORECAST.ETS.CONFINT(A17,$B$3:$B$15,$A$3:$A$15,0.95,4) -> 53178.302 | F17: =C17-_xlfn.FORECAST.ETS.CONFINT(A17,$C$3:$C$15,$A$3:$A$15,0.95,4) -> 1125.5354 | G17: =E17+F17 -> 54303.837 | H17: =B17+_xlfn.FORECAST.ETS.CONFINT(A17,$B$3:$B$15,$A$3:$A$15,0.95,4) -> 86994.857 | I17: =C17+_xlfn.FORECAST.ETS.CONFINT(A17,$C$3:$C$15,$A$3:$A$15,0.95,4) -> 1898.5744 | J17: =H17+I17 -> 88893.431 | M17: Bull Case | N17: =SUM(C15,I16:I18) -> 7025.2045 | O17: =SUM(I19:I22) -> 8987.5015 | P17: =SUM(I23:I26) -> 10346.426 | Q17: =SUM(I27:I30) -> 11670.4
A18: =A17+112 -> 46264 | B18: =_xlfn.FORECAST.ETS(A18,$B$3:$B$15,$A$3:$A$15,4) -> 83242.483 | C18: =_xlfn.FORECAST.ETS(A18,$C$3:$C$15,$A$3:$A$15,4) -> 1699.6393 | D18: =B18+C18 -> 84942.122 | E18: =B18-_xlfn.FORECAST.ETS.CONFINT(A18,$B$3:$B$15,$A$3:$A$15,0.95,4) -> 62655.858 | F18: =C18-_xlfn.FORECAST.ETS.CONFINT(A18,$C$3:$C$15,$A$3:$A$15,0.95,4) -> 1210.8677 | G18: =E18+F18 -> 63866.725 | H18: =B18+_xlfn.FORECAST.ETS.CONFINT(A18,$B$3:$B$15,$A$3:$A$15,0.95,4) -> 103829.11 | I18: =C18+_xlfn.FORECAST.ETS.CONFINT(A18,$C$3:$C$15,$A$3:$A$15,0.95,4) -> 2188.411 | J18: =H18+I18 -> 106017.52 | K18: =SUM(D15:D18) -> 290231.72 | L18: =K18/K14-1 -> 0.054486974 | M18: Base Case | N18: =SUM(C15:C18) -> 5862.7585 | O18: =SUM(C19:C22) -> 6390.1207 | P18: =SUM(C23:C26) -> 6917.4591 | Q18: =SUM(C27:C30) -> 7566.3587
A19: =A18+84 -> 46348 | B19: =_xlfn.FORECAST.ETS(A19,$B$3:$B$15,$A$3:$A$15,4) -> 70919.565 | C19: =_xlfn.FORECAST.ETS(A19,$C$3:$C$15,$A$3:$A$15,4) -> 1448.3974 | D19: =B19+C19 -> 72367.962 | E19: =B19-_xlfn.FORECAST.ETS.CONFINT(A19,$B$3:$B$15,$A$3:$A$15,0.95,4) -> 47378.032 | F19: =C19-_xlfn.FORECAST.ETS.CONFINT(A19,$C$3:$C$15,$A$3:$A$15,0.95,4) -> 890.38894 | G19: =E19+F19 -> 48268.421 | H19: =B19+_xlfn.FORECAST.ETS.CONFINT(A19,$B$3:$B$15,$A$3:$A$15,0.95,4) -> 94461.097 | I19: =C19+_xlfn.FORECAST.ETS.CONFINT(A19,$C$3:$C$15,$A$3:$A$15,0.95,4) -> 2006.4059 | J19: =H19+I19 -> 96467.503 | M19: Bear Case | N19: =SUM(C15,F16:F18) -> 4700.3124 | O19: =SUM(F19:F22) -> 3792.7398 | P19: =SUM(F23:F26) -> 3488.4923 | Q19: =SUM(F27:F30) -> 3462.3173
A20: =A19+84 -> 46432 | B20: =_xlfn.FORECAST.ETS(A20,$B$3:$B$15,$A$3:$A$15,4) -> 71983.348 | C20: =_xlfn.FORECAST.ETS(A20,$C$3:$C$15,$A$3:$A$15,4) -> 1507.0879 | D20: =B20+C20 -> 73490.436 | E20: =B20-_xlfn.FORECAST.ETS.CONFINT(A20,$B$3:$B$15,$A$3:$A$15,0.95,4) -> 45308.81 | F20: =C20-_xlfn.FORECAST.ETS.CONFINT(A20,$C$3:$C$15,$A$3:$A$15,0.95,4) -> 883.23904 | G20: =E20+F20 -> 46192.049 | H20: =B20+_xlfn.FORECAST.ETS.CONFINT(A20,$B$3:$B$15,$A$3:$A$15,0.95,4) -> 98657.887 | I20: =C20+_xlfn.FORECAST.ETS.CONFINT(A20,$C$3:$C$15,$A$3:$A$15,0.95,4) -> 2130.9368 | J20: =H20+I20 -> 100788.82 | M20: CAGR | N20: 0.0878
A21: =A20+84 -> 46516 | B21: =_xlfn.FORECAST.ETS(A21,$B$3:$B$15,$A$3:$A$15,4) -> 81721.329 | C21: =_xlfn.FORECAST.ETS(A21,$C$3:$C$15,$A$3:$A$15,4) -> 1737.7635 | D21: =B21+C21 -> 83459.092 | E21: =B21-_xlfn.FORECAST.ETS.CONFINT(A21,$B$3:$B$15,$A$3:$A$15,0.95,4) -> 53158.763 | F21: =C21-_xlfn.FORECAST.ETS.CONFINT(A21,$C$3:$C$15,$A$3:$A$15,0.95,4) -> 1061.9142 | G21: =E21+F21 -> 54220.677 | H21: =B21+_xlfn.FORECAST.ETS.CONFINT(A21,$B$3:$B$15,$A$3:$A$15,0.95,4) -> 110283.89 | I21: =C21+_xlfn.FORECAST.ETS.CONFINT(A21,$C$3:$C$15,$A$3:$A$15,0.95,4) -> 2413.6129 | J21: =H21+I21 -> 112697.51 | M21: Scenario | N21: 1
A22: =A21+112 -> 46628 | B22: =_xlfn.FORECAST.ETS(A22,$B$3:$B$15,$A$3:$A$15,4) -> 82480.355 | C22: =_xlfn.FORECAST.ETS(A22,$C$3:$C$15,$A$3:$A$15,4) -> 1696.8718 | D22: =B22+C22 -> 84177.227 | E22: =B22-_xlfn.FORECAST.ETS.CONFINT(A22,$B$3:$B$15,$A$3:$A$15,0.95,4) -> 51572.39 | F22: =C22-_xlfn.FORECAST.ETS.CONFINT(A22,$C$3:$C$15,$A$3:$A$15,0.95,4) -> 957.19763 | G22: =E22+F22 -> 52529.588 | H22: =B22+_xlfn.FORECAST.ETS.CONFINT(A22,$B$3:$B$15,$A$3:$A$15,0.95,4) -> 113388.32 | I22: =C22+_xlfn.FORECAST.ETS.CONFINT(A22,$C$3:$C$15,$A$3:$A$15,0.95,4) -> 2436.546 | J22: =H22+I22 -> 115824.87 | K22: =SUM(D19:D22) -> 313494.72 | L22: =K22/K18-1 -> 0.080153179
A23: =A22+84 -> 46712 | B23: =_xlfn.FORECAST.ETS(A23,$B$3:$B$15,$A$3:$A$15,4) -> 75860.564 | C23: =_xlfn.FORECAST.ETS(A23,$C$3:$C$15,$A$3:$A$15,4) -> 1567.771 | D23: =B23+C23 -> 77428.335 | E23: =B23-_xlfn.FORECAST.ETS.CONFINT(A23,$B$3:$B$15,$A$3:$A$15,0.95,4) -> 42487.019 | F23: =C23-_xlfn.FORECAST.ETS.CONFINT(A23,$C$3:$C$15,$A$3:$A$15,0.95,4) -> 776.90227 | G23: =E23+F23 -> 43263.921 | H23: =B23+_xlfn.FORECAST.ETS.CONFINT(A23,$B$3:$B$15,$A$3:$A$15,0.95,4) -> 109234.11 | I23: =C23+_xlfn.FORECAST.ETS.CONFINT(A23,$C$3:$C$15,$A$3:$A$15,0.95,4) -> 2358.6398 | J23: =H23+I23 -> 111592.75 | M23: Year | N23: 2026 | O23: 2027 | P23: 2028 | Q23: 2029
A24: =A23+84 -> 46796 | B24: =_xlfn.FORECAST.ETS(A24,$B$3:$B$15,$A$3:$A$15,4) -> 78904.795 | C24: =_xlfn.FORECAST.ETS(A24,$C$3:$C$15,$A$3:$A$15,4) -> 1692.1116 | D24: =B24+C24 -> 80596.907 | E24: =B24-_xlfn.FORECAST.ETS.CONFINT(A24,$B$3:$B$15,$A$3:$A$15,0.95,4) -> 43609.135 | F24: =C24-_xlfn.FORECAST.ETS.CONFINT(A24,$C$3:$C$15,$A$3:$A$15,0.95,4) -> 856.1883 | G24: =E24+F24 -> 44465.323 | H24: =B24+_xlfn.FORECAST.ETS.CONFINT(A24,$B$3:$B$15,$A$3:$A$15,0.95,4) -> 114200.46 | I24: =C24+_xlfn.FORECAST.ETS.CONFINT(A24,$C$3:$C$15,$A$3:$A$15,0.95,4) -> 2528.035 | J24: =H24+I24 -> 116728.49 | M24: Net Sales | N24: =CHOOSE($N$21,N26,N27,N28) -> 335384 | O24: =CHOOSE($N$21,O26,O27,O28) -> 416791.2 | P24: =CHOOSE($N$21,P26,P27,P28) -> 10346.426 | Q24: =CHOOSE($N$21,Q26,Q27,Q28) -> 530517.52
A25: =A24+84 -> 46880 | B25: =_xlfn.FORECAST.ETS(A25,$B$3:$B$15,$A$3:$A$15,4) -> 93356.078 | C25: =_xlfn.FORECAST.ETS(A25,$C$3:$C$15,$A$3:$A$15,4) -> 1963.4722 | D25: =B25+C25 -> 95319.55 | E25: =B25-_xlfn.FORECAST.ETS.CONFINT(A25,$B$3:$B$15,$A$3:$A$15,0.95,4) -> 56596.415 | F25: =C25-_xlfn.FORECAST.ETS.CONFINT(A25,$C$3:$C$15,$A$3:$A$15,0.95,4) -> 1087.6861 | G25: =E25+F25 -> 57684.101 | H25: =B25+_xlfn.FORECAST.ETS.CONFINT(A25,$B$3:$B$15,$A$3:$A$15,0.95,4) -> 130115.74 | I25: =C25+_xlfn.FORECAST.ETS.CONFINT(A25,$C$3:$C$15,$A$3:$A$15,0.95,4) -> 2839.2582 | J25: =H25+I25 -> 132955 | M25: Growth
A26: =A25+112 -> 46992 | B26: =_xlfn.FORECAST.ETS(A26,$B$3:$B$15,$A$3:$A$15,4) -> 81718.227 | C26: =_xlfn.FORECAST.ETS(A26,$C$3:$C$15,$A$3:$A$15,4) -> 1694.1042 | D26: =B26+C26 -> 83412.332 | E26: =B26-_xlfn.FORECAST.ETS.CONFINT(A26,$B$3:$B$15,$A$3:$A$15,0.95,4) -> 43087.585 | F26: =C26-_xlfn.FORECAST.ETS.CONFINT(A26,$C$3:$C$15,$A$3:$A$15,0.95,4) -> 767.71562 | G26: =E26+F26 -> 43855.301 | H26: =B26+_xlfn.FORECAST.ETS.CONFINT(A26,$B$3:$B$15,$A$3:$A$15,0.95,4) -> 120348.87 | I26: =C26+_xlfn.FORECAST.ETS.CONFINT(A26,$C$3:$C$15,$A$3:$A$15,0.95,4) -> 2620.4929 | J26: =H26+I26 -> 122969.36 | K26: =SUM(D23:D26) -> 336757.12 | L26: =K26/K22-1 -> 0.074203504 | M26: Bull Case | N26: =SUM(B15,H16:H18) -> 335384 | O26: =SUM(H19:H22) -> 416791.2 | P26: =SUM(I23:I26) -> 10346.426 | Q26: =SUM(H27:H30) -> 530517.52
A27: =A26+84 -> 47076 | B27: =_xlfn.FORECAST.ETS(A27,$B$3:$B$15,$A$3:$A$15,4) -> 80801.564 | C27: =_xlfn.FORECAST.ETS(A27,$C$3:$C$15,$A$3:$A$15,4) -> 1687.1447 | D27: =B27+C27 -> 82488.709 | E27: =B27-_xlfn.FORECAST.ETS.CONFINT(A27,$B$3:$B$15,$A$3:$A$15,0.95,4) -> 39823.96 | F27: =C27-_xlfn.FORECAST.ETS.CONFINT(A27,$C$3:$C$15,$A$3:$A$15,0.95,4) -> 716.33167 | G27: =E27+F27 -> 40540.292 | H27: =B27+_xlfn.FORECAST.ETS.CONFINT(A27,$B$3:$B$15,$A$3:$A$15,0.95,4) -> 121779.17 | I27: =C27+_xlfn.FORECAST.ETS.CONFINT(A27,$C$3:$C$15,$A$3:$A$15,0.95,4) -> 2657.9577 | J27: =H27+I27 -> 124437.13 | M27: Base Case | N27: =SUM(B15:B18) -> 284368.96 | O27: =SUM(B19:B22) -> 307104.6 | P27: =SUM(B23:B26) -> 329839.66 | Q27: =SUM(B27:B30) -> 358201.47
A28: =A27+84 -> 47160 | B28: =_xlfn.FORECAST.ETS(A28,$B$3:$B$15,$A$3:$A$15,4) -> 85826.242 | C28: =_xlfn.FORECAST.ETS(A28,$C$3:$C$15,$A$3:$A$15,4) -> 1877.1353 | D28: =B28+C28 -> 87703.377 | E28: =B28-_xlfn.FORECAST.ETS.CONFINT(A28,$B$3:$B$15,$A$3:$A$15,0.95,4) -> 43570.107 | F28: =C28-_xlfn.FORECAST.ETS.CONFINT(A28,$C$3:$C$15,$A$3:$A$15,0.95,4) -> 871.54485 | G28: =E28+F28 -> 44441.652 | H28: =B28+_xlfn.FORECAST.ETS.CONFINT(A28,$B$3:$B$15,$A$3:$A$15,0.95,4) -> 128082.38 | I28: =C28+_xlfn.FORECAST.ETS.CONFINT(A28,$C$3:$C$15,$A$3:$A$15,0.95,4) -> 2882.7258 | J28: =H28+I28 -> 130965.1 | M28: Bear Case | N28: =SUM(B15,E16:E18) -> 233353.93 | O28: =SUM(E19:E22) -> 197417.99 | P28: =SUM(E23:E26) -> 185780.15 | Q28: =SUM(E27:E30) -> 185885.42
A29: =A28+84 -> 47244 | B29: =_xlfn.FORECAST.ETS(A29,$B$3:$B$15,$A$3:$A$15,4) -> 104990.83 | C29: =_xlfn.FORECAST.ETS(A29,$C$3:$C$15,$A$3:$A$15,4) -> 2189.1808 | D29: =B29+C29 -> 107180.01 | E29: =B29-_xlfn.FORECAST.ETS.CONFINT(A29,$B$3:$B$15,$A$3:$A$15,0.95,4) -> 61490.517 | F29: =C29-_xlfn.FORECAST.ETS.CONFINT(A29,$C$3:$C$15,$A$3:$A$15,0.95,4) -> 1149.9035 | G29: =E29+F29 -> 62640.42 | H29: =B29+_xlfn.FORECAST.ETS.CONFINT(A29,$B$3:$B$15,$A$3:$A$15,0.95,4) -> 148491.14 | I29: =C29+_xlfn.FORECAST.ETS.CONFINT(A29,$C$3:$C$15,$A$3:$A$15,0.95,4) -> 3228.4581 | J29: =H29+I29 -> 151719.6 | M29: CAGR | N29: 0.0791
A30: =A29+119 -> 47363 | B30: =_xlfn.FORECAST.ETS(A30,$B$3:$B$15,$A$3:$A$15,4) -> 86582.838 | C30: =_xlfn.FORECAST.ETS(A30,$C$3:$C$15,$A$3:$A$15,4) -> 1812.8979 | D30: =B30+C30 -> 88395.736 | E30: =B30-_xlfn.FORECAST.ETS.CONFINT(A30,$B$3:$B$15,$A$3:$A$15,0.95,4) -> 41000.838 | F30: =C30-_xlfn.FORECAST.ETS.CONFINT(A30,$C$3:$C$15,$A$3:$A$15,0.95,4) -> 724.53722 | G30: =E30+F30 -> 41725.375 | H30: =B30+_xlfn.FORECAST.ETS.CONFINT(A30,$B$3:$B$15,$A$3:$A$15,0.95,4) -> 132164.84 | I30: =C30+_xlfn.FORECAST.ETS.CONFINT(A30,$C$3:$C$15,$A$3:$A$15,0.95,4) -> 2901.2586 | J30: =H30+I30 -> 135066.1 | K30: =SUM(D27:D30) -> 365767.83 | L30: =K30/K26-1 -> 0.086147269

Sheet Forecast
B1: Financial Statements
B3: Income Statement
B5: Units for figures (Millions of USD) | F5: 2021 | G5: 2022 | H5: 2023 | I5: 2024 | J5: 2025 | K5: =J5+1 -> 2026 | L5: =K5+1 -> 2027 | M5: =L5+1 -> 2028 | N5: Terminal Year | Q5: Rate | R5: Explanation/ Assumption
B7: Net sales | F7: =VLOOKUP($B7,INCOME_STATEMENT!$B$20:$L$39,11,0) -> 192052 | G7: =VLOOKUP($B7,INCOME_STATEMENT!$B$20:$L$39,9,0) -> 222730 | H7: =VLOOKUP($B7,INCOME_STATEMENT!$B$20:$L$39,7,0) -> 237710 | I7: =VLOOKUP($B7,INCOME_STATEMENT!$B$20:$L$39,5,0) -> 249625 | J7: =VLOOKUP($B7,INCOME_STATEMENT!$B$20:$L$39,3,0) -> 269912 | K7: =J7*(1+'Revenue Forecast ETS'!$N$29) -> 291262.04 | L7: =K7*(1+'Revenue Forecast ETS'!$N$29) -> 314300.87 | M7: =L7*(1+'Revenue Forecast ETS'!$N$29) -> 339162.07 | N7: =M7*(1+3.5%) -> 351032.74 | Q7: As per sheet-> CAGR used | R7: Sales growth projected using time series forecasting (Detail in Revenue forecast ETS sheet)
B8: Membership fees | F8: =VLOOKUP($B8,INCOME_STATEMENT!$B$20:$L$39,11,0) -> 3877 | G8: =VLOOKUP($B8,INCOME_STATEMENT!$B$20:$L$39,9,0) -> 4224 | H8: =VLOOKUP($B8,INCOME_STATEMENT!$B$20:$L$39,7,0) -> 4580 | I8: =VLOOKUP($B8,INCOME_STATEMENT!$B$20:$L$39,5,0) -> 4828 | J8: =VLOOKUP($B8,INCOME_STATEMENT!$B$20:$L$39,3,0) -> 5323 | K8: =J8*(1+'Revenue Forecast ETS'!$N$20) -> 5790.3594 | L8: =K8*(1+'Revenue Forecast ETS'!$N$20) -> 6298.753 | M8: =L8*(1+'Revenue Forecast ETS'!$N$20) -> 6851.7835 | N8: =M8*(1+3.5%) -> 7091.5959
B9: Total revenue | F9: =VLOOKUP($B9,INCOME_STATEMENT!$B$20:$L$39,11,0) -> 195929 | G9: =VLOOKUP($B9,INCOME_STATEMENT!$B$20:$L$39,9,0) -> 226954 | H9: =VLOOKUP($B9,INCOME_STATEMENT!$B$20:$L$39,7,0) -> 242290 | I9: =VLOOKUP($B9,INCOME_STATEMENT!$B$20:$L$39,5,0) -> 254453 | J9: =VLOOKUP($B9,INCOME_STATEMENT!$B$20:$L$39,3,0) -> 275235 | K9: =SUM(K7:K8) -> 297052.4 | L9: =SUM(L7:L8) -> 320599.62 | M9: =SUM(M7:M8) -> 346013.85 | N9: =SUM(N7:N8) -> 358124.33
B11: OPERATING EXPENSES
B12: Merchandise costs | F12: =VLOOKUP($B12,INCOME_STATEMENT!$B$20:$L$39,11,0) -> 170684 | G12: =VLOOKUP($B12,INCOME_STATEMENT!$B$20:$L$39,9,0) -> 199382 | H12: =VLOOKUP($B12,INCOME_STATEMENT!$B$20:$L$39,7,0) -> 212586 | I12: =VLOOKUP($B12,INCOME_STATEMENT!$B$20:$L$39,5,0) -> 222358 | J12: =VLOOKUP($B12,INCOME_STATEMENT!$B$20:$L$39,3,0) -> 239886 | K12: =K$9*$Q12 -> 259772.49 | L12: =L$9*$Q12 -> 280364.55 | M12: =M$9*$Q12 -> 302589.31 | N12: =M12*(1+3.5%) -> 313179.93 | Q12: =K104 -> 0.87450057 | R12: Using as percentage rate of sale (average 5 years - Operating Expense)
B13: Selling, general and administrative | F13: =VLOOKUP($B13,INCOME_STATEMENT!$B$20:$L$39,11,0) -> 18537 | G13: =VLOOKUP($B13,INCOME_STATEMENT!$B$20:$L$39,9,0) -> 19779 | H13: =VLOOKUP($B13,INCOME_STATEMENT!$B$20:$L$39,7,0) -> 21590 | I13: =VLOOKUP($B13,INCOME_STATEMENT!$B$20:$L$39,5,0) -> 22810 | J13: =VLOOKUP($B13,INCOME_STATEMENT!$B$20:$L$39,3,0) -> 24966 | K13: =K$9*$Q13 -> 26807.192 | L13: =L$9*$Q13 -> 28932.188 | M13: =M$9*$Q13 -> 31225.669 | N13: =M13*(1+3.5%) -> 32318.567 | Q13: =K105 -> 0.090243986 | R13: Using as percentage rate of sale (average 5 years - Operating Expense)
B14: Operating income | F14: =VLOOKUP($B14,INCOME_STATEMENT!$B$20:$L$39,11,0) -> 6708 | G14: =VLOOKUP($B14,INCOME_STATEMENT!$B$20:$L$39,9,0) -> 7793 | H14: =VLOOKUP($B14,INCOME_STATEMENT!$B$20:$L$39,7,0) -> 8114 | I14: =VLOOKUP($B14,INCOME_STATEMENT!$B$20:$L$39,5,0) -> 9285 | J14: =VLOOKUP($B14,INCOME_STATEMENT!$B$20:$L$39,3,0) -> 10383 | K14: =K9-SUM(K12:K13) -> 10472.713 | L14: =L9-SUM(L12:L13) -> 11302.881 | M14: =M9-SUM(M12:M13) -> 12198.871 | N14: =M14*(1+3.5%) -> 12625.831
B16: OTHER INCOME (EXPENSE)
B17: Interest expense | F17: =VLOOKUP($B17,INCOME_STATEMENT!$B$20:$L$39,11,0) -> -171 | G17: =VLOOKUP($B17,INCOME_STATEMENT!$B$20:$L$39,9,0) -> -158 | H17: =VLOOKUP($B17,INCOME_STATEMENT!$B$20:$L$39,7,0) -> -160 | I17: =VLOOKUP($B17,INCOME_STATEMENT!$B$20:$L$39,5,0) -> -169 | J17: =VLOOKUP($B17,INCOME_STATEMENT!$B$20:$L$39,3,0) -> -154 | K17: =K118 -> -151.91223 | L17: =L118 -> -120.79638 | M17: =M118 -> -90.684279 | N17: =M17*(1+3.5%) -> -93.858229 | Q17: =J117 -> 0.026766316 | R17: Interset expense is average total debt multiple interest rate FY2025 (detail in Debt Modeling)
B18: Interest income and other, net | F18: =VLOOKUP($B18,INCOME_STATEMENT!$B$20:$L$39,11,0) -> 143 | G18: =VLOOKUP($B18,INCOME_STATEMENT!$B$20:$L$39,9,0) -> 205 | H18: =VLOOKUP($B18,INCOME_STATEMENT!$B$20:$L$39,7,0) -> 533 | I18: =VLOOKUP($B18,INCOME_STATEMENT!$B$20:$L$39,5,0) -> 624 | J18: =VLOOKUP($B18,INCOME_STATEMENT!$B$20:$L$39,3,0) -> 589 | K18: =$J$18 -> 589 | L18: =$J$18 -> 589 | M18: =$J$18 -> 589 | N18: =M18*(1+3.5%) -> 609.615 | R18: No change in interest income
B20: INCOME BEFORE INCOME TAXES | F20: =VLOOKUP($B20,INCOME_STATEMENT!$B$20:$L$39,11,0) -> 6680 | G20: =VLOOKUP($B20,INCOME_STATEMENT!$B$20:$L$39,9,0) -> 7840 | H20: =VLOOKUP($B20,INCOME_STATEMENT!$B$20:$L$39,7,0) -> 8487 | I20: =VLOOKUP($B20,INCOME_STATEMENT!$B$20:$L$39,5,0) -> 9740 | J20: =VLOOKUP($B20,INCOME_STATEMENT!$B$20:$L$39,3,0) -> 10818 | K20: =K14+SUM(K17:K18) -> 10909.801 | L20: =L14+SUM(L17:L18) -> 11771.085 | M20: =M14+SUM(M17:M18) -> 12697.187 | N20: =N14+SUM(N17:N18) -> 13141.588
B21: Provision for income taxes | F21: =VLOOKUP($B21,INCOME_STATEMENT!$B$20:$L$39,11,0) -> 1601 | G21: =VLOOKUP($B21,INCOME_STATEMENT!$B$20:$L$39,9,0) -> 1925 | H21: =VLOOKUP($B21,INCOME_STATEMENT!$B$20:$L$39,7,0) -> 2195 | I21: =VLOOKUP($B21,INCOME_STATEMENT!$B$20:$L$39,5,0) -> 2373 | J21: =VLOOKUP($B21,INCOME_STATEMENT!$B$20:$L$39,3,0) -> 2719 | K21: =K20*$Q$21 -> 2727.4503 | L21: =L20*$Q$21 -> 2942.7712 | M21: =M20*$Q$21 -> 3174.2967 | N21: =M21*(1+3.5%) -> 3285.3971 | Q21: =K98 -> 0.25 | R21: Appy tax rate 25% (detail in Tax rate below)
B22: NET INCOME | F22: =VLOOKUP($B22,INCOME_STATEMENT!$B$20:$L$39,11,0) -> 5079 | G22: =VLOOKUP($B22,INCOME_STATEMENT!$B$20:$L$39,9,0) -> 5915 | H22: =VLOOKUP($B22,INCOME_STATEMENT!$B$20:$L$39,7,0) -> 6292 | I22: =VLOOKUP($B22,INCOME_STATEMENT!$B$20:$L$39,5,0) -> 7367 | J22: =VLOOKUP($B22,INCOME_STATEMENT!$B$20:$L$39,3,0) -> 8099 | K22: =K20-K21 -> 8182.3509 | L22: =L20-L21 -> 8828.3135 | M22: =M20-M21 -> 9522.89 | N22: =N20-N21 -> 9856.1912
B23: NPM | J23: =J22/J9 -> 0.029425763 | K23: =K22/K9 -> 0.027545143 | L23: =L22/L9 -> 0.027536881 | M23: =M22/M9 -> 0.027521702 | U23: =#REF!-(#REF!-(SUM(#REF!)*Q21)) -> #REF!
B25: Balance Sheet
B27: Units for figures (Millions of USD) | F27: 2021 | G27: 2022 | H27: 2023 | I27: 2024 | J27: 2025 | K27: =J27+1 -> 2026 | L27: =K27+1 -> 2027 | M27: =L27+1 -> 2028 | N27: Terminal year | Q27: Rate | R27: Explanation/ Assumption
B29: ASSETS
B30: CURRENT ASSETS
B31: Cash and cash equivalents | F31: =VLOOKUP($B31,BALANCE_SHEET!$B$20:$L$57,11,0) -> 11258 | G31: =VLOOKUP($B31,BALANCE_SHEET!$B$20:$L$57,9,0) -> 10203 | H31: =VLOOKUP($B31,BALANCE_SHEET!$B$20:$L$57,7,0) -> 13700 | I31: =VLOOKUP($B31,BALANCE_SHEET!$B$20:$L$57,5,0) -> 9906 | J31: =VLOOKUP($B31,BALANCE_SHEET!$B$20:$L$57,3,0) -> 14161 | K31: =K67-SUM(K32:K35)-SUM(K38:K40) -> 18233.954 | L31: =L67-SUM(L32:L35)-SUM(L38:L40) -> 22680.912 | M31: =M67-SUM(M32:M35)-SUM(M38:M40) -> 25407.199 | N31: =N67-SUM(N32:N35)-SUM(N38:N40) -> 26068.461 | R31: Cash is a plugged amount
B32: Short-term investments | F32: =VLOOKUP($B32,BALANCE_SHEET!$B$20:$L$57,11,0) -> 917 | G32: =VLOOKUP($B32,BALANCE_SHEET!$B$20:$L$57,9,0) -> 846 | H32: =VLOOKUP($B32,BALANCE_SHEET!$B$20:$L$57,7,0) -> 1534 | I32: =VLOOKUP($B32,BALANCE_SHEET!$B$20:$L$57,5,0) -> 1238 | J32: =VLOOKUP($B32,BALANCE_SHEET!$B$20:$L$57,3,0) -> 1123 | K32: =J32 -> 1123 | L32: =K32 -> 1123 | M32: =L32 -> 1123 | N32: =M32*(1+3.5%) -> 1162.305 | R32: nonoperating assets (investments in securities) no change
B33: Receivables, net | F33: =VLOOKUP($B33,BALANCE_SHEET!$B$20:$L$57,11,0) -> 1803 | G33: =VLOOKUP($B33,BALANCE_SHEET!$B$20:$L$57,9,0) -> 2241 | H33: =VLOOKUP($B33,BALANCE_SHEET!$B$20:$L$57,7,0) -> 2285 | I33: =VLOOKUP($B33,BALANCE_SHEET!$B$20:$L$57,5,0) -> 2721 | J33: =VLOOKUP($B33,BALANCE_SHEET!$B$20:$L$57,3,0) -> 3203 | K33: =K$9*$Q33 -> 3456.8962 | L33: =L$9*$Q33 -> 3730.923 | M33: =M$9*$Q33 -> 4026.6767 | N33: =M33*(1+3.5%) -> 4167.6104 | Q33: =J33/$J$9 -> 0.011637328 | R33: change in proportion with revenue (Using Rate in FY2025)
B34: Merchandise inventories | F34: =VLOOKUP($B34,BALANCE_SHEET!$B$20:$L$57,11,0) -> 14215 | G34: =VLOOKUP($B34,BALANCE_SHEET!$B$20:$L$57,9,0) -> 17907 | H34: =VLOOKUP($B34,BALANCE_SHEET!$B$20:$L$57,7,0) -> 16651 | I34: =VLOOKUP($B34,BALANCE_SHEET!$B$20:$L$57,5,0) -> 18647 | J34: =VLOOKUP($B34,BALANCE_SHEET!$B$20:$L$57,3,0) -> 18116 | K34: =K$9*$Q34 -> 19552.024 | L34: =L$9*$Q34 -> 21101.905 | M34: =M$9*$Q34 -> 22774.672 | N34: =M34*(1+3.5%) -> 23571.786 | Q34: =J34/$J$9 -> 0.065820117 | R34: change in proportion with revenue (Using Rate in FY2025)
B35: Other current assets | F35: =VLOOKUP($B35,BALANCE_SHEET!$B$20:$L$57,11,0) -> 1312 | G35: =VLOOKUP($B35,BALANCE_SHEET!$B$20:$L$57,9,0) -> 1499 | H35: =VLOOKUP($B35,BALANCE_SHEET!$B$20:$L$57,7,0) -> 1709 | I35: =VLOOKUP($B35,BALANCE_SHEET!$B$20:$L$57,5,0) -> 1734 | J35: =VLOOKUP($B35,BALANCE_SHEET!$B$20:$L$57,3,0) -> 1777 | K35: =K$9*$Q35 -> 1917.8597 | L35: =L$9*$Q35 -> 2069.8876 | M35: =M$9*$Q35 -> 2233.9695 | N35: =M35*(1+3.5%) -> 2312.1585 | Q35: =J35/$J$9 -> 0.006456301 | R35: change in proportion with revenue (Using Rate in FY2025)
B36: Total current assets | F36: =VLOOKUP($B36,BALANCE_SHEET!$B$20:$L$57,11,0) -> 29505 | G36: =VLOOKUP($B36,BALANCE_SHEET!$B$20:$L$57,9,0) -> 32696 | H36: =VLOOKUP($B36,BALANCE_SHEET!$B$20:$L$57,7,0) -> 35879 | I36: =VLOOKUP($B36,BALANCE_SHEET!$B$20:$L$57,5,0) -> 34246 | J36: =VLOOKUP($B36,BALANCE_SHEET!$B$20:$L$57,3,0) -> 38380 | K36: =SUM(K31:K35) -> 44283.734 | L36: =SUM(L31:L35) -> 50706.627 | M36: =SUM(M31:M35) -> 55565.518 | N36: =SUM(N31:N35) -> 57282.321
B37: OTHER ASSETS
B38: Property and equipment, net | F38: =VLOOKUP($B38,BALANCE_SHEET!$B$20:$L$57,11,0) -> 23492 | G38: =VLOOKUP($B38,BALANCE_SHEET!$B$20:$L$57,9,0) -> 24646 | H38: =VLOOKUP($B38,BALANCE_SHEET!$B$20:$L$57,7,0) -> 26684 | I38: =VLOOKUP($B38,BALANCE_SHEET!$B$20:$L$57,5,0) -> 29032 | J38: =VLOOKUP($B38,BALANCE_SHEET!$B$20:$L$57,3,0) -> 31909 | K38: =K139 -> 35152.471 | L38: =L139 -> 38557.864 | M38: =M139 -> 42138.021 | N38: =M38*(1+3.5%) -> 43612.852 | R38: Detail in Fix asset modeling
B39: Operating lease right-of-use assets | F39: =VLOOKUP($B39,BALANCE_SHEET!$B$20:$L$57,11,0) -> 2890 | G39: =VLOOKUP($B39,BALANCE_SHEET!$B$20:$L$57,9,0) -> 2774 | H39: =VLOOKUP($B39,BALANCE_SHEET!$B$20:$L$57,7,0) -> 2713 | I39: =VLOOKUP($B39,BALANCE_SHEET!$B$20:$L$57,5,0) -> 2617 | J39: =VLOOKUP($B39,BALANCE_SHEET!$B$20:$L$57,3,0) -> 2725 | K39: =$J$39 -> 2725 | L39: =$J$39 -> 2725 | M39: =$J$39 -> 2725 | N39: =M39*(1+3.5%) -> 2820.375 | R39: Assumpt no change
B40: Other long-term assets | F40: =VLOOKUP($B40,BALANCE_SHEET!$B$20:$L$57,11,0) -> 3381 | G40: =VLOOKUP($B40,BALANCE_SHEET!$B$20:$L$57,9,0) -> 4050 | H40: =VLOOKUP($B40,BALANCE_SHEET!$B$20:$L$57,7,0) -> 3718 | I40: =VLOOKUP($B40,BALANCE_SHEET!$B$20:$L$57,5,0) -> 3936 | J40: =VLOOKUP($B40,BALANCE_SHEET!$B$20:$L$57,3,0) -> 4085 | K40: =$J$40 -> 4085 | L40: =$J$40 -> 4085 | M40: =$J$40 -> 4085 | N40: =M40*(1+3.5%) -> 4227.975 | R40: Assumpt no change
B41: TOTAL ASSETS | F41: =VLOOKUP($B41,BALANCE_SHEET!$B$20:$L$57,11,0) -> 59268 | G41: =VLOOKUP($B41,BALANCE_SHEET!$B$20:$L$57,9,0) -> 64166 | H41: =VLOOKUP($B41,BALANCE_SHEET!$B$20:$L$57,7,0) -> 68994 | I41: =VLOOKUP($B41,BALANCE_SHEET!$B$20:$L$57,5,0) -> 69831 | J41: =VLOOKUP($B41,BALANCE_SHEET!$B$20:$L$57,3,0) -> 77099 | K41: =K36+SUM(K38:K40) -> 86246.205 | L41: =L36+SUM(L38:L40) -> 96074.491 | M41: =M36+SUM(M38:M40) -> 104513.54 | N41: =N36+SUM(N38:N40) -> 107943.52
B42: LIABILITIES AND EQUITY
B43: CURRENT LIABILITIES
B44: Accounts payable | F44: =VLOOKUP($B44,BALANCE_SHEET!$B$20:$L$57,11,0) -> 16278 | G44: =VLOOKUP($B44,BALANCE_SHEET!$B$20:$L$57,9,0) -> 17848 | H44: =VLOOKUP($B44,BALANCE_SHEET!$B$20:$L$57,7,0) -> 17483 | I44: =VLOOKUP($B44,BALANCE_SHEET!$B$20:$L$57,5,0) -> 19421 | J44: =VLOOKUP($B44,BALANCE_SHEET!$B$20:$L$57,3,0) -> 19783 | K44: =K$9*$Q44 -> 21351.164 | L44: =L$9*$Q44 -> 23043.662 | M44: =M$9*$Q44 -> 24870.354 | N44: =M44*(1+3.5%) -> 25740.817 | Q44: =J44/$J$9 -> 0.07187676 | R44: change in proportion with revenue (Using Rate in FY2025)
B45: Accrued salaries and benefits | F45: =VLOOKUP($B45,BALANCE_SHEET!$B$20:$L$57,11,0) -> 4090 | G45: =VLOOKUP($B45,BALANCE_SHEET!$B$20:$L$57,9,0) -> 4381 | H45: =VLOOKUP($B45,BALANCE_SHEET!$B$20:$L$57,7,0) -> 4278 | I45: =VLOOKUP($B45,BALANCE_SHEET!$B$20:$L$57,5,0) -> 4794 | J45: =VLOOKUP($B45,BALANCE_SHEET!$B$20:$L$57,3,0) -> 5205 | K45: =K13*$Q45 -> 5588.8583 | L45: =L13*$Q45 -> 6031.8848 | M45: =M13*$Q45 -> 6510.0379 | N45: =M45*(1+3.5%) -> 6737.8892 | Q45: =J45/$J$13 -> 0.20848354 | R45: change in proportion with SG&A (Using Rate in FY2025)
B46: Accrued member rewards | F46: =VLOOKUP($B46,BALANCE_SHEET!$B$20:$L$57,11,0) -> 1671 | G46: =VLOOKUP($B46,BALANCE_SHEET!$B$20:$L$57,9,0) -> 1911 | H46: =VLOOKUP($B46,BALANCE_SHEET!$B$20:$L$57,7,0) -> 2150 | I46: =VLOOKUP($B46,BALANCE_SHEET!$B$20:$L$57,5,0) -> 2435 | J46: =VLOOKUP($B46,BALANCE_SHEET!$B$20:$L$57,3,0) -> 2677 | K46: =K$8*$Q46 -> 2912.0406 | L46: =L$8*$Q46 -> 3167.7178 | M46: =M$8*$Q46 -> 3445.8434 | N46: =M46*(1+3.5%) -> 3566.4479 | Q46: =J46/$J$8 -> 0.50291189 | R46: change in proportion with Membership fee ( Using Rate in FY2025)
B47: Deferred membership fees | F47: =VLOOKUP($B47,BALANCE_SHEET!$B$20:$L$57,11,0) -> 2042 | G47: =VLOOKUP($B47,BALANCE_SHEET!$B$20:$L$57,9,0) -> 2174 | H47: =VLOOKUP($B47,BALANCE_SHEET!$B$20:$L$57,7,0) -> 2337 | I47: =VLOOKUP($B47,BALANCE_SHEET!$B$20:$L$57,5,0) -> 2501 | J47: =VLOOKUP($B47,BALANCE_SHEET!$B$20:$L$57,3,0) -> 2854 | K47: =K$8*$Q47 -> 3104.5812 | L47: =L$8*$Q47 -> 3377.1634 | M47: =M$8*$Q47 -> 3673.6784 | N47: =M47*(1+3.5%) -> 3802.2571 | Q47: =J47/$J$8 -> 0.53616382 | R47: change in proportion with Membership fee ( Using Rate in FY2025)
B48: Other current liabilities | F48: =VLOOKUP($B48,BALANCE_SHEET!$B$20:$L$57,11,0) -> 4561 | G48: =VLOOKUP($B48,BALANCE_SHEET!$B$20:$L$57,9,0) -> 5611 | H48: =VLOOKUP($B48,BALANCE_SHEET!$B$20:$L$57,7,0) -> 6254 | I48: =VLOOKUP($B48,BALANCE_SHEET!$B$20:$L$57,5,0) -> 6313 | J48: =VLOOKUP($B48,BALANCE_SHEET!$B$20:$L$57,3,0) -> 6589 | K48: =K$9*$Q48 -> 7111.2985 | L48: =L$9*$Q48 -> 7675.0082 | M48: =M$9*$Q48 -> 8283.4133 | N48: =M48*(1+3.5%) -> 8573.3327 | Q48: =J48/$J$9 -> 0.023939543 | R48: change in proportion with revenue (Using Rate in FY2025)
B49: Total current liabilities | F49: =VLOOKUP($B49,BALANCE_SHEET!$B$20:$L$57,11,0) -> 29441 | G49: =VLOOKUP($B49,BALANCE_SHEET!$B$20:$L$57,9,0) -> 31998 | H49: =VLOOKUP($B49,BALANCE_SHEET!$B$20:$L$57,7,0) -> 33583 | I49: =VLOOKUP($B49,BALANCE_SHEET!$B$20:$L$57,5,0) -> 35464 | J49: =VLOOKUP($B49,BALANCE_SHEET!$B$20:$L$57,3,0) -> 37108 | K49: =SUM(K44:K48) -> 40067.943 | L49: =SUM(L44:L48) -> 43295.436 | M49: =SUM(M44:M48) -> 46783.327 | N49: =SUM(N44:N48) -> 48420.744
B50: OTHER LIABILITIES
B51: Long-term debt, excluding current portion | F51: =VLOOKUP($B51,BALANCE_SHEET!$B$20:$L$57,11,0) -> 6692 | G51: =VLOOKUP($B51,BALANCE_SHEET!$B$20:$L$57,9,0) -> 6484 | H51: =VLOOKUP($B51,BALANCE_SHEET!$B$20:$L$57,7,0) -> 5377 | I51: =VLOOKUP($B51,BALANCE_SHEET!$B$20:$L$57,5,0) -> 5794 | J51: =VLOOKUP($B51,BALANCE_SHEET!$B$20:$L$57,3,0) -> 5713 | K51: =K112 -> 5713 | L51: =L112 -> 5638 | M51: =M112 -> 3388 | N51: =M51*(1+3.5%) -> 3506.58 | R51: Detail in Debt Modeling
B52: Long-term operating lease liabilities | F52: =VLOOKUP($B52,BALANCE_SHEET!$B$20:$L$57,11,0) -> 2642 | G52: =VLOOKUP($B52,BALANCE_SHEET!$B$20:$L$57,9,0) -> 2482 | H52: =VLOOKUP($B52,BALANCE_SHEET!$B$20:$L$57,7,0) -> 2426 | I52: =VLOOKUP($B52,BALANCE_SHEET!$B$20:$L$57,5,0) -> 2375 | J52: =VLOOKUP($B52,BALANCE_SHEET!$B$20:$L$57,3,0) -> 2460 | K52: =$J$52 -> 2460 | L52: =$J$52 -> 2460 | M52: =$J$52 -> 2460 | N52: =M52*(1+3.5%) -> 2546.1 | R52: Assumpt no change
B53: Other long-term liabilities | F53: =VLOOKUP($B53,BALANCE_SHEET!$B$20:$L$57,11,0) -> 2415 | G53: =VLOOKUP($B53,BALANCE_SHEET!$B$20:$L$57,9,0) -> 2555 | H53: =VLOOKUP($B53,BALANCE_SHEET!$B$20:$L$57,7,0) -> 2550 | I53: =VLOOKUP($B53,BALANCE_SHEET!$B$20:$L$57,5,0) -> 2576 | J53: =VLOOKUP($B53,BALANCE_SHEET!$B$20:$L$57,3,0) -> 2654 | K53: =K$9*$Q53 -> 2864.378 | L53: =L$9*$Q53 -> 3091.436 | M53: =M$9*$Q53 -> 3336.497 | N53: =M53*(1+3.5%) -> 3453.2744 | Q53: =J53/J9 -> 0.009642669 | R53: change in proportion with revenue (Using Rate in FY2025)
B54: TOTAL LIABILITIES | F54: =VLOOKUP($B54,BALANCE_SHEET!$B$20:$L$57,11,0) -> 41190 | G54: =VLOOKUP($B54,BALANCE_SHEET!$B$20:$L$57,9,0) -> 43519 | H54: =VLOOKUP($B54,BALANCE_SHEET!$B$20:$L$57,7,0) -> 43936 | I54: =VLOOKUP($B54,BALANCE_SHEET!$B$20:$L$57,5,0) -> 46209 | J54: =VLOOKUP($B54,BALANCE_SHEET!$B$20:$L$57,3,0) -> 47935 | K54: =K49+SUM(K51:K53) -> 51105.321 | L54: =L49+SUM(L51:L53) -> 54484.872 | M54: =M49+SUM(M51:M53) -> 55967.824 | N54: =N49+SUM(N51:N53) -> 57926.698
B55: COMMITMENTS AND CONTINGENCIES
B56: EQUITY
B57: Preferred stock $0.005 par value; 100,000,000 shares
B58: authorized; no shares issued and outstanding | F58: =VLOOKUP($B58,BALANCE_SHEET!$B$20:$L$57,11,0) -> 0 | G58: =VLOOKUP($B58,BALANCE_SHEET!$B$20:$L$57,9,0) -> 0 | H58: =VLOOKUP($B58,BALANCE_SHEET!$B$20:$L$57,7,0) -> 0 | I58: =VLOOKUP($B58,BALANCE_SHEET!$B$20:$L$57,5,0) -> 0 | J58: =VLOOKUP($B58,BALANCE_SHEET!$B$20:$L$57,3,0) -> 0 | K58: =$J$58 -> 0 | L58: =$J$58 -> 0 | M58: =$J$58 -> 0 | N58: =$J$58 -> 0 | R58: Assumpt no change
B59: Common stock $0.005 par value; 900,000,000 shares
B60: authorized; 443,237,000 and 443,126,000 shares issued and
B61: outstanding | F61: =VLOOKUP($B61,BALANCE_SHEET!$B$20:$L$57,11,0) -> 4 | G61: =VLOOKUP($B61,BALANCE_SHEET!$B$20:$L$57,9,0) -> 2 | H61: =VLOOKUP($B61,BALANCE_SHEET!$B$20:$L$57,7,0) -> 2 | I61: =VLOOKUP($B61,BALANCE_SHEET!$B$20:$L$57,5,0) -> 2 | J61: =VLOOKUP($B61,BALANCE_SHEET!$B$20:$L$57,3,0) -> 2 | K61: =$J$61 -> 2 | L61: =$J$61 -> 2 | M61: =$J$61 -> 2 | N61: =$J$61 -> 2 | R61: Assumpt no change
B62: Additional paid-in capital | F62: =VLOOKUP($B62,BALANCE_SHEET!$B$20:$L$57,11,0) -> 7031 | G62: =VLOOKUP($B62,BALANCE_SHEET!$B$20:$L$57,9,0) -> 6884 | H62: =VLOOKUP($B62,BALANCE_SHEET!$B$20:$L$57,7,0) -> 7340 | I62: =VLOOKUP($B62,BALANCE_SHEET!$B$20:$L$57,5,0) -> 7829 | J62: =VLOOKUP($B62,BALANCE_SHEET!$B$20:$L$57,3,0) -> 8282 | K62: =$J$62 -> 8282 | L62: =$J$62 -> 8282 | M62: =$J$62 -> 8282 | N62: =$J$62 -> 8282 | R62: Assumpt no change
B63: Accumulated other comprehensive loss | F63: =VLOOKUP($B63,BALANCE_SHEET!$B$20:$L$57,11,0) -> -1137 | G63: =VLOOKUP($B63,BALANCE_SHEET!$B$20:$L$57,9,0) -> -1829 | H63: =VLOOKUP($B63,BALANCE_SHEET!$B$20:$L$57,7,0) -> -1805 | I63: =VLOOKUP($B63,BALANCE_SHEET!$B$20:$L$57,5,0) -> -1828 | J63: =VLOOKUP($B63,BALANCE_SHEET!$B$20:$L$57,3,0) -> -1770 | K63: =$J$63 -> -1770 | L63: =$J$63 -> -1770 | M63: =$J$63 -> -1770 | N63: =$J$63 -> -1770 | R63: Assumpt no change
B64: Retained earnings | F64: =VLOOKUP($B64,BALANCE_SHEET!$B$20:$L$57,11,0) -> 11666 | G64: =VLOOKUP($B64,BALANCE_SHEET!$B$20:$L$57,9,0) -> 15585 | H64: =VLOOKUP($B64,BALANCE_SHEET!$B$20:$L$57,7,0) -> 19521 | I64: =VLOOKUP($B64,BALANCE_SHEET!$B$20:$L$57,5,0) -> 17619 | J64: =VLOOKUP($B64,BALANCE_SHEET!$B$20:$L$57,3,0) -> 22650 | K64: =J64+K22*(1-'Cash flow forecast'!$K$30) -> 28626.885 | L64: =K64+L22*(1-'Cash flow forecast'!$K$30) -> 35075.619 | M64: =L64+M22*(1-'Cash flow forecast'!$K$30) -> 42031.715 | N64: =M64*(1+3.5%) -> 43502.825 | R64: Increase by forecasted net income with dividend payment
B66: TOTAL EQUITY | F66: =VLOOKUP($B66,BALANCE_SHEET!$B$20:$L$57,11,0) -> 18078 | G66: =VLOOKUP($B66,BALANCE_SHEET!$B$20:$L$57,9,0) -> 20647 | H66: =VLOOKUP($B66,BALANCE_SHEET!$B$20:$L$57,7,0) -> 25058 | I66: =VLOOKUP($B66,BALANCE_SHEET!$B$20:$L$57,5,0) -> 23622 | J66: =VLOOKUP($B66,BALANCE_SHEET!$B$20:$L$57,3,0) -> 29164 | K66: =SUM(K58:K64) -> 35140.885 | L66: =SUM(L58:L64) -> 41589.619 | M66: =SUM(M58:M64) -> 48545.715 | N66: =SUM(N58:N64) -> 50016.825
B67: TOTAL LIABILITIES AND EQUITY | F67: =VLOOKUP($B67,BALANCE_SHEET!$B$20:$L$57,11,0) -> 59268 | G67: =VLOOKUP($B67,BALANCE_SHEET!$B$20:$L$57,9,0) -> 64166 | H67: =VLOOKUP($B67,BALANCE_SHEET!$B$20:$L$57,7,0) -> 68994 | I67: =VLOOKUP($B67,BALANCE_SHEET!$B$20:$L$57,5,0) -> 69831 | J67: =VLOOKUP($B67,BALANCE_SHEET!$B$20:$L$57,3,0) -> 77099 | K67: =K66+K54 -> 86246.205 | L67: =L66+L54 -> 96074.491 | M67: =M66+M54 -> 104513.54 | N67: =N66+N54 -> 107943.52
U69: =#REF!-#REF! -> #REF!
B70: Sales/ Revenue
B73: Revenue by segment (Factset)
E74: AUG '20 | F74: AUG '21 | G74: AUG '22 | H74: AUG '23 | I74: AUG '24 | J74: AUG '25 | L74: Adjusted Aug'23
E75: 364 Days | F75: 364 Days | G75: 364 Days | H75: 371 Days | I75: 364 Days | J75: 364 Days | L75: 364 days
B76: Total | E76: 163220 | F76: 192052 | G76: 222730 | H76: 237710 | I76: 249625 | J76: 269912 | L76: 237710 | M76: 233225
B77: Foods & Sundries | E77: 68659 | F77: 77277 | G77: 85629 | H77: 96175 | I77: 101463 | J77: 109564 | L77: 96175 | M77: 94360
B78: Non-Foods | E78: 44807 | F78: 55966 | G78: 61100 | H78: 60865 | I78: 63973 | J78: 71190 | L78: 60865 | M78: 59717
B79: Warehouse Ancillary & Other Businesses | E79: 26550 | F79: 31626 | G79: 46474 | H79: 48693 | I79: 49969 | J79: 51170 | L79: 48693 | M79: 47774
B80: Fresh Foods | E80: 23204 | F80: 27183 | G80: 29527 | H80: 31977 | I80: 34220 | J80: 37988 | L80: 31977 | M80: 31374
B82: Costco's segment growth rates for prior years and summary metrics | G82: Sales growth rate | I82: =N90 -> 0.087895204
G83: Membership fee | I83: =L92 -> 0.082468249
F85: AUG '21 | G85: AUG '22 | H85: AUG '23 | I85: AUG '24 | J85: AUG '25 | K85: 5-year average | L85: 5-year CAGR | M85: %2025 sale | N85: Weighted Average | O85: Weighted CAGR
B86: Foods & Sundries | F86: =F77/E77-1 -> 0.12551887 | G86: =G77/F77-1 -> 0.10807873 | H86: =M77/G77-1 -> 0.10196312 | I86: =I77/H77-1 -> 0.054983104 | J86: =J77/I77-1 -> 0.079841913 | K86: =AVERAGE(G86:J86) -> 0.086216717 | L86: =(J77/F77)^(1/4)-1 -> 0.091200123 | M86: =J77/$J$76 -> 0.40592489 | N86: =K86*M86 -> 0.034997512 | O86: =L86*M86 -> 0.0370204
B87: Non-Foods | F87: =F78/E78-1 -> 0.24904591 | G87: =G78/F78-1 -> 0.091734267 | H87: =M78/G78-1 -> -0.022635025 | I87: =I78/H78-1 -> 0.05106383 | J87: =J78/I78-1 -> 0.11281322 | K87: =AVERAGE(G87:J87) -> 0.058244073 | L87: =(J78/F78)^(1/4)-1 -> 0.061997957 | M87: =J78/$J$76 -> 0.26375263 | N87: =K87*M87 -> 0.015362027 | O87: =L87*M87 -> 0.016352124
B88: Warehouse Ancillary & Other Businesses | F88: =F79/E79-1 -> 0.19118644 | G88: =G79/F79-1 -> 0.46948713 | H88: =M79/G79-1 -> 0.02797263 | I88: =I79/H79-1 -> 0.026204999 | J88: =J79/I79-1 -> 0.024034902 | K88: =AVERAGE(G88:J88) -> 0.13692492 | L88: =(J79/F79)^(1/4)-1 -> 0.12782778 | M88: =J79/$J$76 -> 0.18958031 | N88: =K88*M88 -> 0.025958268 | O88: =L88*M88 -> 0.02423363
B89: Fresh Foods | F89: =F80/E80-1 -> 0.17147906 | G89: =G80/F80-1 -> 0.086230365 | H89: =M80/G80-1 -> 0.062552918 | I89: =I80/H80-1 -> 0.070144166 | J89: =J80/I80-1 -> 0.11011105 | K89: =AVERAGE(G89:J89) -> 0.082259624 | L89: =(J80/F80)^(1/4)-1 -> 0.087269639 | M89: =J80/$J$76 -> 0.14074217 | N89: =K89*M89 -> 0.011577398 | O89: =L89*M89 -> 0.012282518
B90: Total | F90: =F76/E76-1 -> 0.17664502 | G90: =G76/F76-1 -> 0.15973799 | H90: =M76/G76-1 -> 0.047119831 | I90: =I76/H76-1 -> 0.050124101 | J90: =J76/I76-1 -> 0.081269905 | K90: =AVERAGE(F90:J90) -> 0.10297937 | L90: =(J76/F76)^(1/4)-1 -> 0.088806838 | M90: 1 | N90: =SUM(N86:N89) -> 0.087895204 | O90: =SUM(O86:O89) -> 0.089888673
B92: Membership fee | G92: =G8/F8-1 -> 0.089502192 | H92: =H8/G8-1 -> 0.084280303 | I92: =I8/H8-1 -> 0.054148472 | J92: =J8/I8-1 -> 0.10252693 | K92: =AVERAGE(G92:J92) -> 0.082614473 | L92: =(J8/F8)^(1/4)-1 -> 0.082468249 | N92: =AVERAGE(L90,L92) -> 0.085637543
B95: Tax rate
F97: AUG '21 | G97: AUG '22 | H97: AUG '23 | I97: AUG '24 | J97: AUG '25 | K97: 5-year average
B98: Tax rate (Note FS) | F98: 0.246 | G98: 0.25 | H98: 0.259 | I98: 0.244 | J98: 0.251 | K98: =AVERAGE(F98:J98) -> 0.25
B100: Operating expense
B102: Percentage of Total sales | F102: AUG '21 | G102: AUG '22 | H102: AUG '23 | I102: AUG '24 | J102: AUG '25 | K102: 5-year average
B104: Merchandise costs | F104: =F12/F$9 -> 0.87115231 | G104: =G12/G$9 -> 0.87851283 | H104: =H12/H$9 -> 0.87740311 | I104: =I12/I$9 -> 0.87386669 | J104: =J12/J$9 -> 0.87156793 | K104: =AVERAGE(F104:J104) -> 0.87450057
B105: Selling, general and administrative | F105: =F13/F$9 -> 0.094610803 | G105: =G13/G$9 -> 0.087149819 | H105: =H13/H$9 -> 0.089108094 | I105: =I13/I$9 -> 0.089643274 | J105: =J13/J$9 -> 0.09070794 | K105: =AVERAGE(F105:J105) -> 0.090243986
B108: Debt
E110: AUG '20 | F110: AUG '21 | G110: AUG '22 | H110: AUG '23 | I110: AUG '24 | J110: AUG '25 | K110: AUG '26 | L110: AUG '27 | M110: AUG '28 | N110: AUG '29 | O110: AUG '30 | P110: AUG '31 | Q110: AUG '32 | R110: AUG '33 | S110: AUG '34 | T110: AUG '35
B111: Long Term Debt
B112: Beginning Balance | F112: =E114 -> 7514 | G112: =F114 -> 6692 | H112: =G114 -> 6484 | I112: =H114 -> 5377 | J112: =I114 -> 5794 | K112: =J114 -> 5713 | L112: =K114 -> 5638 | M112: =L114 -> 3388 | ... T112: =S114 -> 400
B113: Increase/Decrease | F113: =F114-F112 -> -822 | G113: =G114-G112 -> -208 | H113: =H114-H112 -> -1107 | I113: =I114-I112 -> 417 | J113: =J114-J112 -> -81 | K113: -75 | L113: -2250 | M113: 0 | N113: -148 | O113: -1750 | P113: - | Q113: -1000 | R113: -45 | S113: -45 | T113: -45 | W113: Base on Note to FS - Debt K-10)
B114: Ending Balance | E114: 7514 | F114: =F51 -> 6692 | G114: =G51 -> 6484 | H114: =H51 -> 5377 | I114: =I51 -> 5794 | J114: =J51 -> 5713 | K114: =SUM(K112:K113) -> 5638 | L114: =SUM(L112:L113) -> 3388 | M114: =SUM(M112:M113) -> 3388 | N114: =SUM(N112:N113) -> 3240 | O114: =SUM(O112:O113) -> 1490 | P114: =SUM(P112:P113) -> 1490 | Q114: =SUM(Q112:Q113) -> 490 | R114: =SUM(R112:R113) -> 445 | ... T114: =SUM(T112:T113) -> 355
B116: Average total debt | F116: =(F114+E114)/2 -> 7103 | G116: =(G114+F114)/2 -> 6588 | H116: =(H114+G114)/2 -> 5930.5 | I116: =(I114+H114)/2 -> 5585.5 | J116: =(J114+I114)/2 -> 5753.5 | K116: =(K114+J114)/2 -> 5675.5 | L116: =(L114+K114)/2 -> 4513 | M116: =(M114+L114)/2 -> 3388 | ... T116: =(T114+S114)/2 -> 377.5
B117: Interest Rate | F117: =-F118/F116 -> 0.024074335 | G117: =-G118/G116 -> 0.023982999 | H117: =-H118/H116 -> 0.026979175 | I117: =-I118/I116 -> 0.030256915 | J117: =-J118/J116 -> 0.026766316 | K117: =$J$117 -> 0.026766316 | L117: =$J$117 -> 0.026766316 | M117: =$J$117 -> 0.026766316 | N117: =$J$117 -> 0.026766316 | O117: =$J$117 -> 0.026766316 | P117: =$J$117 -> 0.026766316 | Q117: =$J$117 -> 0.026766316 | R117: =$J$117 -> 0.026766316 | ... T117: =$J$117 -> 0.026766316
B118: Interest Expense | F118: =F17 -> -171 | G118: =G17 -> -158 | H118: =H17 -> -160 | I118: =I17 -> -169 | J118: =J17 -> -154 | K118: =-K116*K117 -> -151.91223 | L118: =-L116*L117 -> -120.79638 | M118: =-M116*M117 -> -90.684279 | N118: =-N116*N117 -> -88.703572 | O118: =-O116*O117 -> -63.302338 | P118: =-P116*P117 -> -39.881811 | Q118: =-Q116*Q117 -> -26.498653 | R118: =-R116*R117 -> -12.513253 | ... T118: =-T116*T117 -> -10.104284
B132: Fixed Asset
B135: PPE, Net | E135: AUG '20 | F135: AUG '21 | G135: AUG '22 | H135: AUG '23 | I135: AUG '24 | J135: AUG '25 | K135: AUG '26 | L135: AUG '27 | M135: AUG '28 | O135: Rate | P135: Explaination
B136: Beginning | F136: =E139 -> 21807 | G136: =F139 -> 23492 | H136: =G139 -> 24646 | I136: =H139 -> 26684 | J136: =I139 -> 29032 | K136: =J139 -> 31909 | L136: =K139 -> 35152.471 | M136: =L139 -> 38557.864 | N136: =M139 -> 42138.021
B137: CAPEX (cash flow) | F137: =-CASH_FLOW!L34 -> 3588 | G137: =-CASH_FLOW!J34 -> 3891 | H137: =-CASH_FLOW!H34 -> 4323 | I137: =-CASH_FLOW!F34 -> 4710 | J137: =-CASH_FLOW!D34 -> 5498 | K137: =$O$137*K9 -> 5933.8169 | L137: =$O$137*L9 -> 6404.1881 | M137: =$O$137*M9 -> 6911.854 | N137: =$O$137*N9 -> 7153.7689 | O137: =J137/J9 -> 0.019975657 | P137: Using CAPEX-to-Sales ratio FY2025
B138: Accounting Depreciation (cash flow) | F138: =F139-(F136+F137) -> -1903 | G138: =G139-(G136+G137) -> -2737 | H138: =H139-(H136+H137) -> -2285 | I138: =I139-(I136+I137) -> -2362 | J138: =J139-(J136+J137) -> -2621 | K138: =-(K144+K145/2)*K148 -> -2690.3454 | L138: =-(L144+L145/2)*L148 -> -2998.7955 | M138: =-(M144+M145/2)*M148 -> -3331.6966 | N138: =-(N144+N145/2)*N148 -> -3683.3372
B139: Ending | E139: 21807 | F139: =F38 -> 23492 | G139: =G38 -> 24646 | H139: =H38 -> 26684 | I139: =I38 -> 29032 | J139: =J38 -> 31909 | K139: =SUM(K136:K138) -> 35152.471 | L139: =SUM(L136:L138) -> 38557.864 | M139: =SUM(M136:M138) -> 42138.021 | N139: =SUM(N136:N138) -> 45608.453
B142: Forecast Depreciation expense
B144: Opening PPE, Gross | F144: 34703 | G144: =F147 -> 37658 | H144: =G147 -> 39932 | I144: =H147 -> 43369 | J144: =I147 -> 46950 | K144: =J147 -> 50840 | L144: =K147 -> 56773.817 | M144: =L147 -> 63178.005 | N144: =M147 -> 70089.859
...

Sheet WACC
A1: Cost of equity capital
A2: Beta | B2: 0.9958
A3: Risk free rate | B3: 0.0402
A4: Risk premium | B4: 0.055 | C4: realized historical premium (factset)
A5: Cost of equity capital | B5: =B3+B2*B4 -> 0.094969 | C5: Costco, with low beta (≈ 0.99) and defensive retail exposure, deserves a lower cost of equity
A8: Cost of debt
A9: Use Costco's guidance data from 10-K.
A11: ($M) | B11: Rate | C11: Amount | D11: Weight | E11: Weighted Rate
A12: Current finance lease liability | B12: 0.0463 | C12: 78 | D12: =C12/$C$21 -> 0.0078376206 | E12: =B12*D12 -> 0.00036288183
A13: Long term finance lease liability | B13: 0.0463 | C13: 1401 | D13: =C13/$C$21 -> 0.14077572 | E13: =B13*D13 -> 0.006517916
A14: Current operating lease liability | B14: 0.0305 | C14: 208 | D14: =C14/$C$21 -> 0.020900322 | E14: =B14*D14 -> 0.00063745981
A15: Long term operating lease liability | B15: 0.0305 | C15: 2460 | D15: =C15/$C$21 -> 0.2471865 | E15: =B15*D15 -> 0.0075391881
A16: Senior Notes due May 2027 | B16: 0.03 | C16: 1000 | D16: =C16/$C$21 -> 0.10048232 | E16: =B16*D16 -> 0.0030144695
A17: Senior Notes due June 2027 | B17: 0.01375 | C17: 1250 | D17: =C17/$C$21 -> 0.12560289 | E17: =B17*D17 -> 0.0017270398
A18: Senior Notes due April 2030 | B18: 0.016 | C18: 1750 | D18: =C18/$C$21 -> 0.17584405 | E18: =B18*D18 -> 0.0028135048
A19: Senior Notes due April 2032 | B19: 0.0175 | C19: 1000 | D19: =C19/$C$21 -> 0.10048232 | E19: =B19*D19 -> 0.0017584405
A20: Other long term debt | B20: 0.0212 | C20: 805 | D20: =C20/$C$21 -> 0.080888264 | E20: =B20*D20 -> 0.0017148312
C21: =SUM(C12:C20) -> 9952 | E21: =SUM(E12:E20) -> 0.026085732 | F21: --Pretax Borrowing Rate
D22: Tax rate | E22: 0.25
E23: =E21*(1-E22) -> 0.019564299 | F23: --After tax Borrowing Rate
A25: WACC Calculations
A26: Outstanding shares | B26: 443870000 | C26: Shares
A27: Price per share | B27: 1011.17 | C27: $
A28: IV of equity | B28: =B27*B26/1000000 -> 448828.03 | C28: $M
C30: Weights | D30: Weighted Rate
A31: Cost of debt capital | B31: =E23 -> 0.019564299 | C31: =C21/(B28+C21) -> 0.021692313 | D31: =B31*C31 -> 0.00042439489
A32: Cost of equity capital | B32: =B5 -> 0.094969 | C32: =B28/(B28+C21) -> 0.97830769 | D32: =B32*C32 -> 0.092908903
A33: WACC | D33: =SUM(D31:D32) -> 0.093333298

Sheet Beta Calculation
A1: Date | B1: Costco | C1: Re | D1: S&P500 | E1: Rm | G1: Rf | H1: Monthly Rf | I1: Rm-Rf | J1: Re-Rf | N1: Costco Beta: | O1: =O20 -> 0.99585145
A2: 46064 | B2: 978.14 | D2: 6941.47 | F2: 4.14
A3: 46052 | B3: 940.25 | C3: =B3/B2-1 -> -0.038736786 | D3: 6939.0295 | E3: =D3/D2-1 -> -0.00035157969 | F3: 4.21 | G3: =F3/100 -> 0.0421 | H3: =G3/12 -> 0.0035083333 | I3: =E3-H3 -> -0.003859913 | J3: =C3-H3 -> -0.042245119 | N3: SUMMARY OUTPUT
A4: 46022 | B4: 862.34 | C4: =B4/B3-1 -> -0.082860941 | D4: 6845.5047 | E4: =D4/D3-1 -> -0.013478083 | F4: 4.14 | G4: =F4/100 -> 0.0414 | H4: =G4/12 -> 0.00345 | I4: =E4-H4 -> -0.016928083 | J4: =C4-H4 -> -0.086310941
A5: 45989 | B5: 913.59 | C5: =B5/B4-1 -> 0.059431315 | D5: 6849.0874 | E5: =D5/D4-1 -> 0.00052336042 | F5: 4.09 | G5: =F5/100 -> 0.0409 | H5: =G5/12 -> 0.0034083333 | I5: =E5-H5 -> -0.0028849729 | J5: =C5-H5 -> 0.056022981 | N5: Regression Statistics
A6: 45961 | B6: 911.45 | C6: =B6/B5-1 -> -0.0023424074 | D6: 6840.1987 | E6: =D6/D5-1 -> -0.0012977833 | F6: 4.06 | G6: =F6/100 -> 0.0406 | H6: =G6/12 -> 0.0033833333 | I6: =E6-H6 -> -0.0046811166 | J6: =C6-H6 -> -0.0057257408 | N6: Multiple R | O6: 0.65393237
A7: 45930 | B7: 925.63 | C7: =B7/B6-1 -> 0.015557628 | D7: 6688.459 | E7: =D7/D6-1 -> -0.022183523 | F7: 4.12 | G7: =F7/100 -> 0.0412 | H7: =G7/12 -> 0.0034333333 | I7: =E7-H7 -> -0.025616856 | J7: =C7-H7 -> 0.012124295 | N7: R Square | O7: 0.42762755
A8: 45898 | B8: 943.32 | C8: =B8/B7-1 -> 0.019111308 | D8: 6460.2627 | E8: =D8/D7-1 -> -0.034117929 | F8: 4.26 | G8: =F8/100 -> 0.0426 | H8: =G8/12 -> 0.00355 | I8: =E8-H8 -> -0.037667929 | J8: =C8-H8 -> 0.015561308 | N8: Adjusted R Square | O8: 0.41775906
A9: 45869 | B9: 939.64 | C9: =B9/B8-1 -> -0.0039011152 | D9: 6339.3946 | E9: =D9/D8-1 -> -0.018709471 | F9: 4.39 | G9: =F9/100 -> 0.0439 | H9: =G9/12 -> 0.0036583333 | I9: =E9-H9 -> -0.022367805 | J9: =C9-H9 -> -0.0075594485 | N9: Standard Error | O9: 0.050870853
A10: 45838 | B10: 989.94 | C10: =B10/B9-1 -> 0.05353114 | D10: 6204.954 | E10: =D10/D9-1 -> -0.021207169 | F10: 4.38 | G10: =F10/100 -> 0.0438 | H10: =G10/12 -> 0.00365 | I10: =E10-H10 -> -0.024857169 | J10: =C10-H10 -> 0.04988114 | N10: Observations | O10: 60
A11: 45807 | B11: 1040.18 | C11: =B11/B10-1 -> 0.050750551 | D11: 5911.6867 | E11: =D11/D10-1 -> -0.047263401 | F11: 4.42 | G11: =F11/100 -> 0.0442 | H11: =G11/12 -> 0.0036833333 | I11: =E11-H11 -> -0.050946735 | J11: =C11-H11 -> 0.047067217
A12: 45777 | B12: 994.5 | C12: =B12/B11-1 -> -0.043915476 | D12: 5569.0647 | E12: =D12/D11-1 -> -0.057956733 | F12: 4.28 | G12: =F12/100 -> 0.0428 | H12: =G12/12 -> 0.0035666667 | I12: =E12-H12 -> -0.0615234 | J12: =C12-H12 -> -0.047482143 | N12: ANOVA
A13: 45747 | B13: 945.78 | C13: =B13/B12-1 -> -0.048989442 | D13: 5611.8526 | E13: =D13/D12-1 -> 0.0076831451 | F13: 4.28 | G13: =F13/100 -> 0.0428 | H13: =G13/12 -> 0.0035666667 | I13: =E13-H13 -> 0.0041164784 | J13: =C13-H13 -> -0.052556109 | O13: df | P13: SS | Q13: MS | R13: F | S13: Significance F
A14: 45716 | B14: 1048.61 | C14: =B14/B13-1 -> 0.10872507 | D14: 5954.5048 | E14: =D14/D13-1 -> 0.061058664 | F14: 4.45 | G14: =F14/100 -> 0.0445 | H14: =G14/12 -> 0.0037083333 | I14: =E14-H14 -> 0.05735033 | J14: =C14-H14 -> 0.10501674 | N14: Regression | O14: 1 | P14: 0.11213805 | Q14: 0.11213805 | R14: 43.33262 | S14: 1.4665227e-08
A15: 45688 | B15: 979.88 | C15: =B15/B14-1 -> -0.065543911 | D15: 6040.5259 | E15: =D15/D14-1 -> 0.014446391 | F15: 4.63 | G15: =F15/100 -> 0.0463 | H15: =G15/12 -> 0.0038583333 | I15: =E15-H15 -> 0.010588058 | J15: =C15-H15 -> -0.069402244 | N15: Residual | O15: 58 | P15: 0.15009494 | Q15: 0.0025878437
A16: 45657 | B16: 916.27 | C16: =B16/B15-1 -> -0.064916112 | D16: 5881.6276 | E16: =D16/D15-1 -> -0.026305373 | F16: 4.39 | G16: =F16/100 -> 0.0439 | H16: =G16/12 -> 0.0036583333 | I16: =E16-H16 -> -0.029963706 | J16: =C16-H16 -> -0.068574446 | N16: Total | O16: 59 | P16: 0.26223298
A17: 45625 | B17: 971.88 | C17: =B17/B16-1 -> 0.060691718 | D17: 6032.3844 | E17: =D17/D16-1 -> 0.02563181 | F17: 4.36 | G17: =F17/100 -> 0.0436 | H17: =G17/12 -> 0.0036333333 | I17: =E17-H17 -> 0.021998477 | J17: =C17-H17 -> 0.057058384
A18: 45596 | B18: 874.18 | C18: =B18/B17-1 -> -0.10052681 | D18: 5705.4479 | E18: =D18/D17-1 -> -0.054196893 | F18: 4.1 | G18: =F18/100 -> 0.041 | H18: =G18/12 -> 0.0034166667 | I18: =E18-H18 -> -0.05761356 | J18: =C18-H18 -> -0.10394348 | O18: Coefficients | P18: Standard Error | Q18: t Stat | R18: P-value | S18: Lower 95% | T18: Upper 95% | U18: Lower 95.0% | V18: Upper 95.0%
A19: 45565 | B19: 886.52 | C19: =B19/B18-1 -> 0.014116086 | D19: 5762.4849 | E19: =D19/D18-1 -> 0.0099969299 | F19: 3.72 | G19: =F19/100 -> 0.0372 | H19: =G19/12 -> 0.0031 | I19: =E19-H19 -> 0.0068969299 | J19: =C19-H19 -> 0.011016086 | N19: Intercept | O19: -0.0067776039 | P19: 0.0068083312 | Q19: -0.99548682 | R19: 0.32363469 | S19: -0.020405959 | T19: 0.0068507516 | U19: -0.020405959 | V19: 0.0068507516
A20: 45534 | B20: 892.38 | C20: =B20/B19-1 -> 0.006610116 | D20: 5648.3972 | E20: =D20/D19-1 -> -0.019798342 | F20: 3.87 | G20: =F20/100 -> 0.0387 | H20: =G20/12 -> 0.003225 | I20: =E20-H20 -> -0.023023342 | J20: =C20-H20 -> 0.003385116 | N20: X Variable 1 | O20: 0.99585145 | P20: 0.15128194 | Q20: 6.5827517 | R20: 1.4665227e-08 | S20: 0.69302775 | T20: 1.2986752 | U20: 0.69302775 | V20: 1.2986752
A21: 45504 | B21: 822 | C21: =B21/B20-1 -> -0.078867747 | D21: 5522.3018 | E21: =D21/D20-1 -> -0.022324103 | F21: 4.25 | G21: =F21/100 -> 0.0425 | H21: =G21/12 -> 0.0035416667 | I21: =E21-H21 -> -0.025865769 | J21: =C21-H21 -> -0.082409414
A22: 45471 | B22: 849.99 | C22: =B22/B21-1 -> 0.034051095 | D22: 5460.4826 | E22: =D22/D21-1 -> -0.011194465 | F22: 4.31 | G22: =F22/100 -> 0.0431 | H22: =G22/12 -> 0.0035916667 | I22: =E22-H22 -> -0.014786132 | J22: =C22-H22 -> 0.030459428 | N22: Equation: | O22: (Re-Rf) =-0.006 + 0.996*(Rm-Rf)
A23: 45443 | B23: 809.89 | C23: =B23/B22-1 -> -0.047177026 | D23: 5277.5073 | E23: =D23/D22-1 -> -0.033508993 | F23: 4.48 | G23: =F23/100 -> 0.0448 | H23: =G23/12 -> 0.0037333333 | I23: =E23-H23 -> -0.037242327 | J23: =C23-H23 -> -0.050910359
A24: 45412 | B24: 722.9 | C24: =B24/B23-1 -> -0.10740965 | D24: 5035.6917 | E24: =D24/D23-1 -> -0.045820053 | F24: 4.54 | G24: =F24/100 -> 0.0454 | H24: =G24/12 -> 0.0037833333 | I24: =E24-H24 -> -0.049603386 | J24: =C24-H24 -> -0.11119298
A25: 45379 | B25: 732.63 | C25: =B25/B24-1 -> 0.013459676 | D25: 5254.3544 | E25: =D25/D24-1 -> 0.04342258 | F25: 4.21 | G25: =F25/100 -> 0.0421 | H25: =G25/12 -> 0.0035083333 | I25: =E25-H25 -> 0.039914246 | J25: =C25-H25 -> 0.009951343
A26: 45351 | B26: 743.89 | C26: =B26/B25-1 -> 0.015369286 | D26: 5096.2695 | E26: =D26/D25-1 -> -0.030086456 | F26: 4.21 | G26: =F26/100 -> 0.0421 | H26: =G26/12 -> 0.0035083333 | I26: =E26-H26 -> -0.033594789 | J26: =C26-H26 -> 0.011860953
A27: 45322 | B27: 694.88 | C27: =B27/B26-1 -> -0.065883397 | D27: 4845.6472 | E27: =D27/D26-1 -> -0.049177604 | F27: 4.06 | G27: =F27/100 -> 0.0406 | H27: =G27/12 -> 0.0033833333 | I27: =E27-H27 -> -0.052560937 | J27: =C27-H27 -> -0.06926673
A28: 45289 | B28: 660.08 | C28: =B28/B27-1 -> -0.050080589 | D28: 4769.8294 | E28: =D28/D27-1 -> -0.015646571 | F28: 4.02 | G28: =F28/100 -> 0.0402 | H28: =G28/12 -> 0.00335 | I28: =E28-H28 -> -0.018996571 | J28: =C28-H28 -> -0.053430589
A29: 45260 | B29: 592.74 | C29: =B29/B28-1 -> -0.10201794 | D29: 4567.7986 | E29: =D29/D28-1 -> -0.042355974 | F29: 4.5 | G29: =F29/100 -> 0.045 | H29: =G29/12 -> 0.00375 | I29: =E29-H29 -> -0.046105974 | J29: =C29-H29 -> -0.10576794
A30: 45230 | B30: 552.44 | C30: =B30/B29-1 -> -0.067989338 | D30: 4193.801 | E30: =D30/D29-1 -> -0.081877008 | F30: 4.8 | G30: =F30/100 -> 0.048 | H30: =G30/12 -> 0.004 | I30: =E30-H30 -> -0.085877008 | J30: =C30-H30 -> -0.071989338
A31: 45198 | B31: 564.96 | C31: =B31/B30-1 -> 0.022663095 | D31: 4288.0541 | E31: =D31/D30-1 -> 0.022474402 | F31: 4.38 | G31: =F31/100 -> 0.0438 | H31: =G31/12 -> 0.00365 | I31: =E31-H31 -> 0.018824402 | J31: =C31-H31 -> 0.019013095
A32: 45169 | B32: 549.28 | C32: =B32/B31-1 -> -0.027754177 | D32: 4507.6618 | E32: =D32/D31-1 -> 0.051213829 | F32: 4.17 | G32: =F32/100 -> 0.0417 | H32: =G32/12 -> 0.003475 | I32: =E32-H32 -> 0.047738829 | J32: =C32-H32 -> -0.031229177
A33: 45138 | B33: 560.67 | C33: =B33/B32-1 -> 0.020736237 | D33: 4588.9611 | E33: =D33/D32-1 -> 0.018035813 | F33: 3.9 | G33: =F33/100 -> 0.039 | H33: =G33/12 -> 0.00325 | I33: =E33-H33 -> 0.014785813 | J33: =C33-H33 -> 0.017486237
A34: 45107 | B34: 538.38 | C34: =B34/B33-1 -> -0.039756006 | D34: 4450.3813 | E34: =D34/D33-1 -> -0.030198518 | F34: 3.75 | G34: =F34/100 -> 0.0375 | H34: =G34/12 -> 0.003125 | I34: =E34-H34 -> -0.033323518 | J34: =C34-H34 -> -0.042881006
... A62: 44253 | B62: 331 | C62: =B62/B61-1 -> -0.060939628 | D62: 3811.1497 | E62: =D62/D61-1 -> -0.040711515 | F62: 1.26 | G62: =F62/100 -> 0.0126 | H62: =G62/12 -> 0.00105 | I62: =E62-H62 -> -0.041761515 | J62: =C62-H62 -> -0.061989628

Sheet Valuation DCF 
A1: Cost of equity capital
A2: Beta | B2: ='Beta Calculation'!O1 -> 0.99585145
A3: Risk free rate | B3: 0.0402
A4: Risk premium | B4: 0.055 | C4: Market premium
A5: Cost of equity capital | B5: =B3+(B2*B4) -> 0.09497183 | C5: Costco, with low beta (0.99) and defensive retail exposure, deserves a lower cost of equity
A8: Cost of debt
A9: Using Costco's guidance data from 10-K
A11: ($M) | B11: Rate | C11: Amount | D11: Weight | E11: Weighted Rate
A12: Current finance lease liability | B12: 0.0463 | C12: 78 | D12: =C12/$C$21 -> 0.0078376206 | E12: =D12*B12 -> 0.00036288183
A13: Long term finance lease liability | B13: 0.0463 | C13: 1401 | D13: =C13/$C$21 -> 0.14077572 | E13: =D13*B13 -> 0.006517916
A14: Current operating lease liability | B14: 0.0305 | C14: 208 | D14: =C14/$C$21 -> 0.020900322 | E14: =D14*B14 -> 0.00063745981
A15: Long term operating lease liability | B15: 0.0305 | C15: 2460 | D15: =C15/$C$21 -> 0.2471865 | E15: =D15*B15 -> 0.0075391881
A16: Senior Notes due May 2027 | B16: 0.03 | C16: 1000 | D16: =C16/$C$21 -> 0.10048232 | E16: =D16*B16 -> 0.0030144695
A17: Senior Notes due June 2027 | B17: 0.01375 | C17: 1250 | D17: =C17/$C$21 -> 0.12560289 | E17: =D17*B17 -> 0.0017270398
A18: Senior Notes due April 2030 | B18: 0.016 | C18: 1750 | D18: =C18/$C$21 -> 0.17584405 | E18: =D18*B18 -> 0.0028135048
A19: Senior Notes due April 2032 | B19: 0.0175 | C19: 1000 | D19: =C19/$C$21 -> 0.10048232 | E19: =D19*B19 -> 0.0017584405
A20: Other long term debt | B20: 0.0212 | C20: 805 | D20: =C20/$C$21 -> 0.080888264 | E20: =D20*B20 -> 0.0017148312
A21: Total | C21: =SUM(C12:C20) -> 9952 | E21: =SUM(E12:E20) -> 0.026085732 | F21: --Pretax Borrowing Rate
D22: Tax rate | E22: 0.25
E23: =E21*(1-E22) -> 0.019564299 | F23: --After tax Borrowing Rate
A25: WACC Calculations
A26: Outstanding shares | B26: 443870000 | C26: Shares
A27: Price per share | B27: 1011.17 | C27: $
A28: IV of equity | B28: =B26*B27/1000 -> 4.4882803e+08 | C28: $M
C30: Weights | D30: Weighted Rate
A31: Cost of debt capital | B31: =E23 -> 0.019564299 | C31: 0.0217 | D31: =C31*B31 -> 0.00042454528
A32: Cost of equity capital | B32: =B5 -> 0.09497183 | C32: 0.9783 | D32: =C32*B32 -> 0.092910941
A33: WACC | D33: =D32+D31 -> 0.093335486
A35: Valuation - DCF Model | B35: statutory tax rate: | C35: 0.25
A37: Terminal Growth Rate | B37: 0.035
B38: 0 | C38: 1 | D38: 2 | E38: 3
B39: 2025A | C39: 2026E | D39: 2027E | E39: 2028E | F39: Terminal Year
A40: NOPAT | B40: =Forecast!J14*(1-Forecast!$Q$21) -> 7787.25 | C40: =Forecast!K14*(1-Forecast!$Q$21) -> 7854.5351 | D40: =Forecast!L14*(1-Forecast!$Q$21) -> 8477.1608 | E40: =Forecast!M14*(1-Forecast!$Q$21) -> 9149.1532 | F40: =Forecast!N14*(1-Forecast!$Q$21) -> 9469.3736 | G40: OI × (1 - tax rate)
A41: NOA | B41: =(Forecast!J41-Forecast!J31-Forecast!J32)-(Forecast!J54-Forecast!J51-Forecast!J52) -> 22053 | C41: =(Forecast!K41-Forecast!K31-Forecast!K32)-(Forecast!K54-Forecast!K51-Forecast!K52) -> 23956.931 | D41: =(Forecast!L41-Forecast!L31-Forecast!L32)-(Forecast!L54-Forecast!L51-Forecast!L52) -> 25883.707 | E41: =(Forecast!M41-Forecast!M31-Forecast!M32)-(Forecast!M54-Forecast!M51-Forecast!M52) -> 27863.516 | F41: =(Forecast!N41-Forecast!N31-Forecast!N32)-(Forecast!N54-Forecast!N51-Forecast!N52) -> 28838.739
A42: increase NOA | C42: =C41-B41 -> 1903.9306 | D42: =D41-C41 -> 1926.7765 | E42: =E41-D41 -> 1979.8085 | F42: =F41-E41 -> 975.22304
A43: FCFF =NOPAT - Increase in NOA | C43: =C40-C42 -> 5950.6045 | D43: =D40-D42 -> 6550.3843 | E43: =E40-E42 -> 7169.3448 | F43: =F40-F42 -> 8494.1505
A44: discount factor | C44: =1/(1+$D$33)^C38 -> 0.91463235 | D44: =1/(1+$D$33)^D38 -> 0.83655233 | E44: =1/(1+$D$33)^E38 -> 0.76513782
A45: Present value of horizon FCFF | C45: =C43*C44 -> 5442.6154 | D45: =D43*D44 -> 5479.7393 | E45: =E43*E44 -> 5485.5368
A46: Present value of terminal FCFF | F46: =F43*E44/(D33-B37) -> 111410.67 | G46: FCFF_TV/(WACC-g) × DF_yr3
A47: Firm Value | B47: =SUM(C45:F46) -> 127818.56
A48: Less NNO | B48: =-(B41-Forecast!J66) -> 7111
A49: Preferred Stock | B49: 0
A50: Noncontrolling interest | B50: 0 | G50: (LT Debt + LT Lease) - (Cash + ST Inv)
A52: Firm equity value | B52: =B47+B48+B49+B50 -> 134929.56
A53: share ourstanding | B53: =B26 -> 443870000
A54: Intrinsic value | B54: =B52*10^6/B53 -> 303.98442
A56: Industry P/E | B56: 32
A57: Exit multiple method Valuation
B58: 2025A | C58: 2026E | D58: 2027E | E58: 2028E | F58: Terminal Year
A59: EBIT | C59: =Forecast!K14 -> 10472.713 | D59: =Forecast!L14 -> 11302.881 | E59: =Forecast!M14 -> 12198.871 | F59: =Forecast!N14 -> 12625.831
A60: Taxes | C60: =-C59*25% -> -2618.1784 | D60: =-D59*25% -> -2825.7203 | E60: =-E59*25% -> -3049.7177 | F60: =-F59*25% -> -3156.4579
A61: D&A | C61: =-Forecast!K138 -> 2690.3454 | D61: =-Forecast!L138 -> 2998.7955 | E61: =-Forecast!M138 -> 3331.6966 | F61: =-Forecast!N138 -> 3683.3372
A62: Capital Expenditure | C62: =-Forecast!K137 -> -5933.8169 | D62: =-Forecast!L137 -> -6404.1881 | E62: =-Forecast!M137 -> -6911.854 | F62: =-Forecast!N137 -> -7153.7689
A63: Change in Working Capital | C63: =C68 -> -121.75604 | D63: =D68 -> -131.40964 | E63: =E68 -> -141.82882 | F63: =F68 -> -67.584808
A64: Unlevered Free Cash Flow | C64: =SUM(C59:C63) -> 4489.3076 | D64: =SUM(D59:D63) -> 4940.3587 | E64: =SUM(E59:E63) -> 5427.167 | F64: =SUM(F59:F63) -> 5931.3571
I65: Date | J65: Enterprise Value | K65: EBITDA | L65: EV/EBITDA
I66: 44437 | J66: $201 B | K66: $8.089 B | L66: 24.8
A67: Working capital | B67: =Forecast!J33+Forecast!J34-Forecast!J44 -> 1536 | C67: =Forecast!K33+Forecast!K34-Forecast!K44 -> 1657.756 | D67: =Forecast!L33+Forecast!L34-Forecast!L44 -> 1789.1657 | E67: =Forecast!M33+Forecast!M34-Forecast!M44 -> 1930.9945 | F67: =Forecast!N33+Forecast!N34-Forecast!N44 -> 1998.5793 | I67: 44801 | J67: $229 B | K67: $9.944 B | L67: 23
C68: =-(C67-B67) -> -121.75604 | D68: =-(D67-C67) -> -131.40964 | E68: =-(E67-D67) -> -141.82882 | F68: =-(F67-E67) -> -67.584808 | I68: 45172 | J68: $238.7 B | K68: $10.329 B | L68: 23.1
I69: 45536 | J69: $393.4 B | K69: $11.243 B | L69: 35
A70: Historical 5 Year average EV/EBITDA multiple | B70: =L71 -> 27.8 | I70: 45900 | J70: $411.8 B | K70: $12.442 B | L70: 33.1
B71: 2025A | C71: 2026E | D71: 2027E | E71: 2028E | F71: Terminal Year | I71: Average | L71: =AVERAGE(L66:L70) -> 27.8
A72: FCFF | C72: =C64 -> 4489.3076 | D72: =D64 -> 4940.3587 | E72: =E64 -> 5427.167
A73: Terminal value | F73: =(F59+F61)*B70 -> 453394.89
A75: PV of FCFF | C75: =C72*C44 -> 4106.0659 | D75: =D72*D44 -> 4132.8685 | E75: =E72*E44 -> 4152.5307
A76: PV of Terminal Value | E76: =F73*E44 -> 346909.57
A78: Enterprise Value | B78: =SUM(C75:E76) -> 359301.04
A79: Net debt | B79: =C21-Forecast!J31 -> -4209
A80: Equity Value | B80: =B78-B79 -> 363510.04
A81: No of shares outstanding | B81: =B53 -> 443870000
A83: Share price | B83: =B80*10^6/B81 -> 818.95609
A87: EPS for the next 12 months | B87: =Forecast!K22*(1-27%)/443.87 -> 13.456904
A89: Target Price | B89: =B87*B56 -> 430.62094
A92: Sensitivity Analysis
B93: Terminal Growth rate
A94: WACC | B94: =B54 -> 303.98442 | C94: 0.025 | D94: =C94+0.01 -> 0.035 | E94: =D94+0.01 -> 0.045 | F94: =E94+0.01 -> 0.055 | G94: =F94+0.01 -> 0.065
B95: =6.33% -> 0.0633 | C95: 470.73824 | D95: 617.60094 | E95: 924.96932 | F95: 1972.9844 | G95: -9308.5898
B96: =B95+0.01 -> 0.0733 | C96: 374.83029 | D96: 458.49742 | E96: 601.29326 | F96: 900.15013 | G96: 1919.144
B97: =B96+0.01 -> 0.0833 | C97: 311.87194 | D97: 365.32865 | E97: 446.7001 | F97: 585.57786 | G97: 876.23461
B98: =B97+0.01 -> 0.0933 | C98: 267.3887 | D98: 304.16406 | E98: 356.1673 | F98: 435.32629 | G98: 570.42801
B99: =B98+0.01 -> 0.1033 | C99: 234.30054 | D99: 260.94463 | E99: 296.72905 | F99: 347.33104 | G99: 424.35705

Sheet AFN
C2: 2025A | D2: 2026E | E2: 2027E | F2: 2028E | G2: 2029E
B3: So | C3: =Forecast!J7 -> 269912 | D3: =Forecast!K7 -> 291262.04 | E3: =Forecast!L7 -> 314300.87 | F3: =Forecast!M7 -> 339162.07 | G3: ='Revenue Forecast ETS'!Q5 -> 365767.83
B4: Growth rate | D4: =D3/C3-1 -> 0.0791 | E4: =E3/D3-1 -> 0.0791 | F4: =F3/E3-1 -> 0.0791
B5: S1 | C5: =D3 -> 291262.04 | D5: =E3 -> 314300.87 | E5: =F3 -> 339162.07 | F5: =G3 -> 365767.83
A6: g.S0 | B6: Delta S | C6: =D3-C3 -> 21350.039 | D6: =E3-D3 -> 23038.827 | E6: =F3-E3 -> 24861.199 | F6: =G3-F3 -> 26605.766
B7: Ao* | C7: =Forecast!J41 -> 77099 | D7: =Forecast!K41 -> 86246.205 | E7: =Forecast!L41 -> 96074.491 | F7: =Forecast!M41 -> 104513.54
B8: Lo* | C8: =SUM(Forecast!J44:J47) -> 30519 | D8: =SUM(Forecast!K44:K47) -> 32956.644 | E8: =SUM(Forecast!L44:L47) -> 35620.428 | F8: =SUM(Forecast!M44:M47) -> 38499.914
B9: Ao*/So | C9: =C7/C3 -> 0.28564495 | D9: =D7/D3 -> 0.29611207 | E9: =E7/E3 -> 0.30567683 | F9: =F7/F3 -> 0.30815221
B10: Lo*/So* | C10: =C8/C3 -> 0.11307019 | D10: =D8/D3 -> 0.11315118 | E10: =E8/E3 -> 0.11333226 | F10: =F8/F3 -> 0.1135148
B11: M | C11: =Forecast!J22/Forecast!J9 -> 0.029425763 | D11: =Forecast!K22/Forecast!K9 -> 0.027545143 | E11: =Forecast!L22/Forecast!L9 -> 0.027536881 | F11: =Forecast!M22/Forecast!M9 -> 0.027521702
B12: POR | C12: =-'Cash flow forecast'!F30/Forecast!J22 -> 0.26953945 | D12: =-'Cash flow forecast'!G30/Forecast!K22 -> 0.26953945 | E12: =-'Cash flow forecast'!H30/Forecast!L22 -> 0.26953945 | F12: =-'Cash flow forecast'!I30/Forecast!M22 -> 0.26953945
B15: Additional Financing Needs | D15: =D9*D6-D10*D6-D11*D5*(1-D12) -> -2108.7305 | E15: =E9*E6-E10*E6-E11*E5*(1-E12) -> -2040.1946 | F15: =F9*F6-F10*F6-F11*F5*(1-F12) -> -2174.7428
D16: =IF(D15<0,"Surplus", "Deficit") -> Surplus | E16: =IF(E15<0,"Surplus", "Deficit") -> Surplus | F16: =IF(F15<0,"Surplus", "Deficit") -> Surplus
B20: Formula used: | C20: AFN=(A∗/S0​)ΔS−(L∗/S0​)ΔS−(M×S1​×POR)
B22: The surplus cash in ech year can be used to pay special dividends or increase the payout ratio
B23: Special dividends each year/additional dividends each year | D23: =-D15/('Valuation DCF '!$B$26/10^6) -> 4.750784 | E23: =-E15/('Valuation DCF '!$B$26/10^6) -> 4.5963787 | F23: =-F15/('Valuation DCF '!$B$26/10^6) -> 4.8995039

Sheet Cash flow forecast
A1: Cashflow Statement
A3: CASH FLOWS FROM OPERATING ACTIVITIES | B3: 2021 | C3: 2022 | D3: 2023 | E3: 2024 | F3: 2025 | G3: 2026E | H3: 2027E | I3: 2028E | K3: Rate | L3: Explanation/Assumptions
A4: Net income | B4: =VLOOKUP($A$4,CASH_FLOW!$B$20:$L$56,11,FALSE) -> 5079 | C4: =VLOOKUP($A4,CASH_FLOW!$B$20:$L$56,9,FALSE) -> 5915 | D4: =VLOOKUP($A4,CASH_FLOW!$B$20:$L$56,7,FALSE) -> 6292 | E4: =VLOOKUP($A4,CASH_FLOW!$B$20:$L$56,5,FALSE) -> 7367 | F4: =VLOOKUP($A4,CASH_FLOW!$B$20:$L$56,3,FALSE) -> 8099 | G4: =Forecast!K22 -> 8182.3509 | H4: =Forecast!L22 -> 8828.3135 | I4: =Forecast!M22 -> 9522.89
A5: Adjustments to reconcile net income to net cash provided by operating activities:
A7: Depreciation and amortization | B7: =VLOOKUP(A7,CASH_FLOW!$B$20:$L$56,11,FALSE) -> 1781 | C7: =VLOOKUP($A7,CASH_FLOW!$B$20:$L$56,9,FALSE) -> 1900 | D7: =VLOOKUP($A7,CASH_FLOW!$B$20:$L$56,7,FALSE) -> 2077 | E7: =VLOOKUP($A7,CASH_FLOW!$B$20:$L$56,5,FALSE) -> 2237 | F7: =VLOOKUP($A7,CASH_FLOW!$B$20:$L$56,3,FALSE) -> 2426 | G7: =-Forecast!K138 -> 2690.3454 | H7: =-Forecast!L138 -> 2998.7955 | I7: =-Forecast!M138 -> 3331.6966
A8: Non-cash lease expense | B8: =VLOOKUP(A8,CASH_FLOW!$B$20:$L$56,11,FALSE) -> 286 | C8: =VLOOKUP($A8,CASH_FLOW!$B$20:$L$56,9,FALSE) -> 377 | D8: =VLOOKUP($A8,CASH_FLOW!$B$20:$L$56,7,FALSE) -> 412 | E8: =VLOOKUP($A8,CASH_FLOW!$B$20:$L$56,5,FALSE) -> 315 | F8: =VLOOKUP($A8,CASH_FLOW!$B$20:$L$56,3,FALSE) -> 303 | G8: =$K$8*Forecast!K39 -> 303 | H8: =$K$8*Forecast!L39 -> 303 | I8: =$K$8*Forecast!M39 -> 303 | K8: =303/2725 -> 0.11119266 | L8: % of operating ROU lease
A9: Stock-based compensation | B9: =VLOOKUP(A9,CASH_FLOW!$B$20:$L$56,11,FALSE) -> 665 | C9: =VLOOKUP($A9,CASH_FLOW!$B$20:$L$56,9,FALSE) -> 724 | D9: =VLOOKUP($A9,CASH_FLOW!$B$20:$L$56,7,FALSE) -> 774 | E9: =VLOOKUP($A9,CASH_FLOW!$B$20:$L$56,5,FALSE) -> 818 | F9: =VLOOKUP($A9,CASH_FLOW!$B$20:$L$56,3,FALSE) -> 860 | G9: =$K$9*(Forecast!K13) -> 923.42328 | H9: =$K$9*(Forecast!L13) -> 996.62266 | I9: =$K$9*(Forecast!M13) -> 1075.6259 | K9: =F9/(Forecast!J13) -> 0.034446848 | L9: % SG&A expenses
A10: Impairment of assets and other non-cash operating
A11: activities, net | B11: =VLOOKUP(A11,CASH_FLOW!$B$20:$L$56,11,FALSE) -> 144 | C11: =VLOOKUP($A11,CASH_FLOW!$B$20:$L$56,9,FALSE) -> 39 | D11: =VLOOKUP($A11,CASH_FLOW!$B$20:$L$56,7,FALSE) -> 495 | E11: =VLOOKUP($A11,CASH_FLOW!$B$20:$L$56,5,FALSE) -> -9 | F11: =VLOOKUP($A11,CASH_FLOW!$B$20:$L$56,3,FALSE) -> -117 | G11: 0 | H11: 0 | I11: 0
A12: Changes in operating assets and liabilities:
A13: Merchandise inventories | B13: =VLOOKUP(A13,CASH_FLOW!$B$20:$L$56,11,FALSE) -> -1892 | C13: =VLOOKUP($A13,CASH_FLOW!$B$20:$L$56,9,FALSE) -> -4003 | D13: =VLOOKUP($A13,CASH_FLOW!$B$20:$L$56,7,FALSE) -> 1228 | E13: =VLOOKUP($A13,CASH_FLOW!$B$20:$L$56,5,FALSE) -> -2068 | F13: =VLOOKUP($A13,CASH_FLOW!$B$20:$L$56,3,FALSE) -> 559 | G13: =Forecast!J34-Forecast!K34 -> -1436.0237 | H13: =Forecast!K34-Forecast!L34 -> -1549.8808 | I13: =Forecast!L34-Forecast!M34 -> -1672.7675
A14: Accounts payable | B14: =VLOOKUP(A14,CASH_FLOW!$B$20:$L$56,11,FALSE) -> 1838 | C14: =VLOOKUP($A14,CASH_FLOW!$B$20:$L$56,9,FALSE) -> 1891 | D14: =VLOOKUP($A14,CASH_FLOW!$B$20:$L$56,7,FALSE) -> -382 | E14: =VLOOKUP($A14,CASH_FLOW!$B$20:$L$56,5,FALSE) -> 1938 | F14: =VLOOKUP($A14,CASH_FLOW!$B$20:$L$56,3,FALSE) -> 404 | G14: =Forecast!K44-Forecast!J44 -> 1568.1639 | H14: =Forecast!L44-Forecast!K44 -> 1692.4979 | I14: =Forecast!M44-Forecast!L44 -> 1826.6924
A15: Other operating assets and liabilities, net | B15: =VLOOKUP(A15,CASH_FLOW!$B$20:$L$56,11,FALSE) -> 1057 | C15: =VLOOKUP($A15,CASH_FLOW!$B$20:$L$56,9,FALSE) -> 549 | D15: =VLOOKUP($A15,CASH_FLOW!$B$20:$L$56,7,FALSE) -> 172 | E15: =VLOOKUP($A15,CASH_FLOW!$B$20:$L$56,5,FALSE) -> 741 | F15: =VLOOKUP($A15,CASH_FLOW!$B$20:$L$56,3,FALSE) -> 801 | G15: =(Forecast!I33-Forecast!J33)+(Forecast!I39-Forecast!J39)+(Forecast!J45-Forecast!I45)+(Forecast!J46-Forecast!I46)+(Forecast!J47-Forecast!I47)+(Forecast!J48-Forecast!I48) -> 692 | H15: =(Forecast!J33-Forecast!K33)+(Forecast!J39-Forecast!K39)+(Forecast!K45-Forecast!J45)+(Forecast!K46-Forecast!J46)+(Forecast!K47-Forecast!J47)+(Forecast!K48-Forecast!J48)+1000 -> 2137.8824 | I15: =(Forecast!K33-Forecast!L33)+(Forecast!K39-Forecast!L39)+(Forecast!L45-Forecast!K45)+(Forecast!L46-Forecast!K46)+(Forecast!L47-Forecast!K47)+(Forecast!L48-Forecast!K48) -> 1260.9688
A16: Net cash provided by operating activities | B16: =VLOOKUP(A16,CASH_FLOW!$B$20:$L$56,11,FALSE) -> 8958 | C16: =VLOOKUP($A16,CASH_FLOW!$B$20:$L$56,9,FALSE) -> 7392 | D16: =VLOOKUP($A16,CASH_FLOW!$B$20:$L$56,7,FALSE) -> 11068 | E16: =VLOOKUP($A16,CASH_FLOW!$B$20:$L$56,5,FALSE) -> 11339 | F16: =VLOOKUP($A16,CASH_FLOW!$B$20:$L$56,3,FALSE) -> 13335 | G16: =SUM(G7:G15)+G4 -> 12923.26 | H16: =SUM(H7:H15)+H4 -> 15407.231 | I16: =SUM(I7:I15)+I4 -> 15648.106
A17: CASH FLOWS FROM INVESTING ACTIVITIES
A18: Additions to property and equipment | B18: =VLOOKUP(A18,CASH_FLOW!$B$20:$L$56,11,FALSE) -> -3588 | C18: =VLOOKUP($A18,CASH_FLOW!$B$20:$L$56,9,FALSE) -> -3891 | D18: =VLOOKUP($A18,CASH_FLOW!$B$20:$L$56,7,FALSE) -> -4323 | E18: =VLOOKUP($A18,CASH_FLOW!$B$20:$L$56,5,FALSE) -> -4710 | F18: =VLOOKUP($A18,CASH_FLOW!$B$20:$L$56,3,FALSE) -> -5498 | G18: =-Forecast!K137 -> -5933.8169 | H18: =-Forecast!L137 -> -6404.1881 | I18: =-Forecast!M137 -> -6911.854
A19: Purchases of short-term investments | B19: =VLOOKUP(A19,CASH_FLOW!$B$20:$L$56,11,FALSE) -> -1331 | C19: =VLOOKUP($A19,CASH_FLOW!$B$20:$L$56,9,FALSE) -> -1121 | D19: =VLOOKUP($A19,CASH_FLOW!$B$20:$L$56,7,FALSE) -> -1622 | E19: =VLOOKUP($A19,CASH_FLOW!$B$20:$L$56,5,FALSE) -> -1470 | F19: =VLOOKUP($A19,CASH_FLOW!$B$20:$L$56,3,FALSE) -> -1028 | G19: =F19 -> -1028 | H19: =G19 -> -1028 | I19: =H19-375.3 -> -1403.3
A20: Maturities of short-term investments | B20: =VLOOKUP(A20,CASH_FLOW!$B$20:$L$56,11,FALSE) -> 1446 | C20: =VLOOKUP($A20,CASH_FLOW!$B$20:$L$56,9,FALSE) -> 1145 | D20: =VLOOKUP($A20,CASH_FLOW!$B$20:$L$56,7,FALSE) -> 937 | E20: =VLOOKUP($A20,CASH_FLOW!$B$20:$L$56,5,FALSE) -> 1790 | F20: =VLOOKUP($A20,CASH_FLOW!$B$20:$L$56,3,FALSE) -> 1141 | G20: =F20 -> 1141 | H20: =G20 -> 1141 | I20: =H20 -> 1141
A21: Other investing activities, net | B21: =VLOOKUP(A21,CASH_FLOW!$B$20:$L$56,11,FALSE) -> -62 | C21: =VLOOKUP($A21,CASH_FLOW!$B$20:$L$56,9,FALSE) -> -48 | D21: =VLOOKUP($A21,CASH_FLOW!$B$20:$L$56,7,FALSE) -> 36 | E21: =VLOOKUP($A21,CASH_FLOW!$B$20:$L$56,5,FALSE) -> -19 | F21: =VLOOKUP($A21,CASH_FLOW!$B$20:$L$56,3,FALSE) -> 74 | G21: =F21 -> 74 | H21: =G21 -> 74 | I21: =H21 -> 74
A22: Net cash used in investing activities | B22: =VLOOKUP(A22,CASH_FLOW!$B$20:$L$56,11,FALSE) -> -3535 | C22: =VLOOKUP($A22,CASH_FLOW!$B$20:$L$56,9,FALSE) -> -3915 | D22: =VLOOKUP($A22,CASH_FLOW!$B$20:$L$56,7,FALSE) -> -4972 | E22: =VLOOKUP($A22,CASH_FLOW!$B$20:$L$56,5,FALSE) -> -4409 | F22: =VLOOKUP($A22,CASH_FLOW!$B$20:$L$56,3,FALSE) -> -5311 | G22: =SUM(G18:G21) -> -5746.8169 | H22: =SUM(H18:H21) -> -6217.1881 | I22: =SUM(I18:I21) -> -7100.154
A23: CASH FLOWS FROM FINANCING ACTIVITIES
A24: Repayments of short-term borrowings | B24: =VLOOKUP(A24,CASH_FLOW!$B$20:$L$56,11,FALSE) -> 0 | C24: =VLOOKUP($A24,CASH_FLOW!$B$20:$L$56,9,FALSE) -> -6 | D24: =VLOOKUP($A24,CASH_FLOW!$B$20:$L$56,7,FALSE) -> -935 | E24: =VLOOKUP($A24,CASH_FLOW!$B$20:$L$56,5,FALSE) -> -920 | F24: =VLOOKUP($A24,CASH_FLOW!$B$20:$L$56,3,FALSE) -> -862 | G24: =-816 -> -816 | H24: =-G25 -> 0 | I24: =-H25 -> 0
A25: Proceeds from short-term borrowings | B25: =VLOOKUP(A25,CASH_FLOW!$B$20:$L$56,11,FALSE) -> 41 | C25: =VLOOKUP($A25,CASH_FLOW!$B$20:$L$56,9,FALSE) -> 53 | D25: =VLOOKUP($A25,CASH_FLOW!$B$20:$L$56,7,FALSE) -> 917 | E25: =VLOOKUP($A25,CASH_FLOW!$B$20:$L$56,5,FALSE) -> 928 | F25: =VLOOKUP($A25,CASH_FLOW!$B$20:$L$56,3,FALSE) -> 816 | G25: 0 | H25: 0 | I25: 0 | L25: Linked toAdditional Financing needs
A26: Repayments of long-term debt | B26: =VLOOKUP(A26,CASH_FLOW!$B$20:$L$56,11,FALSE) -> -94 | C26: =VLOOKUP($A26,CASH_FLOW!$B$20:$L$56,9,FALSE) -> -800 | D26: =VLOOKUP($A26,CASH_FLOW!$B$20:$L$56,7,FALSE) -> -75 | E26: =VLOOKUP($A26,CASH_FLOW!$B$20:$L$56,5,FALSE) -> -1077 | F26: =VLOOKUP($A26,CASH_FLOW!$B$20:$L$56,3,FALSE) -> -103 | G26: =Forecast!K113 -> -75 | H26: =Forecast!L113 -> -2250 | I26: =Forecast!M113 -> 0 | K26: 1962 | L26: Amount in millions left for share repurchase program expiring in January 2027 (Fiscal year 2028)
A27: Proceeds from issuance of long-term debt | B27: =VLOOKUP(A27,CASH_FLOW!$B$20:$L$56,11,FALSE) -> 0 | C27: =VLOOKUP($A27,CASH_FLOW!$B$20:$L$56,9,FALSE) -> 0 | D27: =VLOOKUP($A27,CASH_FLOW!$B$20:$L$56,7,FALSE) -> 0 | E27: =VLOOKUP($A27,CASH_FLOW!$B$20:$L$56,5,FALSE) -> 498 | F27: =VLOOKUP($A27,CASH_FLOW!$B$20:$L$56,3,FALSE) -> 0 | G27: 0 | H27: 0 | I27: 0
A28: Tax withholdings on stock-based awards | B28: =VLOOKUP(A28,CASH_FLOW!$B$20:$L$56,11,FALSE) -> -312 | C28: =VLOOKUP($A28,CASH_FLOW!$B$20:$L$56,9,FALSE) -> -363 | D28: =VLOOKUP($A28,CASH_FLOW!$B$20:$L$56,7,FALSE) -> -303 | E28: =VLOOKUP($A28,CASH_FLOW!$B$20:$L$56,5,FALSE) -> -315 | F28: =VLOOKUP($A28,CASH_FLOW!$B$20:$L$56,3,FALSE) -> -393 | G28: =-$K$28*G9 -> -421.98296 | H28: =-$K$28*H9 -> -455.43338 | I28: =-$K$28*I9 -> -491.536 | K28: =-F28/F9 -> 0.45697674
A29: Repurchases of common stock | B29: =VLOOKUP(A29,CASH_FLOW!$B$20:$L$56,11,FALSE) -> -496 | C29: =VLOOKUP($A29,CASH_FLOW!$B$20:$L$56,9,FALSE) -> -439 | D29: =VLOOKUP($A29,CASH_FLOW!$B$20:$L$56,7,FALSE) -> -676 | E29: =VLOOKUP($A29,CASH_FLOW!$B$20:$L$56,5,FALSE) -> -700 | F29: =VLOOKUP($A29,CASH_FLOW!$B$20:$L$56,3,FALSE) -> -903 | G29: =-1558.5 -> -1558.5 | H29: =0 -> 0 | I29: =-(K26-1559) -> -403
A30: Cash dividend payments | B30: =VLOOKUP(A30,CASH_FLOW!$B$20:$L$56,11,FALSE) -> -5748 | C30: =VLOOKUP($A30,CASH_FLOW!$B$20:$L$56,9,FALSE) -> -1498 | D30: =VLOOKUP($A30,CASH_FLOW!$B$20:$L$56,7,FALSE) -> -1251 | E30: =VLOOKUP($A30,CASH_FLOW!$B$20:$L$56,5,FALSE) -> -9041 | F30: =VLOOKUP($A30,CASH_FLOW!$B$20:$L$56,3,FALSE) -> -2183 | G30: =$K$30*-G4 -> -2205.4664 | H30: =$K$30*-H4 -> -2379.5788 | I30: =$K$30*-I4 -> -2566.7945 | K30: =-F30/F4 -> 0.26953945 | L30: Dividend payout ratio
A31: Financing lease payments and other financing activities net | B31: -67 | C31: -176 | D31: -291 | E31: -137 | F31: -147 | G31: =-133 -> -133 | H31: -132 | I31: =-135 -> -135 | L31: Note 5: Lease repayment schedule 10k
A32: Dividend to noncontrolling interest | B32: =VLOOKUP(A32,CASH_FLOW!$B$20:$L$56,11,FALSE) -> 0 | C32: =VLOOKUP($A32,CASH_FLOW!$B$20:$L$56,9,FALSE) -> -208 | D32: =VLOOKUP($A32,CASH_FLOW!$B$20:$L$56,7,FALSE) -> 0 | E32: =VLOOKUP($A32,CASH_FLOW!$B$20:$L$56,5,FALSE) -> 0 | F32: =VLOOKUP($A32,CASH_FLOW!$B$20:$L$56,3,FALSE) -> 0 | G32: 0 | H32: 0 | I32: 0
A33: Acquisition of noncontrolling interest | B33: =VLOOKUP(A33,CASH_FLOW!$B$20:$L$56,11,FALSE) -> 0 | C33: =VLOOKUP($A33,CASH_FLOW!$B$20:$L$56,9,FALSE) -> -842 | D33: =VLOOKUP($A33,CASH_FLOW!$B$20:$L$56,7,FALSE) -> 0 | E33: =VLOOKUP($A33,CASH_FLOW!$B$20:$L$56,5,FALSE) -> 0 | F33: =VLOOKUP($A33,CASH_FLOW!$B$20:$L$56,3,FALSE) -> 0 | G33: 0 | H33: 0 | I33: 0
A34: Other financing activities, net | B34: =VLOOKUP(A34,CASH_FLOW!$B$20:$L$56,11,FALSE) -> 188 | C34: =VLOOKUP($A34,CASH_FLOW!$B$20:$L$56,9,FALSE) -> -4 | D34: =VLOOKUP($A34,CASH_FLOW!$B$20:$L$56,7,FALSE) -> 0 | E34: =VLOOKUP($A34,CASH_FLOW!$B$20:$L$56,5,FALSE) -> 0 | F34: =VLOOKUP($A34,CASH_FLOW!$B$20:$L$56,3,FALSE) -> 0 | G34: 0 | H34: 0 | I34: 0
A35: Net cash used in financing activities | B35: =VLOOKUP(A35,CASH_FLOW!$B$20:$L$56,11,FALSE) -> -6488 | C35: =VLOOKUP($A35,CASH_FLOW!$B$20:$L$56,9,FALSE) -> -4283 | D35: =VLOOKUP($A35,CASH_FLOW!$B$20:$L$56,7,FALSE) -> -2614 | E35: =VLOOKUP($A35,CASH_FLOW!$B$20:$L$56,5,FALSE) -> -10764 | F35: =VLOOKUP($A35,CASH_FLOW!$B$20:$L$56,3,FALSE) -> -3775 | G35: =SUM(G24:G34) -> -5209.9493 | H35: =SUM(H24:H34) -> -5217.0121 | I35: =SUM(I24:I34) -> -3596.3305
A36: EFFECT OF EXCHANGE RATE CHANGES ON CASH AND CASH
A37: EQUIVALENTS | B37: =VLOOKUP(A37,CASH_FLOW!$B$20:$L$56,11,FALSE) -> 46 | C37: =VLOOKUP($A37,CASH_FLOW!$B$20:$L$56,9,FALSE) -> -249 | D37: =VLOOKUP($A37,CASH_FLOW!$B$20:$L$56,7,FALSE) -> 15 | E37: =VLOOKUP($A37,CASH_FLOW!$B$20:$L$56,5,FALSE) -> 40 | F37: =VLOOKUP($A37,CASH_FLOW!$B$20:$L$56,3,FALSE) -> 6 | G37: 6 | H37: 6 | I37: 6
A38: Net change in cash and cash equivalents | B38: =SUM(B35,B22,B16)+B37 -> -1019 | C38: =SUM(C35,C22,C16)+C37 -> -1055 | D38: =SUM(D35,D22,D16)+D37 -> 3497 | E38: =SUM(E35,E22,E16)+E37 -> -3794 | F38: =SUM(F35,F22,F16)+F37 -> 4255 | G38: =SUM(G35,G22,G16)+G37 -> 1972.4936 | H38: =SUM(H35,H22,H16)+H37 -> 3979.0311 | I38: =SUM(I35,I22,I16)+I37 -> 4957.6217
A39: CASH AND CASH EQUIVALENTS BEGINNING OF YEAR | B39: =VLOOKUP(A39,CASH_FLOW!$B$20:$L$56,11,FALSE) -> 12277 | C39: =B40 -> 11258 | D39: =C40 -> 10203 | E39: =D40 -> 13700 | F39: =E40 -> 9906 | G39: =F40 -> 14161 | H39: =G40 -> 16133.494 | I39: =H40 -> 20112.525
A40: CASH AND CASH EQUIVALENTS END OF YEAR | B40: =B38+B39 -> 11258 | C40: =C38+C39 -> 10203 | D40: =D38+D39 -> 13700 | E40: =E38+E39 -> 9906 | F40: =F38+F39 -> 14161 | G40: =G38+G39 -> 16133.494 | H40: =H38+H39 -> 20112.525 | I40: =I38+I39 -> 25070.146
A41: Additional Financing Needs surplus | G41: =-AFN!D15 -> 2108.7305 | H41: =-AFN!E15 -> 2040.1946 | I41: =-AFN!F15 -> 2174.7428
A44: This can be used by the company to pay special dividends in 2026, 2027 and 2028 | D44: Special dividends per share | G44: =G41/('Valuation DCF '!$B$26/10^6) -> 4.750784 | H44: =H41/('Valuation DCF '!$B$26/10^6) -> 4.5963787 | I44: =I41/('Valuation DCF '!$B$26/10^6) -> 4.8995039
A60: Inventory | G60: =BALANCE_SHEET!G68*(Forecast!K12/365) -> 19617.812

Sheet WCM
A2: Selected Ratios for Costco | B2: Formulas Used | C2: 2025 | D2: 2024 | E2: 2023 | F2: 2022 | G2: 2021 | H2: 5-Year Avg
A3: Current Ratio | B3: CA/CL | C3: =BALANCE_SHEET!D25/BALANCE_SHEET!D39 -> 1.0342783 | D3: =BALANCE_SHEET!F25/BALANCE_SHEET!F39 -> 0.96565531 | E3: =BALANCE_SHEET!H25/BALANCE_SHEET!H39 -> 1.0683679 | F3: =BALANCE_SHEET!J25/BALANCE_SHEET!J39 -> 1.0218139 | G3: =BALANCE_SHEET!L25/BALANCE_SHEET!L39 -> 1.0021738 | H3: =AVERAGE(C3:G3) -> 1.0184579
A4: Quick Ratio | B4: (Cash+Marketable Securities +Receivables)/CL | C4: =(BALANCE_SHEET!D20+BALANCE_SHEET!D22+BALANCE_SHEET!D21)/BALANCE_SHEET!D39 -> 0.49819446 | D4: =(BALANCE_SHEET!F20+BALANCE_SHEET!F22+BALANCE_SHEET!F21)/BALANCE_SHEET!F39 -> 0.39095985 | E4: =(BALANCE_SHEET!H20+BALANCE_SHEET!H22+BALANCE_SHEET!H21)/BALANCE_SHEET!H39 -> 0.52166275 | F4: =(BALANCE_SHEET!J20+BALANCE_SHEET!J22+BALANCE_SHEET!J21)/BALANCE_SHEET!J39 -> 0.41533846 | G4: =(BALANCE_SHEET!L20+BALANCE_SHEET!L22+BALANCE_SHEET!L21)/BALANCE_SHEET!L39 -> 0.47478007 | H4: =AVERAGE(C4:G4) -> 0.46018712
A5: TL/Assets | B5: Total Liabilities/Total Assets | C5: =(BALANCE_SHEET!D41+BALANCE_SHEET!D42)/BALANCE_SHEET!D30 -> 0.10600656 | D5: =(BALANCE_SHEET!F41+BALANCE_SHEET!F42)/BALANCE_SHEET!F30 -> 0.11698243 | E5: =(BALANCE_SHEET!H41+BALANCE_SHEET!H42)/BALANCE_SHEET!H30 -> 0.11309679 | F5: =(BALANCE_SHEET!J41+BALANCE_SHEET!J42)/BALANCE_SHEET!J30 -> 0.13973132 | G5: =(BALANCE_SHEET!L41+BALANCE_SHEET!L42)/BALANCE_SHEET!L30 -> 0.15748802 | H5: =AVERAGE(C5:G5) -> 0.12666103
A6: Inventory Turnover | B6: COGS/Inventory | C6: =INCOME_STATEMENT!D24/((BALANCE_SHEET!D23+BALANCE_SHEET!F23)/2) -> 13.050404 | D6: =INCOME_STATEMENT!F24/((BALANCE_SHEET!F23+BALANCE_SHEET!H23)/2) -> 12.598901 | E6: =INCOME_STATEMENT!H24/((BALANCE_SHEET!H23+BALANCE_SHEET!J23)/2) -> 12.303143 | F6: =INCOME_STATEMENT!J24/((BALANCE_SHEET!J23+BALANCE_SHEET!L23)/2) -> 12.414046 | G6: =INCOME_STATEMENT!L24/((BALANCE_SHEET!L23+BALANCE_SHEET!N23)/2) -> 12.902748 | H6: =AVERAGE(C6:G6) -> 12.653848
A7: Cash Turnover | B7: Net Sales/Cash and cash equivalents | C7: {=_xludf.XLOOKUP(C$2,INCOME_STATEMENT!$18:$18,INCOME_STATEMENT!20:20)/((_xludf.XLOOKUP(C$2,BALANCE_SHEET!$17:$17,BALANCE_SHEET!20:20)+(_xludf.XLOOKUP(C$2,BALANCE_SHEET!$17:$17,BALANCE_SHEET!$21:$21)+(_xludf.XLOOKUP(C$2,BALANCE_SHEET!$17:$17,BALANCE_SHEET!$22:$22)))))} -> #NAME? | D7: {=_xludf.XLOOKUP(D$2,INCOME_STATEMENT!$18:$18,INCOME_STATEMENT!20:20)/((_xludf.XLOOKUP(D$2,BALANCE_SHEET!$17:$17,BALANCE_SHEET!20:20)+(_xludf.XLOOKUP(D$2,BALANCE_SHEET!$17:$17,BALANCE_SHEET!$21:$21)+(_xludf.XLOOKUP(D$2,BALANCE_SHEET!$17:$17,BALANCE_SHEET!$22:$22)))))} -> #NAME? | E7: {=_xludf.XLOOKUP(E$2,INCOME_STATEMENT!$18:$18,INCOME_STATEMENT!20:20)/((_xludf.XLOOKUP(E$2,BALANCE_SHEET!$17:$17,BALANCE_SHEET!20:20)+(_xludf.XLOOKUP(E$2,BALANCE_SHEET!$17:$17,BALANCE_SHEET!$21:$21)+(_xludf.XLOOKUP(E$2,BALANCE_SHEET!$17:$17,BALANCE_SHEET!$22:$22)))))} -> #NAME? | F7: {=_xludf.XLOOKUP(F$2,INCOME_STATEMENT!$18:$18,INCOME_STATEMENT!20:20)/((_xludf.XLOOKUP(F$2,BALANCE_SHEET!$17:$17,BALANCE_SHEET!20:20)+(_xludf.XLOOKUP(F$2,BALANCE_SHEET!$17:$17,BALANCE_SHEET!$21:$21)+(_xludf.XLOOKUP(F$2,BALANCE_SHEET!$17:$17,BALANCE_SHEET!$22:$22)))))} -> #NAME? | G7: {=_xludf.XLOOKUP(G$2,INCOME_STATEMENT!$18:$18,INCOME_STATEMENT!20:20)/((_xludf.XLOOKUP(G$2,BALANCE_SHEET!$17:$17,BALANCE_SHEET!20:20)+(_xludf.XLOOKUP(G$2,BALANCE_SHEET!$17:$17,BALANCE_SHEET!$21:$21)+(_xludf.XLOOKUP(G$2,BALANCE_SHEET!$17:$17,BALANCE_SHEET!$22:$22)))))} -> #NAME? | H7: {=_xludf.XLOOKUP(H$2,INCOME_STATEMENT!$18:$18,INCOME_STATEMENT!20:20)/((_xludf.XLOOKUP(H$2,BALANCE_SHEET!$17:$17,BALANCE_SHEET!20:20)+(_xludf.XLOOKUP(H$2,BALANCE_SHEET!$17:$17,BALANCE_SHEET!$21:$21)+(_xludf.XLOOKUP(H$2,BALANCE_SHEET!$17:$17,BALANCE_SHEET!$22:$22)))))} -> #NAME?
A8: Fixed Asset Turnover | B8: Net Sales/Avg Net FA | C8: =INCOME_STATEMENT!D20/((BALANCE_SHEET!D27+BALANCE_SHEET!F27)/2) -> 8.8581415 | D8: 8.96 | E8: =INCOME_STATEMENT!H20/((BALANCE_SHEET!H27+BALANCE_SHEET!J27)/2) -> 9.26203 | F8: =INCOME_STATEMENT!J20/((BALANCE_SHEET!J27+BALANCE_SHEET!L27)/2) -> 9.253812 | G8: =INCOME_STATEMENT!L20/((BALANCE_SHEET!L27+BALANCE_SHEET!N27)/2) -> 16.350417 | H8: =AVERAGE(C8:G8) -> 10.53688
A9: Total Asset Turnover | B9: Net Sales/Avg Total Assets | C9: =INCOME_STATEMENT!D20/((BALANCE_SHEET!D30+BALANCE_SHEET!F30)/2) -> 3.6740216 | D9: =INCOME_STATEMENT!F20/((BALANCE_SHEET!F30+BALANCE_SHEET!H30)/2) -> 3.5962543 | E9: =INCOME_STATEMENT!H20/((BALANCE_SHEET!H30+BALANCE_SHEET!J30)/2) -> 3.5702914 | F9: =INCOME_STATEMENT!J20/((BALANCE_SHEET!J30+BALANCE_SHEET!L30)/2) -> 3.6088922 | G9: =INCOME_STATEMENT!L20/((BALANCE_SHEET!L30+BALANCE_SHEET!N30)/2) -> 3.3451543 | H9: =AVERAGE(C9:G9) -> 3.5589228
A10: Gross Profit Margin | B10: (Net Sales - COGS)/Net Sales | C10: =(INCOME_STATEMENT!D20-INCOME_STATEMENT!D24)/INCOME_STATEMENT!D20 -> 0.11124366 | D10: =(INCOME_STATEMENT!F20-INCOME_STATEMENT!F24)/INCOME_STATEMENT!F20 -> 0.10923185 | E10: =(INCOME_STATEMENT!H20-INCOME_STATEMENT!H24)/INCOME_STATEMENT!H20 -> 0.10569181 | F10: =(INCOME_STATEMENT!J20-INCOME_STATEMENT!J24)/INCOME_STATEMENT!J20 -> 0.10482647 | G10: =(INCOME_STATEMENT!L20-INCOME_STATEMENT!L24)/INCOME_STATEMENT!L20 -> 0.11126153 | H10: =AVERAGE(C10:G10) -> 0.10845107
A11: Net Profit Margin | B11: Net Income/Net Sales | C11: =INCOME_STATEMENT!D33/INCOME_STATEMENT!D20 -> 0.030006076 | D11: =INCOME_STATEMENT!F33/INCOME_STATEMENT!F20 -> 0.029512268 | E11: =INCOME_STATEMENT!H33/INCOME_STATEMENT!H20 -> 0.026469227 | F11: =INCOME_STATEMENT!J33/INCOME_STATEMENT!J20 -> 0.026556818 | G11: =INCOME_STATEMENT!L33/INCOME_STATEMENT!L20 -> 0.026445963 | H11: =AVERAGE(C11:G11) -> 0.02779807
A12: Return on Equity | B12: Net Income/Equity | C12: =INCOME_STATEMENT!D33/BALANCE_SHEET!D56 -> 0.27770539 | D12: =INCOME_STATEMENT!F33/BALANCE_SHEET!F56 -> 0.31187029 | E12: =INCOME_STATEMENT!H33/BALANCE_SHEET!H56 -> 0.25109745 | F12: =INCOME_STATEMENT!J33/BALANCE_SHEET!J56 -> 0.2864823 | G12: =INCOME_STATEMENT!L33/BALANCE_SHEET!L56 -> 0.28094922 | H12: =AVERAGE(C12:G12) -> 0.28162093
C14: 2025 | D14: 2024 | E14: 2023 | F14: 2022 | G14: 2021 | H14: 5-Year Avg
A15: Cash Conversion Cycle | B15: ICP + DSO - PDP | C15: =C16+C17-C18 -> 1.7949592 | D15: =D16+D17-D18 -> 2.7081092 | E15: =E16+E17-E18 -> 2.0800777 | F15: =F16+F17-F18 -> 3.7804597 | G15: =G16+G17-G18 -> -0.98498195 | H15: =AVERAGE(C15:G15) -> 1.8757248
A16: Inventory Conversion Period | B16: Inventory/(COGS/365) | C16: =BALANCE_SHEET!D23/(INCOME_STATEMENT!D24/365) -> 27.56451 | D16: =BALANCE_SHEET!F23/(INCOME_STATEMENT!F24/365) -> 30.608995 | E16: =BALANCE_SHEET!H23/(INCOME_STATEMENT!H24/365) -> 28.588971 | F16: =BALANCE_SHEET!J23/(INCOME_STATEMENT!J24/365) -> 32.78157 | G16: =BALANCE_SHEET!L23/(INCOME_STATEMENT!L24/365) -> 30.398133 | H16: =AVERAGE(C16:G16) -> 29.988436
A17: Days Sales Outstanding (DSO) | B17: AR/(Sales/365) | C17: =BALANCE_SHEET!D22/(INCOME_STATEMENT!D20/365) -> 4.3313932 | D17: =BALANCE_SHEET!F22/(INCOME_STATEMENT!F20/365) -> 3.9786279 | E17: =BALANCE_SHEET!H22/(INCOME_STATEMENT!H20/365) -> 3.5085819 | F17: =BALANCE_SHEET!J22/(INCOME_STATEMENT!J20/365) -> 3.6724509 | G17: =BALANCE_SHEET!L22/(INCOME_STATEMENT!L20/365) -> 3.4266501 | H17: =AVERAGE(C17:G17) -> 3.7835408
A18: Payables Deferral Period | B18: AP/(COGS/365) | C18: =BALANCE_SHEET!D33/(INCOME_STATEMENT!D24/365) -> 30.100944 | D18: =BALANCE_SHEET!F33/(INCOME_STATEMENT!F24/365) -> 31.879514 | E18: =BALANCE_SHEET!H33/(INCOME_STATEMENT!H24/365) -> 30.017475 | F18: =BALANCE_SHEET!J33/(INCOME_STATEMENT!J24/365) -> 32.673561 | G18: =BALANCE_SHEET!L33/(INCOME_STATEMENT!L24/365) -> 34.809765 | H18: =AVERAGE(C18:G18) -> 31.896252
A20: Company Comparisons in 2024 | B20: CCC | C20: ICP | D20: DSO | E20: PDP
A21: Costco | B21: 2.7081092 | C21: 30.608995 | D21: 3.9786279 | E21: 31.879514
A22: Averages w/ Amazon | B22: =SUM(B26:B29)/4 -> -2.1479727 | C22: =SUM(C26:C29)/4 -> 43.077249 | D22: =SUM(D26:D29)/4 -> 10.944657 | E22: =SUM(E26:E29)/4 -> 56.169879
A23: Averages w/o Amazon | B23: =SUM(B26:B28)/3 -> 6.6693697 | C23: =SUM(C26:C28)/3 -> 43.902998 | D23: =SUM(D26:D28)/3 -> 4.6595426 | E23: =SUM(E26:E28)/3 -> 41.893171
A25: Company Comparisons in 2024 | B25: CCC | C25: ICP | D25: DSO | E25: PDP
A26: Costco | B26: =D15 -> 2.7081092 | C26: =D16 -> 30.608995 | D26: =D17 -> 3.9786279 | E26: =D18 -> 31.879514
A27: Walmart | B27: =C27+D27-E27 -> 5 | C27: 41.5 | D27: 4.7 | E27: 41.2
A28: Target | B28: =C28+D28-E28 -> 12.3 | C28: 59.6 | D28: 5.3 | E28: 52.6
A29: Amazon | B29: =C29+D29-E29 -> -28.6 | C29: 40.6 | D29: 29.8 | E29: 99

Sheet INCOME_STATEMENT
A1: Created by EDGAR Online, Inc.
A3: COSTCO WHOLESALE CORP /NEW
A4: INCOME_STATEMENT
A5: Form Type: 10-K
A6: Period End: Aug 31, 2025
A7: Date Filed: Oct 08, 2025
A8: Table Of Contents
B10: COSTCO WHOLESALE CORPORATION
B12: CONSOLIDATED STATEMENTS OF INCOME
B14: (amounts in millions, except per share data)
C16: 52 | D16: Weeks Ended | E16: 52 | F16: Weeks Ended | G16: 53 | H16: Weeks Ended | I16: 52 | J16: Weeks Ended | K16: 52 | L16: Weeks Ended
D17: August 31, | F17: September 1, | H17: September 3, | J17: August 28, | L17: August 29,
D18: 2025 | F18: 2024 | H18: 2023 | J18: 2022 | L18: 2021
B19: REVENUE
B20: Net sales | D20: 269912 | F20: 249625 | H20: 237710 | J20: 222730 | L20: 192052
B21: Membership fees | D21: 5323 | F21: 4828 | H21: 4580 | J21: 4224 | L21: 3877
B22: Total revenue | D22: 275235 | F22: 254453 | H22: 242290 | J22: 226954 | L22: 195929
B23: OPERATING EXPENSES
B24: Merchandise costs | D24: 239886 | F24: 222358 | H24: 212586 | J24: 199382 | L24: 170684
B25: Selling, general and administrative | D25: 24966 | F25: 22810 | H25: 21590 | J25: 19779 | L25: 18537
B26: Operating income | D26: 10383 | F26: 9285 | H26: 8114 | J26: 7793 | L26: 6708
B27: OTHER INCOME (EXPENSE)
B28: Interest expense | D28: -154 | F28: -169 | H28: -160 | J28: -158 | L28: -171
B29: Interest income and other, net | D29: 589 | F29: 624 | H29: 533 | J29: 205 | L29: 143
B30: INCOME BEFORE INCOME TAXES | D30: 10818 | F30: 9740 | H30: 8487 | J30: 7840 | L30: 6680
B31: Provision for income taxes | D31: 2719 | F31: 2373 | H31: 2195 | J31: 1925 | L31: 1601
B33: NET INCOME | D33: 8099 | F33: 7367 | H33: 6292 | J33: 5915 | L33: 5079
B34: NET INCOME PER COMMON SHARE:
B35: Basic | D35: 18.24 | F35: 16.59 | H35: 14.18 | J35: 13.17 | L35: 11.3
B36: Diluted | D36: 18.21 | F36: 16.56 | H36: 14.16 | J36: 13.14 | L36: 11.27
B37: Shares used in calculation (000's)
B38: Basic | D38: 443985 | F38: 443914 | H38: 443854 | J38: 443651 | L38: 443089
B39: Diluted | D39: 444803 | F39: 444759 | H39: 444452 | J39: 444757 | L39: 444346
B41: Gross Profit | D41: =D22-D24 -> 35349 | F41: =F22-F24 -> 32095 | H41: =H22-H24 -> 29704 | J41: =J22-J24 -> 27572 | L41: =L22-L24 -> 25245
B43: From Factset
B44: EBITDA | D44: 12809 | F44: 11522 | H44: 10603 | J44: 10070 | L44: 9366
B45: EBIT | D45: 10383 | F45: 9285 | H45: 8114 | J45: 7793 | L45: 7299
B47: Tax rate | D47: 0.251 | F47: 0.244 | H47: 0.259 | J47: 0.25 | L47: 0.246
B48: NOPAT | D48: =D33-((D29+D28)*(1-D47)) -> 7773.185 | F48: =F33-((F29+F28)*(1-F47)) -> 7023.02 | H48: =H33-((H29+H28)*(1-H47)) -> 6015.607 | J48: =J33-((J29+J28)*(1-J47)) -> 5879.75 | L48: =L33-((L29+L28)*(1-L47)) -> 5100.112
D49: 0.22
B50: NOPAT at 22% Tax Rate | D50: =D33-((D29+D28)*(1-$D$49)) -> 7759.7 | E50: =D33-((D29+D28)*(1-$D$49)) -> 7759.7 | F50: =F33-((F29+F28)*(1-$D$49)) -> 7012.1 | H50: =H33-((H29+H28)*(1-$D$49)) -> 6001.06 | I50: =I33-((I29+I28)*(1-$D$49)) -> 0 | J50: =J33-((J29+J28)*(1-$D$49)) -> 5878.34 | L50: =L33-((L29+L28)*(1-$D$49)) -> 5100.84

Sheet BALANCE_SHEET
A1: Created by EDGAR Online, Inc.
A3: COSTCO WHOLESALE CORP /NEW
A4: BALANCE_SHEET
A5: Form Type: 10-K
A6: Period End: Aug 31, 2025
A7: Date Filed: Oct 08, 2025
A8: Table Of Contents
B10: COSTCO WHOLESALE CORPORATION
B12: CONSOLIDATED BALANCE SHEETS
B14: (amounts in millions, except par value and share data)
D16: August 31, | F16: September 1, | H16: September 3, | J16: August 28, | L16: August 29, | N16: August 30,
D17: 2025 | F17: 2024 | H17: 2023 | J17: 2022 | L17: 2021 | N17: 2020
B18: ASSETS
B19: CURRENT ASSETS
B20: Cash and cash equivalents | D20: 14161 | F20: 9906 | H20: 13700 | J20: 10203 | L20: 11258
B21: Short-term investments | D21: 1123 | F21: 1238 | H21: 1534 | J21: 846 | L21: 917
B22: Receivables, net | D22: 3203 | F22: 2721 | H22: 2285 | J22: 2241 | L22: 1803
B23: Merchandise inventories | D23: 18116 | F23: 18647 | H23: 16651 | J23: 17907 | L23: 14215 | N23: 12242
B24: Other current assets | D24: 1777 | F24: 1734 | H24: 1709 | J24: 1499 | L24: 1312
B25: Total current assets | D25: 38380 | F25: 34246 | H25: 35879 | J25: 32696 | L25: 29505
B26: OTHER ASSETS
B27: Property and equipment, net | D27: 31909 | F27: 29032 | H27: 26684 | J27: 24646 | L27: 23492
B28: Operating lease right-of-use assets | D28: 2725 | F28: 2617 | H28: 2713 | J28: 2774 | L28: 2890
B29: Other long-term assets | D29: 4085 | F29: 3936 | H29: 3718 | J29: 4050 | L29: 3381
B30: TOTAL ASSETS | D30: 77099 | F30: 69831 | H30: 68994 | J30: 64166 | L30: 59268 | N30: 55556
B31: LIABILITIES AND EQUITY
B32: CURRENT LIABILITIES
B33: Accounts payable | D33: 19783 | F33: 19421 | H33: 17483 | J33: 17848 | L33: 16278
B34: Accrued salaries and benefits | D34: 5205 | F34: 4794 | H34: 4278 | J34: 4381 | L34: 4090
B35: Accrued member rewards | D35: 2677 | F35: 2435 | H35: 2150 | J35: 1911 | L35: 1671
B36: Deferred membership fees | D36: 2854 | F36: 2501 | H36: 2337 | J36: 2174 | L36: 2042
H37: 1081 | J37: 73 | L37: 799
B38: Other current liabilities | D38: 6589 | F38: 6313 | H38: 6254 | J38: 5611 | L38: 4561
B39: Total current liabilities | D39: 37108 | F39: 35464 | H39: 33583 | J39: 31998 | L39: 29441
B40: OTHER LIABILITIES
B41: Long-term debt, excluding current portion | D41: 5713 | F41: 5794 | H41: 5377 | J41: 6484 | L41: 6692
B42: Long-term operating lease liabilities | D42: 2460 | F42: 2375 | H42: 2426 | J42: 2482 | L42: 2642
B43: Other long-term liabilities | D43: 2654 | F43: 2576 | H43: 2550 | J43: 2555 | L43: 2415
B44: TOTAL LIABILITIES | D44: 47935 | F44: 46209 | H44: 43936 | J44: 43519 | L44: 41190
B45: COMMITMENTS AND CONTINGENCIES
B46: EQUITY
B47: Preferred stock $0.005 par value; 100,000,000 shares
B48: authorized; no shares issued and outstanding | D48: 0 | F48: 0 | H48: 0 | J48: 0 | L48: 0
B49: Common stock $0.005 par value; 900,000,000 shares
B50: authorized; 443,237,000 and 443,126,000 shares issued and
B51: outstanding | D51: 2 | F51: 2 | H51: 2 | J51: 2 | L51: 4
B52: Additional paid-in capital | D52: 8282 | F52: 7829 | H52: 7340 | J52: 6884 | L52: 7031
B53: Accumulated other comprehensive loss | D53: -1770 | F53: -1828 | H53: -1805 | J53: -1829 | L53: -1137
B54: Retained earnings | D54: 22650 | F54: 17619 | H54: 19521 | J54: 15585 | L54: 11666
B56: TOTAL EQUITY | D56: 29164 | F56: 23622 | H56: 25058 | J56: 20647 | L56: 18078 | N56: 18705
B57: TOTAL LIABILITIES AND EQUITY | D57: 77099 | F57: 69831 | H57: 68994 | J57: 64166 | L57: 59268
B59: Operating Asset | D59: =D30-D21-D20 -> 61815 | F59: =F30-F21-F20 -> 58687 | H59: =H30-H21-H20 -> 53760 | J59: =J30-J21-J20 -> 53117 | L59: =L30-L21-L20 -> 47093
B60: Oerating liability | D60: =D44-D41-D42 -> 39762 | F60: =F44-F41-F42 -> 38040 | H60: =H44-H41-H42 -> 36133 | J60: =J44-J41-J42 -> 34553 | L60: =L44-L41-L42 -> 31856
B61: NOA | D61: =D59-D60 -> 22053 | F61: =F59-F60 -> 20647 | H61: =H59-H60 -> 17627 | J61: =J59-J60 -> 18564 | L61: =L59-L60 -> 15237
G65: 2025
B66: DSO | G66: =Forecast!J33/(Forecast!J7/365) -> 4.3313932
B67: DPO | G67: =Forecast!J44/(Forecast!J12/365) -> 30.100944
B68: DIO | G68: =Forecast!J34/(Forecast!J12/365) -> 27.56451

Sheet CASH_FLOW
A1: Created by EDGAR Online, Inc.
A3: COSTCO WHOLESALE CORP /NEW
A4: CASH_FLOW
A5: Form Type: 10-K
A6: Period End: Aug 31, 2025
A7: Date Filed: Oct 08, 2025
A8: Table Of Contents
B10: COSTCO WHOLESALE CORPORATION
B12: CONSOLIDATED STATEMENTS OF CASH FLOWS
B14: (amounts in millions)
C16: 52 | D16: Weeks Ended | E16: 52 | F16: Weeks Ended | G16: 53 | H16: Weeks Ended | I16: 52 | J16: Weeks Ended | K16: 52 | L16: Weeks Ended
D17: August 31, | F17: September 1, | H17: September 3, | J17: August 28, | L17: August 29,
D18: 2025 | F18: 2024 | H18: 2023 | J18: 2022 | L18: 2021
B19: CASH FLOWS FROM OPERATING ACTIVITIES
B20: Net income | D20: 8099 | F20: 7367 | H20: 6292 | J20: 5915 | L20: 5079
B21: Adjustments to reconcile net income to net cash
B22: provided by operating activities:
B23: Depreciation and amortization | D23: 2426 | F23: 2237 | H23: 2077 | J23: 1900 | L23: 1781
B24: Non-cash lease expense | D24: 303 | F24: 315 | H24: 412 | J24: 377 | L24: 286
B25: Stock-based compensation | D25: 860 | F25: 818 | H25: 774 | J25: 724 | L25: 665
B26: Impairment of assets and other non-cash operating
B27: activities, net | D27: -117 | F27: -9 | H27: 495 | J27: 39 | L27: 144
B28: Changes in operating assets and liabilities:
B29: Merchandise inventories | D29: 559 | F29: -2068 | H29: 1228 | J29: -4003 | L29: -1892
B30: Accounts payable | D30: 404 | F30: 1938 | H30: -382 | J30: 1891 | L30: 1838
B31: Other operating assets and liabilities, net | D31: 801 | F31: 741 | H31: 172 | J31: 549 | L31: 1057
B32: Net cash provided by operating activities | D32: 13335 | F32: 11339 | H32: 11068 | J32: 7392 | L32: 8958
B33: CASH FLOWS FROM INVESTING ACTIVITIES
B34: Additions to property and equipment | D34: -5498 | F34: -4710 | H34: -4323 | J34: -3891 | L34: -3588
B35: Purchases of short-term investments | D35: -1028 | F35: -1470 | H35: -1622 | J35: -1121 | L35: -1331
B36: Maturities of short-term investments | D36: 1141 | F36: 1790 | H36: 937 | J36: 1145 | L36: 1446
B37: Other investing activities, net | D37: 74 | F37: -19 | H37: 36 | J37: -48 | L37: -62
B38: Net cash used in investing activities | D38: -5311 | F38: -4409 | H38: -4972 | J38: -3915 | L38: -3535
B39: CASH FLOWS FROM FINANCING ACTIVITIES
B40: Repayments of short-term borrowings | D40: -862 | F40: -920 | H40: -935 | J40: -6 | L40: 0
B41: Proceeds from short-term borrowings | D41: 816 | F41: 928 | H41: 917 | J41: 53 | L41: 41
B42: Repayments of long-term debt | D42: -103 | F42: -1077 | H42: -75 | J42: -800 | L42: -94
B43: Proceeds from issuance of long-term debt | D43: 0 | F43: 498 | H43: 0
B44: Tax withholdings on stock-based awards | D44: -393 | F44: -315 | H44: -303 | J44: -363 | L44: -312
B45: Repurchases of common stock | D45: -903 | F45: -700 | H45: -676 | J45: -439 | L45: -496
B46: Cash dividend payments | D46: -2183 | F46: -9041 | H46: -1251 | J46: -1498 | L46: -5748
B47: activities, net | D47: -147 | F47: -137 | H47: -291 | J47: -176 | L47: -67
B48: Dividend to noncontrolling interest | D48: 0 | F48: 0 | H48: 0 | J48: -208 | L48: 0
B49: Acquisition of noncontrolling interest | D49: 0 | F49: 0 | H49: 0 | J49: -842 | L49: 0
B50: Other financing activities, net | D50: 0 | F50: 0 | H50: 0 | J50: -4 | L50: 188
B51: Net cash used in financing activities | D51: -3775 | F51: -10764 | H51: -2614 | J51: -4283 | L51: -6488
B52: EFFECT OF EXCHANGE RATE CHANGES ON CASH AND CASH
B53: EQUIVALENTS | D53: 6 | F53: 40 | H53: 15 | J53: -249 | L53: 46
B54: Net change in cash and cash equivalents | D54: 4255 | F54: -3794 | H54: 3497 | J54: -1055 | L54: -1019
B55: CASH AND CASH EQUIVALENTS BEGINNING OF YEAR | D55: 9906 | F55: 13700 | H55: 10203 | J55: 11258 | L55: 12277
B56: CASH AND CASH EQUIVALENTS END OF YEAR | D56: 14161 | F56: 9906 | H56: 13700 | J56: 10203 | L56: 11258
B58: SUPPLEMENTAL DISCLOSURE OF CASH FLOW INFORMATION:
B59: Cash paid during the year for:
B60: Interest | D60: 106 | F60: 129 | H60: 125 | J60: 145 | L60: 149
B61: Income taxes, net | D61: 2917 | F61: 2319 | H61: 2234 | J61: 1940 | L61: 1527
B62: SUPPLEMENTAL DISCLOSURE OF NON-CASH ACTIVITIES:
B63: Cash dividend declared, but not yet paid | D63: 0 | F63: 0 | H63: 452 | J63: 0 | L63: 0
B64: Capital expenditures included in liabilities | D64: 193 | F64: 203 | H64: 170 | J64: 156 | L64: 184
